Workbook

Sheet Final Data
A1: LEAID | B1: Year | C1: employer_code | D1: original_employer_name | E1: standardized_employer_name | F1: employer_contributions | G1: state_contributions | H1: LEAID
B2: 2015 | C2: 4010 | D2: DEPARTMENT OF ADMIN SERVICE | E2: DEPARTMENT OF ADMIN SERVICE | F2: 6542.85 | H2: =IFERROR(VLOOKUP(E2,'GASB Match'!$A$2:$B$240,2,FALSE),"")
B3: 2016 | C3: 4010 | D3: DEPARTMENT OF ADMIN SERVICE | E3: DEPARTMENT OF ADMIN SERVICE | F3: 10068.75 | H3: =IFERROR(VLOOKUP(E3,'GASB Match'!$A$2:$B$240,2,FALSE),"")
B4: 2017 | C4: 4010 | D4: DEPARTMENT OF ADMIN SERVICE | E4: DEPARTMENT OF ADMIN SERVICE | F4: 26928 | H4: =IFERROR(VLOOKUP(E4,'GASB Match'!$A$2:$B$240,2,FALSE),"")
B5: 2018 | C5: 4010 | D5: DEPARTMENT OF ADMIN SERVICE | E5: DEPARTMENT OF ADMIN SERVICE | F5: 48505 | H5: =IFERROR(VLOOKUP(E5,'GASB Match'!$A$2:$B$240,2,FALSE),"")
B6: 2019 | C6: 4010 | D6: DEPARTMENT OF ADMIN SERVICE | E6: DEPARTMENT OF ADMIN SERVICE | F6: 54920 | H6: =IFERROR(VLOOKUP(E6,'GASB Match'!$A$2:$B$240,2,FALSE),"")
B7: 2020 | C7: 4010 | D7: DEPARTMENT OF ADMIN SERVICE | E7: DEPARTMENT OF ADMIN SERVICE | F7: 63308 | H7: =IFERROR(VLOOKUP(E7,'GASB Match'!$A$2:$B$240,2,FALSE),"")
B8: 2021 | C8: 4010 | D8: DEPARTMENT OF ADMIN SERVICE | E8: DEPARTMENT OF ADMIN SERVICE | F8: 66819 | H8: =IFERROR(VLOOKUP(E8,'GASB Match'!$A$2:$B$240,2,FALSE),"")
B9: 2022 | C9: 4010 | D9: DEPARTMENT OF ADMIN SERVICE | E9: DEPARTMENT OF ADMIN SERVICE | F9: 82013 | H9: =IFERROR(VLOOKUP(E9,'GASB Match'!$A$2:$B$240,2,FALSE),"")
B10: 2023 | C10: 4010 | D10: DEPARTMENT OF ADMIN SERVICE | E10: DEPARTMENT OF ADMIN SERVICE | F10: 92730 | H10: =IFERROR(VLOOKUP(E10,'GASB Match'!$A$2:$B$240,2,FALSE),"")
B11: 2015 | C11: 4020 | D11: GEORGIA DEPARTMENT OF AGRICULTURE | E11: GEORGIA DEPARTMENT OF AGRICULTURE | H11: =IFERROR(VLOOKUP(E11,'GASB Match'!$A$2:$B$240,2,FALSE),"")
B12: 2016 | C12: 4020 | D12: GEORGIA DEPARTMENT OF AGRICULTURE | E12: GEORGIA DEPARTMENT OF AGRICULTURE | F12: 2779.67 | H12: =IFERROR(VLOOKUP(E12,'GASB Match'!$A$2:$B$240,2,FALSE),"")
B13: 2017 | C13: 4020 | D13: GEORGIA DEPARTMENT OF AGRICULTURE | E13: GEORGIA DEPARTMENT OF AGRICULTURE | F13: 7863 | H13: =IFERROR(VLOOKUP(E13,'GASB Match'!$A$2:$B$240,2,FALSE),"")
B14: 2018 | C14: 4020 | D14: GEORGIA DEPARTMENT OF AGRICULTURE | E14: GEORGIA DEPARTMENT OF AGRICULTURE | F14: 10451 | H14: =IFERROR(VLOOKUP(E14,'GASB Match'!$A$2:$B$240,2,FALSE),"")
B15: 2019 | C15: 4020 | D15: GEORGIA DEPARTMENT OF AGRICULTURE | E15: GEORGIA DEPARTMENT OF AGRICULTURE | F15: 28999 | H15: =IFERROR(VLOOKUP(E15,'GASB Match'!$A$2:$B$240,2,FALSE),"")
B16: 2020 | C16: 4020 | D16: GEORGIA DEPARTMENT OF AGRICULTURE | E16: GEORGIA DEPARTMENT OF AGRICULTURE | F16: 32834 | H16: =IFERROR(VLOOKUP(E16,'GASB Match'!$A$2:$B$240,2,FALSE),"")
B17: 2021 | C17: 4020 | D17: GEORGIA DEPARTMENT OF AGRICULTURE | E17: GEORGIA DEPARTMENT OF AGRICULTURE | F17: 30377 | H17: =IFERROR(VLOOKUP(E17,'GASB Match'!$A$2:$B$240,2,FALSE),"")
B18: 2022 | C18: 4020 | D18: GEORGIA DEPARTMENT OF AGRICULTURE | E18: GEORGIA DEPARTMENT OF AGRICULTURE | F18: 30294 | H18: =IFERROR(VLOOKUP(E18,'GASB Match'!$A$2:$B$240,2,FALSE),"")
B19: 2023 | C19: 4020 | D19: GEORGIA DEPARTMENT OF AGRICULTURE | E19: GEORGIA DEPARTMENT OF AGRICULTURE | F19: 23356 | H19: =IFERROR(VLOOKUP(E19,'GASB Match'!$A$2:$B$240,2,FALSE),"")
B20: 2015 | C20: 4040 | D20: GEORGIA DEPARTMENT OF AUDITS | E20: GEORGIA DEPARTMENT OF AUDITS | F20: 9704.27 | H20: =IFERROR(VLOOKUP(E20,'GASB Match'!$A$2:$B$240,2,FALSE),"")
B21: 2016 | C21: 4040 | D21: GEORGIA DEPARTMENT OF AUDITS | E21: GEORGIA DEPARTMENT OF AUDITS | F21: 23667.52 | H21: =IFERROR(VLOOKUP(E21,'GASB Match'!$A$2:$B$240,2,FALSE),"")
B22: 2017 | C22: 4040 | D22: GEORGIA DEPARTMENT OF AUDITS | E22: GEORGIA DEPARTMENT OF AUDITS | F22: 14228 | H22: =IFERROR(VLOOKUP(E22,'GASB Match'!$A$2:$B$240,2,FALSE),"")
B23: 2018 | C23: 4040 | D23: GEORGIA DEPARTMENT OF AUDITS | E23: GEORGIA DEPARTMENT OF AUDITS | F23: 9803 | H23: =IFERROR(VLOOKUP(E23,'GASB Match'!$A$2:$B$240,2,FALSE),"")
... B66: 2023 | C66: 4220 | D66: GOVERNORS OFFICE OF PLANNING AND BUDGET | E66: GOVERNORS OFFICE OF PLANNING AND BUDGET | F66: 263497 | H66: =IFERROR(VLOOKUP(E66,'GASB Match'!$A$2:$B$240,2,FALSE),"")
A67: 1300027 | B67: 2015 | C67: 4270 | D67: DEPARTMENT OF HUMAN SERVICES | E67: DEPARTMENT OF HUMAN SERVICES | F67: 30903.98 | H67: =IFERROR(VLOOKUP(E67,'GASB Match'!$A$2:$B$240,2,FALSE),"") -> 1300027
A68: 1300027 | B68: 2016 | C68: 4270 | D68: DEPARTMENT OF HUMAN SERVICES | E68: DEPARTMENT OF HUMAN SERVICES | F68: 41851.7 | H68: =IFERROR(VLOOKUP(E68,'GASB Match'!$A$2:$B$240,2,FALSE),"") -> 1300027
A69: 1300027 | B69: 2017 | C69: 4270 | D69: DEPARTMENT OF HUMAN SERVICES | E69: DEPARTMENT OF HUMAN SERVICES | F69: 73617 | H69: =IFERROR(VLOOKUP(E69,'GASB Match'!$A$2:$B$240,2,FALSE),"") -> 1300027
A70: 1300027 | B70: 2018 | C70: 4270 | D70: DEPARTMENT OF HUMAN SERVICES | E70: DEPARTMENT OF HUMAN SERVICES | F70: 100104 | H70: =IFERROR(VLOOKUP(E70,'GASB Match'!$A$2:$B$240,2,FALSE),"") -> 1300027
A71: 1300027 | B71: 2019 | C71: 4270 | D71: DEPARTMENT OF HUMAN SERVICES | E71: DEPARTMENT OF HUMAN SERVICES | F71: 102528 | H71: =IFERROR(VLOOKUP(E71,'GASB Match'!$A$2:$B$240,2,FALSE),"") -> 1300027
A72: 1300027 | B72: 2020 | C72: 4270 | D72: DEPARTMENT OF HUMAN SERVICES | E72: DEPARTMENT OF HUMAN SERVICES | F72: 116495 | H72: =IFERROR(VLOOKUP(E72,'GASB Match'!$A$2:$B$240,2,FALSE),"") -> 1300027
A73: 1300027 | B73: 2021 | C73: 4270 | D73: DEPARTMENT OF HUMAN SERVICES | E73: DEPARTMENT OF HUMAN SERVICES | F73: 114946 | H73: =IFERROR(VLOOKUP(E73,'GASB Match'!$A$2:$B$240,2,FALSE),"") -> 1300027
A74: 1300027 | B74: 2022 | C74: 4270 | D74: DEPARTMENT OF HUMAN SERVICES | E74: DEPARTMENT OF HUMAN SERVICES | F74: 35636 | H74: =IFERROR(VLOOKUP(E74,'GASB Match'!$A$2:$B$240,2,FALSE),"") -> 1300027
A75: 1300027 | B75: 2023 | C75: 4270 | D75: DEPARTMENT OF HUMAN SERVICES | E75: DEPARTMENT OF HUMAN SERVICES | F75: 41802 | H75: =IFERROR(VLOOKUP(E75,'GASB Match'!$A$2:$B$240,2,FALSE),"") -> 1300027
B76: 2016 | C76: 4290 | D76: GEORGIA DEPARTMENT OF ECONOMIC DEVELOPMENT | E76: GEORGIA DEPARTMENT OF ECONOMIC DEVELOPMENT | F76: 11523.03 | H76: =IFERROR(VLOOKUP(E76,'GASB Match'!$A$2:$B$240,2,FALSE),"")
B77: 2017 | C77: 4290 | D77: GEORGIA DEPARTMENT OF ECONOMIC DEVELOPMENT | E77: GEORGIA DEPARTMENT OF ECONOMIC DEVELOPMENT | F77: 14701 | H77: =IFERROR(VLOOKUP(E77,'GASB Match'!$A$2:$B$240,2,FALSE),"")
B78: 2018 | C78: 4290 | D78: GEORGIA DEPARTMENT OF ECONOMIC DEVELOPMENT | E78: GEORGIA DEPARTMENT OF ECONOMIC DEVELOPMENT | F78: 25264 | H78: =IFERROR(VLOOKUP(E78,'GASB Match'!$A$2:$B$240,2,FALSE),"")
B79: 2019 | C79: 4290 | D79: GEORGIA DEPARTMENT OF ECONOMIC DEVELOPMENT | E79: GEORGIA DEPARTMENT OF ECONOMIC DEVELOPMENT | F79: 49116 | H79: =IFERROR(VLOOKUP(E79,'GASB Match'!$A$2:$B$240,2,FALSE),"")
B80: 2020 | C80: 4290 | D80: GEORGIA DEPARTMENT OF ECONOMIC DEVELOPMENT | E80: GEORGIA DEPARTMENT OF ECONOMIC DEVELOPMENT | F80: 40136 | H80: =IFERROR(VLOOKUP(E80,'GASB Match'!$A$2:$B$240,2,FALSE),"")
B81: 2021 | C81: 4290 | D81: GEORGIA DEPARTMENT OF ECONOMIC DEVELOPMENT | E81: GEORGIA DEPARTMENT OF ECONOMIC DEVELOPMENT | F81: 27265 | H81: =IFERROR(VLOOKUP(E81,'GASB Match'!$A$2:$B$240,2,FALSE),"")
B82: 2022 | C82: 4290 | D82: GEORGIA DEPARTMENT OF ECONOMIC DEVELOPMENT | E82: GEORGIA DEPARTMENT OF ECONOMIC DEVELOPMENT | F82: 13124 | H82: =IFERROR(VLOOKUP(E82,'GASB Match'!$A$2:$B$240,2,FALSE),"")
B83: 2023 | C83: 4290 | D83: GEORGIA DEPARTMENT OF ECONOMIC DEVELOPMENT | E83: GEORGIA DEPARTMENT OF ECONOMIC DEVELOPMENT | F83: 14186 | H83: =IFERROR(VLOOKUP(E83,'GASB Match'!$A$2:$B$240,2,FALSE),"")
B84: 2015 | C84: 4400 | D84: GEORGIA DEPT OF LABOR | E84: GEORGIA DEPARTMENT OF LABOR | F84: 9574.85 | H84: =IFERROR(VLOOKUP(E84,'GASB Match'!$A$2:$B$240,2,FALSE),"")
B85: 2016 | C85: 4400 | D85: GEORGIA DEPT OF LABOR | E85: GEORGIA DEPARTMENT OF LABOR | F85: 6881.52 | H85: =IFERROR(VLOOKUP(E85,'GASB Match'!$A$2:$B$240,2,FALSE),"")
B86: 2017 | C86: 4400 | D86: GEORGIA DEPT OF LABOR | E86: GEORGIA DEPARTMENT OF LABOR | F86: 16839 | H86: =IFERROR(VLOOKUP(E86,'GASB Match'!$A$2:$B$240,2,FALSE),"")
B87: 2018 | C87: 4400 | D87: GEORGIA DEPT OF LABOR | E87: GEORGIA DEPARTMENT OF LABOR | F87: 21786 | H87: =IFERROR(VLOOKUP(E87,'GASB Match'!$A$2:$B$240,2,FALSE),"")
... B127: 2023 | C127: 4660 | D127: DEPARTMENT OF PUBLIC SAFETY | E127: DEPARTMENT OF PUBLIC SAFETY | F127: 59207 | H127: =IFERROR(VLOOKUP(E127,'GASB Match'!$A$2:$B$240,2,FALSE),"")
A128: 1300025 | B128: 2015 | C128: 4670 | D128: DEPARTMENT OF CORRECTIONS | E128: DEPARTMENT OF CORRECTIONS | F128: 49401.38 | H128: =IFERROR(VLOOKUP(E128,'GASB Match'!$A$2:$B$240,2,FALSE),"") -> 1300025
A129: 1300025 | B129: 2016 | C129: 4670 | D129: DEPARTMENT OF CORRECTIONS | E129: DEPARTMENT OF CORRECTIONS | F129: 150403.04 | H129: =IFERROR(VLOOKUP(E129,'GASB Match'!$A$2:$B$240,2,FALSE),"") -> 1300025
A130: 1300025 | B130: 2017 | C130: 4670 | D130: DEPARTMENT OF CORRECTIONS | E130: DEPARTMENT OF CORRECTIONS | F130: 232749 | H130: =IFERROR(VLOOKUP(E130,'GASB Match'!$A$2:$B$240,2,FALSE),"") -> 1300025
A131: 1300025 | B131: 2018 | C131: 4670 | D131: DEPARTMENT OF CORRECTIONS | E131: DEPARTMENT OF CORRECTIONS | F131: 401454 | H131: =IFERROR(VLOOKUP(E131,'GASB Match'!$A$2:$B$240,2,FALSE),"") -> 1300025
A132: 1300025 | B132: 2019 | C132: 4670 | D132: DEPARTMENT OF CORRECTIONS | E132: DEPARTMENT OF CORRECTIONS | F132: 540222 | H132: =IFERROR(VLOOKUP(E132,'GASB Match'!$A$2:$B$240,2,FALSE),"") -> 1300025
A133: 1300025 | B133: 2020 | C133: 4670 | D133: DEPARTMENT OF CORRECTIONS | E133: DEPARTMENT OF CORRECTIONS | F133: 440279 | H133: =IFERROR(VLOOKUP(E133,'GASB Match'!$A$2:$B$240,2,FALSE),"") -> 1300025
A134: 1300025 | B134: 2021 | C134: 4670 | D134: DEPARTMENT OF CORRECTIONS | E134: DEPARTMENT OF CORRECTIONS | F134: 294998 | H134: =IFERROR(VLOOKUP(E134,'GASB Match'!$A$2:$B$240,2,FALSE),"") -> 1300025
A135: 1300025 | B135: 2022 | C135: 4670 | D135: DEPARTMENT OF CORRECTIONS | E135: DEPARTMENT OF CORRECTIONS | F135: 325343 | H135: =IFERROR(VLOOKUP(E135,'GASB Match'!$A$2:$B$240,2,FALSE),"") -> 1300025
A136: 1300025 | B136: 2023 | C136: 4670 | D136: DEPARTMENT OF CORRECTIONS | E136: DEPARTMENT OF CORRECTIONS | F136: 317056 | H136: =IFERROR(VLOOKUP(E136,'GASB Match'!$A$2:$B$240,2,FALSE),"") -> 1300025
B137: 2015 | C137: 4690 | D137: GEORGIA DEPT OF EARLY CARE & LEARNING | E137: GEORGIA DEPARTMENT OF EARLY CARE AND LEARNING | F137: 71460.33 | H137: =IFERROR(VLOOKUP(E137,'GASB Match'!$A$2:$B$240,2,FALSE),"")
B138: 2016 | C138: 4690 | D138: GEORGIA DEPT OF EARLY CARE & LEARNING | E138: GEORGIA DEPARTMENT OF EARLY CARE AND LEARNING | F138: 78470.07 | H138: =IFERROR(VLOOKUP(E138,'GASB Match'!$A$2:$B$240,2,FALSE),"")
B139: 2017 | C139: 4690 | D139: GEORGIA DEPT OF EARLY CARE & LEARNING | E139: GEORGIA DEPARTMENT OF EARLY CARE AND LEARNING | F139: 88528 | H139: =IFERROR(VLOOKUP(E139,'GASB Match'!$A$2:$B$240,2,FALSE),"")
B140: 2018 | C140: 4690 | D140: GEORGIA DEPT OF EARLY CARE & LEARNING | E140: GEORGIA DEPARTMENT OF EARLY CARE AND LEARNING | F140: 116732 | H140: =IFERROR(VLOOKUP(E140,'GASB Match'!$A$2:$B$240,2,FALSE),"")
B141: 2019 | C141: 4690 | D141: GEORGIA DEPT OF EARLY CARE & LEARNING | E141: GEORGIA DEPARTMENT OF EARLY CARE AND LEARNING | F141: 125913 | H141: =IFERROR(VLOOKUP(E141,'GASB Match'!$A$2:$B$240,2,FALSE),"")
B142: 2020 | C142: 4690 | D142: GEORGIA DEPT OF EARLY CARE & LEARNING | E142: GEORGIA DEPARTMENT OF EARLY CARE AND LEARNING | F142: 126433 | H142: =IFERROR(VLOOKUP(E142,'GASB Match'!$A$2:$B$240,2,FALSE),"")
B143: 2021 | C143: 4690 | D143: GEORGIA DEPT OF EARLY CARE & LEARNING | E143: GEORGIA DEPARTMENT OF EARLY CARE AND LEARNING | F143: 107781 | H143: =IFERROR(VLOOKUP(E143,'GASB Match'!$A$2:$B$240,2,FALSE),"")
B144: 2022 | C144: 4690 | D144: GEORGIA DEPARTMENT OF EARLY CARE AND LEARNING | E144: GEORGIA DEPARTMENT OF EARLY CARE AND LEARNING | F144: 138484 | H144: =IFERROR(VLOOKUP(E144,'GASB Match'!$A$2:$B$240,2,FALSE),"")
B145: 2023 | C145: 4690 | D145: GEORGIA DEPARTMENT OF EARLY CARE AND LEARNING | E145: GEORGIA DEPARTMENT OF EARLY CARE AND LEARNING | F145: 140662 | H145: =IFERROR(VLOOKUP(E145,'GASB Match'!$A$2:$B$240,2,FALSE),"")
B146: 2015 | C146: 4720 | D146: BOARD OF REGENTS | E146: BOARD OF REGENTS | F146: 3412152.7 | H146: =IFERROR(VLOOKUP(E146,'GASB Match'!$A$2:$B$240,2,FALSE),"")
B147: 2016 | C147: 4720 | D147: BOARD OF REGENTS | E147: BOARD OF REGENTS | F147: 4035643.1 | H147: =IFERROR(VLOOKUP(E147,'GASB Match'!$A$2:$B$240,2,FALSE),"")
B148: 2017 | C148: 4720 | D148: BOARD OF REGENTS | E148: BOARD OF REGENTS | F148: 4351427 | H148: =IFERROR(VLOOKUP(E148,'GASB Match'!$A$2:$B$240,2,FALSE),"")
... B444: 2023 | C444: 5900 | D444: ATLANTA METROPOLITAN STATE COLLEGE | E444: ATLANTA METROPOLITAN STATE COLLEGE | F444: 993299 | H444: =IFERROR(VLOOKUP(E444,'GASB Match'!$A$2:$B$240,2,FALSE),"")
A445: 1300060 | B445: 2015 | C445: 6011 | D445: APPLING COUNTY SCHOOLS | E445: APPLING COUNTY SCHOOLS | F445: 2538305.7 | G445: 52737.87 | H445: =IFERROR(VLOOKUP(E445,'GASB Match'!$A$2:$B$240,2,FALSE),"") -> 1300060
A446: 1300060 | B446: 2016 | C446: 6011 | D446: APPLING COUNTY SCHOOLS | E446: APPLING COUNTY SCHOOLS | F446: 2802144.4 | G446: 45497.64 | H446: =IFERROR(VLOOKUP(E446,'GASB Match'!$A$2:$B$240,2,FALSE),"") -> 1300060
A447: 1300060 | B447: 2017 | C447: 6011 | D447: APPLING COUNTY SCHOOLS | E447: APPLING COUNTY SCHOOLS | F447: 2835052 | G447: 39621 | H447: =IFERROR(VLOOKUP(E447,'GASB Match'!$A$2:$B$240,2,FALSE),"") -> 1300060
A448: 1300060 | B448: 2018 | C448: 6011 | D448: APPLING COUNTY SCHOOLS | E448: APPLING COUNTY SCHOOLS | F448: 3355287 | G448: 36438 | H448: =IFERROR(VLOOKUP(E448,'GASB Match'!$A$2:$B$240,2,FALSE),"") -> 1300060
A449: 1300060 | B449: 2019 | C449: 6011 | D449: APPLING COUNTY SCHOOLS | E449: APPLING COUNTY SCHOOLS | F449: 4248442 | G449: 46649 | H449: =IFERROR(VLOOKUP(E449,'GASB Match'!$A$2:$B$240,2,FALSE),"") -> 1300060
A450: 1300060 | B450: 2020 | C450: 6011 | D450: APPLING COUNTY SCHOOLS | E450: APPLING COUNTY SCHOOLS | F450: 4448981 | G450: 50169 | H450: =IFERROR(VLOOKUP(E450,'GASB Match'!$A$2:$B$240,2,FALSE),"") -> 1300060
A451: 1300060 | B451: 2021 | C451: 6011 | D451: APPLING COUNTY SCHOOLS | E451: APPLING COUNTY SCHOOLS | F451: 4232264 | G451: 46644 | H451: =IFERROR(VLOOKUP(E451,'GASB Match'!$A$2:$B$240,2,FALSE),"") -> 1300060
A452: 1300060 | B452: 2022 | C452: 6011 | D452: APPLING COUNTY SCHOOLS | E452: APPLING COUNTY SCHOOLS | F452: 4453994 | G452: 35093 | H452: =IFERROR(VLOOKUP(E452,'GASB Match'!$A$2:$B$240,2,FALSE),"") -> 1300060
A453: 1300060 | B453: 2023 | C453: 6011 | D453: APPLING COUNTY SCHOOLS | E453: APPLING COUNTY SCHOOLS | F453: 4749437 | G453: 27466 | H453: =IFERROR(VLOOKUP(E453,'GASB Match'!$A$2:$B$240,2,FALSE),"") -> 1300060
A454: 1300090 | B454: 2015 | C454: 6021 | D454: ATKINSON COUNTY SCHOOLS | E454: ATKINSON COUNTY SCHOOLS | F454: 1123783.9 | G454: 6274.19 | H454: =IFERROR(VLOOKUP(E454,'GASB Match'!$A$2:$B$240,2,FALSE),"") -> 1300090
A455: 1300090 | B455: 2016 | C455: 6021 | D455: ATKINSON COUNTY SCHOOLS | E455: ATKINSON COUNTY SCHOOLS | F455: 1221427.1 | G455: 7011.31 | H455: =IFERROR(VLOOKUP(E455,'GASB Match'!$A$2:$B$240,2,FALSE),"") -> 1300090
A456: 1300090 | B456: 2017 | C456: 6021 | D456: ATKINSON COUNTY SCHOOLS | E456: ATKINSON COUNTY SCHOOLS | F456: 1262927 | G456: 7148 | H456: =IFERROR(VLOOKUP(E456,'GASB Match'!$A$2:$B$240,2,FALSE),"") -> 1300090
... A471: 1300180 | B471: 2023 | C471: 6031 | D471: BACON COUNTY SCHOOLS | E471: BACON COUNTY SCHOOLS | F471: 2824472 | G471: 5498 | H471: =IFERROR(VLOOKUP(E471,'GASB Match'!$A$2:$B$240,2,FALSE),"") -> 1300180
B472: 2015 | C472: 6041 | D472: BAKER COUNTY SCHOOLS | E472: BAKER COUNTY SCHOOLS | F472: 237954.89 | G472: 2077.1 | H472: =IFERROR(VLOOKUP(E472,'GASB Match'!$A$2:$B$240,2,FALSE),"")
B473: 2016 | C473: 6041 | D473: BAKER COUNTY SCHOOLS | E473: BAKER COUNTY SCHOOLS | F473: 275065.95 | G473: 4746.67 | H473: =IFERROR(VLOOKUP(E473,'GASB Match'!$A$2:$B$240,2,FALSE),"")
B474: 2017 | C474: 6041 | D474: BAKER COUNTY SCHOOLS | E474: BAKER COUNTY SCHOOLS | F474: 287822 | G474: 1219 | H474: =IFERROR(VLOOKUP(E474,'GASB Match'!$A$2:$B$240,2,FALSE),"")
B475: 2018 | C475: 6041 | D475: BAKER COUNTY SCHOOLS | E475: BAKER COUNTY SCHOOLS | F475: 322696 | G475: 5189 | H475: =IFERROR(VLOOKUP(E475,'GASB Match'!$A$2:$B$240,2,FALSE),"")
B476: 2019 | C476: 6041 | D476: BAKER CO SCHOOLS | E476: BAKER COUNTY SCHOOLS | F476: 496700 | H476: =IFERROR(VLOOKUP(E476,'GASB Match'!$A$2:$B$240,2,FALSE),"")
B477: 2020 | C477: 6041 | D477: BAKER COUNTY SCHOOLS | E477: BAKER COUNTY SCHOOLS | F477: 539353 | H477: =IFERROR(VLOOKUP(E477,'GASB Match'!$A$2:$B$240,2,FALSE),"")
B478: 2021 | C478: 6041 | D478: BAKER COUNTY SCHOOLS | E478: BAKER COUNTY SCHOOLS | F478: 432223 | H478: =IFERROR(VLOOKUP(E478,'GASB Match'!$A$2:$B$240,2,FALSE),"")
B479: 2022 | C479: 6041 | D479: BAKER COUNTY SCHOOLS | E479: BAKER COUNTY SCHOOLS | F479: 430972 | H479: =IFERROR(VLOOKUP(E479,'GASB Match'!$A$2:$B$240,2,FALSE),"")
B480: 2023 | C480: 6041 | D480: BAKER COUNTY SCHOOLS | E480: BAKER COUNTY SCHOOLS | F480: 455183 | H480: =IFERROR(VLOOKUP(E480,'GASB Match'!$A$2:$B$240,2,FALSE),"")
A481: 1300210 | B481: 2015 | C481: 6051 | D481: BALDWIN COUNTY SCHOOLS | E481: BALDWIN COUNTY SCHOOLS | F481: 3482207.5 | G481: 19519.52 | H481: =IFERROR(VLOOKUP(E481,'GASB Match'!$A$2:$B$240,2,FALSE),"") -> 1300210
A482: 1300210 | B482: 2016 | C482: 6051 | D482: BALDWIN COUNTY SCHOOLS | E482: BALDWIN COUNTY SCHOOLS | F482: 3674203.1 | G482: 23078.7 | H482: =IFERROR(VLOOKUP(E482,'GASB Match'!$A$2:$B$240,2,FALSE),"") -> 1300210
A483: 1300210 | B483: 2017 | C483: 6051 | D483: BALDWIN COUNTY SCHOOLS | E483: BALDWIN COUNTY SCHOOLS | F483: 3721167 | G483: 27155 | H483: =IFERROR(VLOOKUP(E483,'GASB Match'!$A$2:$B$240,2,FALSE),"") -> 1300210
A484: 1300210 | B484: 2018 | C484: 6051 | D484: BALDWIN COUNTY SCHOOLS | E484: BALDWIN COUNTY SCHOOLS | F484: 4293038 | G484: 32627 | H484: =IFERROR(VLOOKUP(E484,'GASB Match'!$A$2:$B$240,2,FALSE),"") -> 1300210
A485: 1300210 | B485: 2019 | C485: 6051 | D485: BALDWIN CO SCHOOLS | E485: BALDWIN COUNTY SCHOOLS | F485: 5617040 | G485: 44660 | H485: =IFERROR(VLOOKUP(E485,'GASB Match'!$A$2:$B$240,2,FALSE),"") -> 1300210
A486: 1300210 | B486: 2020 | C486: 6051 | D486: BALDWIN COUNTY SCHOOLS | E486: BALDWIN COUNTY SCHOOLS | F486: 5922892 | G486: 32559 | H486: =IFERROR(VLOOKUP(E486,'GASB Match'!$A$2:$B$240,2,FALSE),"") -> 1300210
A487: 1300210 | B487: 2021 | C487: 6051 | D487: BALDWIN COUNTY SCHOOLS | E487: BALDWIN COUNTY SCHOOLS | F487: 5411801 | G487: 25205 | H487: =IFERROR(VLOOKUP(E487,'GASB Match'!$A$2:$B$240,2,FALSE),"") -> 1300210
A488: 1300210 | B488: 2022 | C488: 6051 | D488: BALDWIN COUNTY SCHOOLS | E488: BALDWIN COUNTY SCHOOLS | F488: 5994808 | G488: 18948 | H488: =IFERROR(VLOOKUP(E488,'GASB Match'!$A$2:$B$240,2,FALSE),"") -> 1300210
A489: 1300210 | B489: 2023 | C489: 6051 | D489: BALDWIN COUNTY SCHOOLS | E489: BALDWIN COUNTY SCHOOLS | F489: 6284593 | G489: 42446 | H489: =IFERROR(VLOOKUP(E489,'GASB Match'!$A$2:$B$240,2,FALSE),"") -> 1300210
B490: 2015 | C490: 6055 | D490: GEORGIA MILITARY COLLEGE | E490: GEORGIA MILITARY COLLEGE | F490: 2096622.5 | H490: =IFERROR(VLOOKUP(E490,'GASB Match'!$A$2:$B$240,2,FALSE),"")
...

Sheet GASB Match
A1: Districts | B1: LEAID
A2: HENRY CO SCHOOLS | B2: 1302820 | C2: =COUNTIF($B$2:$B$240,B2) -> 1
A3: HOUSTON CO SCHOOLS | B3: 1302880 | C3: =COUNTIF($B$2:$B$240,B3) -> 1
A4: ROCKDALE CO SCHOOLS | B4: 1304410 | C4: =COUNTIF($B$2:$B$240,B4) -> 1
A5: ROME CITY SCHOOLS | B5: 1304440 | C5: =COUNTIF($B$2:$B$240,B5) -> 1
A6: TROUP CO SCHOOLS | B6: 1300001 | C6: =COUNTIF($B$2:$B$240,B6) -> 1
A7: NORTHWEST GEORGIA RESA | B7: 1300006 | C7: =COUNTIF($B$2:$B$240,B7) -> 1
A8: NORTH GEORGIA RESA | B8: 1300007 | C8: =COUNTIF($B$2:$B$240,B8) -> 1
A9: PIONEER RESA | B9: 1300008 | C9: =COUNTIF($B$2:$B$240,B9) -> 1
A10: METRO RESA | B10: 1300009 | C10: =COUNTIF($B$2:$B$240,B10) -> 1
A11: NORTHEAST GEORGIA RESA | B11: 1300010 | C11: =COUNTIF($B$2:$B$240,B11) -> 1
A12: WEST GEORGIA RESA | B12: 1300011 | C12: =COUNTIF($B$2:$B$240,B12) -> 1
A13: GRIFFIN RESA | B13: 1300012 | C13: =COUNTIF($B$2:$B$240,B13) -> 1
... A240: IVY PREPARATORY ACAD. | B240: 1300215 | C240: =COUNTIF($B$2:$B$240,B240) -> 1
