Workbook

Sheet GASB 67 Data
A1: CENSUSID | B1: Year of Reporting | C1: plan_idx | D1: unique_id | E1: Month of Reporting | F1: State Name | G1: Plan Name | H1: Plan Abbreviation | I1: Available? | J1: Service Cost | K1: Interest Cost | L1: Changes in Benefit Terms | M1: Expected vs Actual Experience | N1: Assumption Changes | O1: Benefit Payments (including Refunds if combined) | P1: Refunds | Q1: Net Change in TPL | R1: TPL boy | S1: TPL eoy | T1: Employer Contribs | U1: Non-Employer/State Contributions | V1: Member Contributions | W1: Net Inv Inc | X1: Transfers Among Employers | Y1: Administrative Expenses | Z1: Other (+ = improves) | AA1: Net Change in FNP | AB1: FNP boy | AC1: FNP eoy | AD1: NPL eoy | AE1: NPL boy | AF1: Net Changes to NPL | AG1: Covered Employee Payroll | AH1: State Contributions as a % of Payroll | AI1: Check | AJ1: Imputed Flag | AK1: Discount Rate Previous Year | AL1: Discount Rate (current year) | AM1: Expected Rate of Return | AN1: Prior Year's Expected Rate of Return | AO1: State/Local Plan | AP1: Discount - Expected | AQ1: Muni Rate | AR1: Exhaustion | AS1: NPL - 1% | AT1: NPL + 1% | AU1: Exact Source | AV1: Link to Exact Source | BB1: Stated Funding Ratio | BD1: Duration Calculation | BF1: Dur(-) | BG1: Dur(+) | BH1: Dur | BI1: Conv/2 | BJ1: Rounded Duration | BK1: Treas Zero boy | BL1: Adj boy | BM1: TPL * boy | BN1: NPL * boy | BP1: Treas Zero eoy | BQ1: Adj eoy | BR1: TPL * eoy | BS1: NPL * eoy | BU1: SC Duration | BV1: SC Adj | BW1: Service Cost * | BX1: Interest Cost * | BY1: Interest on NPL* | BZ1: SC Orig + IC Orig | CA1: SC + IntNPLAdj | CC1: TPL* | CE1: FNP / TPL | CF1: FNP / TPL*
A2: 5000000015801 | B2: 2015 | C2: 39 | D2: plan134_y2021 | E2: 6 | F2: California | G2: California State Teachers Retirement System | H2: CalSTRS | I2: TRUE | J2: 5556000 | K2: 18556000 | M2: -1312000 | O2: 12565000 | Q2: 10235000 | R2: 248911000 | S2: 259146000 | T2: 2678000 | U2: 1426000 | V2: 2510000 | W2: 7612000 | Y2: 145000 | Z2: 10000 | AA2: 1510000 | AB2: 190312000 | AC2: 191822000 | AD2: 67324000 | AE2: 58599000 | AF2: 8725000 | AG2: 32026000 | AH2: 0.083619559 | AI2: TRUE | AJ2: =AA2-Q2+AF2 -> 0 | AK2: 0.076 | AL2: 0.076 | AM2: 0.076 | AN2: 0.075 | AO2: 1 | AP2: 0 | AS2: 101654000 | AT2: 38793000 | AU2: p75 of CAFR | AV2: https://www.calstrs.com/sites/main/files/file-attachments/cafr2015.pdf | BB2: =AC2/S2 -> 0.74020822 | BD2: =AS2-AD2 -> 34330000 | BE2: =AT2-AD2 -> -28531000 | BF2: =BD2/S2*100 -> 13.247359 | BG2: =BE2/S2*100 -> -11.009624 | BH2: =(BD2-BE2)/(2*S2)*100 -> 12.128491 | BI2: =(BD2+BE2)/(2*S2*(0.01^2)) -> 111.88674 | BJ2: =ROUND(BH2,0) -> 12 | BK2: =IF($BJ2<=30,IF($B2=2015,VLOOKUP($BJ2,'Treasury Yields'!$C$5:$N$34,$E2,FALSE)/100,IF($B2=2016,VLOOKUP($BJ2,'Treasury Yields'!$C$40:$N$69,$E2,FALSE)/100,IF($B2=2017,VLOOKUP($BJ2,'Treasury Yields'!$C$75:$N$104,$E2,FALSE)/100,IF($B2=2018,VLOOKUP($BJ2,'Treasury Yields'!$C$110:$N$139,$E2,FALSE)/100,IF($B2=2019,VLOOKUP($BJ2,'Treasury Yields'!$C$145:$N$174,$E2,FALSE)/100,IF($B2=2020,VLOOKUP($BJ2,'Treasury Yields'!$C$180:$N$209,$E2,FALSE)/100,IF($B2=2021,VLOOKUP($BJ2,'Treasury Yields'!$C$215:$N$244,$E2,FALSE)/100,IF($B2=2022,VLOOKUP($BJ2,'Treasury Yields'!$C$250:$N$279,$E2,FALSE)/100)))))))),0) -> 0.029186 | BL2: =1+BH2*(AL2-BK2)+(AL2-BK2)^2 -> 1.5699747 | BM2: =BL2*R2 -> 3.9078398e+08 | BN2: =BM2-AB2 -> 2.0047198e+08 | BP2: =IF($BJ2<=30,IF($B2=2015,VLOOKUP($BJ2,'Treasury Yields'!$C$40:$N$69,$E2,FALSE)/100,IF($B2=2016,VLOOKUP($BJ2,'Treasury Yields'!$C$75:$N$104,$E2,FALSE)/100,IF($B2=2017,VLOOKUP($BJ2,'Treasury Yields'!$C$110:$N$139,$E2,FALSE)/100,IF($B2=2018,VLOOKUP($BJ2,'Treasury Yields'!$C$145:$N$174,$E2,FALSE)/100,IF($B2=2019,VLOOKUP($BJ2,'Treasury Yields'!$C$180:$N$209,$E2,FALSE)/100,IF($B2=2020,VLOOKUP($BJ2,'Treasury Yields'!$C$215:$N$244,$E2,FALSE)/100,IF($B2=2021,VLOOKUP($BJ2,'Treasury Yields'!$C$250:$N$279,$E2,FALSE)/100,IF($B2=2022,VLOOKUP($BJ2,'Treasury Yields'!$C$285:$N$314,$E2,FALSE)/100)))))))),0) -> 0.027046 | BQ2: =1+BH2*(AN2-BP2)+(AN2-BP2)^2 -> 1.5839093 | BR2: =BQ2*S2 -> 4.1046375e+08 | BS2: =BR2-AC2 -> 2.1864175e+08 | BT2: 3 | BU2: =IF(BJ2="","",ROUND(BJ2+$BT$2,0)) -> 15 | BV2: =1+(BH2+BU2)*(AN2-BK2)+(AN2-BK2)^2*BI2 -> 2.4777063 | BW2: =BV2*J2 -> 13766136 | BX2: =(BM2+BW2-O2)*BK2 -> 11440478 | BY2: =BK2*(BN2+BW2-O2) -> 5886031.7 | BZ2: =SUM(J2:K2) -> 24112000 | CA2: =SUM(BW2+BY2) -> 19652168 | CC2: =BR2 -> 4.1046375e+08 | CD2: =F2 -> California | CE2: =BB2 -> 0.74020822 | CF2: =AC2/CC2 -> 0.46732994
A3: 5000000015801 | B3: 2016 | C3: 39 | D3: plan134_y2021 | E3: 6 | F3: California | G3: California State Teachers Retirement System | H3: CalSTRS | I3: TRUE | J3: 5874000 | K3: 19332000 | M3: -1209000 | O3: 13149000 | Q3: 10848000 | R3: 259146000 | S3: 269994000 | T3: 3391000 | U3: 1940000 | V3: 2957000 | W3: 2305000 | Y3: 1800000 | Z3: 15000 | AA3: -2709000 | AB3: 191822000 | AC3: 189113000 | AD3: 80881000 | AE3: 67324000 | AF3: 13557000 | AG3: 31910000 | AH3: 0.10626763 | AI3: TRUE | AK3: 0.076 | AL3: 0.076 | AM3: 0.076 | AN3: 0.076 | AO3: 1 | AP3: 0 | AS3: 116406000 | AT3: 51376000 | AU3: p80 of CAFR | AV3: https://www.calstrs.com/sites/main/files/file-attachments/cafr2016.pdf | BB3: =AC3/S3 -> 0.70043408 | BD3: =AS3-AD3 -> 35525000 | BE3: =AT3-AD3 -> -29505000 | BF3: =BD3/S3*100 -> 13.1577 | BG3: =BE3/S3*100 -> -10.928021 | BH3: =(BD3-BE3)/(2*S3)*100 -> 12.04286 | BI3: =(BD3+BE3)/(2*S3*(0.01^2)) -> 111.48396 | BJ3: =ROUND(BH3,0) -> 12 | BK3: =IF($BJ3<=30,IF($B3=2015,VLOOKUP($BJ3,'Treasury Yields'!$C$5:$N$34,$E3,FALSE)/100,IF($B3=2016,VLOOKUP($BJ3,'Treasury Yields'!$C$40:$N$69,$E3,FALSE)/100,IF($B3=2017,VLOOKUP($BJ3,'Treasury Yields'!$C$75:$N$104,$E3,FALSE)/100,IF($B3=2018,VLOOKUP($BJ3,'Treasury Yields'!$C$110:$N$139,$E3,FALSE)/100,IF($B3=2019,VLOOKUP($BJ3,'Treasury Yields'!$C$145:$N$174,$E3,FALSE)/100,IF($B3=2020,VLOOKUP($BJ3,'Treasury Yields'!$C$180:$N$209,$E3,FALSE)/100,IF($B3=2021,VLOOKUP($BJ3,'Treasury Yields'!$C$215:$N$244,$E3,FALSE)/100,IF($B3=2022,VLOOKUP($BJ3,'Treasury Yields'!$C$250:$N$279,$E3,FALSE)/100)))))))),0) -> 0.027046 | BL3: =1+BH3*(AL3-BK3)+(AL3-BK3)^2 -> 1.5919427 | BM3: =BL3*R3 -> 4.1254558e+08 | BN3: =BM3-AB3 -> 2.2072358e+08 | BP3: =IF($BJ3<=30,IF($B3=2015,VLOOKUP($BJ3,'Treasury Yields'!$C$40:$N$69,$E3,FALSE)/100,IF($B3=2016,VLOOKUP($BJ3,'Treasury Yields'!$C$75:$N$104,$E3,FALSE)/100,IF($B3=2017,VLOOKUP($BJ3,'Treasury Yields'!$C$110:$N$139,$E3,FALSE)/100,IF($B3=2018,VLOOKUP($BJ3,'Treasury Yields'!$C$145:$N$174,$E3,FALSE)/100,IF($B3=2019,VLOOKUP($BJ3,'Treasury Yields'!$C$180:$N$209,$E3,FALSE)/100,IF($B3=2020,VLOOKUP($BJ3,'Treasury Yields'!$C$215:$N$244,$E3,FALSE)/100,IF($B3=2021,VLOOKUP($BJ3,'Treasury Yields'!$C$250:$N$279,$E3,FALSE)/100,IF($B3=2022,VLOOKUP($BJ3,'Treasury Yields'!$C$285:$N$314,$E3,FALSE)/100)))))))),0) -> 0.017546 | BQ3: =1+BH3*(AN3-BP3)+(AN3-BP3)^2 -> 1.7073702 | BR3: =BQ3*S3 -> 4.6097972e+08 | BS3: =BR3-AC3 -> 2.7186672e+08 | BU3: =IF(BJ3="","",ROUND(BJ3+$BT$2,0)) -> 15 | BV3: =1+(BH3+BU3)*(AN3-BK3)+(AN3-BK3)^2*BI3 -> 2.5910268 | BW3: =BV3*J3 -> 15219692 | BX3: =(BM3+BW3-O3)*BK3 -> 11213712 | BY3: =BK3*(BN3+BW3-O3) -> 6025693.8 | BZ3: =SUM(J3:K3) -> 25206000 | CA3: =SUM(BW3+BY3) -> 21245385 | CC3: =BR3 -> 4.6097972e+08 | CD3: =F3 -> California | CE3: =BB3 -> 0.70043408 | CF3: =AC3/CC3 -> 0.41024148
A4: 5000000015801 | B4: 2017 | C4: 39 | D4: plan134_y2021 | E4: 6 | F4: California | G4: California State Teachers Retirement System | H4: CalSTRS | I4: TRUE | J4: 6064000 | K4: 20227000 | M4: 399000 | N4: 19988000 | O4: 13903000 | Q4: 32775000 | R4: 269994000 | S4: 302769000 | T4: 4173000 | U4: 2478000 | V4: 3441000 | W4: 25165000 | Y4: 182000 | Z4: 10000 | AA4: 21176000 | AB4: 189113000 | AC4: 210289000 | AD4: 92480000 | AE4: 80881000 | AF4: 11599000 | AG4: 34126000 | AH4: 0.12228213 | AI4: TRUE | AK4: 0.076 | AL4: 0.071 | AM4: 0.071 | AN4: 0.076 | AO4: 1 | AP4: 0 | AS4: 135790000 | AT4: 57331000 | AU4: p88 of CAFR | AV4: https://www.calstrs.com/sites/main/files/file-attachments/cafr2017.pdf | BB4: =AC4/S4 -> 0.69455261 | BD4: =AS4-AD4 -> 43310000 | BE4: =AT4-AD4 -> -35149000 | BF4: =BD4/S4*100 -> 14.304635 | BG4: =BE4/S4*100 -> -11.609181 | BH4: =(BD4-BE4)/(2*S4)*100 -> 12.956908 | BI4: =(BD4+BE4)/(2*S4*(0.01^2)) -> 134.77271 | BJ4: =ROUND(BH4,0) -> 13 | BK4: =IF($BJ4<=30,IF($B4=2015,VLOOKUP($BJ4,'Treasury Yields'!$C$5:$N$34,$E4,FALSE)/100,IF($B4=2016,VLOOKUP($BJ4,'Treasury Yields'!$C$40:$N$69,$E4,FALSE)/100,IF($B4=2017,VLOOKUP($BJ4,'Treasury Yields'!$C$75:$N$104,$E4,FALSE)/100,IF($B4=2018,VLOOKUP($BJ4,'Treasury Yields'!$C$110:$N$139,$E4,FALSE)/100,IF($B4=2019,VLOOKUP($BJ4,'Treasury Yields'!$C$145:$N$174,$E4,FALSE)/100,IF($B4=2020,VLOOKUP($BJ4,'Treasury Yields'!$C$180:$N$209,$E4,FALSE)/100,IF($B4=2021,VLOOKUP($BJ4,'Treasury Yields'!$C$215:$N$244,$E4,FALSE)/100,IF($B4=2022,VLOOKUP($BJ4,'Treasury Yields'!$C$250:$N$279,$E4,FALSE)/100)))))))),0) -> 0.018144 | BL4: =1+BH4*(AL4-BK4)+(AL4-BK4)^2 -> 1.6876441 | BM4: =BL4*R4 -> 4.5565377e+08 | BN4: =BM4-AB4 -> 2.6654077e+08 | BP4: =IF($BJ4<=30,IF($B4=2015,VLOOKUP($BJ4,'Treasury Yields'!$C$40:$N$69,$E4,FALSE)/100,IF($B4=2016,VLOOKUP($BJ4,'Treasury Yields'!$C$75:$N$104,$E4,FALSE)/100,IF($B4=2017,VLOOKUP($BJ4,'Treasury Yields'!$C$110:$N$139,$E4,FALSE)/100,IF($B4=2018,VLOOKUP($BJ4,'Treasury Yields'!$C$145:$N$174,$E4,FALSE)/100,IF($B4=2019,VLOOKUP($BJ4,'Treasury Yields'!$C$180:$N$209,$E4,FALSE)/100,IF($B4=2020,VLOOKUP($BJ4,'Treasury Yields'!$C$215:$N$244,$E4,FALSE)/100,IF($B4=2021,VLOOKUP($BJ4,'Treasury Yields'!$C$250:$N$279,$E4,FALSE)/100,IF($B4=2022,VLOOKUP($BJ4,'Treasury Yields'!$C$285:$N$314,$E4,FALSE)/100)))))))),0) -> 0.0258664 | BQ4: =1+BH4*(AN4-BP4)+(AN4-BP4)^2 -> 1.6520898 | BR4: =BQ4*S4 -> 5.0020158e+08 | BS4: =BR4-AC4 -> 2.8991258e+08 | BU4: =IF(BJ4="","",ROUND(BJ4+$BT$2,0)) -> 16 | BV4: =1+(BH4+BU4)*(AN4-BK4)+(AN4-BK4)^2*BI4 -> 3.1264578 | BW4: =BV4*J4 -> 18958840 | BX4: =(BM4+BW4-O4)*BK4 -> 8359115.2 | BY4: =BK4*(BN4+BW4-O4) -> 4927849 | BZ4: =SUM(J4:K4) -> 26291000 | CA4: =SUM(BW4+BY4) -> 23886689 | CC4: =BR4 -> 5.0020158e+08 | CD4: =F4 -> California | CE4: =BB4 -> 0.69455261 | CF4: =AC4/CC4 -> 0.42040851
A5: 5000000015801 | B5: 2018 | C5: 39 | D5: plan134_y2021 | E5: 6 | F5: California | G5: California State Teachers Retirement System | H5: CalSTRS | I5: TRUE | J5: 7142000 | K5: 21496000 | M5: -94000 | N5: 0 | O5: 14537000 | Q5: 14007000 | R5: 302769000 | S5: 316776000 | T5: 4867000 | U5: 2797000 | V5: 3496000 | W5: 18674000 | Y5: 216000 | Z5: 2000 | AA5: 15091000 | AB5: 210289000 | AC5: 224869000 | AD5: 91907000 | AE5: 92480000 | AF5: -573000 | AG5: 34753000 | AH5: 0.14004546 | AI5: TRUE | AK5: 0.071 | AL5: 0.071 | AM5: 0.071 | AN5: 0.071 | AO5: 1 | AP5: 0 | AS5: 134633000 | AT5: 56483000 | AU5: p94 of CAFR | AV5: https://www.calstrs.com/sites/main/files/file-attachments/cafr2018.pdf | BB5: =AC5/S5 -> 0.70986754 | BD5: =AS5-AD5 -> 42726000 | BE5: =AT5-AD5 -> -35424000 | BF5: =BD5/S5*100 -> 13.487764 | BG5: =BE5/S5*100 -> -11.182665 | BH5: =(BD5-BE5)/(2*S5)*100 -> 12.335215 | BI5: =(BD5+BE5)/(2*S5*(0.01^2)) -> 115.25494 | BJ5: =ROUND(BH5,0) -> 12 | BK5: =IF($BJ5<=30,IF($B5=2015,VLOOKUP($BJ5,'Treasury Yields'!$C$5:$N$34,$E5,FALSE)/100,IF($B5=2016,VLOOKUP($BJ5,'Treasury Yields'!$C$40:$N$69,$E5,FALSE)/100,IF($B5=2017,VLOOKUP($BJ5,'Treasury Yields'!$C$75:$N$104,$E5,FALSE)/100,IF($B5=2018,VLOOKUP($BJ5,'Treasury Yields'!$C$110:$N$139,$E5,FALSE)/100,IF($B5=2019,VLOOKUP($BJ5,'Treasury Yields'!$C$145:$N$174,$E5,FALSE)/100,IF($B5=2020,VLOOKUP($BJ5,'Treasury Yields'!$C$180:$N$209,$E5,FALSE)/100,IF($B5=2021,VLOOKUP($BJ5,'Treasury Yields'!$C$215:$N$244,$E5,FALSE)/100,IF($B5=2022,VLOOKUP($BJ5,'Treasury Yields'!$C$250:$N$279,$E5,FALSE)/100)))))))),0) -> 0.0254676 | BL5: =1+BH5*(AL5-BK5)+(AL5-BK5)^2 -> 1.5637251 | BM5: =BL5*R5 -> 4.7344749e+08 | BN5: =BM5-AB5 -> 2.6315849e+08 | BP5: =IF($BJ5<=30,IF($B5=2015,VLOOKUP($BJ5,'Treasury Yields'!$C$40:$N$69,$E5,FALSE)/100,IF($B5=2016,VLOOKUP($BJ5,'Treasury Yields'!$C$75:$N$104,$E5,FALSE)/100,IF($B5=2017,VLOOKUP($BJ5,'Treasury Yields'!$C$110:$N$139,$E5,FALSE)/100,IF($B5=2018,VLOOKUP($BJ5,'Treasury Yields'!$C$145:$N$174,$E5,FALSE)/100,IF($B5=2019,VLOOKUP($BJ5,'Treasury Yields'!$C$180:$N$209,$E5,FALSE)/100,IF($B5=2020,VLOOKUP($BJ5,'Treasury Yields'!$C$215:$N$244,$E5,FALSE)/100,IF($B5=2021,VLOOKUP($BJ5,'Treasury Yields'!$C$250:$N$279,$E5,FALSE)/100,IF($B5=2022,VLOOKUP($BJ5,'Treasury Yields'!$C$285:$N$314,$E5,FALSE)/100)))))))),0) -> 0.028906473 | BQ5: =1+BH5*(AN5-BP5)+(AN5-BP5)^2 -> 1.5210046 | BR5: =BQ5*S5 -> 4.8181774e+08 | BS5: =BR5-AC5 -> 2.5694874e+08 | BU5: =IF(BJ5="","",ROUND(BJ5+$BT$2,0)) -> 15 | BV5: =1+(BH5+BU5)*(AN5-BK5)+(AN5-BK5)^2*BI5 -> 2.4835844 | BW5: =BV5*J5 -> 17737760 | BX5: =(BM5+BW5-O5)*BK5 -> 12139087 | BY5: =BK5*(BN5+BW5-O5) -> 6783531 | BZ5: =SUM(J5:K5) -> 28638000 | CA5: =SUM(BW5+BY5) -> 24521291 | CC5: =BR5 -> 4.8181774e+08 | CD5: =F5 -> California | CE5: =BB5 -> 0.70986754 | CF5: =AC5/CC5 -> 0.46670967
A6: 5000000015801 | B6: 2019 | C6: 39 | D6: plan134_y2021 | E6: 6 | F6: California | G6: California State Teachers Retirement System | H6: CalSTRS | I6: TRUE | J6: 7055000 | K6: 22458000 | L6: 32000 | M6: -1847000 | N6: 0 | O6: 15296000 | Q6: 12402000 | R6: 316776000 | S6: 329178000 | T6: 5644000 | U6: 5335000 | V6: 3648000 | W6: 14898000 | Y6: 254000 | Z6: 4000 | AA6: 13993000 | AB6: 224869000 | AC6: 238862000 | AD6: 90316000 | AE6: 91907000 | AF6: -1591000 | AG6: 35805000 | AH6: 0.15763162 | AI6: TRUE | AK6: 0.071 | AL6: 0.071 | AM6: 0.071 | AN6: 0.071 | AO6: 1 | AP6: 0 | AS6: 134488000 | AT6: 53689000 | AU6: p86 of CAFR | AV6: https://www.calstrs.com/sites/main/files/file-attachments/cafr2019.pdf | BB6: =AC6/S6 -> 0.72563173 | BD6: =AS6-AD6 -> 44172000 | BE6: =AT6-AD6 -> -36627000 | BF6: =BD6/S6*100 -> 13.41888 | BG6: =BE6/S6*100 -> -11.126807 | BH6: =(BD6-BE6)/(2*S6)*100 -> 12.272843 | BI6: =(BD6+BE6)/(2*S6*(0.01^2)) -> 114.60365 | BJ6: =ROUND(BH6,0) -> 12 | BK6: =IF($BJ6<=30,IF($B6=2015,VLOOKUP($BJ6,'Treasury Yields'!$C$5:$N$34,$E6,FALSE)/100,IF($B6=2016,VLOOKUP($BJ6,'Treasury Yields'!$C$40:$N$69,$E6,FALSE)/100,IF($B6=2017,VLOOKUP($BJ6,'Treasury Yields'!$C$75:$N$104,$E6,FALSE)/100,IF($B6=2018,VLOOKUP($BJ6,'Treasury Yields'!$C$110:$N$139,$E6,FALSE)/100,IF($B6=2019,VLOOKUP($BJ6,'Treasury Yields'!$C$145:$N$174,$E6,FALSE)/100,IF($B6=2020,VLOOKUP($BJ6,'Treasury Yields'!$C$180:$N$209,$E6,FALSE)/100,IF($B6=2021,VLOOKUP($BJ6,'Treasury Yields'!$C$215:$N$244,$E6,FALSE)/100,IF($B6=2022,VLOOKUP($BJ6,'Treasury Yields'!$C$250:$N$279,$E6,FALSE)/100)))))))),0) -> 0.028906473 | BL6: =1+BH6*(AL6-BK6)+(AL6-BK6)^2 -> 1.5183791 | BM6: =BL6*R6 -> 4.8098607e+08 | BN6: =BM6-AB6 -> 2.5611707e+08 | BP6: =IF($BJ6<=30,IF($B6=2015,VLOOKUP($BJ6,'Treasury Yields'!$C$40:$N$69,$E6,FALSE)/100,IF($B6=2016,VLOOKUP($BJ6,'Treasury Yields'!$C$75:$N$104,$E6,FALSE)/100,IF($B6=2017,VLOOKUP($BJ6,'Treasury Yields'!$C$110:$N$139,$E6,FALSE)/100,IF($B6=2018,VLOOKUP($BJ6,'Treasury Yields'!$C$145:$N$174,$E6,FALSE)/100,IF($B6=2019,VLOOKUP($BJ6,'Treasury Yields'!$C$180:$N$209,$E6,FALSE)/100,IF($B6=2020,VLOOKUP($BJ6,'Treasury Yields'!$C$215:$N$244,$E6,FALSE)/100,IF($B6=2021,VLOOKUP($BJ6,'Treasury Yields'!$C$250:$N$279,$E6,FALSE)/100,IF($B6=2022,VLOOKUP($BJ6,'Treasury Yields'!$C$285:$N$314,$E6,FALSE)/100)))))))),0) -> 0.022184 | BQ6: =1+BH6*(AN6-BP6)+(AN6-BP6)^2 -> 1.6014941 | BR6: =BQ6*S6 -> 5.2717663e+08 | BS6: =BR6-AC6 -> 2.8831463e+08 | BU6: =IF(BJ6="","",ROUND(BJ6+$BT$2,0)) -> 15 | BV6: =1+(BH6+BU6)*(AN6-BK6)+(AN6-BK6)^2*BI6 -> 2.3510724 | BW6: =BV6*J6 -> 16586816 | BX6: =(BM6+BW6-O6)*BK6 -> 13940924 | BY6: =BK6*(BN6+BW6-O6) -> 7440753.9 | BZ6: =SUM(J6:K6) -> 29513000 | CA6: =SUM(BW6+BY6) -> 24027570 | CC6: =BR6 -> 5.2717663e+08 | CD6: =F6 -> California | CE6: =BB6 -> 0.72563173 | CF6: =AC6/CC6 -> 0.45309672
A7: 5000000015801 | B7: 2020 | C7: 39 | D7: plan134_y2021 | E7: 6 | F7: California | G7: California State Teachers Retirement System | H7: CalSTRS | I7: TRUE | J7: 7340000 | K7: 23334000 | M7: -963000 | N7: 1029000 | O7: 16025000 | Q7: 14715000 | R7: 329178000 | S7: 343893000 | T7: 6080000 | U7: 4447000 | V7: 3735000 | W7: 10103000 | Y7: 219000 | Z7: 5000 | AA7: 8122000 | AB7: 238862000 | AC7: 246984000 | AD7: 96909000 | AE7: 90316000 | AF7: 6593000 | AG7: 36668000 | AH7: 0.16581215 | AI7: TRUE | AK7: 0.071 | AL7: 0.071 | AM7: 0.071 | AN7: 0.071 | AO7: 1 | AP7: 0 | AS7: 146416000 | AT7: 56034000 | AU7: p83 of CAFR | AV7: https://www.calstrs.com/sites/main/files/file-attachments/cafr2020.pdf | BB7: =AC7/S7 -> 0.71820014 | BD7: =AS7-AD7 -> 49507000 | BE7: =AT7-AD7 -> -40875000 | BF7: =BD7/S7*100 -> 14.396048 | BG7: =BE7/S7*100 -> -11.885965 | BH7: =(BD7-BE7)/(2*S7)*100 -> 13.141006 | BI7: =(BD7+BE7)/(2*S7*(0.01^2)) -> 125.50415 | BJ7: =ROUND(BH7,0) -> 13 | BK7: =IF($BJ7<=30,IF($B7=2015,VLOOKUP($BJ7,'Treasury Yields'!$C$5:$N$34,$E7,FALSE)/100,IF($B7=2016,VLOOKUP($BJ7,'Treasury Yields'!$C$40:$N$69,$E7,FALSE)/100,IF($B7=2017,VLOOKUP($BJ7,'Treasury Yields'!$C$75:$N$104,$E7,FALSE)/100,IF($B7=2018,VLOOKUP($BJ7,'Treasury Yields'!$C$110:$N$139,$E7,FALSE)/100,IF($B7=2019,VLOOKUP($BJ7,'Treasury Yields'!$C$145:$N$174,$E7,FALSE)/100,IF($B7=2020,VLOOKUP($BJ7,'Treasury Yields'!$C$180:$N$209,$E7,FALSE)/100,IF($B7=2021,VLOOKUP($BJ7,'Treasury Yields'!$C$215:$N$244,$E7,FALSE)/100,IF($B7=2022,VLOOKUP($BJ7,'Treasury Yields'!$C$250:$N$279,$E7,FALSE)/100)))))))),0) -> 0.022646 | BL7: =1+BH7*(AL7-BK7)+(AL7-BK7)^2 -> 1.6377583 | BM7: =BL7*R7 -> 5.3911401e+08 | BN7: =BM7-AB7 -> 3.0025201e+08 | BP7: =IF($BJ7<=30,IF($B7=2015,VLOOKUP($BJ7,'Treasury Yields'!$C$40:$N$69,$E7,FALSE)/100,IF($B7=2016,VLOOKUP($BJ7,'Treasury Yields'!$C$75:$N$104,$E7,FALSE)/100,IF($B7=2017,VLOOKUP($BJ7,'Treasury Yields'!$C$110:$N$139,$E7,FALSE)/100,IF($B7=2018,VLOOKUP($BJ7,'Treasury Yields'!$C$145:$N$174,$E7,FALSE)/100,IF($B7=2019,VLOOKUP($BJ7,'Treasury Yields'!$C$180:$N$209,$E7,FALSE)/100,IF($B7=2020,VLOOKUP($BJ7,'Treasury Yields'!$C$215:$N$244,$E7,FALSE)/100,IF($B7=2021,VLOOKUP($BJ7,'Treasury Yields'!$C$250:$N$279,$E7,FALSE)/100,IF($B7=2022,VLOOKUP($BJ7,'Treasury Yields'!$C$285:$N$314,$E7,FALSE)/100)))))))),0) -> 0.012827818 | BQ7: =1+BH7*(AN7-BP7)+(AN7-BP7)^2 -> 1.767825 | BR7: =BQ7*S7 -> 6.0794264e+08 | BS7: =BR7-AC7 -> 3.6095864e+08 | BU7: =IF(BJ7="","",ROUND(BJ7+$BT$2,0)) -> 16 | BV7: =1+(BH7+BU7)*(AN7-BK7)+(AN7-BK7)^2*BI7 -> 2.7025266 | BW7: =BV7*J7 -> 19836546 | BX7: =(BM7+BW7-O7)*BK7 -> 12295092 | BY7: =BK7*(BN7+BW7-O7) -> 6885823.2 | BZ7: =SUM(J7:K7) -> 30674000 | CA7: =SUM(BW7+BY7) -> 26722369 | CC7: =BR7 -> 6.0794264e+08 | CD7: =F7 -> California | CE7: =BB7 -> 0.71820014 | CF7: =AC7/CC7 -> 0.40626201
A8: 5000000015801 | B8: 2021 | C8: 39 | D8: plan134_y2021 | E8: 6 | F8: California | G8: California State Teachers Retirement System | H8: CalSTRS | I8: TRUE | J8: 7612000 | K8: 24373000 | M8: -3369000 | O8: 16708000 | Q8: 11908000 | R8: 343893000 | S8: 355801000 | T8: 5758000 | U8: 3731000 | V8: 3743000 | W8: 67039000 | Y8: 252000 | Z8: 2000 | AA8: 63309000 | AB8: 246984000 | AC8: 310293000 | AD8: 45508000 | AE8: 96909000 | AF8: -51401000 | AG8: 36737000 | AI8: TRUE | AK8: 0.071 | AL8: 0.071 | AM8: 0.071 | AN8: 0.071 | AS8: 92638000 | AT8: 6391000 | BB8: =AC8/S8 -> 0.87209704 | BD8: =AS8-AD8 -> 47130000 | BE8: =AT8-AD8 -> -39117000 | BF8: =BD8/S8*100 -> 13.246169 | BG8: =BE8/S8*100 -> -10.994067 | BH8: =(BD8-BE8)/(2*S8)*100 -> 12.120118 | BI8: =(BD8+BE8)/(2*S8*(0.01^2)) -> 112.60508 | BJ8: =ROUND(BH8,0) -> 12 | BK8: =IF($BJ8<=30,IF($B8=2015,VLOOKUP($BJ8,'Treasury Yields'!$C$5:$N$34,$E8,FALSE)/100,IF($B8=2016,VLOOKUP($BJ8,'Treasury Yields'!$C$40:$N$69,$E8,FALSE)/100,IF($B8=2017,VLOOKUP($BJ8,'Treasury Yields'!$C$75:$N$104,$E8,FALSE)/100,IF($B8=2018,VLOOKUP($BJ8,'Treasury Yields'!$C$110:$N$139,$E8,FALSE)/100,IF($B8=2019,VLOOKUP($BJ8,'Treasury Yields'!$C$145:$N$174,$E8,FALSE)/100,IF($B8=2020,VLOOKUP($BJ8,'Treasury Yields'!$C$180:$N$209,$E8,FALSE)/100,IF($B8=2021,VLOOKUP($BJ8,'Treasury Yields'!$C$215:$N$244,$E8,FALSE)/100,IF($B8=2022,VLOOKUP($BJ8,'Treasury Yields'!$C$250:$N$279,$E8,FALSE)/100)))))))),0) -> 0.013689455 | BL8: =1+BH8*(AL8-BK8)+(AL8-BK8)^2 -> 1.6978951 | BM8: =BL8*R8 -> 5.8389422e+08 | BN8: =BM8-AB8 -> 3.3691022e+08 | BP8: =IF($BJ8<=30,IF($B8=2015,VLOOKUP($BJ8,'Treasury Yields'!$C$40:$N$69,$E8,FALSE)/100,IF($B8=2016,VLOOKUP($BJ8,'Treasury Yields'!$C$75:$N$104,$E8,FALSE)/100,IF($B8=2017,VLOOKUP($BJ8,'Treasury Yields'!$C$110:$N$139,$E8,FALSE)/100,IF($B8=2018,VLOOKUP($BJ8,'Treasury Yields'!$C$145:$N$174,$E8,FALSE)/100,IF($B8=2019,VLOOKUP($BJ8,'Treasury Yields'!$C$180:$N$209,$E8,FALSE)/100,IF($B8=2020,VLOOKUP($BJ8,'Treasury Yields'!$C$215:$N$244,$E8,FALSE)/100,IF($B8=2021,VLOOKUP($BJ8,'Treasury Yields'!$C$250:$N$279,$E8,FALSE)/100,IF($B8=2022,VLOOKUP($BJ8,'Treasury Yields'!$C$285:$N$314,$E8,FALSE)/100)))))))),0) -> 0.021085818 | BQ8: =1+BH8*(AN8-BP8)+(AN8-BP8)^2 -> 1.6074572 | BR8: =BQ8*S8 -> 5.7193487e+08 | BS8: =BR8-AC8 -> 2.6164187e+08 | BU8: =IF(BJ8="","",ROUND(BJ8+$BT$2,0)) -> 15 | BV8: =1+(BH8+BU8)*(AN8-BK8)+(AN8-BK8)^2*BI8 -> 2.92412 | BW8: =BV8*J8 -> 22258401 | BX8: =(BM8+BW8-O8)*BK8 -> 8069175.4 | BY8: =BK8*(BN8+BW8-O8) -> 4688099.2 | BZ8: =SUM(J8:K8) -> 31985000 | CA8: =SUM(BW8+BY8) -> 26946500 | CC8: =BR8 -> 5.7193487e+08 | CD8: =F8 -> California | CE8: =BB8 -> 0.87209704 | CF8: =AC8/CC8 -> 0.54253205
A9: 5000000015801 | B9: 2022 | C9: 39 | D9: plan134_y2021 | E9: 6 | F9: California | G9: California State Teachers Retirement System | H9: CalSTRS | I9: TRUE | J9: 7675000 | K9: 25196000 | L9: 70000 | M9: -1673000 | N9: 0 | O9: 17527000 | Q9: 13741000 | R9: 355801000 | S9: 369542000 | T9: 6521000 | U9: 4280000 | V9: 4068000 | W9: -7390000 | Y9: 191000 | Z9: 5000 | AA9: -10237000 | AB9: 310293000 | AC9: 300056000 | AD9: 69486000 | AE9: 45508000 | AF9: 23978000 | AG9: 40103000 | AI9: TRUE | AK9: 0.071 | AL9: 0.071 | AM9: 0.071 | AN9: 0.071 | AS9: 118013000 | AT9: 29194000 | AU9: p78 of CAFR | AV9: https://www.calstrs.com/files/621ec3ae1/ACFR2021-22.pdf | BB9: =AC9/S9 -> 0.81196725 | BD9: =AS9-AD9 -> 48527000 | BE9: =AT9-AD9 -> -40292000 | BF9: =BD9/S9*100 -> 13.13166 | BG9: =BE9/S9*100 -> -10.903226 | BH9: =(BD9-BE9)/(2*S9)*100 -> 12.017443 | BI9: =(BD9+BE9)/(2*S9*(0.01^2)) -> 111.42171 | BJ9: =ROUND(BH9,0) -> 12 | BK9: =IF($BJ9<=30,IF($B9=2015,VLOOKUP($BJ9,'Treasury Yields'!$C$5:$N$34,$E9,FALSE)/100,IF($B9=2016,VLOOKUP($BJ9,'Treasury Yields'!$C$40:$N$69,$E9,FALSE)/100,IF($B9=2017,VLOOKUP($BJ9,'Treasury Yields'!$C$75:$N$104,$E9,FALSE)/100,IF($B9=2018,VLOOKUP($BJ9,'Treasury Yields'!$C$110:$N$139,$E9,FALSE)/100,IF($B9=2019,VLOOKUP($BJ9,'Treasury Yields'!$C$145:$N$174,$E9,FALSE)/100,IF($B9=2020,VLOOKUP($BJ9,'Treasury Yields'!$C$180:$N$209,$E9,FALSE)/100,IF($B9=2021,VLOOKUP($BJ9,'Treasury Yields'!$C$215:$N$244,$E9,FALSE)/100,IF($B9=2022,VLOOKUP($BJ9,'Treasury Yields'!$C$250:$N$279,$E9,FALSE)/100)))))))),0) -> 0.021085818 | BL9: =1+BH9*(AL9-BK9)+(AL9-BK9)^2 -> 1.6023323 | BM9: =BL9*R9 -> 5.7011142e+08 | BN9: =BM9-AB9 -> 2.5981842e+08 | BP9: =IF($BJ9<=30,IF($B9=2015,VLOOKUP($BJ9,'Treasury Yields'!$C$40:$N$69,$E9,FALSE)/100,IF($B9=2016,VLOOKUP($BJ9,'Treasury Yields'!$C$75:$N$104,$E9,FALSE)/100,IF($B9=2017,VLOOKUP($BJ9,'Treasury Yields'!$C$110:$N$139,$E9,FALSE)/100,IF($B9=2018,VLOOKUP($BJ9,'Treasury Yields'!$C$145:$N$174,$E9,FALSE)/100,IF($B9=2019,VLOOKUP($BJ9,'Treasury Yields'!$C$180:$N$209,$E9,FALSE)/100,IF($B9=2020,VLOOKUP($BJ9,'Treasury Yields'!$C$215:$N$244,$E9,FALSE)/100,IF($B9=2021,VLOOKUP($BJ9,'Treasury Yields'!$C$250:$N$279,$E9,FALSE)/100,IF($B9=2022,VLOOKUP($BJ9,'Treasury Yields'!$C$285:$N$314,$E9,FALSE)/100)))))))),0) -> 0.032402273 | BQ9: =1+BH9*(AN9-BP9)+(AN9-BP9)^2 -> 1.4653358 | BR9: =BQ9*S9 -> 5.4150311e+08 | BS9: =BR9-AC9 -> 2.4144711e+08 | BU9: =IF(BJ9="","",ROUND(BJ9+$BT$2,0)) -> 15 | BV9: =1+(BH9+BU9)*(AN9-BK9)+(AN9-BK9)^2*BI9 -> 2.6261525 | BW9: =BV9*J9 -> 20155720 | BX9: =(BM9+BW9-O9)*BK9 -> 12076695 | BY9: =BK9*(BN9+BW9-O9) -> 5533912.8 | BZ9: =SUM(J9:K9) -> 32871000 | CA9: =SUM(BW9+BY9) -> 25689633 | CC9: =BR9 -> 5.4150311e+08 | CD9: =F9 -> California | CE9: =BB9 -> 0.81196725 | CF9: =AC9/CC9 -> 0.55411685
A10: 44000000011101 | B10: 2015 | C10: 569 | D10: plan314_y2021 | E10: 8 | F10: Texas | G10: Teachers Retirement System of Texas | H10: TRS | I10: TRUE | J10: 4225449 | K10: 12555646 | M10: -1588619 | N10: -1474724 | O10: 8935112 | P10: 391341 | Q10: 4391299 | R10: 159496076 | S10: 163887375 | T10: 1377973 | U10: 1591483 | V10: 2576024 | W10: -412759 | Y10: 35557 | Z10: -11248 | AA10: -4240537 | AB10: 132779243 | AC10: 128538706 | AD10: 35348669 | AE10: 26716833 | AF10: 8631836 | AG10: 38448124 | AH10: 0.035839798 | AI10: TRUE | AK10: 0.08 | AL10: 0.08 | AM10: 0.08 | AN10: 0.08 | AO10: 1 | AP10: 0 | AS10: 55384702 | AT10: 18659899 | BB10: =AC10/S10 -> 0.78431121 | BD10: =AS10-AD10 -> 20036033 | BE10: =AT10-AD10 -> -16688770 | BF10: =BD10/S10*100 -> 12.225489 | BG10: =BE10/S10*100 -> -10.183072 | BH10: =(BD10-BE10)/(2*S10)*100 -> 11.204281 | BI10: =(BD10+BE10)/(2*S10*(0.01^2)) -> 102.12082 | BJ10: =ROUND(BH10,0) -> 11 | BK10: =IF($BJ10<=30,IF($B10=2015,VLOOKUP($BJ10,'Treasury Yields'!$C$5:$N$34,$E10,FALSE)/100,IF($B10=2016,VLOOKUP($BJ10,'Treasury Yields'!$C$40:$N$69,$E10,FALSE)/100,IF($B10=2017,VLOOKUP($BJ10,'Treasury Yields'!$C$75:$N$104,$E10,FALSE)/100,IF($B10=2018,VLOOKUP($BJ10,'Treasury Yields'!$C$110:$N$139,$E10,FALSE)/100,IF($B10=2019,VLOOKUP($BJ10,'Treasury Yields'!$C$145:$N$174,$E10,FALSE)/100,IF($B10=2020,VLOOKUP($BJ10,'Treasury Yields'!$C$180:$N$209,$E10,FALSE)/100,IF($B10=2021,VLOOKUP($BJ10,'Treasury Yields'!$C$215:$N$244,$E10,FALSE)/100,IF($B10=2022,VLOOKUP($BJ10,'Treasury Yields'!$C$250:$N$279,$E10,FALSE)/100)))))))),0) -> 0.024838 | BL10: =1+BH10*(AL10-BK10)+(AL10-BK10)^2 -> 1.6210934 | BM10: =BL10*R10 -> 2.5855803e+08 | BN10: =BM10-AB10 -> 1.2577879e+08 | BP10: =IF($BJ10<=30,IF($B10=2015,VLOOKUP($BJ10,'Treasury Yields'!$C$40:$N$69,$E10,FALSE)/100,IF($B10=2016,VLOOKUP($BJ10,'Treasury Yields'!$C$75:$N$104,$E10,FALSE)/100,IF($B10=2017,VLOOKUP($BJ10,'Treasury Yields'!$C$110:$N$139,$E10,FALSE)/100,IF($B10=2018,VLOOKUP($BJ10,'Treasury Yields'!$C$145:$N$174,$E10,FALSE)/100,IF($B10=2019,VLOOKUP($BJ10,'Treasury Yields'!$C$180:$N$209,$E10,FALSE)/100,IF($B10=2020,VLOOKUP($BJ10,'Treasury Yields'!$C$215:$N$244,$E10,FALSE)/100,IF($B10=2021,VLOOKUP($BJ10,'Treasury Yields'!$C$250:$N$279,$E10,FALSE)/100,IF($B10=2022,VLOOKUP($BJ10,'Treasury Yields'!$C$285:$N$314,$E10,FALSE)/100)))))))),0) -> 0.024838 | BQ10: =1+BH10*(AN10-BP10)+(AN10-BP10)^2 -> 1.6210934 | BR10: =BQ10*S10 -> 2.6567674e+08 | BS10: =BR10-AC10 -> 1.3713803e+08 | BU10: =IF(BJ10="","",ROUND(BJ10+$BT$2,0)) -> 14 | BV10: =1+(BH10+BU10)*(AN10-BK10)+(AN10-BK10)^2*BI10 -> 2.7010565 | BW10: =BV10*J10 -> 11413176 | BX10: =(BM10+BW10-O10)*BK10 -> 6483614.6 | BY10: =BK10*(BN10+BW10-O10) -> 3185643.7 | BZ10: =SUM(J10:K10) -> 16781095 | CA10: =SUM(BW10+BY10) -> 14598820 | CC10: =BR10 -> 2.6567674e+08 | CD10: =F10 -> Texas | CE10: =BB10 -> 0.78431121 | CF10: =AC10/CC10 -> 0.48381619
A11: 44000000011101 | B11: 2016 | C11: 569 | D11: plan314_y2021 | E11: 8 | F11: Texas | G11: Teachers Retirement System of Texas | H11: TRS | I11: TRUE | J11: 4392077 | K11: 12896571 | M11: 373669 | O11: 9379123 | P11: 373419 | Q11: 7909775 | R11: 163887375 | S11: 171797150 | T11: 1483390 | U11: 1675631 | V11: 2943669 | W11: 9193281 | Y11: 44403 | Z11: -29095 | AA11: 5469931 | AB11: 128538706 | AC11: 134008637 | AD11: 37788513 | AE11: 35348669 | AF11: 2439844 | AG11: 40742826 | AH11: 0.036408618 | AI11: TRUE | AK11: 0.08 | AL11: 0.08 | AM11: 0.08 | AN11: 0.08 | AO11: 1 | AP11: 0 | AS11: 58483889 | AT11: 20234651 | AU11: p88 of CAFR | AV11: https://www.trs.texas.gov/TRS%20Documents/cafr_2016.pdf | BB11: =AC11/S11 -> 0.78003993 | BD11: =AS11-AD11 -> 20695376 | BE11: =AT11-AD11 -> -17553862 | BF11: =BD11/S11*100 -> 12.046402 | BG11: =BE11/S11*100 -> -10.217784 | BH11: =(BD11-BE11)/(2*S11)*100 -> 11.132093 | BI11: =(BD11+BE11)/(2*S11*(0.01^2)) -> 91.430911 | BJ11: =ROUND(BH11,0) -> 11 | BK11: =IF($BJ11<=30,IF($B11=2015,VLOOKUP($BJ11,'Treasury Yields'!$C$5:$N$34,$E11,FALSE)/100,IF($B11=2016,VLOOKUP($BJ11,'Treasury Yields'!$C$40:$N$69,$E11,FALSE)/100,IF($B11=2017,VLOOKUP($BJ11,'Treasury Yields'!$C$75:$N$104,$E11,FALSE)/100,IF($B11=2018,VLOOKUP($BJ11,'Treasury Yields'!$C$110:$N$139,$E11,FALSE)/100,IF($B11=2019,VLOOKUP($BJ11,'Treasury Yields'!$C$145:$N$174,$E11,FALSE)/100,IF($B11=2020,VLOOKUP($BJ11,'Treasury Yields'!$C$180:$N$209,$E11,FALSE)/100,IF($B11=2021,VLOOKUP($BJ11,'Treasury Yields'!$C$215:$N$244,$E11,FALSE)/100,IF($B11=2022,VLOOKUP($BJ11,'Treasury Yields'!$C$250:$N$279,$E11,FALSE)/100)))))))),0) -> 0.024838 | BL11: =1+BH11*(AL11-BK11)+(AL11-BK11)^2 -> 1.6171114 | BM11: =BL11*R11 -> 2.6502414e+08 | BN11: =BM11-AB11 -> 1.3648543e+08 | BP11: =IF($BJ11<=30,IF($B11=2015,VLOOKUP($BJ11,'Treasury Yields'!$C$40:$N$69,$E11,FALSE)/100,IF($B11=2016,VLOOKUP($BJ11,'Treasury Yields'!$C$75:$N$104,$E11,FALSE)/100,IF($B11=2017,VLOOKUP($BJ11,'Treasury Yields'!$C$110:$N$139,$E11,FALSE)/100,IF($B11=2018,VLOOKUP($BJ11,'Treasury Yields'!$C$145:$N$174,$E11,FALSE)/100,IF($B11=2019,VLOOKUP($BJ11,'Treasury Yields'!$C$180:$N$209,$E11,FALSE)/100,IF($B11=2020,VLOOKUP($BJ11,'Treasury Yields'!$C$215:$N$244,$E11,FALSE)/100,IF($B11=2021,VLOOKUP($BJ11,'Treasury Yields'!$C$250:$N$279,$E11,FALSE)/100,IF($B11=2022,VLOOKUP($BJ11,'Treasury Yields'!$C$285:$N$314,$E11,FALSE)/100)))))))),0) -> 0.017736 | BQ11: =1+BH11*(AN11-BP11)+(AN11-BP11)^2 -> 1.6970055 | BR11: =BQ11*S11 -> 2.915407e+08 | BS11: =BR11-AC11 -> 1.5753206e+08 | BU11: =IF(BJ11="","",ROUND(BJ11+$BT$2,0)) -> 14 | BV11: =1+(BH11+BU11)*(AN11-BK11)+(AN11-BK11)^2*BI11 -> 2.6645467 | BW11: =BV11*J11 -> 11702894 | BX11: =(BM11+BW11-O11)*BK11 -> 6640387.4 | BY11: =BK11*(BN11+BW11-O11) -> 3447743 | BZ11: =SUM(J11:K11) -> 17288648 | CA11: =SUM(BW11+BY11) -> 15150637 | CC11: =BR11 -> 2.915407e+08 | CD11: =F11 -> Texas | CE11: =BB11 -> 0.78003993 | CF11: =AC11/CC11 -> 0.4596567
A12: 44000000011101 | B12: 2017 | C12: 569 | D12: plan314_y2021 | E12: 8 | F12: Texas | G12: Teachers Retirement System of Texas | H12: TRS | I12: TRUE | J12: 4489046 | K12: 13515486 | M12: -969831 | N12: 700880 | O12: 9775775 | P12: 420421 | Q12: 7539385 | R12: 171797150 | S12: 179336535 | T12: 1588309 | U12: 1697963 | V12: 3242556 | W12: 17079807 | Y12: 44190 | Z12: -14964 | AA12: 13353285 | AB12: 134008637 | AC12: 147361922 | AD12: 31974613 | AE12: 37788513 | AF12: -5813900 | AG12: 42111120 | AH12: 0.037717092 | AI12: TRUE | AJ12: 1 | AK12: 0.08 | AL12: 0.08 | AM12: 0.08 | AN12: 0.08 | AO12: 1 | AP12: 0 | AS12: 53902880 | AT12: 13715772 | AU12: p94 of CAFR | AV12: https://www.trs.texas.gov/TRS%20Documents/cafr_2017.pdf | BB12: =AC12/S12 -> 0.82170608 | BD12: =AS12-AD12 -> 21928267 | BE12: =AT12-AD12 -> -18258841 | BF12: =BD12/S12*100 -> 12.22744 | BG12: =BE12/S12*100 -> -10.181328 | BH12: =(BD12-BE12)/(2*S12)*100 -> 11.204384 | BI12: =(BD12+BE12)/(2*S12*(0.01^2)) -> 102.30559 | BJ12: =ROUND(BH12,0) -> 11 | BK12: =IF($BJ12<=30,IF($B12=2015,VLOOKUP($BJ12,'Treasury Yields'!$C$5:$N$34,$E12,FALSE)/100,IF($B12=2016,VLOOKUP($BJ12,'Treasury Yields'!$C$40:$N$69,$E12,FALSE)/100,IF($B12=2017,VLOOKUP($BJ12,'Treasury Yields'!$C$75:$N$104,$E12,FALSE)/100,IF($B12=2018,VLOOKUP($BJ12,'Treasury Yields'!$C$110:$N$139,$E12,FALSE)/100,IF($B12=2019,VLOOKUP($BJ12,'Treasury Yields'!$C$145:$N$174,$E12,FALSE)/100,IF($B12=2020,VLOOKUP($BJ12,'Treasury Yields'!$C$180:$N$209,$E12,FALSE)/100,IF($B12=2021,VLOOKUP($BJ12,'Treasury Yields'!$C$215:$N$244,$E12,FALSE)/100,IF($B12=2022,VLOOKUP($BJ12,'Treasury Yields'!$C$250:$N$279,$E12,FALSE)/100)))))))),0) -> 0.017736 | BL12: =1+BH12*(AL12-BK12)+(AL12-BK12)^2 -> 1.7015066 | BM12: =BL12*R12 -> 2.9231398e+08 | BN12: =BM12-AB12 -> 1.5830534e+08 | BP12: =IF($BJ12<=30,IF($B12=2015,VLOOKUP($BJ12,'Treasury Yields'!$C$40:$N$69,$E12,FALSE)/100,IF($B12=2016,VLOOKUP($BJ12,'Treasury Yields'!$C$75:$N$104,$E12,FALSE)/100,IF($B12=2017,VLOOKUP($BJ12,'Treasury Yields'!$C$110:$N$139,$E12,FALSE)/100,IF($B12=2018,VLOOKUP($BJ12,'Treasury Yields'!$C$145:$N$174,$E12,FALSE)/100,IF($B12=2019,VLOOKUP($BJ12,'Treasury Yields'!$C$180:$N$209,$E12,FALSE)/100,IF($B12=2020,VLOOKUP($BJ12,'Treasury Yields'!$C$215:$N$244,$E12,FALSE)/100,IF($B12=2021,VLOOKUP($BJ12,'Treasury Yields'!$C$250:$N$279,$E12,FALSE)/100,IF($B12=2022,VLOOKUP($BJ12,'Treasury Yields'!$C$285:$N$314,$E12,FALSE)/100)))))))),0) -> 0.0229824 | BQ12: =1+BH12*(AN12-BP12)+(AN12-BP12)^2 -> 1.6420981 | BR12: =BQ12*S12 -> 2.9448818e+08 | BS12: =BR12-AC12 -> 1.4712626e+08 | BU12: =IF(BJ12="","",ROUND(BJ12+$BT$2,0)) -> 14 | BV12: =1+(BH12+BU12)*(AN12-BK12)+(AN12-BK12)^2*BI12 -> 2.9659447 | BW12: =BV12*J12 -> 13314262 | BX12: =(BM12+BW12-O12)*BK12 -> 5247239.3 | BY12: =BK12*(BN12+BW12-O12) -> 2870462.2 | BZ12: =SUM(J12:K12) -> 18004532 | CA12: =SUM(BW12+BY12) -> 16184724 | CC12: =BR12 -> 2.9448818e+08 | CD12: =F12 -> Texas | CE12: =BB12 -> 0.82170608 | CF12: =AC12/CC12 -> 0.50040012
A13: 44000000011101 | B13: 2018 | C13: 569 | D13: plan314_y2021 | E13: 8 | F13: Texas | G13: Teachers Retirement System of Texas | H13: TRS | I13: TRUE | J13: 4654171 | K13: 14109277 | M13: 0 | N13: 22106679 | O13: 10172997 | P13: 422336 | Q13: 30274794 | R13: 179336535 | S13: 209611329 | T13: 1671257 | U13: 1715785 | V13: 3360773 | W13: 11242814 | Y13: 64926 | Z13: -123390 | AA13: 7206980 | AB13: 147361922 | AC13: 154568902 | AD13: 55042427 | AE13: 31974613 | AF13: 23067814 | AG13: 43646405 | AH13: 0.038290828 | AI13: TRUE | AJ13: 1 | AK13: 0.08 | AL13: 0.06907 | AM13: 0.0725 | AN13: 0.08 | AO13: 1 | AP13: 0.00343 | AS13: 83072221 | AT13: 32350646 | AU13: p82 of CAFR | AV13: https://www.trs.texas.gov/TRS%20Documents/cafr_2018.pdf | BB13: =AC13/S13 -> 0.73740719 | BD13: =AS13-AD13 -> 28029794 | BE13: =AT13-AD13 -> -22691781 | BF13: =BD13/S13*100 -> 13.372271 | BG13: =BE13/S13*100 -> -10.825646 | BH13: =(BD13-BE13)/(2*S13)*100 -> 12.098958 | BI13: =(BD13+BE13)/(2*S13*(0.01^2)) -> 127.33121 | BJ13: =ROUND(BH13,0) -> 12 | BK13: =IF($BJ13<=30,IF($B13=2015,VLOOKUP($BJ13,'Treasury Yields'!$C$5:$N$34,$E13,FALSE)/100,IF($B13=2016,VLOOKUP($BJ13,'Treasury Yields'!$C$40:$N$69,$E13,FALSE)/100,IF($B13=2017,VLOOKUP($BJ13,'Treasury Yields'!$C$75:$N$104,$E13,FALSE)/100,IF($B13=2018,VLOOKUP($BJ13,'Treasury Yields'!$C$110:$N$139,$E13,FALSE)/100,IF($B13=2019,VLOOKUP($BJ13,'Treasury Yields'!$C$145:$N$174,$E13,FALSE)/100,IF($B13=2020,VLOOKUP($BJ13,'Treasury Yields'!$C$180:$N$209,$E13,FALSE)/100,IF($B13=2021,VLOOKUP($BJ13,'Treasury Yields'!$C$215:$N$244,$E13,FALSE)/100,IF($B13=2022,VLOOKUP($BJ13,'Treasury Yields'!$C$250:$N$279,$E13,FALSE)/100)))))))),0) -> 0.0233448 | BL13: =1+BH13*(AL13-BK13)+(AL13-BK13)^2 -> 1.5553181 | BM13: =BL13*R13 -> 2.7892536e+08 | BN13: =BM13-AB13 -> 1.3156343e+08 | BP13: =IF($BJ13<=30,IF($B13=2015,VLOOKUP($BJ13,'Treasury Yields'!$C$40:$N$69,$E13,FALSE)/100,IF($B13=2016,VLOOKUP($BJ13,'Treasury Yields'!$C$75:$N$104,$E13,FALSE)/100,IF($B13=2017,VLOOKUP($BJ13,'Treasury Yields'!$C$110:$N$139,$E13,FALSE)/100,IF($B13=2018,VLOOKUP($BJ13,'Treasury Yields'!$C$145:$N$174,$E13,FALSE)/100,IF($B13=2019,VLOOKUP($BJ13,'Treasury Yields'!$C$180:$N$209,$E13,FALSE)/100,IF($B13=2020,VLOOKUP($BJ13,'Treasury Yields'!$C$215:$N$244,$E13,FALSE)/100,IF($B13=2021,VLOOKUP($BJ13,'Treasury Yields'!$C$250:$N$279,$E13,FALSE)/100,IF($B13=2022,VLOOKUP($BJ13,'Treasury Yields'!$C$285:$N$314,$E13,FALSE)/100)))))))),0) -> 0.028935352 | BQ13: =1+BH13*(AN13-BP13)+(AN13-BP13)^2 -> 1.6204366 | BR13: =BQ13*S13 -> 3.3966188e+08 | BS13: =BR13-AC13 -> 1.8509298e+08 | BU13: =IF(BJ13="","",ROUND(BJ13+$BT$2,0)) -> 15 | BV13: =1+(BH13+BU13)*(AN13-BK13)+(AN13-BK13)^2*BI13 -> 2.9440061 | BW13: =BV13*J13 -> 13701908 | BX13: =(BM13+BW13-O13)*BK13 -> 6593838.4 | BY13: =BK13*(BN13+BW13-O13) -> 3153703.8 | BZ13: =SUM(J13:K13) -> 18763448 | CA13: =SUM(BW13+BY13) -> 16855612 | CC13: =BR13 -> 3.3966188e+08 | CD13: =F13 -> Texas | CE13: =BB13 -> 0.73740719 | CF13: =AC13/CC13 -> 0.45506697
A14: 44000000011101 | B14: 2019 | C14: 569 | D14: plan314_y2021 | E14: 8 | F14: Texas | G14: Teachers Retirement System of Texas | H14: TRS | I14: TRUE | J14: 5642075 | K14: 14267256 | M14: -982694 | N14: -7425279 | O14: 11253729 | P14: 486461 | Q14: 349996 | R14: 209611329 | S14: 209961325 | T14: 1761822 | U14: 1737852 | V14: 3482870 | W14: 7669029 | Y14: 60486 | Z14: 558400 | AA14: 3409297 | AB14: 154568902 | AC14: 157978199 | AD14: 51983126 | AE14: 55042427 | AF14: -3059301 | AG14: 45232074 | AH14: 0.038950723 | AI14: TRUE | AK14: 0.06907 | AL14: 0.0725 | AM14: 0.0725 | AN14: 0.0725 | AO14: 1 | AP14: 0 | AQ14: 0.0263 | AS14: 79905617 | AT14: 29360519 | AU14: p80 of CAFR | AV14: https://www.trs.texas.gov/TRS%20Documents/cafr_2019.pdf | BB14: =AC14/S14 -> 0.75241571 | BD14: =AS14-AD14 -> 27922491 | BE14: =AT14-AD14 -> -22622607 | BF14: =BD14/S14*100 -> 13.298873 | BG14: =BE14/S14*100 -> -10.774654 | BH14: =(BD14-BE14)/(2*S14)*100 -> 12.036764 | BI14: =(BD14+BE14)/(2*S14*(0.01^2)) -> 126.21096 | BJ14: =ROUND(BH14,0) -> 12 | BK14: =IF($BJ14<=30,IF($B14=2015,VLOOKUP($BJ14,'Treasury Yields'!$C$5:$N$34,$E14,FALSE)/100,IF($B14=2016,VLOOKUP($BJ14,'Treasury Yields'!$C$40:$N$69,$E14,FALSE)/100,IF($B14=2017,VLOOKUP($BJ14,'Treasury Yields'!$C$75:$N$104,$E14,FALSE)/100,IF($B14=2018,VLOOKUP($BJ14,'Treasury Yields'!$C$110:$N$139,$E14,FALSE)/100,IF($B14=2019,VLOOKUP($BJ14,'Treasury Yields'!$C$145:$N$174,$E14,FALSE)/100,IF($B14=2020,VLOOKUP($BJ14,'Treasury Yields'!$C$180:$N$209,$E14,FALSE)/100,IF($B14=2021,VLOOKUP($BJ14,'Treasury Yields'!$C$215:$N$244,$E14,FALSE)/100,IF($B14=2022,VLOOKUP($BJ14,'Treasury Yields'!$C$250:$N$279,$E14,FALSE)/100)))))))),0) -> 0.028935352 | BL14: =1+BH14*(AL14-BK14)+(AL14-BK14)^2 -> 1.5262753 | BM14: =BL14*R14 -> 3.1992459e+08 | BN14: =BM14-AB14 -> 1.6535568e+08 | BP14: =IF($BJ14<=30,IF($B14=2015,VLOOKUP($BJ14,'Treasury Yields'!$C$40:$N$69,$E14,FALSE)/100,IF($B14=2016,VLOOKUP($BJ14,'Treasury Yields'!$C$75:$N$104,$E14,FALSE)/100,IF($B14=2017,VLOOKUP($BJ14,'Treasury Yields'!$C$110:$N$139,$E14,FALSE)/100,IF($B14=2018,VLOOKUP($BJ14,'Treasury Yields'!$C$145:$N$174,$E14,FALSE)/100,IF($B14=2019,VLOOKUP($BJ14,'Treasury Yields'!$C$180:$N$209,$E14,FALSE)/100,IF($B14=2020,VLOOKUP($BJ14,'Treasury Yields'!$C$215:$N$244,$E14,FALSE)/100,IF($B14=2021,VLOOKUP($BJ14,'Treasury Yields'!$C$250:$N$279,$E14,FALSE)/100,IF($B14=2022,VLOOKUP($BJ14,'Treasury Yields'!$C$285:$N$314,$E14,FALSE)/100)))))))),0) -> 0.016946 | BQ14: =1+BH14*(AN14-BP14)+(AN14-BP14)^2 -> 1.6717766 | BR14: =BQ14*S14 -> 3.5100844e+08 | BS14: =BR14-AC14 -> 1.9303024e+08 | BU14: =IF(BJ14="","",ROUND(BJ14+$BT$2,0)) -> 15 | BV14: =1+(BH14+BU14)*(AN14-BK14)+(AN14-BK14)^2*BI14 -> 2.4173802 | BW14: =BV14*J14 -> 13639040 | BX14: =(BM14+BW14-O14)*BK14 -> 9326150.4 | BY14: =BK14*(BN14+BW14-O14) -> 4853644.8 | BZ14: =SUM(J14:K14) -> 19909331 | CA14: =SUM(BW14+BY14) -> 18492685 | CC14: =BR14 -> 3.5100844e+08 | CD14: =F14 -> Texas | CE14: =BB14 -> 0.75241571 | CF14: =AC14/CC14 -> 0.45006952
A15: 44000000011101 | B15: 2020 | C15: 569 | D15: plan314_y2021 | E15: 8 | F15: Texas | G15: Teachers Retirement System of Texas | H15: TRS | I15: TRUE | J15: 5651647 | K15: 15014048 | M15: -259157 | N15: 0 | O15: 10972292 | P15: 421366 | Q15: 9012880 | R15: 209961325 | S15: 218974205 | T15: 2016482 | U15: 2107999 | V15: 3736877 | W15: 11032131 | Y15: 67136 | Z15: -31435 | AA15: 7438046 | AB15: 157978199 | AC15: 165416245 | AD15: 53557960 | AE15: 51983126 | AF15: 1574834 | AG15: 48530876 | AH15: 0.041550497 | AI15: TRUE | AK15: 0.0725 | AL15: 0.0725 | AM15: 0.0725 | AN15: 0.0725 | AO15: 1 | AP15: 0 | AQ15: 0.0233 | AS15: 82585416 | AT15: 29973788 | AU15: p87 of CAFR | AV15: https://www.trs.texas.gov/TRS%20Documents/cafr_2020.pdf | BB15: =AC15/S15 -> 0.7554143 | BD15: =AS15-AD15 -> 29027456 | BE15: =AT15-AD15 -> -23584172 | BF15: =BD15/S15*100 -> 13.256107 | BG15: =BE15/S15*100 -> -10.770297 | BH15: =(BD15-BE15)/(2*S15)*100 -> 12.013202 | BI15: =(BD15+BE15)/(2*S15*(0.01^2)) -> 124.29053 | BJ15: =ROUND(BH15,0) -> 12 | BK15: =IF($BJ15<=30,IF($B15=2015,VLOOKUP($BJ15,'Treasury Yields'!$C$5:$N$34,$E15,FALSE)/100,IF($B15=2016,VLOOKUP($BJ15,'Treasury Yields'!$C$40:$N$69,$E15,FALSE)/100,IF($B15=2017,VLOOKUP($BJ15,'Treasury Yields'!$C$75:$N$104,$E15,FALSE)/100,IF($B15=2018,VLOOKUP($BJ15,'Treasury Yields'!$C$110:$N$139,$E15,FALSE)/100,IF($B15=2019,VLOOKUP($BJ15,'Treasury Yields'!$C$145:$N$174,$E15,FALSE)/100,IF($B15=2020,VLOOKUP($BJ15,'Treasury Yields'!$C$180:$N$209,$E15,FALSE)/100,IF($B15=2021,VLOOKUP($BJ15,'Treasury Yields'!$C$215:$N$244,$E15,FALSE)/100,IF($B15=2022,VLOOKUP($BJ15,'Treasury Yields'!$C$250:$N$279,$E15,FALSE)/100)))))))),0) -> 0.016946 | BL15: =1+BH15*(AL15-BK15)+(AL15-BK15)^2 -> 1.6704677 | BM15: =BL15*R15 -> 3.5073361e+08 | BN15: =BM15-AB15 -> 1.9275541e+08 | BP15: =IF($BJ15<=30,IF($B15=2015,VLOOKUP($BJ15,'Treasury Yields'!$C$40:$N$69,$E15,FALSE)/100,IF($B15=2016,VLOOKUP($BJ15,'Treasury Yields'!$C$75:$N$104,$E15,FALSE)/100,IF($B15=2017,VLOOKUP($BJ15,'Treasury Yields'!$C$110:$N$139,$E15,FALSE)/100,IF($B15=2018,VLOOKUP($BJ15,'Treasury Yields'!$C$145:$N$174,$E15,FALSE)/100,IF($B15=2019,VLOOKUP($BJ15,'Treasury Yields'!$C$180:$N$209,$E15,FALSE)/100,IF($B15=2020,VLOOKUP($BJ15,'Treasury Yields'!$C$215:$N$244,$E15,FALSE)/100,IF($B15=2021,VLOOKUP($BJ15,'Treasury Yields'!$C$250:$N$279,$E15,FALSE)/100,IF($B15=2022,VLOOKUP($BJ15,'Treasury Yields'!$C$285:$N$314,$E15,FALSE)/100)))))))),0) -> 0.012643048 | BQ15: =1+BH15*(AN15-BP15)+(AN15-BP15)^2 -> 1.7226565 | BR15: =BQ15*S15 -> 3.7721734e+08 | BS15: =BR15-AC15 -> 2.118011e+08 | BU15: =IF(BJ15="","",ROUND(BJ15+$BT$2,0)) -> 15 | BV15: =1+(BH15+BU15)*(AN15-BK15)+(AN15-BK15)^2*BI15 -> 2.8842827 | BW15: =BV15*J15 -> 16300948 | BX15: =(BM15+BW15-O15)*BK15 -> 6033831.1 | BY15: =BK15*(BN15+BW15-O15) -> 3356732.6 | BZ15: =SUM(J15:K15) -> 20665695 | CA15: =SUM(BW15+BY15) -> 19657680 | CC15: =BR15 -> 3.7721734e+08 | CD15: =F15 -> Texas | CE15: =BB15 -> 0.7554143 | CF15: =AC15/CC15 -> 0.43851707
A16: 44000000011101 | B16: 2021 | C16: 569 | D16: plan314_y2021 | E16: 8 | F16: Texas | G16: Teachers Retirement System of Texas | H16: TRS | I16: TRUE | J16: 5793398 | K16: 15645734 | M16: -1004527 | O16: 11686211 | P16: 449136 | Q16: 8299259 | R16: 218974205 | S16: 227273464 | T16: 2124028 | U16: 2140553 | V16: 3839244 | W16: 40512139 | Y16: 71360 | Z16: -18500 | AA16: 36390757 | AB16: 165416245 | AC16: 201807002 | AD16: 25466461 | AE16: 53557960 | AF16: -28091499 | AG16: 49860307 | AI16: TRUE | AK16: 0.0725 | AL16: 0.0725 | AM16: 0.0725 | AN16: 0.0725 | AS16: 55648260 | AT16: 979861 | BB16: =AC16/S16 -> 0.88794793 | BD16: =AS16-AD16 -> 30181799 | BE16: =AT16-AD16 -> -24486600 | BF16: =BD16/S16*100 -> 13.279949 | BG16: =BE16/S16*100 -> -10.774069 | BH16: =(BD16-BE16)/(2*S16)*100 -> 12.027009 | BI16: =(BD16+BE16)/(2*S16*(0.01^2)) -> 125.29397 | BJ16: =ROUND(BH16,0) -> 12 | BK16: =IF($BJ16<=30,IF($B16=2015,VLOOKUP($BJ16,'Treasury Yields'!$C$5:$N$34,$E16,FALSE)/100,IF($B16=2016,VLOOKUP($BJ16,'Treasury Yields'!$C$40:$N$69,$E16,FALSE)/100,IF($B16=2017,VLOOKUP($BJ16,'Treasury Yields'!$C$75:$N$104,$E16,FALSE)/100,IF($B16=2018,VLOOKUP($BJ16,'Treasury Yields'!$C$110:$N$139,$E16,FALSE)/100,IF($B16=2019,VLOOKUP($BJ16,'Treasury Yields'!$C$145:$N$174,$E16,FALSE)/100,IF($B16=2020,VLOOKUP($BJ16,'Treasury Yields'!$C$180:$N$209,$E16,FALSE)/100,IF($B16=2021,VLOOKUP($BJ16,'Treasury Yields'!$C$215:$N$244,$E16,FALSE)/100,IF($B16=2022,VLOOKUP($BJ16,'Treasury Yields'!$C$250:$N$279,$E16,FALSE)/100)))))))),0) -> 0.012643048 | BL16: =1+BH16*(AL16-BK16)+(AL16-BK16)^2 -> 1.7234829 | BM16: =BL16*R16 -> 3.7739831e+08 | BN16: =BM16-AB16 -> 2.1198206e+08 | BP16: =IF($BJ16<=30,IF($B16=2015,VLOOKUP($BJ16,'Treasury Yields'!$C$40:$N$69,$E16,FALSE)/100,IF($B16=2016,VLOOKUP($BJ16,'Treasury Yields'!$C$75:$N$104,$E16,FALSE)/100,IF($B16=2017,VLOOKUP($BJ16,'Treasury Yields'!$C$110:$N$139,$E16,FALSE)/100,IF($B16=2018,VLOOKUP($BJ16,'Treasury Yields'!$C$145:$N$174,$E16,FALSE)/100,IF($B16=2019,VLOOKUP($BJ16,'Treasury Yields'!$C$180:$N$209,$E16,FALSE)/100,IF($B16=2020,VLOOKUP($BJ16,'Treasury Yields'!$C$215:$N$244,$E16,FALSE)/100,IF($B16=2021,VLOOKUP($BJ16,'Treasury Yields'!$C$250:$N$279,$E16,FALSE)/100,IF($B16=2022,VLOOKUP($BJ16,'Treasury Yields'!$C$285:$N$314,$E16,FALSE)/100)))))))),0) -> 0.018741 | BQ16: =1+BH16*(AN16-BP16)+(AN16-BP16)^2 -> 1.64945 | BR16: =BQ16*S16 -> 3.7487621e+08 | BS16: =BR16-AC16 -> 1.7306921e+08 | BU16: =IF(BJ16="","",ROUND(BJ16+$BT$2,0)) -> 15 | BV16: =1+(BH16+BU16)*(AN16-BK16)+(AN16-BK16)^2*BI16 -> 3.0666645 | BW16: =BV16*J16 -> 17766408 | BX16: =(BM16+BW16-O16)*BK16 -> 4848337 | BY16: =BK16*(BN16+BW16-O16) -> 2756971.5 | BZ16: =SUM(J16:K16) -> 21439132 | CA16: =SUM(BW16+BY16) -> 20523379 | CC16: =BR16 -> 3.7487621e+08 | CD16: =F16 -> Texas | CE16: =BB16 -> 0.88794793 | CF16: =AC16/CC16 -> 0.53832971
A17: 44000000011101 | B17: 2022 | C17: 569 | D17: plan314_y2021 | E17: 8 | F17: Texas | G17: Teachers Retirement System of Texas | H17: TRS | I17: TRUE | J17: 6093119 | K17: 16201213 | M17: 1043774 | N17: 6651511 | O17: 13130574 | P17: 579462 | Q17: 16279582 | R17: 227273464 | S17: 243553045 | T17: 2504170 | U17: 2153483 | V17: 4213622 | W17: -13383751 | Y17: 62053 | Z17: 663179 | AA17: -17621385 | AB17: 201807002 | AC17: 184185617 | AD17: 59367428 | AE17: 25466461 | AF17: 33900967 | AG17: 52670273 | AI17: TRUE | AK17: 0.0725 | AL17: 0.07 | AM17: 0.07 | AN17: 0.0725 | AS17: 92353209 | AT17: 32630905 | AV17: https://www.trs.texas.gov/TRS%20Documents/acfr-2022.pdf | BB17: =AC17/S17 -> 0.75624436 | BD17: =AS17-AD17 -> 32985781 | BE17: =AT17-AD17 -> -26736523 | BF17: =BD17/S17*100 -> 13.543572 | BG17: =BE17/S17*100 -> -10.9777 | BH17: =(BD17-BE17)/(2*S17)*100 -> 12.260636 | BI17: =(BD17+BE17)/(2*S17*(0.01^2)) -> 128.29357 | BJ17: =ROUND(BH17,0) -> 12 | BK17: =IF($BJ17<=30,IF($B17=2015,VLOOKUP($BJ17,'Treasury Yields'!$C$5:$N$34,$E17,FALSE)/100,IF($B17=2016,VLOOKUP($BJ17,'Treasury Yields'!$C$40:$N$69,$E17,FALSE)/100,IF($B17=2017,VLOOKUP($BJ17,'Treasury Yields'!$C$75:$N$104,$E17,FALSE)/100,IF($B17=2018,VLOOKUP($BJ17,'Treasury Yields'!$C$110:$N$139,$E17,FALSE)/100,IF($B17=2019,VLOOKUP($BJ17,'Treasury Yields'!$C$145:$N$174,$E17,FALSE)/100,IF($B17=2020,VLOOKUP($BJ17,'Treasury Yields'!$C$180:$N$209,$E17,FALSE)/100,IF($B17=2021,VLOOKUP($BJ17,'Treasury Yields'!$C$215:$N$244,$E17,FALSE)/100,IF($B17=2022,VLOOKUP($BJ17,'Treasury Yields'!$C$250:$N$279,$E17,FALSE)/100)))))))),0) -> 0.018741 | BL17: =1+BH17*(AL17-BK17)+(AL17-BK17)^2 -> 1.6310954 | BM17: =BL17*R17 -> 3.7070471e+08 | BN17: =BM17-AB17 -> 1.688977e+08 | BP17: =IF($BJ17<=30,IF($B17=2015,VLOOKUP($BJ17,'Treasury Yields'!$C$40:$N$69,$E17,FALSE)/100,IF($B17=2016,VLOOKUP($BJ17,'Treasury Yields'!$C$75:$N$104,$E17,FALSE)/100,IF($B17=2017,VLOOKUP($BJ17,'Treasury Yields'!$C$110:$N$139,$E17,FALSE)/100,IF($B17=2018,VLOOKUP($BJ17,'Treasury Yields'!$C$145:$N$174,$E17,FALSE)/100,IF($B17=2019,VLOOKUP($BJ17,'Treasury Yields'!$C$180:$N$209,$E17,FALSE)/100,IF($B17=2020,VLOOKUP($BJ17,'Treasury Yields'!$C$215:$N$244,$E17,FALSE)/100,IF($B17=2021,VLOOKUP($BJ17,'Treasury Yields'!$C$250:$N$279,$E17,FALSE)/100,IF($B17=2022,VLOOKUP($BJ17,'Treasury Yields'!$C$285:$N$314,$E17,FALSE)/100)))))))),0) -> 0.031534348 | BQ17: =1+BH17*(AN17-BP17)+(AN17-BP17)^2 -> 1.5039431 | BR17: =BQ17*S17 -> 3.6628993e+08 | BS17: =BR17-AC17 -> 1.8210431e+08 | BU17: =IF(BJ17="","",ROUND(BJ17+$BT$2,0)) -> 15 | BV17: =1+(BH17+BU17)*(AN17-BK17)+(AN17-BK17)^2*BI17 -> 2.8362768 | BW17: =BV17*J17 -> 17281772 | BX17: =(BM17+BW17-O17)*BK17 -> 7025174.5 | BY17: =BK17*(BN17+BW17-O17) -> 3243109.5 | BZ17: =SUM(J17:K17) -> 22294332 | CA17: =SUM(BW17+BY17) -> 20524882 | CC17: =BR17 -> 3.6628993e+08 | CD17: =F17 -> Texas | CE17: =BB17 -> 0.75624436 | CF17: =AC17/CC17 -> 0.50284106
A18: 10000000000401 | B18: 2015 | C18: 231 | D18: plan70_y2021 | E18: 6 | F18: Florida | G18: Florida Retirement System Pension Plan | H18: FRS | I18: TRUE | J18: 2114047 | K18: 11721563 | L18: 0 | M18: 1620863 | N18: 0 | O18: 10201501 | Q18: 5254972 | R18: 156115763 | S18: 161370735 | T18: 2438085 | V18: 698304 | W18: 5523287 | Y18: 18074 | AA18: -1559898 | AB18: 150014292 | AC18: 148454394 | AD18: 12916341 | AE18: 6101471 | AF18: 6814870 | AG18: 32726034 | AH18: 0.074499861 | AI18: TRUE | AK18: 0.0765 | AL18: 0.0765 | AM18: 0.0765 | AN18: 0.0765 | AO18: 1 | AP18: 0 | AS18: 33469191 | AT18: -4186981 | BB18: =AC18/S18 -> 0.91995859 | BD18: =AS18-AD18 -> 20552850 | BE18: =AT18-AD18 -> -17103322 | BF18: =BD18/S18*100 -> 12.736417 | BG18: =BE18/S18*100 -> -10.598776 | BH18: =(BD18-BE18)/(2*S18)*100 -> 11.667596 | BI18: =(BD18+BE18)/(2*S18*(0.01^2)) -> 106.88209 | BJ18: =ROUND(BH18,0) -> 12 | BK18: =IF($BJ18<=30,IF($B18=2015,VLOOKUP($BJ18,'Treasury Yields'!$C$5:$N$34,$E18,FALSE)/100,IF($B18=2016,VLOOKUP($BJ18,'Treasury Yields'!$C$40:$N$69,$E18,FALSE)/100,IF($B18=2017,VLOOKUP($BJ18,'Treasury Yields'!$C$75:$N$104,$E18,FALSE)/100,IF($B18=2018,VLOOKUP($BJ18,'Treasury Yields'!$C$110:$N$139,$E18,FALSE)/100,IF($B18=2019,VLOOKUP($BJ18,'Treasury Yields'!$C$145:$N$174,$E18,FALSE)/100,IF($B18=2020,VLOOKUP($BJ18,'Treasury Yields'!$C$180:$N$209,$E18,FALSE)/100,IF($B18=2021,VLOOKUP($BJ18,'Treasury Yields'!$C$215:$N$244,$E18,FALSE)/100,IF($B18=2022,VLOOKUP($BJ18,'Treasury Yields'!$C$250:$N$279,$E18,FALSE)/100)))))))),0) -> 0.029186 | BL18: =1+BH18*(AL18-BK18)+(AL18-BK18)^2 -> 1.5542793 | BM18: =BL18*R18 -> 2.4264749e+08 | BN18: =BM18-AB18 -> 92633202 | BP18: =IF($BJ18<=30,IF($B18=2015,VLOOKUP($BJ18,'Treasury Yields'!$C$40:$N$69,$E18,FALSE)/100,IF($B18=2016,VLOOKUP($BJ18,'Treasury Yields'!$C$75:$N$104,$E18,FALSE)/100,IF($B18=2017,VLOOKUP($BJ18,'Treasury Yields'!$C$110:$N$139,$E18,FALSE)/100,IF($B18=2018,VLOOKUP($BJ18,'Treasury Yields'!$C$145:$N$174,$E18,FALSE)/100,IF($B18=2019,VLOOKUP($BJ18,'Treasury Yields'!$C$180:$N$209,$E18,FALSE)/100,IF($B18=2020,VLOOKUP($BJ18,'Treasury Yields'!$C$215:$N$244,$E18,FALSE)/100,IF($B18=2021,VLOOKUP($BJ18,'Treasury Yields'!$C$250:$N$279,$E18,FALSE)/100,IF($B18=2022,VLOOKUP($BJ18,'Treasury Yields'!$C$285:$N$314,$E18,FALSE)/100)))))))),0) -> 0.027046 | BQ18: =1+BH18*(AN18-BP18)+(AN18-BP18)^2 -> 1.579455 | BR18: =BQ18*S18 -> 2.5487782e+08 | BS18: =BR18-AC18 -> 1.0642342e+08 | BU18: =IF(BJ18="","",ROUND(BJ18+$BT$2,0)) -> 15 | BV18: =1+(BH18+BU18)*(AN18-BK18)+(AN18-BK18)^2*BI18 -> 2.5010185 | BW18: =BV18*J18 -> 5287270.6 | BX18: =(BM18+BW18-O18)*BK18 -> 6938483 | BY18: =BK18*(BN18+BW18-O18) -> 2560165.9 | BZ18: =SUM(J18:K18) -> 13835610 | CA18: =SUM(BW18+BY18) -> 7847436.5 | CC18: =BR18 -> 2.5487782e+08 | CD18: =F18 -> Florida | CE18: =BB18 -> 0.91995859 | CF18: =AC18/CC18 -> 0.58245318
A19: 10000000000401 | B19: 2016 | C19: 231 | D19: plan70_y2021 | E19: 6 | F19: Florida | G19: Florida Retirement System Pension Plan | H19: FRS | I19: TRUE | J19: 2132906 | K19: 12109114 | L19: 32310 | M19: 980192 | N19: 1030667 | O19: 10624925 | Q19: 5660264 | R19: 161370735 | S19: 167030999 | T19: 2438659 | V19: 710717 | W19: 820582 | Y19: 18507 | AA19: -6673473 | AB19: 148454394 | AC19: 141780921 | AD19: 25250078 | AE19: 12916341 | AF19: 12333737 | AG19: 33214217 | AH19: 0.073422143 | AI19: TRUE | AK19: 0.0765 | AL19: 0.076 | AM19: 0.076 | AN19: 0.0765 | AO19: 1 | AP19: 0 | AS19: 46487104 | AT19: 7573059 | AU19: p66 of CAFR | AV19: https://www.rol.frs.state.fl.us/forms/2015-16_CAFR.pdf | BB19: =AC19/S19 -> 0.84882999 | BD19: =AS19-AD19 -> 21237026 | BE19: =AT19-AD19 -> -17677019 | BF19: =BD19/S19*100 -> 12.714422 | BG19: =BE19/S19*100 -> -10.583077 | BH19: =(BD19-BE19)/(2*S19)*100 -> 11.648749 | BI19: =(BD19+BE19)/(2*S19*(0.01^2)) -> 106.56725 | BJ19: =ROUND(BH19,0) -> 12 | BK19: =IF($BJ19<=30,IF($B19=2015,VLOOKUP($BJ19,'Treasury Yields'!$C$5:$N$34,$E19,FALSE)/100,IF($B19=2016,VLOOKUP($BJ19,'Treasury Yields'!$C$40:$N$69,$E19,FALSE)/100,IF($B19=2017,VLOOKUP($BJ19,'Treasury Yields'!$C$75:$N$104,$E19,FALSE)/100,IF($B19=2018,VLOOKUP($BJ19,'Treasury Yields'!$C$110:$N$139,$E19,FALSE)/100,IF($B19=2019,VLOOKUP($BJ19,'Treasury Yields'!$C$145:$N$174,$E19,FALSE)/100,IF($B19=2020,VLOOKUP($BJ19,'Treasury Yields'!$C$180:$N$209,$E19,FALSE)/100,IF($B19=2021,VLOOKUP($BJ19,'Treasury Yields'!$C$215:$N$244,$E19,FALSE)/100,IF($B19=2022,VLOOKUP($BJ19,'Treasury Yields'!$C$250:$N$279,$E19,FALSE)/100)))))))),0) -> 0.027046 | BL19: =1+BH19*(AL19-BK19)+(AL19-BK19)^2 -> 1.5726494 | BM19: =BL19*R19 -> 2.5377959e+08 | BN19: =BM19-AB19 -> 1.0532519e+08 | BP19: =IF($BJ19<=30,IF($B19=2015,VLOOKUP($BJ19,'Treasury Yields'!$C$40:$N$69,$E19,FALSE)/100,IF($B19=2016,VLOOKUP($BJ19,'Treasury Yields'!$C$75:$N$104,$E19,FALSE)/100,IF($B19=2017,VLOOKUP($BJ19,'Treasury Yields'!$C$110:$N$139,$E19,FALSE)/100,IF($B19=2018,VLOOKUP($BJ19,'Treasury Yields'!$C$145:$N$174,$E19,FALSE)/100,IF($B19=2019,VLOOKUP($BJ19,'Treasury Yields'!$C$180:$N$209,$E19,FALSE)/100,IF($B19=2020,VLOOKUP($BJ19,'Treasury Yields'!$C$215:$N$244,$E19,FALSE)/100,IF($B19=2021,VLOOKUP($BJ19,'Treasury Yields'!$C$250:$N$279,$E19,FALSE)/100,IF($B19=2022,VLOOKUP($BJ19,'Treasury Yields'!$C$285:$N$314,$E19,FALSE)/100)))))))),0) -> 0.017546 | BQ19: =1+BH19*(AN19-BP19)+(AN19-BP19)^2 -> 1.6902159 | BR19: =BQ19*S19 -> 2.8231846e+08 | BS19: =BR19-AC19 -> 1.4053754e+08 | BU19: =IF(BJ19="","",ROUND(BJ19+$BT$2,0)) -> 15 | BV19: =1+(BH19+BU19)*(AN19-BK19)+(AN19-BK19)^2*BI19 -> 2.5785186 | BW19: =BV19*J19 -> 5499737.8 | BX19: =(BM19+BW19-O19)*BK19 -> 6725106.8 | BY19: =BK19*(BN19+BW19-O19) -> 2710009.3 | BZ19: =SUM(J19:K19) -> 14242020 | CA19: =SUM(BW19+BY19) -> 8209747.1 | CC19: =BR19 -> 2.8231846e+08 | CD19: =F19 -> Florida | CE19: =BB19 -> 0.84882999 | CF19: =AC19/CC19 -> 0.50220209
A20: 10000000000401 | B20: 2017 | C20: 231 | D20: plan70_y2021 | E20: 6 | F20: Florida | G20: Florida Retirement System Pension Plan | H20: FRS | I20: TRUE | J20: 2073754 | K20: 12484167 | L20: 92185 | M20: 1412462 | N20: 10398344 | O20: 9859319 | Q20: 16601593 | R20: 167030999 | S20: 183632592 | T20: 2603246 | V20: 744839 | W20: 18801917 | Y20: 18340 | AA20: 12272342 | AB20: 141780921 | AC20: 154053263 | AD20: 29579329 | AE20: 25250078 | AF20: 4329251 | AG20: 33775800 | AH20: 0.077074296 | AI20: TRUE | AK20: 0.076 | AL20: 0.071 | AM20: 0.071 | AN20: 0.076 | AO20: 1 | AP20: 0 | AS20: 53536799 | AT20: 9689140 | AU20: p71 of CAFR | AV20: https://www.rol.frs.state.fl.us/forms/2016-17_CAFR.pdf | BB20: =AC20/S20 -> 0.83892114 | BD20: =AS20-AD20 -> 23957470 | BE20: =AT20-AD20 -> -19890189 | BF20: =BD20/S20*100 -> 13.046415 | BG20: =BE20/S20*100 -> -10.831514 | BH20: =(BD20-BE20)/(2*S20)*100 -> 11.938964 | BI20: =(BD20+BE20)/(2*S20*(0.01^2)) -> 110.74507 | BJ20: =ROUND(BH20,0) -> 12 | BK20: =IF($BJ20<=30,IF($B20=2015,VLOOKUP($BJ20,'Treasury Yields'!$C$5:$N$34,$E20,FALSE)/100,IF($B20=2016,VLOOKUP($BJ20,'Treasury Yields'!$C$40:$N$69,$E20,FALSE)/100,IF($B20=2017,VLOOKUP($BJ20,'Treasury Yields'!$C$75:$N$104,$E20,FALSE)/100,IF($B20=2018,VLOOKUP($BJ20,'Treasury Yields'!$C$110:$N$139,$E20,FALSE)/100,IF($B20=2019,VLOOKUP($BJ20,'Treasury Yields'!$C$145:$N$174,$E20,FALSE)/100,IF($B20=2020,VLOOKUP($BJ20,'Treasury Yields'!$C$180:$N$209,$E20,FALSE)/100,IF($B20=2021,VLOOKUP($BJ20,'Treasury Yields'!$C$215:$N$244,$E20,FALSE)/100,IF($B20=2022,VLOOKUP($BJ20,'Treasury Yields'!$C$250:$N$279,$E20,FALSE)/100)))))))),0) -> 0.017546 | BL20: =1+BH20*(AL20-BK20)+(AL20-BK20)^2 -> 1.6410427 | BM20: =BL20*R20 -> 2.7410501e+08 | BN20: =BM20-AB20 -> 1.3232408e+08 | BP20: =IF($BJ20<=30,IF($B20=2015,VLOOKUP($BJ20,'Treasury Yields'!$C$40:$N$69,$E20,FALSE)/100,IF($B20=2016,VLOOKUP($BJ20,'Treasury Yields'!$C$75:$N$104,$E20,FALSE)/100,IF($B20=2017,VLOOKUP($BJ20,'Treasury Yields'!$C$110:$N$139,$E20,FALSE)/100,IF($B20=2018,VLOOKUP($BJ20,'Treasury Yields'!$C$145:$N$174,$E20,FALSE)/100,IF($B20=2019,VLOOKUP($BJ20,'Treasury Yields'!$C$180:$N$209,$E20,FALSE)/100,IF($B20=2020,VLOOKUP($BJ20,'Treasury Yields'!$C$215:$N$244,$E20,FALSE)/100,IF($B20=2021,VLOOKUP($BJ20,'Treasury Yields'!$C$250:$N$279,$E20,FALSE)/100,IF($B20=2022,VLOOKUP($BJ20,'Treasury Yields'!$C$285:$N$314,$E20,FALSE)/100)))))))),0) -> 0.0254676 | BQ20: =1+BH20*(AN20-BP20)+(AN20-BP20)^2 -> 1.605858 | BR20: =BQ20*S20 -> 2.9488787e+08 | BS20: =BR20-AC20 -> 1.4083461e+08 | BU20: =IF(BJ20="","",ROUND(BJ20+$BT$2,0)) -> 15 | BV20: =1+(BH20+BU20)*(AN20-BK20)+(AN20-BK20)^2*BI20 -> 2.9530917 | BW20: =BV20*J20 -> 6123985.8 | BX20: =(BM20+BW20-O20)*BK20 -> 4743906.3 | BY20: =BK20*(BN20+BW20-O20) -> 2256218.2 | BZ20: =SUM(J20:K20) -> 14557921 | CA20: =SUM(BW20+BY20) -> 8380204.1 | CC20: =BR20 -> 2.9488787e+08 | CD20: =F20 -> Florida | CE20: =BB20 -> 0.83892114 | CF20: =AC20/CC20 -> 0.52241301
A21: 10000000000401 | B21: 2018 | C21: 231 | D21: plan70_y2021 | E21: 6 | F21: Florida | G21: Florida Retirement System Pension Plan | H21: FRS | I21: TRUE | J21: 2423987 | K21: 12847930 | L21: 0 | M21: 554811 | N21: 2235654 | O21: 10377575 | Q21: 7684807 | R21: 183632592 | S21: 191317399 | T21: 2849920 | V21: 746370 | W21: 13955233 | Y21: 20178 | AA21: 7153770 | AB21: 154043111 | AC21: 161196881 | AD21: 30120518 | AE21: 29589481 | AF21: 531037 | AG21: 34675000 | AH21: 0.082189474 | AI21: TRUE | AK21: 0.071 | AL21: 0.07 | AM21: 0.07 | AN21: 0.071 | AO21: 1 | AP21: 0 | AS21: 54971209 | AT21: 9480550 | AU21: p73 of CAFR | AV21: https://www.rol.frs.state.fl.us/forms/2017-18_CAFR.pdf | BB21: =AC21/S21 -> 0.84256258 | BD21: =AS21-AD21 -> 24850691 | BE21: =AT21-AD21 -> -20639968 | BF21: =BD21/S21*100 -> 12.989248 | BG21: =BE21/S21*100 -> -10.788338 | BH21: =(BD21-BE21)/(2*S21)*100 -> 11.888793 | BI21: =(BD21+BE21)/(2*S21*(0.01^2)) -> 110.04548 | BJ21: =ROUND(BH21,0) -> 12 | BK21: =IF($BJ21<=30,IF($B21=2015,VLOOKUP($BJ21,'Treasury Yields'!$C$5:$N$34,$E21,FALSE)/100,IF($B21=2016,VLOOKUP($BJ21,'Treasury Yields'!$C$40:$N$69,$E21,FALSE)/100,IF($B21=2017,VLOOKUP($BJ21,'Treasury Yields'!$C$75:$N$104,$E21,FALSE)/100,IF($B21=2018,VLOOKUP($BJ21,'Treasury Yields'!$C$110:$N$139,$E21,FALSE)/100,IF($B21=2019,VLOOKUP($BJ21,'Treasury Yields'!$C$145:$N$174,$E21,FALSE)/100,IF($B21=2020,VLOOKUP($BJ21,'Treasury Yields'!$C$180:$N$209,$E21,FALSE)/100,IF($B21=2021,VLOOKUP($BJ21,'Treasury Yields'!$C$215:$N$244,$E21,FALSE)/100,IF($B21=2022,VLOOKUP($BJ21,'Treasury Yields'!$C$250:$N$279,$E21,FALSE)/100)))))))),0) -> 0.0254676 | BL21: =1+BH21*(AL21-BK21)+(AL21-BK21)^2 -> 1.5314196 | BM21: =BL21*R21 -> 2.8121855e+08 | BN21: =BM21-AB21 -> 1.2717544e+08 | BP21: =IF($BJ21<=30,IF($B21=2015,VLOOKUP($BJ21,'Treasury Yields'!$C$40:$N$69,$E21,FALSE)/100,IF($B21=2016,VLOOKUP($BJ21,'Treasury Yields'!$C$75:$N$104,$E21,FALSE)/100,IF($B21=2017,VLOOKUP($BJ21,'Treasury Yields'!$C$110:$N$139,$E21,FALSE)/100,IF($B21=2018,VLOOKUP($BJ21,'Treasury Yields'!$C$145:$N$174,$E21,FALSE)/100,IF($B21=2019,VLOOKUP($BJ21,'Treasury Yields'!$C$180:$N$209,$E21,FALSE)/100,IF($B21=2020,VLOOKUP($BJ21,'Treasury Yields'!$C$215:$N$244,$E21,FALSE)/100,IF($B21=2021,VLOOKUP($BJ21,'Treasury Yields'!$C$250:$N$279,$E21,FALSE)/100,IF($B21=2022,VLOOKUP($BJ21,'Treasury Yields'!$C$285:$N$314,$E21,FALSE)/100)))))))),0) -> 0.028906473 | BQ21: =1+BH21*(AN21-BP21)+(AN21-BP21)^2 -> 1.5022131 | BR21: =BQ21*S21 -> 2.873995e+08 | BS21: =BR21-AC21 -> 1.2620262e+08 | BU21: =IF(BJ21="","",ROUND(BJ21+$BT$2,0)) -> 15 | BV21: =1+(BH21+BU21)*(AN21-BK21)+(AN21-BK21)^2*BI21 -> 2.4524575 | BW21: =BV21*J21 -> 5944725.1 | BX21: =(BM21+BW21-O21)*BK21 -> 7049067.6 | BY21: =BK21*(BN21+BW21-O21) -> 3125959.3 | BZ21: =SUM(J21:K21) -> 15271917 | CA21: =SUM(BW21+BY21) -> 9070684.4 | CC21: =BR21 -> 2.873995e+08 | CD21: =F21 -> Florida | CE21: =BB21 -> 0.84256258 | CF21: =AC21/CC21 -> 0.56088086
A22: 10000000000401 | B22: 2019 | C22: 231 | D22: plan70_y2021 | E22: 6 | F22: Florida | G22: Florida Retirement System Pension Plan | H22: FRS | I22: TRUE | J22: 2523070 | K22: 13194902 | L22: 11404 | M22: 247482 | N22: 1585626 | O22: 10867549 | Q22: 6694935 | R22: 191317399 | S22: 198012334 | T22: 3100721 | V22: 752813 | W22: 9410440 | Y22: 19580 | AA22: 2376845 | AB22: 161196881 | AC22: 163573726 | AD22: 34438608 | AE22: 30120518 | AF22: 4318090 | AG22: 35471200 | AH22: 0.087415171 | AI22: TRUE | AK22: 0.07 | AL22: 0.069 | AM22: 0.069 | AN22: 0.07 | AO22: 1 | AP22: 0 | AS22: 59532885 | AT22: 13480642 | AU22: p86 of CAFR | AV22: https://frs.fl.gov/forms/2018-19_CAFR.pdf | BB22: =AC22/S22 -> 0.82607847 | BD22: =AS22-AD22 -> 25094277 | BE22: =AT22-AD22 -> -20957966 | BF22: =BD22/S22*100 -> 12.673088 | BG22: =BE22/S22*100 -> -10.584172 | BH22: =(BD22-BE22)/(2*S22)*100 -> 11.62863 | BI22: =(BD22+BE22)/(2*S22*(0.01^2)) -> 104.44579 | BJ22: =ROUND(BH22,0) -> 12 | BK22: =IF($BJ22<=30,IF($B22=2015,VLOOKUP($BJ22,'Treasury Yields'!$C$5:$N$34,$E22,FALSE)/100,IF($B22=2016,VLOOKUP($BJ22,'Treasury Yields'!$C$40:$N$69,$E22,FALSE)/100,IF($B22=2017,VLOOKUP($BJ22,'Treasury Yields'!$C$75:$N$104,$E22,FALSE)/100,IF($B22=2018,VLOOKUP($BJ22,'Treasury Yields'!$C$110:$N$139,$E22,FALSE)/100,IF($B22=2019,VLOOKUP($BJ22,'Treasury Yields'!$C$145:$N$174,$E22,FALSE)/100,IF($B22=2020,VLOOKUP($BJ22,'Treasury Yields'!$C$180:$N$209,$E22,FALSE)/100,IF($B22=2021,VLOOKUP($BJ22,'Treasury Yields'!$C$215:$N$244,$E22,FALSE)/100,IF($B22=2022,VLOOKUP($BJ22,'Treasury Yields'!$C$250:$N$279,$E22,FALSE)/100)))))))),0) -> 0.028906473 | BL22: =1+BH22*(AL22-BK22)+(AL22-BK22)^2 -> 1.4678403 | BM22: =BL22*R22 -> 2.8082338e+08 | BN22: =BM22-AB22 -> 1.196265e+08 | BP22: =IF($BJ22<=30,IF($B22=2015,VLOOKUP($BJ22,'Treasury Yields'!$C$40:$N$69,$E22,FALSE)/100,IF($B22=2016,VLOOKUP($BJ22,'Treasury Yields'!$C$75:$N$104,$E22,FALSE)/100,IF($B22=2017,VLOOKUP($BJ22,'Treasury Yields'!$C$110:$N$139,$E22,FALSE)/100,IF($B22=2018,VLOOKUP($BJ22,'Treasury Yields'!$C$145:$N$174,$E22,FALSE)/100,IF($B22=2019,VLOOKUP($BJ22,'Treasury Yields'!$C$180:$N$209,$E22,FALSE)/100,IF($B22=2020,VLOOKUP($BJ22,'Treasury Yields'!$C$215:$N$244,$E22,FALSE)/100,IF($B22=2021,VLOOKUP($BJ22,'Treasury Yields'!$C$250:$N$279,$E22,FALSE)/100,IF($B22=2022,VLOOKUP($BJ22,'Treasury Yields'!$C$285:$N$314,$E22,FALSE)/100)))))))),0) -> 0.022184 | BQ22: =1+BH22*(AN22-BP22)+(AN22-BP22)^2 -> 1.5583209 | BR22: =BQ22*S22 -> 3.0856677e+08 | BS22: =BR22-AC22 -> 1.4499304e+08 | BU22: =IF(BJ22="","",ROUND(BJ22+$BT$2,0)) -> 15 | BV22: =1+(BH22+BU22)*(AN22-BK22)+(AN22-BK22)^2*BI22 -> 2.2706396 | BW22: =BV22*J22 -> 5728982.8 | BX22: =(BM22+BW22-O22)*BK22 -> 7969075.7 | BY22: =BK22*(BN22+BW22-O22) -> 3309442.4 | BZ22: =SUM(J22:K22) -> 15717972 | CA22: =SUM(BW22+BY22) -> 9038425.2 | CC22: =BR22 -> 3.0856677e+08 | CD22: =F22 -> Florida | CE22: =BB22 -> 0.82607847 | CF22: =AC22/CC22 -> 0.53010805
A23: 10000000000401 | B23: 2020 | C23: 231 | D23: plan70_y2021 | E23: 6 | F23: Florida | G23: Florida Retirement System Pension Plan | H23: FRS | I23: TRUE | J23: 2647456 | K23: 13458929 | L23: 0 | M23: 448646 | N23: 1738139 | O23: 11395765 | Q23: 6897405 | R23: 198012334 | S23: 204909739 | T23: 3322557 | V23: 748455 | W23: 5339908 | Y23: 21556 | AA23: -2006402 | AB23: 163574667 | AC23: 161568265 | AD23: 43341474 | AE23: 34438608 | AF23: 8902866 | AG23: 36898200 | AH23: 0.090046588 | AI23: TRUE | AK23: 0.069 | AL23: 0.068 | AM23: 0.068 | AN23: 0.069 | AO23: 1 | AP23: 0 | AS23: 69209050 | AT23: 21736762 | AU23: p88 of CAFR | AV23: https://frs.fl.gov/forms/2019-20_CAFR.pdf | BB23: =AC23/S23 -> 0.78848505 | BD23: =AS23-AD23 -> 25867576 | BE23: =AT23-AD23 -> -21604712 | BF23: =BD23/S23*100 -> 12.623888 | BG23: =BE23/S23*100 -> -10.543526 | BH23: =(BD23-BE23)/(2*S23)*100 -> 11.583707 | BI23: =(BD23+BE23)/(2*S23*(0.01^2)) -> 104.01809 | BJ23: =ROUND(BH23,0) -> 12 | BK23: =IF($BJ23<=30,IF($B23=2015,VLOOKUP($BJ23,'Treasury Yields'!$C$5:$N$34,$E23,FALSE)/100,IF($B23=2016,VLOOKUP($BJ23,'Treasury Yields'!$C$40:$N$69,$E23,FALSE)/100,IF($B23=2017,VLOOKUP($BJ23,'Treasury Yields'!$C$75:$N$104,$E23,FALSE)/100,IF($B23=2018,VLOOKUP($BJ23,'Treasury Yields'!$C$110:$N$139,$E23,FALSE)/100,IF($B23=2019,VLOOKUP($BJ23,'Treasury Yields'!$C$145:$N$174,$E23,FALSE)/100,IF($B23=2020,VLOOKUP($BJ23,'Treasury Yields'!$C$180:$N$209,$E23,FALSE)/100,IF($B23=2021,VLOOKUP($BJ23,'Treasury Yields'!$C$215:$N$244,$E23,FALSE)/100,IF($B23=2022,VLOOKUP($BJ23,'Treasury Yields'!$C$250:$N$279,$E23,FALSE)/100)))))))),0) -> 0.022184 | BL23: =1+BH23*(AL23-BK23)+(AL23-BK23)^2 -> 1.5328182 | BM23: =BL23*R23 -> 3.0351692e+08 | BN23: =BM23-AB23 -> 1.3994225e+08 | BP23: =IF($BJ23<=30,IF($B23=2015,VLOOKUP($BJ23,'Treasury Yields'!$C$40:$N$69,$E23,FALSE)/100,IF($B23=2016,VLOOKUP($BJ23,'Treasury Yields'!$C$75:$N$104,$E23,FALSE)/100,IF($B23=2017,VLOOKUP($BJ23,'Treasury Yields'!$C$110:$N$139,$E23,FALSE)/100,IF($B23=2018,VLOOKUP($BJ23,'Treasury Yields'!$C$145:$N$174,$E23,FALSE)/100,IF($B23=2019,VLOOKUP($BJ23,'Treasury Yields'!$C$180:$N$209,$E23,FALSE)/100,IF($B23=2020,VLOOKUP($BJ23,'Treasury Yields'!$C$215:$N$244,$E23,FALSE)/100,IF($B23=2021,VLOOKUP($BJ23,'Treasury Yields'!$C$250:$N$279,$E23,FALSE)/100,IF($B23=2022,VLOOKUP($BJ23,'Treasury Yields'!$C$285:$N$314,$E23,FALSE)/100)))))))),0) -> 0.013689455 | BQ23: =1+BH23*(AN23-BP23)+(AN23-BP23)^2 -> 1.6437604 | BR23: =BQ23*S23 -> 3.3682252e+08 | BS23: =BR23-AC23 -> 1.7525425e+08 | BU23: =IF(BJ23="","",ROUND(BJ23+$BT$2,0)) -> 15 | BV23: =1+(BH23+BU23)*(AN23-BK23)+(AN23-BK23)^2*BI23 -> 2.4725232 | BW23: =BV23*J23 -> 6545896.4 | BX23: =(BM23+BW23-O23)*BK23 -> 6625629.8 | BY23: =BK23*(BN23+BW23-O23) -> 2996889.4 | BZ23: =SUM(J23:K23) -> 16106385 | CA23: =SUM(BW23+BY23) -> 9542785.8 | CC23: =BR23 -> 3.3682252e+08 | CD23: =F23 -> Florida | CE23: =BB23 -> 0.78848505 | CF23: =AC23/CC23 -> 0.47968368
A24: 10000000000401 | B24: 2021 | C24: 231 | D24: plan70_y2021 | E24: 6 | F24: Florida | G24: Florida Retirement System Pension Plan | H24: FRS | I24: TRUE | J24: 2648469 | K24: 13713166 | L24: 0 | M24: 349779 | N24: 0 | O24: 11985107 | Q24: 4726307 | R24: 204909739 | S24: 209636046 | T24: 3809568 | V24: 756530 | W24: 47954667 | Y24: 21741 | AA24: 40513917 | AB24: 161568265 | AC24: 202082183 | AD24: 7553863 | AE24: 43341474 | AF24: -35787611 | AG24: 37590100 | AI24: TRUE | AK24: 0.068 | AL24: 0.068 | AM24: 0.068 | AN24: 0.068 | AS24: 33781383 | AT24: -14369403 | BB24: =AC24/S24 -> 0.96396677 | BD24: =AS24-AD24 -> 26227520 | BE24: =AT24-AD24 -> -21923266 | BF24: =BD24/S24*100 -> 12.510978 | BG24: =BE24/S24*100 -> -10.457775 | BH24: =(BD24-BE24)/(2*S24)*100 -> 11.484377 | BI24: =(BD24+BE24)/(2*S24*(0.01^2)) -> 102.66016 | BJ24: =ROUND(BH24,0) -> 11 | BK24: =IF($BJ24<=30,IF($B24=2015,VLOOKUP($BJ24,'Treasury Yields'!$C$5:$N$34,$E24,FALSE)/100,IF($B24=2016,VLOOKUP($BJ24,'Treasury Yields'!$C$40:$N$69,$E24,FALSE)/100,IF($B24=2017,VLOOKUP($BJ24,'Treasury Yields'!$C$75:$N$104,$E24,FALSE)/100,IF($B24=2018,VLOOKUP($BJ24,'Treasury Yields'!$C$110:$N$139,$E24,FALSE)/100,IF($B24=2019,VLOOKUP($BJ24,'Treasury Yields'!$C$145:$N$174,$E24,FALSE)/100,IF($B24=2020,VLOOKUP($BJ24,'Treasury Yields'!$C$180:$N$209,$E24,FALSE)/100,IF($B24=2021,VLOOKUP($BJ24,'Treasury Yields'!$C$215:$N$244,$E24,FALSE)/100,IF($B24=2022,VLOOKUP($BJ24,'Treasury Yields'!$C$250:$N$279,$E24,FALSE)/100)))))))),0) -> 0.014551091 | BL24: =1+BH24*(AL24-BK24)+(AL24-BK24)^2 -> 1.6166842 | BM24: =BL24*R24 -> 3.3127433e+08 | BN24: =BM24-AB24 -> 1.6970607e+08 | BP24: =IF($BJ24<=30,IF($B24=2015,VLOOKUP($BJ24,'Treasury Yields'!$C$40:$N$69,$E24,FALSE)/100,IF($B24=2016,VLOOKUP($BJ24,'Treasury Yields'!$C$75:$N$104,$E24,FALSE)/100,IF($B24=2017,VLOOKUP($BJ24,'Treasury Yields'!$C$110:$N$139,$E24,FALSE)/100,IF($B24=2018,VLOOKUP($BJ24,'Treasury Yields'!$C$145:$N$174,$E24,FALSE)/100,IF($B24=2019,VLOOKUP($BJ24,'Treasury Yields'!$C$180:$N$209,$E24,FALSE)/100,IF($B24=2020,VLOOKUP($BJ24,'Treasury Yields'!$C$215:$N$244,$E24,FALSE)/100,IF($B24=2021,VLOOKUP($BJ24,'Treasury Yields'!$C$250:$N$279,$E24,FALSE)/100,IF($B24=2022,VLOOKUP($BJ24,'Treasury Yields'!$C$285:$N$314,$E24,FALSE)/100)))))))),0) -> 0.021554273 | BQ24: =1+BH24*(AN24-BP24)+(AN24-BP24)^2 -> 1.5355574 | BR24: =BQ24*S24 -> 3.2190819e+08 | BS24: =BR24-AC24 -> 1.19826e+08 | BU24: =IF(BJ24="","",ROUND(BJ24+$BT$2,0)) -> 14 | BV24: =1+(BH24+BU24)*(AN24-BK24)+(AN24-BK24)^2*BI24 -> 2.6553902 | BW24: =BV24*J24 -> 7032718.7 | BX24: =(BM24+BW24-O24)*BK24 -> 4748340.3 | BY24: =BK24*(BN24+BW24-O24) -> 2397345.8 | BZ24: =SUM(J24:K24) -> 16361635 | CA24: =SUM(BW24+BY24) -> 9430064.5 | CC24: =BR24 -> 3.2190819e+08 | CD24: =F24 -> Florida | CE24: =BB24 -> 0.96396677 | CF24: =AC24/CC24 -> 0.62776341
A25: 10000000000401 | B25: 2022 | C25: 231 | D25: plan70_y2021 | E25: 6 | F25: Florida | G25: Florida Retirement System Pension Plan | H25: FRS | I25: TRUE | J25: 2635672 | K25: 14012135 | L25: 99285 | M25: 1243179 | N25: 2437637 | O25: 12629514 | Q25: 7798395 | R25: 209636046 | S25: 217434441 | T25: 4267182 | V25: 769228 | W25: -14240179 | Y25: 22495 | AA25: -21855778 | AB25: 202082183 | AC25: 180226405 | AD25: 37208036 | AE25: 7553863 | AF25: 29654173 | AG25: 38208036 | AI25: TRUE | AK25: 0.068 | AL25: 0.067 | AM25: 0.067 | AN25: 0.068 | AS25: 64348740 | AT25: 14515178 | AV25: https://employer.frs.fl.gov/forms/2021-22_ACFR.pdf | BB25: =AC25/S25 -> 0.82887699 | BD25: =AS25-AD25 -> 27140704 | BE25: =AT25-AD25 -> -22692858 | BF25: =BD25/S25*100 -> 12.482247 | BG25: =BE25/S25*100 -> -10.436644 | BH25: =(BD25-BE25)/(2*S25)*100 -> 11.459445 | BI25: =(BD25+BE25)/(2*S25*(0.01^2)) -> 102.28016 | BJ25: =ROUND(BH25,0) -> 11 | BK25: =IF($BJ25<=30,IF($B25=2015,VLOOKUP($BJ25,'Treasury Yields'!$C$5:$N$34,$E25,FALSE)/100,IF($B25=2016,VLOOKUP($BJ25,'Treasury Yields'!$C$40:$N$69,$E25,FALSE)/100,IF($B25=2017,VLOOKUP($BJ25,'Treasury Yields'!$C$75:$N$104,$E25,FALSE)/100,IF($B25=2018,VLOOKUP($BJ25,'Treasury Yields'!$C$110:$N$139,$E25,FALSE)/100,IF($B25=2019,VLOOKUP($BJ25,'Treasury Yields'!$C$145:$N$174,$E25,FALSE)/100,IF($B25=2020,VLOOKUP($BJ25,'Treasury Yields'!$C$180:$N$209,$E25,FALSE)/100,IF($B25=2021,VLOOKUP($BJ25,'Treasury Yields'!$C$215:$N$244,$E25,FALSE)/100,IF($B25=2022,VLOOKUP($BJ25,'Treasury Yields'!$C$250:$N$279,$E25,FALSE)/100)))))))),0) -> 0.021554273 | BL25: =1+BH25*(AL25-BK25)+(AL25-BK25)^2 -> 1.5228481 | BM25: =BL25*R25 -> 3.1924386e+08 | BN25: =BM25-AB25 -> 1.1716168e+08 | BP25: =IF($BJ25<=30,IF($B25=2015,VLOOKUP($BJ25,'Treasury Yields'!$C$40:$N$69,$E25,FALSE)/100,IF($B25=2016,VLOOKUP($BJ25,'Treasury Yields'!$C$75:$N$104,$E25,FALSE)/100,IF($B25=2017,VLOOKUP($BJ25,'Treasury Yields'!$C$110:$N$139,$E25,FALSE)/100,IF($B25=2018,VLOOKUP($BJ25,'Treasury Yields'!$C$145:$N$174,$E25,FALSE)/100,IF($B25=2019,VLOOKUP($BJ25,'Treasury Yields'!$C$180:$N$209,$E25,FALSE)/100,IF($B25=2020,VLOOKUP($BJ25,'Treasury Yields'!$C$215:$N$244,$E25,FALSE)/100,IF($B25=2021,VLOOKUP($BJ25,'Treasury Yields'!$C$250:$N$279,$E25,FALSE)/100,IF($B25=2022,VLOOKUP($BJ25,'Treasury Yields'!$C$285:$N$314,$E25,FALSE)/100)))))))),0) -> 0.031935909 | BQ25: =1+BH25*(AN25-BP25)+(AN25-BP25)^2 -> 1.4145751 | BR25: =BQ25*S25 -> 3.0757735e+08 | BS25: =BR25-AC25 -> 1.2735094e+08 | BU25: =IF(BJ25="","",ROUND(BJ25+$BT$2,0)) -> 14 | BV25: =1+(BH25+BU25)*(AN25-BK25)+(AN25-BK25)^2*BI25 -> 2.4031218 | BW25: =BV25*J25 -> 6333840.8 | BX25: =(BM25+BW25-O25)*BK25 -> 6745370.6 | BY25: =BK25*(BN25+BW25-O25) -> 2389636.2 | BZ25: =SUM(J25:K25) -> 16647807 | CA25: =SUM(BW25+BY25) -> 8723477 | CC25: =BR25 -> 3.0757735e+08 | CD25: =F25 -> Florida | CE25: =BB25 -> 0.82887699 | CF25: =AC25/CC25 -> 0.58595474
A26: 11000000011301 | B26: 2015 | C26: 576 | D26: plan315_y2021 | E26: 6 | F26: Georgia | G26: Teachers' Retirement System of Georgia | H26: TRS | I26: TRUE | J26: 1386498 | K26: 5779597 | L26: 0 | M26: -165785 | N26: 0 | O26: 3996879 | P26: 80085 | Q26: 2923346 | R26: 79099772 | S26: 82023118 | T26: 1399668 | U26: 7038 | V26: 661835 | W26: 2384145 | Y26: 14996 | Z26: -27706 | AA26: 333020 | AB26: 66466091 | AC26: 66799111 | AD26: 15224007 | AE26: 12633681 | AF26: 2590326 | AG26: 10697384 | AH26: 0.13084208 | AI26: TRUE | AK26: 0.075 | AL26: 0.075 | AM26: 0.075 | AN26: 0.075 | AO26: 1 | AP26: 0 | AS26: 26161305 | AT26: 6209071 | BB26: =AC26/S26 -> 0.81439371 | BD26: =AS26-AD26 -> 10937298 | BE26: =AT26-AD26 -> -9014936 | BF26: =BD26/S26*100 -> 13.334409 | BG26: =BE26/S26*100 -> -10.990726 | BH26: =(BD26-BE26)/(2*S26)*100 -> 12.162567 | BI26: =(BD26+BE26)/(2*S26*(0.01^2)) -> 117.18416 | BJ26: =ROUND(BH26,0) -> 12 | BK26: =IF($BJ26<=30,IF($B26=2015,VLOOKUP($BJ26,'Treasury Yields'!$C$5:$N$34,$E26,FALSE)/100,IF($B26=2016,VLOOKUP($BJ26,'Treasury Yields'!$C$40:$N$69,$E26,FALSE)/100,IF($B26=2017,VLOOKUP($BJ26,'Treasury Yields'!$C$75:$N$104,$E26,FALSE)/100,IF($B26=2018,VLOOKUP($BJ26,'Treasury Yields'!$C$110:$N$139,$E26,FALSE)/100,IF($B26=2019,VLOOKUP($BJ26,'Treasury Yields'!$C$145:$N$174,$E26,FALSE)/100,IF($B26=2020,VLOOKUP($BJ26,'Treasury Yields'!$C$180:$N$209,$E26,FALSE)/100,IF($B26=2021,VLOOKUP($BJ26,'Treasury Yields'!$C$215:$N$244,$E26,FALSE)/100,IF($B26=2022,VLOOKUP($BJ26,'Treasury Yields'!$C$250:$N$279,$E26,FALSE)/100)))))))),0) -> 0.029186 | BL26: =1+BH26*(AL26-BK26)+(AL26-BK26)^2 -> 1.5593148 | BM26: =BL26*R26 -> 1.2334144e+08 | BN26: =BM26-AB26 -> 56875353 | BP26: =IF($BJ26<=30,IF($B26=2015,VLOOKUP($BJ26,'Treasury Yields'!$C$40:$N$69,$E26,FALSE)/100,IF($B26=2016,VLOOKUP($BJ26,'Treasury Yields'!$C$75:$N$104,$E26,FALSE)/100,IF($B26=2017,VLOOKUP($BJ26,'Treasury Yields'!$C$110:$N$139,$E26,FALSE)/100,IF($B26=2018,VLOOKUP($BJ26,'Treasury Yields'!$C$145:$N$174,$E26,FALSE)/100,IF($B26=2019,VLOOKUP($BJ26,'Treasury Yields'!$C$180:$N$209,$E26,FALSE)/100,IF($B26=2020,VLOOKUP($BJ26,'Treasury Yields'!$C$215:$N$244,$E26,FALSE)/100,IF($B26=2021,VLOOKUP($BJ26,'Treasury Yields'!$C$250:$N$279,$E26,FALSE)/100,IF($B26=2022,VLOOKUP($BJ26,'Treasury Yields'!$C$285:$N$314,$E26,FALSE)/100)))))))),0) -> 0.027046 | BQ26: =1+BH26*(AN26-BP26)+(AN26-BP26)^2 -> 1.5855433 | BR26: =BQ26*S26 -> 1.3005121e+08 | BS26: =BR26-AC26 -> 63252098 | BU26: =IF(BJ26="","",ROUND(BJ26+$BT$2,0)) -> 15 | BV26: =1+(BH26+BU26)*(AN26-BK26)+(AN26-BK26)^2*BI26 -> 2.4903863 | BW26: =BV26*J26 -> 3452915.7 | BX26: =(BM26+BW26-O26)*BK26 -> 3583967.3 | BY26: =BK26*(BN26+BW26-O26) -> 1644087.9 | BZ26: =SUM(J26:K26) -> 7166095 | CA26: =SUM(BW26+BY26) -> 5097003.6 | CC26: =BR26 -> 1.3005121e+08 | CD26: =F26 -> Georgia | CE26: =BB26 -> 0.81439371 | CF26: =AC26/CC26 -> 0.51363699
A27: 11000000011301 | B27: 2016 | C27: 576 | D27: plan315_y2021 | E27: 6 | F27: Georgia | G27: Teachers' Retirement System of Georgia | H27: TRS | I27: TRUE | J27: 1435808 | K27: 5990178 | M27: 380526 | N27: 662047 | O27: 4228819 | P27: 79334 | Q27: 4160408 | R27: 82023118 | S27: 86183526 | T27: 1572624 | U27: 7908 | V27: 685626 | W27: 810574 | Y27: 15279 | AA27: -1246700 | AB27: 66799111 | AC27: 65552411 | AD27: 20631115 | AE27: 15224007 | AF27: 5407108 | AG27: 11075907 | AH27: 0.14198602 | AI27: TRUE | AK27: 0.075 | AL27: 0.075 | AM27: 0.075 | AN27: 0.075 | AO27: 1 | AP27: 0 | AS27: 32112585 | AT27: 11178017 | AU27: p37 of CAFR | AV27: http://www.trsga.com/downloadPublications/CAFR2016_web.pdf | BB27: =AC27/S27 -> 0.76061417 | BD27: =AS27-AD27 -> 11481470 | BE27: =AT27-AD27 -> -9453098 | BF27: =BD27/S27*100 -> 13.322117 | BG27: =BE27/S27*100 -> -10.968567 | BH27: =(BD27-BE27)/(2*S27)*100 -> 12.145342 | BI27: =(BD27+BE27)/(2*S27*(0.01^2)) -> 117.67748 | BJ27: =ROUND(BH27,0) -> 12 | BK27: =IF($BJ27<=30,IF($B27=2015,VLOOKUP($BJ27,'Treasury Yields'!$C$5:$N$34,$E27,FALSE)/100,IF($B27=2016,VLOOKUP($BJ27,'Treasury Yields'!$C$40:$N$69,$E27,FALSE)/100,IF($B27=2017,VLOOKUP($BJ27,'Treasury Yields'!$C$75:$N$104,$E27,FALSE)/100,IF($B27=2018,VLOOKUP($BJ27,'Treasury Yields'!$C$110:$N$139,$E27,FALSE)/100,IF($B27=2019,VLOOKUP($BJ27,'Treasury Yields'!$C$145:$N$174,$E27,FALSE)/100,IF($B27=2020,VLOOKUP($BJ27,'Treasury Yields'!$C$180:$N$209,$E27,FALSE)/100,IF($B27=2021,VLOOKUP($BJ27,'Treasury Yields'!$C$215:$N$244,$E27,FALSE)/100,IF($B27=2022,VLOOKUP($BJ27,'Treasury Yields'!$C$250:$N$279,$E27,FALSE)/100)))))))),0) -> 0.027046 | BL27: =1+BH27*(AL27-BK27)+(AL27-BK27)^2 -> 1.5847173 | BM27: =BL27*R27 -> 1.2998346e+08 | BN27: =BM27-AB27 -> 63184345 | BP27: =IF($BJ27<=30,IF($B27=2015,VLOOKUP($BJ27,'Treasury Yields'!$C$40:$N$69,$E27,FALSE)/100,IF($B27=2016,VLOOKUP($BJ27,'Treasury Yields'!$C$75:$N$104,$E27,FALSE)/100,IF($B27=2017,VLOOKUP($BJ27,'Treasury Yields'!$C$110:$N$139,$E27,FALSE)/100,IF($B27=2018,VLOOKUP($BJ27,'Treasury Yields'!$C$145:$N$174,$E27,FALSE)/100,IF($B27=2019,VLOOKUP($BJ27,'Treasury Yields'!$C$180:$N$209,$E27,FALSE)/100,IF($B27=2020,VLOOKUP($BJ27,'Treasury Yields'!$C$215:$N$244,$E27,FALSE)/100,IF($B27=2021,VLOOKUP($BJ27,'Treasury Yields'!$C$250:$N$279,$E27,FALSE)/100,IF($B27=2022,VLOOKUP($BJ27,'Treasury Yields'!$C$285:$N$314,$E27,FALSE)/100)))))))),0) -> 0.017546 | BQ27: =1+BH27*(AN27-BP27)+(AN27-BP27)^2 -> 1.7010994 | BR27: =BQ27*S27 -> 1.4660675e+08 | BS27: =BR27-AC27 -> 81054337 | BU27: =IF(BJ27="","",ROUND(BJ27+$BT$2,0)) -> 15 | BV27: =1+(BH27+BU27)*(AN27-BK27)+(AN27-BK27)^2*BI27 -> 2.5723372 | BW27: =BV27*J27 -> 3693382.4 | BX27: =(BM27+BW27-O27)*BK27 -> 3501051.1 | BY27: =BK27*(BN27+BW27-O27) -> 1694402.4 | BZ27: =SUM(J27:K27) -> 7425986 | CA27: =SUM(BW27+BY27) -> 5387784.7 | CC27: =BR27 -> 1.4660675e+08 | CD27: =F27 -> Georgia | CE27: =BB27 -> 0.76061417 | CF27: =AC27/CC27 -> 0.44713093
A28: 11000000011301 | B28: 2017 | C28: 576 | D28: plan315_y2021 | E28: 6 | F28: Georgia | G28: Teachers' Retirement System of Georgia | H28: TRS | I28: TRUE | J28: 1413080 | K28: 6293611 | M28: 573483 | N28: 0 | O28: 4461124 | P28: 76296 | Q28: 3742754 | R28: 86183526 | S28: 89926280 | T28: 1648411 | U28: 6175 | V28: 716233 | W28: 7971677 | Y28: 16733 | Z28: 258 | AA28: 5788561 | AB28: 65552411 | AC28: 71340972 | AD28: 18585308 | AE28: 20631115 | AF28: -2045807 | AG28: 11596664 | AH28: 0.14214528 | AI28: TRUE | AK28: 0.075 | AL28: 0.075 | AM28: 0.075 | AN28: 0.075 | AO28: 1 | AP28: 0 | AS28: 30500671 | AT28: 8769727 | AU28: p211 of CAFR | AV28: https://sao.georgia.gov/sites/sao.georgia.gov/files/related_files/site_page/sao-17-cafr.pdf | BB28: =AC28/S28 -> 0.79332729 | BD28: =AS28-AD28 -> 11915363 | BE28: =AT28-AD28 -> -9815581 | BF28: =BD28/S28*100 -> 13.250146 | BG28: =BE28/S28*100 -> -10.915142 | BH28: =(BD28-BE28)/(2*S28)*100 -> 12.082644 | BI28: =(BD28+BE28)/(2*S28*(0.01^2)) -> 116.75019 | BJ28: =ROUND(BH28,0) -> 12 | BK28: =IF($BJ28<=30,IF($B28=2015,VLOOKUP($BJ28,'Treasury Yields'!$C$5:$N$34,$E28,FALSE)/100,IF($B28=2016,VLOOKUP($BJ28,'Treasury Yields'!$C$40:$N$69,$E28,FALSE)/100,IF($B28=2017,VLOOKUP($BJ28,'Treasury Yields'!$C$75:$N$104,$E28,FALSE)/100,IF($B28=2018,VLOOKUP($BJ28,'Treasury Yields'!$C$110:$N$139,$E28,FALSE)/100,IF($B28=2019,VLOOKUP($BJ28,'Treasury Yields'!$C$145:$N$174,$E28,FALSE)/100,IF($B28=2020,VLOOKUP($BJ28,'Treasury Yields'!$C$180:$N$209,$E28,FALSE)/100,IF($B28=2021,VLOOKUP($BJ28,'Treasury Yields'!$C$215:$N$244,$E28,FALSE)/100,IF($B28=2022,VLOOKUP($BJ28,'Treasury Yields'!$C$250:$N$279,$E28,FALSE)/100)))))))),0) -> 0.017546 | BL28: =1+BH28*(AL28-BK28)+(AL28-BK28)^2 -> 1.6974972 | BM28: =BL28*R28 -> 1.4629629e+08 | BN28: =BM28-AB28 -> 80743881 | BP28: =IF($BJ28<=30,IF($B28=2015,VLOOKUP($BJ28,'Treasury Yields'!$C$40:$N$69,$E28,FALSE)/100,IF($B28=2016,VLOOKUP($BJ28,'Treasury Yields'!$C$75:$N$104,$E28,FALSE)/100,IF($B28=2017,VLOOKUP($BJ28,'Treasury Yields'!$C$110:$N$139,$E28,FALSE)/100,IF($B28=2018,VLOOKUP($BJ28,'Treasury Yields'!$C$145:$N$174,$E28,FALSE)/100,IF($B28=2019,VLOOKUP($BJ28,'Treasury Yields'!$C$180:$N$209,$E28,FALSE)/100,IF($B28=2020,VLOOKUP($BJ28,'Treasury Yields'!$C$215:$N$244,$E28,FALSE)/100,IF($B28=2021,VLOOKUP($BJ28,'Treasury Yields'!$C$250:$N$279,$E28,FALSE)/100,IF($B28=2022,VLOOKUP($BJ28,'Treasury Yields'!$C$285:$N$314,$E28,FALSE)/100)))))))),0) -> 0.0254676 | BQ28: =1+BH28*(AN28-BP28)+(AN28-BP28)^2 -> 1.6009358 | BR28: =BQ28*S28 -> 1.439662e+08 | BS28: =BR28-AC28 -> 72625229 | BU28: =IF(BJ28="","",ROUND(BJ28+$BT$2,0)) -> 15 | BV28: =1+(BH28+BU28)*(AN28-BK28)+(AN28-BK28)^2*BI28 -> 2.9413942 | BW28: =BV28*J28 -> 4156425.3 | BX28: =(BM28+BW28-O28)*BK28 -> 2561568.5 | BY28: =BK28*(BN28+BW28-O28) -> 1411385.9 | BZ28: =SUM(J28:K28) -> 7706691 | CA28: =SUM(BW28+BY28) -> 5567811.1 | CC28: =BR28 -> 1.439662e+08 | CD28: =F28 -> Georgia | CE28: =BB28 -> 0.79332729 | CF28: =AC28/CC28 -> 0.49553973
A29: 11000000011301 | B29: 2018 | C29: 576 | D29: plan315_y2021 | E29: 6 | F29: Georgia | G29: Teachers' Retirement System of Georgia | H29: TRS | I29: TRUE | J29: 1484705 | K29: 6565372 | M29: 894691 | N29: 0 | O29: 4699920 | P29: 76061 | Q29: 4168787 | R29: 89926280 | S29: 94095067 | T29: 2014088 | U29: 4416 | V29: 745574 | W29: 6247155 | Y29: 15865 | Z29: -27434 | AA29: 4191953 | AB29: 71340972 | AC29: 75532925 | AD29: 18562142 | AE29: 18585308 | AF29: -23166 | AG29: 12009066 | AH29: 0.16771396 | AI29: TRUE | AK29: 0.075 | AL29: 0.075 | AM29: 0.075 | AN29: 0.075 | AO29: 1 | AP29: 0 | AS29: 30985530 | AT29: 8234638 | AU29: p238 of CAFR | AV29: https://sao.georgia.gov/statewide-reporting/comprehensive-annual-financial-reports | BB29: =AC29/S29 -> 0.80272991 | BD29: =AS29-AD29 -> 12423388 | BE29: =AT29-AD29 -> -10327504 | BF29: =BD29/S29*100 -> 13.203017 | BG29: =BE29/S29*100 -> -10.975606 | BH29: =(BD29-BE29)/(2*S29)*100 -> 12.089312 | BI29: =(BD29+BE29)/(2*S29*(0.01^2)) -> 111.37056 | BJ29: =ROUND(BH29,0) -> 12 | BK29: =IF($BJ29<=30,IF($B29=2015,VLOOKUP($BJ29,'Treasury Yields'!$C$5:$N$34,$E29,FALSE)/100,IF($B29=2016,VLOOKUP($BJ29,'Treasury Yields'!$C$40:$N$69,$E29,FALSE)/100,IF($B29=2017,VLOOKUP($BJ29,'Treasury Yields'!$C$75:$N$104,$E29,FALSE)/100,IF($B29=2018,VLOOKUP($BJ29,'Treasury Yields'!$C$110:$N$139,$E29,FALSE)/100,IF($B29=2019,VLOOKUP($BJ29,'Treasury Yields'!$C$145:$N$174,$E29,FALSE)/100,IF($B29=2020,VLOOKUP($BJ29,'Treasury Yields'!$C$180:$N$209,$E29,FALSE)/100,IF($B29=2021,VLOOKUP($BJ29,'Treasury Yields'!$C$215:$N$244,$E29,FALSE)/100,IF($B29=2022,VLOOKUP($BJ29,'Treasury Yields'!$C$250:$N$279,$E29,FALSE)/100)))))))),0) -> 0.0254676 | BL29: =1+BH29*(AL29-BK29)+(AL29-BK29)^2 -> 1.6012661 | BM29: =BL29*R29 -> 1.439959e+08 | BN29: =BM29-AB29 -> 72654930 | BP29: =IF($BJ29<=30,IF($B29=2015,VLOOKUP($BJ29,'Treasury Yields'!$C$40:$N$69,$E29,FALSE)/100,IF($B29=2016,VLOOKUP($BJ29,'Treasury Yields'!$C$75:$N$104,$E29,FALSE)/100,IF($B29=2017,VLOOKUP($BJ29,'Treasury Yields'!$C$110:$N$139,$E29,FALSE)/100,IF($B29=2018,VLOOKUP($BJ29,'Treasury Yields'!$C$145:$N$174,$E29,FALSE)/100,IF($B29=2019,VLOOKUP($BJ29,'Treasury Yields'!$C$180:$N$209,$E29,FALSE)/100,IF($B29=2020,VLOOKUP($BJ29,'Treasury Yields'!$C$215:$N$244,$E29,FALSE)/100,IF($B29=2021,VLOOKUP($BJ29,'Treasury Yields'!$C$250:$N$279,$E29,FALSE)/100,IF($B29=2022,VLOOKUP($BJ29,'Treasury Yields'!$C$285:$N$314,$E29,FALSE)/100)))))))),0) -> 0.028906473 | BQ29: =1+BH29*(AN29-BP29)+(AN29-BP29)^2 -> 1.5593636 | BR29: =BQ29*S29 -> 1.4672843e+08 | BS29: =BR29-AC29 -> 71195501 | BU29: =IF(BJ29="","",ROUND(BJ29+$BT$2,0)) -> 15 | BV29: =1+(BH29+BU29)*(AN29-BK29)+(AN29-BK29)^2*BI29 -> 2.6150417 | BW29: =BV29*J29 -> 3882565.5 | BX29: =(BM29+BW29-O29)*BK29 -> 3646414 | BY29: =BK29*(BN29+BW29-O29) -> 1829530.6 | BZ29: =SUM(J29:K29) -> 8050077 | CA29: =SUM(BW29+BY29) -> 5712096.1 | CC29: =BR29 -> 1.4672843e+08 | CD29: =F29 -> Georgia | CE29: =BB29 -> 0.80272991 | CF29: =AC29/CC29 -> 0.51478045
A30: 11000000011301 | B30: 2019 | C30: 576 | D30: plan315_y2021 | E30: 6 | F30: Georgia | G30: Teachers' Retirement System of Georgia | H30: TRS | I30: TRUE | J30: 1536336 | K30: 6868617 | M30: 430272 | N30: 2388357 | O30: 4950465 | P30: 76543 | Q30: 6196574 | R30: 94095067 | S30: 100291641 | T30: 2560810 | U30: 5414 | V30: 759474 | W30: 4972419 | Y30: 15276 | Z30: 0 | AA30: 3256012 | AB30: 75532925 | AC30: 78788937 | AD30: 21502704 | AE30: 18562142 | AF30: 2940562 | AG30: 12279440 | AH30: 0.20854453 | AI30: TRUE | AK30: 0.075 | AL30: 0.0725 | AM30: 0.0725 | AN30: 0.075 | AO30: 1 | AP30: 0 | AS30: 34905182 | AT30: 10481105 | AU30: p233 of CAFR | AV30: https://sao.georgia.gov/statewide-reporting/comprehensive-annual-financial-reports | BB30: =AC30/S30 -> 0.78559824 | BD30: =AS30-AD30 -> 13402478 | BE30: =AT30-AD30 -> -11021599 | BF30: =BD30/S30*100 -> 13.363505 | BG30: =BE30/S30*100 -> -10.989549 | BH30: =(BD30-BE30)/(2*S30)*100 -> 12.176527 | BI30: =(BD30+BE30)/(2*S30*(0.01^2)) -> 118.69778 | BJ30: =ROUND(BH30,0) -> 12 | BK30: =IF($BJ30<=30,IF($B30=2015,VLOOKUP($BJ30,'Treasury Yields'!$C$5:$N$34,$E30,FALSE)/100,IF($B30=2016,VLOOKUP($BJ30,'Treasury Yields'!$C$40:$N$69,$E30,FALSE)/100,IF($B30=2017,VLOOKUP($BJ30,'Treasury Yields'!$C$75:$N$104,$E30,FALSE)/100,IF($B30=2018,VLOOKUP($BJ30,'Treasury Yields'!$C$110:$N$139,$E30,FALSE)/100,IF($B30=2019,VLOOKUP($BJ30,'Treasury Yields'!$C$145:$N$174,$E30,FALSE)/100,IF($B30=2020,VLOOKUP($BJ30,'Treasury Yields'!$C$180:$N$209,$E30,FALSE)/100,IF($B30=2021,VLOOKUP($BJ30,'Treasury Yields'!$C$215:$N$244,$E30,FALSE)/100,IF($B30=2022,VLOOKUP($BJ30,'Treasury Yields'!$C$250:$N$279,$E30,FALSE)/100)))))))),0) -> 0.028906473 | BL30: =1+BH30*(AL30-BK30)+(AL30-BK30)^2 -> 1.5327181 | BM30: =BL30*R30 -> 1.4422122e+08 | BN30: =BM30-AB30 -> 68688292 | BP30: =IF($BJ30<=30,IF($B30=2015,VLOOKUP($BJ30,'Treasury Yields'!$C$40:$N$69,$E30,FALSE)/100,IF($B30=2016,VLOOKUP($BJ30,'Treasury Yields'!$C$75:$N$104,$E30,FALSE)/100,IF($B30=2017,VLOOKUP($BJ30,'Treasury Yields'!$C$110:$N$139,$E30,FALSE)/100,IF($B30=2018,VLOOKUP($BJ30,'Treasury Yields'!$C$145:$N$174,$E30,FALSE)/100,IF($B30=2019,VLOOKUP($BJ30,'Treasury Yields'!$C$180:$N$209,$E30,FALSE)/100,IF($B30=2020,VLOOKUP($BJ30,'Treasury Yields'!$C$215:$N$244,$E30,FALSE)/100,IF($B30=2021,VLOOKUP($BJ30,'Treasury Yields'!$C$250:$N$279,$E30,FALSE)/100,IF($B30=2022,VLOOKUP($BJ30,'Treasury Yields'!$C$285:$N$314,$E30,FALSE)/100)))))))),0) -> 0.022184 | BQ30: =1+BH30*(AN30-BP30)+(AN30-BP30)^2 -> 1.645905 | BR30: =BQ30*S30 -> 1.6507051e+08 | BS30: =BR30-AC30 -> 86281573 | BU30: =IF(BJ30="","",ROUND(BJ30+$BT$2,0)) -> 15 | BV30: =1+(BH30+BU30)*(AN30-BK30)+(AN30-BK30)^2*BI30 -> 2.5048489 | BW30: =BV30*J30 -> 3848289.5 | BX30: =(BM30+BW30-O30)*BK30 -> 4137066.7 | BY30: =BK30*(BN30+BW30-O30) -> 1953676.2 | BZ30: =SUM(J30:K30) -> 8404953 | CA30: =SUM(BW30+BY30) -> 5801965.7 | CC30: =BR30 -> 1.6507051e+08 | CD30: =F30 -> Georgia | CE30: =BB30 -> 0.78559824 | CF30: =AC30/CC30 -> 0.47730474
A31: 11000000011301 | B31: 2020 | C31: 576 | D31: plan315_y2021 | E31: 6 | F31: Georgia | G31: Teachers' Retirement System of Georgia | H31: TRS | I31: TRUE | J31: 1597714 | K31: 7080133 | M31: 368463 | N31: 1316780 | O31: 5192283 | P31: 76976 | Q31: 5093831 | R31: 100291641 | S31: 105385472 | T31: 2733089 | U31: 5729 | V31: 800864 | W31: 4119609 | Y31: 17411 | Z31: 0 | AA31: 2372621 | AB31: 78788937 | AC31: 81161558 | AD31: 24223914 | AE31: 21502704 | AF31: 2721210 | AG31: 12955620 | AH31: 0.21095779 | AI31: TRUE | AK31: 0.0725 | AL31: 0.0725 | AM31: 0.0725 | AN31: 0.0725 | AO31: 1 | AP31: 0 | AS31: 38413345 | AT31: 12592649 | AU31: p41 of CAFR | AV31: https://www.trsga.com/uploads/TRS_CAFR_2020_final_web.pdf | BB31: =AC31/S31 -> 0.77013991 | BD31: =AS31-AD31 -> 14189431 | BE31: =AT31-AD31 -> -11631265 | BF31: =BD31/S31*100 -> 13.464314 | BG31: =BE31/S31*100 -> -11.036877 | BH31: =(BD31-BE31)/(2*S31)*100 -> 12.250596 | BI31: =(BD31+BE31)/(2*S31*(0.01^2)) -> 121.37185 | BJ31: =ROUND(BH31,0) -> 12 | BK31: =IF($BJ31<=30,IF($B31=2015,VLOOKUP($BJ31,'Treasury Yields'!$C$5:$N$34,$E31,FALSE)/100,IF($B31=2016,VLOOKUP($BJ31,'Treasury Yields'!$C$40:$N$69,$E31,FALSE)/100,IF($B31=2017,VLOOKUP($BJ31,'Treasury Yields'!$C$75:$N$104,$E31,FALSE)/100,IF($B31=2018,VLOOKUP($BJ31,'Treasury Yields'!$C$110:$N$139,$E31,FALSE)/100,IF($B31=2019,VLOOKUP($BJ31,'Treasury Yields'!$C$145:$N$174,$E31,FALSE)/100,IF($B31=2020,VLOOKUP($BJ31,'Treasury Yields'!$C$180:$N$209,$E31,FALSE)/100,IF($B31=2021,VLOOKUP($BJ31,'Treasury Yields'!$C$215:$N$244,$E31,FALSE)/100,IF($B31=2022,VLOOKUP($BJ31,'Treasury Yields'!$C$250:$N$279,$E31,FALSE)/100)))))))),0) -> 0.022184 | BL31: =1+BH31*(AL31-BK31)+(AL31-BK31)^2 -> 1.6189327 | BM31: =BL31*R31 -> 1.6236541e+08 | BN31: =BM31-AB31 -> 83576477 | BP31: =IF($BJ31<=30,IF($B31=2015,VLOOKUP($BJ31,'Treasury Yields'!$C$40:$N$69,$E31,FALSE)/100,IF($B31=2016,VLOOKUP($BJ31,'Treasury Yields'!$C$75:$N$104,$E31,FALSE)/100,IF($B31=2017,VLOOKUP($BJ31,'Treasury Yields'!$C$110:$N$139,$E31,FALSE)/100,IF($B31=2018,VLOOKUP($BJ31,'Treasury Yields'!$C$145:$N$174,$E31,FALSE)/100,IF($B31=2019,VLOOKUP($BJ31,'Treasury Yields'!$C$180:$N$209,$E31,FALSE)/100,IF($B31=2020,VLOOKUP($BJ31,'Treasury Yields'!$C$215:$N$244,$E31,FALSE)/100,IF($B31=2021,VLOOKUP($BJ31,'Treasury Yields'!$C$250:$N$279,$E31,FALSE)/100,IF($B31=2022,VLOOKUP($BJ31,'Treasury Yields'!$C$285:$N$314,$E31,FALSE)/100)))))))),0) -> 0.013689455 | BQ31: =1+BH31*(AN31-BP31)+(AN31-BP31)^2 -> 1.7239229 | BR31: =BQ31*S31 -> 1.8167643e+08 | BS31: =BR31-AC31 -> 1.0051487e+08 | BU31: =IF(BJ31="","",ROUND(BJ31+$BT$2,0)) -> 15 | BV31: =1+(BH31+BU31)*(AN31-BK31)+(AN31-BK31)^2*BI31 -> 2.6784181 | BW31: =BV31*J31 -> 4279346 | BX31: =(BM31+BW31-O31)*BK31 -> 3581661.8 | BY31: =BK31*(BN31+BW31-O31) -> 1833808 | BZ31: =SUM(J31:K31) -> 8677847 | CA31: =SUM(BW31+BY31) -> 6113154 | CC31: =BR31 -> 1.8167643e+08 | CD31: =F31 -> Georgia | CE31: =BB31 -> 0.77013991 | CF31: =AC31/CC31 -> 0.44673687
A32: 11000000011301 | B32: 2021 | C32: 576 | D32: plan315_y2021 | E32: 6 | F32: Georgia | G32: Teachers' Retirement System of Georgia | H32: TRS | I32: TRUE | J32: 1734145 | K32: 7440942 | M32: 1934042 | N32: 0 | O32: 5434414 | P32: 69166 | Q32: 5605549 | R32: 105385472 | S32: 110991021 | T32: 2490267 | U32: 5123 | V32: 817090 | W32: 23192761 | Y32: 16668 | Z32: 0 | AA32: 20985130 | AB32: 81161558 | AC32: 102146688 | AD32: 8844333 | AE32: 24223914 | AF32: -15379581 | AG32: 13093006 | AH32: 0.19019826 | AI32: TRUE | AK32: 0.0725 | AL32: 0.0725 | AM32: 0.0725 | AN32: 0.0725 | AS32: 23824290 | AT32: -3430708 | BB32: =AC32/S32 -> 0.92031488 | BD32: =AS32-AD32 -> 14979957 | BE32: =AT32-AD32 -> -12275041 | BF32: =BD32/S32*100 -> 13.496549 | BG32: =BE32/S32*100 -> -11.05949 | BH32: =(BD32-BE32)/(2*S32)*100 -> 12.278019 | BI32: =(BD32+BE32)/(2*S32*(0.01^2)) -> 121.85292 | BJ32: =ROUND(BH32,0) -> 12 | BK32: =IF($BJ32<=30,IF($B32=2015,VLOOKUP($BJ32,'Treasury Yields'!$C$5:$N$34,$E32,FALSE)/100,IF($B32=2016,VLOOKUP($BJ32,'Treasury Yields'!$C$40:$N$69,$E32,FALSE)/100,IF($B32=2017,VLOOKUP($BJ32,'Treasury Yields'!$C$75:$N$104,$E32,FALSE)/100,IF($B32=2018,VLOOKUP($BJ32,'Treasury Yields'!$C$110:$N$139,$E32,FALSE)/100,IF($B32=2019,VLOOKUP($BJ32,'Treasury Yields'!$C$145:$N$174,$E32,FALSE)/100,IF($B32=2020,VLOOKUP($BJ32,'Treasury Yields'!$C$180:$N$209,$E32,FALSE)/100,IF($B32=2021,VLOOKUP($BJ32,'Treasury Yields'!$C$215:$N$244,$E32,FALSE)/100,IF($B32=2022,VLOOKUP($BJ32,'Treasury Yields'!$C$250:$N$279,$E32,FALSE)/100)))))))),0) -> 0.013689455 | BL32: =1+BH32*(AL32-BK32)+(AL32-BK32)^2 -> 1.7255357 | BM32: =BL32*R32 -> 1.8184639e+08 | BN32: =BM32-AB32 -> 1.0068484e+08 | BP32: =IF($BJ32<=30,IF($B32=2015,VLOOKUP($BJ32,'Treasury Yields'!$C$40:$N$69,$E32,FALSE)/100,IF($B32=2016,VLOOKUP($BJ32,'Treasury Yields'!$C$75:$N$104,$E32,FALSE)/100,IF($B32=2017,VLOOKUP($BJ32,'Treasury Yields'!$C$110:$N$139,$E32,FALSE)/100,IF($B32=2018,VLOOKUP($BJ32,'Treasury Yields'!$C$145:$N$174,$E32,FALSE)/100,IF($B32=2019,VLOOKUP($BJ32,'Treasury Yields'!$C$180:$N$209,$E32,FALSE)/100,IF($B32=2020,VLOOKUP($BJ32,'Treasury Yields'!$C$215:$N$244,$E32,FALSE)/100,IF($B32=2021,VLOOKUP($BJ32,'Treasury Yields'!$C$250:$N$279,$E32,FALSE)/100,IF($B32=2022,VLOOKUP($BJ32,'Treasury Yields'!$C$285:$N$314,$E32,FALSE)/100)))))))),0) -> 0.021085818 | BQ32: =1+BH32*(AN32-BP32)+(AN32-BP32)^2 -> 1.6339077 | BR32: =BQ32*S32 -> 1.8134909e+08 | BS32: =BR32-AC32 -> 79202400 | BU32: =IF(BJ32="","",ROUND(BJ32+$BT$2,0)) -> 15 | BV32: =1+(BH32+BU32)*(AN32-BK32)+(AN32-BK32)^2*BI32 -> 3.0256855 | BW32: =BV32*J32 -> 5246977.4 | BX32: =(BM32+BW32-O32)*BK32 -> 2486812 | BY32: =BK32*(BN32+BW32-O32) -> 1375754.6 | BZ32: =SUM(J32:K32) -> 9175087 | CA32: =SUM(BW32+BY32) -> 6622731.9 | CC32: =BR32 -> 1.8134909e+08 | CD32: =F32 -> Georgia | CE32: =BB32 -> 0.92031488 | CF32: =AC32/CC32 -> 0.56326
A33: 11000000011301 | B33: 2022 | C33: 576 | D33: plan315_y2021 | E33: 6 | F33: Georgia | G33: Teachers' Retirement System of Georgia | H33: TRS | I33: TRUE | J33: 1742643 | K33: 7837074 | M33: -215975 | N33: 5026914 | O33: 5692032 | P33: 94853 | Q33: 8603771 | R33: 110991021 | S33: 119594792 | T33: 2691316 | U33: 5398 | V33: 853376 | W33: -12770564 | Y33: 16470 | AA33: -15023829 | AB33: 102146688 | AC33: 87122859 | AD33: 32471933 | AE33: 8844333 | AF33: 23627600 | AG33: 13612892 | AH33: 0.19770347 | AI33: TRUE | AK33: 0.0725 | AL33: 0.069 | AM33: 0.069 | AN33: 0.0725 | AS33: 48989393 | AT33: 18983242 | AV33: https://api.trsga.com/library/files/publications/TRS%20ACFR%202022_Final.pdf | BB33: =AC33/S33 -> 0.72848372 | BD33: =AS33-AD33 -> 16517460 | BE33: =AT33-AD33 -> -13488691 | BF33: =BD33/S33*100 -> 13.811187 | BG33: =BE33/S33*100 -> -11.278661 | BH33: =(BD33-BE33)/(2*S33)*100 -> 12.544924 | BI33: =(BD33+BE33)/(2*S33*(0.01^2)) -> 126.62629 | BJ33: =ROUND(BH33,0) -> 13 | BK33: =IF($BJ33<=30,IF($B33=2015,VLOOKUP($BJ33,'Treasury Yields'!$C$5:$N$34,$E33,FALSE)/100,IF($B33=2016,VLOOKUP($BJ33,'Treasury Yields'!$C$40:$N$69,$E33,FALSE)/100,IF($B33=2017,VLOOKUP($BJ33,'Treasury Yields'!$C$75:$N$104,$E33,FALSE)/100,IF($B33=2018,VLOOKUP($BJ33,'Treasury Yields'!$C$110:$N$139,$E33,FALSE)/100,IF($B33=2019,VLOOKUP($BJ33,'Treasury Yields'!$C$145:$N$174,$E33,FALSE)/100,IF($B33=2020,VLOOKUP($BJ33,'Treasury Yields'!$C$180:$N$209,$E33,FALSE)/100,IF($B33=2021,VLOOKUP($BJ33,'Treasury Yields'!$C$215:$N$244,$E33,FALSE)/100,IF($B33=2022,VLOOKUP($BJ33,'Treasury Yields'!$C$250:$N$279,$E33,FALSE)/100)))))))),0) -> 0.020617364 | BL33: =1+BH33*(AL33-BK33)+(AL33-BK33)^2 -> 1.6092974 | BM33: =BL33*R33 -> 1.7861756e+08 | BN33: =BM33-AB33 -> 76470870 | BP33: =IF($BJ33<=30,IF($B33=2015,VLOOKUP($BJ33,'Treasury Yields'!$C$40:$N$69,$E33,FALSE)/100,IF($B33=2016,VLOOKUP($BJ33,'Treasury Yields'!$C$75:$N$104,$E33,FALSE)/100,IF($B33=2017,VLOOKUP($BJ33,'Treasury Yields'!$C$110:$N$139,$E33,FALSE)/100,IF($B33=2018,VLOOKUP($BJ33,'Treasury Yields'!$C$145:$N$174,$E33,FALSE)/100,IF($B33=2019,VLOOKUP($BJ33,'Treasury Yields'!$C$180:$N$209,$E33,FALSE)/100,IF($B33=2020,VLOOKUP($BJ33,'Treasury Yields'!$C$215:$N$244,$E33,FALSE)/100,IF($B33=2021,VLOOKUP($BJ33,'Treasury Yields'!$C$250:$N$279,$E33,FALSE)/100,IF($B33=2022,VLOOKUP($BJ33,'Treasury Yields'!$C$285:$N$314,$E33,FALSE)/100)))))))),0) -> 0.032868636 | BQ33: =1+BH33*(AN33-BP33)+(AN33-BP33)^2 -> 1.4987431 | BR33: =BQ33*S33 -> 1.7924187e+08 | BS33: =BR33-AC33 -> 92119008 | BU33: =IF(BJ33="","",ROUND(BJ33+$BT$2,0)) -> 16 | BV33: =1+(BH33+BU33)*(AN33-BK33)+(AN33-BK33)^2*BI33 -> 2.8218396 | BW33: =BV33*J33 -> 4917459 | BX33: =(BM33+BW33-O33)*BK33 -> 3666653.5 | BY33: =BK33*(BN33+BW33-O33) -> 1560658.1 | BZ33: =SUM(J33:K33) -> 9579717 | CA33: =SUM(BW33+BY33) -> 6478117 | CC33: =BR33 -> 1.7924187e+08 | CD33: =F33 -> Georgia | CE33: =BB33 -> 0.72848372 | CF33: =AC33/CC33 -> 0.48606311
A34: 22000000000703 | B34: 2015 | C34: 344 | D34: plan24_y2021 | E34: 6 | F34: Massachusetts | G34: Massachusetts Teachers' Retirement System | H34: TRS | I34: TRUE | J34: 768032 | K34: 3166728 | M34: 153000 | N34: 1890000 | O34: 2684049 | Q34: 3293711 | R34: 41435000 | S34: 44728711 | T34: 1021930 | U34: 190925 | V34: 669941 | W34: 845503 | Y34: 23444 | Z34: -130384 | AA34: -109578 | AB34: 25538646 | AC34: 25429068 | AD34: 19299643 | AE34: 15896354 | AF34: 3403289 | AG34: 6204274 | AH34: 0.16471387 | AI34: TRUE | AK34: 0.08 | AL34: 0.0775 | AM34: 0.0775 | AN34: 0.08 | AO34: 1 | AP34: 0 | AS34: 23959568 | AT34: 15271501 | AU34: p137 of CAFR | AV34: http://www.mass.gov/comptroller/docs/reports-audits/cafr/fy2015-cafr.pdf | BB34: =AC34/S34 -> 0.56851779 | BD34: =AS34-AD34 -> 4659925 | BE34: =AT34-AD34 -> -4028142 | BF34: =BD34/S34*100 -> 10.418196 | BG34: =BE34/S34*100 -> -9.0057189 | BH34: =(BD34-BE34)/(2*S34)*100 -> 9.7119577 | BI34: =(BD34+BE34)/(2*S34*(0.01^2)) -> 70.623877 | BJ34: =ROUND(BH34,0) -> 10 | BK34: =IF($BJ34<=30,IF($B34=2015,VLOOKUP($BJ34,'Treasury Yields'!$C$5:$N$34,$E34,FALSE)/100,IF($B34=2016,VLOOKUP($BJ34,'Treasury Yields'!$C$40:$N$69,$E34,FALSE)/100,IF($B34=2017,VLOOKUP($BJ34,'Treasury Yields'!$C$75:$N$104,$E34,FALSE)/100,IF($B34=2018,VLOOKUP($BJ34,'Treasury Yields'!$C$110:$N$139,$E34,FALSE)/100,IF($B34=2019,VLOOKUP($BJ34,'Treasury Yields'!$C$145:$N$174,$E34,FALSE)/100,IF($B34=2020,VLOOKUP($BJ34,'Treasury Yields'!$C$180:$N$209,$E34,FALSE)/100,IF($B34=2021,VLOOKUP($BJ34,'Treasury Yields'!$C$215:$N$244,$E34,FALSE)/100,IF($B34=2022,VLOOKUP($BJ34,'Treasury Yields'!$C$250:$N$279,$E34,FALSE)/100)))))))),0) -> 0.02711 | BL34: =1+BH34*(AL34-BK34)+(AL34-BK34)^2 -> 1.4919247 | BM34: =BL34*R34 -> 61817900 | BN34: =BM34-AB34 -> 36279254 | BP34: =IF($BJ34<=30,IF($B34=2015,VLOOKUP($BJ34,'Treasury Yields'!$C$40:$N$69,$E34,FALSE)/100,IF($B34=2016,VLOOKUP($BJ34,'Treasury Yields'!$C$75:$N$104,$E34,FALSE)/100,IF($B34=2017,VLOOKUP($BJ34,'Treasury Yields'!$C$110:$N$139,$E34,FALSE)/100,IF($B34=2018,VLOOKUP($BJ34,'Treasury Yields'!$C$145:$N$174,$E34,FALSE)/100,IF($B34=2019,VLOOKUP($BJ34,'Treasury Yields'!$C$180:$N$209,$E34,FALSE)/100,IF($B34=2020,VLOOKUP($BJ34,'Treasury Yields'!$C$215:$N$244,$E34,FALSE)/100,IF($B34=2021,VLOOKUP($BJ34,'Treasury Yields'!$C$250:$N$279,$E34,FALSE)/100,IF($B34=2022,VLOOKUP($BJ34,'Treasury Yields'!$C$285:$N$314,$E34,FALSE)/100)))))))),0) -> 0.02547 | BQ34: =1+BH34*(AN34-BP34)+(AN34-BP34)^2 -> 1.5325666 | BR34: =BQ34*S34 -> 68549727 | BS34: =BR34-AC34 -> 43120659 | BU34: =IF(BJ34="","",ROUND(BJ34+$BT$2,0)) -> 13 | BV34: =1+(BH34+BU34)*(AN34-BK34)+(AN34-BK34)^2*BI34 -> 2.3987953 | BW34: =BV34*J34 -> 1842351.5 | BX34: =(BM34+BW34-O34)*BK34 -> 1653064.9 | BY34: =BK34*(BN34+BW34-O34) -> 960712.16 | BZ34: =SUM(J34:K34) -> 3934760 | CA34: =SUM(BW34+BY34) -> 2803063.7 | CC34: =BR34 -> 68549727 | CD34: =F34 -> Massachusetts | CE34: =BB34 -> 0.56851779 | CF34: =AC34/CC34 -> 0.37095797
A35: 22000000000703 | B35: 2016 | C35: 344 | D35: plan24_y2021 | E35: 6 | F35: Massachusetts | G35: Massachusetts Teachers' Retirement System | H35: TRS | I35: TRUE | J35: 843800 | K35: 3402525 | M35: -74025 | O35: 2791011 | Q35: 1381289 | R35: 45918711 | S35: 47300000 | T35: 1124583 | U35: 202796 | V35: 699422 | W35: 441363 | Y35: 24220 | Z35: -139929 | AA35: -486996 | AB35: 25429068 | AC35: 24942072 | AD35: 22357928 | AE35: 20489643 | AF35: 1868285 | AG35: 6388732 | AH35: 0.17602601 | AI35: TRUE | AK35: 0.0775 | AL35: 0.075 | AM35: 0.075 | AN35: 0.0775 | AO35: 1 | AP35: 0 | AS35: 27464000 | AT35: 18022000 | AU35: p139 of CAFR | AV35: http://www.mass.gov/comptroller/docs/reports-audits/cafr/2016-cafr.pdf | BB35: =AC35/S35 -> 0.52731653 | BD35: =AS35-AD35 -> 5106072 | BE35: =AT35-AD35 -> -4335928 | BF35: =BD35/S35*100 -> 10.795078 | BG35: =BE35/S35*100 -> -9.1668668 | BH35: =(BD35-BE35)/(2*S35)*100 -> 9.9809725 | BI35: =(BD35+BE35)/(2*S35*(0.01^2)) -> 81.410571 | BJ35: =ROUND(BH35,0) -> 10 | BK35: =IF($BJ35<=30,IF($B35=2015,VLOOKUP($BJ35,'Treasury Yields'!$C$5:$N$34,$E35,FALSE)/100,IF($B35=2016,VLOOKUP($BJ35,'Treasury Yields'!$C$40:$N$69,$E35,FALSE)/100,IF($B35=2017,VLOOKUP($BJ35,'Treasury Yields'!$C$75:$N$104,$E35,FALSE)/100,IF($B35=2018,VLOOKUP($BJ35,'Treasury Yields'!$C$110:$N$139,$E35,FALSE)/100,IF($B35=2019,VLOOKUP($BJ35,'Treasury Yields'!$C$145:$N$174,$E35,FALSE)/100,IF($B35=2020,VLOOKUP($BJ35,'Treasury Yields'!$C$180:$N$209,$E35,FALSE)/100,IF($B35=2021,VLOOKUP($BJ35,'Treasury Yields'!$C$215:$N$244,$E35,FALSE)/100,IF($B35=2022,VLOOKUP($BJ35,'Treasury Yields'!$C$250:$N$279,$E35,FALSE)/100)))))))),0) -> 0.02547 | BL35: =1+BH35*(AL35-BK35)+(AL35-BK35)^2 -> 1.4968108 | BM35: =BL35*R35 -> 68731622 | BN35: =BM35-AB35 -> 43302554 | BP35: =IF($BJ35<=30,IF($B35=2015,VLOOKUP($BJ35,'Treasury Yields'!$C$40:$N$69,$E35,FALSE)/100,IF($B35=2016,VLOOKUP($BJ35,'Treasury Yields'!$C$75:$N$104,$E35,FALSE)/100,IF($B35=2017,VLOOKUP($BJ35,'Treasury Yields'!$C$110:$N$139,$E35,FALSE)/100,IF($B35=2018,VLOOKUP($BJ35,'Treasury Yields'!$C$145:$N$174,$E35,FALSE)/100,IF($B35=2019,VLOOKUP($BJ35,'Treasury Yields'!$C$180:$N$209,$E35,FALSE)/100,IF($B35=2020,VLOOKUP($BJ35,'Treasury Yields'!$C$215:$N$244,$E35,FALSE)/100,IF($B35=2021,VLOOKUP($BJ35,'Treasury Yields'!$C$250:$N$279,$E35,FALSE)/100,IF($B35=2022,VLOOKUP($BJ35,'Treasury Yields'!$C$285:$N$314,$E35,FALSE)/100)))))))),0) -> 0.01635 | BQ35: =1+BH35*(AN35-BP35)+(AN35-BP35)^2 -> 1.6140758 | BR35: =BQ35*S35 -> 76345785 | BS35: =BR35-AC35 -> 51403713 | BU35: =IF(BJ35="","",ROUND(BJ35+$BT$2,0)) -> 13 | BV35: =1+(BH35+BU35)*(AN35-BK35)+(AN35-BK35)^2*BI35 -> 2.4160883 | BW35: =BV35*J35 -> 2038695.3 | BX35: =(BM35+BW35-O35)*BK35 -> 1731432.9 | BY35: =BK35*(BN35+BW35-O35) -> 1083754.6 | BZ35: =SUM(J35:K35) -> 4246325 | CA35: =SUM(BW35+BY35) -> 3122449.8 | CC35: =BR35 -> 76345785 | CD35: =F35 -> Massachusetts | CE35: =BB35 -> 0.52731653 | CF35: =AC35/CC35 -> 0.32669874
A36: 22000000000703 | B36: 2017 | C36: 344 | D36: plan24_y2021 | E36: 6 | F36: Massachusetts | G36: Massachusetts Teachers' Retirement System | H36: TRS | I36: TRUE | J36: 891760 | K36: 3505761 | M36: 47046 | N36: 1176000 | O36: 2896567 | Q36: 2724000 | R36: 47300000 | S36: 50024000 | T36: 1235515 | U36: 223746 | V36: 730212 | W36: 3100352 | Y36: 24053 | Z36: -172668 | AA36: 2196537 | AB36: 24942072 | AC36: 27138609 | AD36: 22885391 | AE36: 22357928 | AF36: 527463 | AG36: 6583871 | AH36: 0.18765784 | AI36: TRUE | AK36: 0.075 | AL36: 0.075 | AM36: 0.075 | AN36: 0.075 | AO36: 1 | AP36: 0 | AS36: 28424300 | AT36: 18193400 | AU36: p143 of CAFR | AV36: http://www.macomptroller.info/comptroller/docs/reports-audits/cafr/cafr-fy17.pdf | BB36: =AC36/S36 -> 0.54251177 | BD36: =AS36-AD36 -> 5538909 | BE36: =AT36-AD36 -> -4691991 | BF36: =BD36/S36*100 -> 11.072503 | BG36: =BE36/S36*100 -> -9.3794798 | BH36: =(BD36-BE36)/(2*S36)*100 -> 10.225992 | BI36: =(BD36+BE36)/(2*S36*(0.01^2)) -> 84.651167 | BJ36: =ROUND(BH36,0) -> 10 | BK36: =IF($BJ36<=30,IF($B36=2015,VLOOKUP($BJ36,'Treasury Yields'!$C$5:$N$34,$E36,FALSE)/100,IF($B36=2016,VLOOKUP($BJ36,'Treasury Yields'!$C$40:$N$69,$E36,FALSE)/100,IF($B36=2017,VLOOKUP($BJ36,'Treasury Yields'!$C$75:$N$104,$E36,FALSE)/100,IF($B36=2018,VLOOKUP($BJ36,'Treasury Yields'!$C$110:$N$139,$E36,FALSE)/100,IF($B36=2019,VLOOKUP($BJ36,'Treasury Yields'!$C$145:$N$174,$E36,FALSE)/100,IF($B36=2020,VLOOKUP($BJ36,'Treasury Yields'!$C$180:$N$209,$E36,FALSE)/100,IF($B36=2021,VLOOKUP($BJ36,'Treasury Yields'!$C$215:$N$244,$E36,FALSE)/100,IF($B36=2022,VLOOKUP($BJ36,'Treasury Yields'!$C$250:$N$279,$E36,FALSE)/100)))))))),0) -> 0.01635 | BL36: =1+BH36*(AL36-BK36)+(AL36-BK36)^2 -> 1.6031942 | BM36: =BL36*R36 -> 75831087 | BN36: =BM36-AB36 -> 50889015 | BP36: =IF($BJ36<=30,IF($B36=2015,VLOOKUP($BJ36,'Treasury Yields'!$C$40:$N$69,$E36,FALSE)/100,IF($B36=2016,VLOOKUP($BJ36,'Treasury Yields'!$C$75:$N$104,$E36,FALSE)/100,IF($B36=2017,VLOOKUP($BJ36,'Treasury Yields'!$C$110:$N$139,$E36,FALSE)/100,IF($B36=2018,VLOOKUP($BJ36,'Treasury Yields'!$C$145:$N$174,$E36,FALSE)/100,IF($B36=2019,VLOOKUP($BJ36,'Treasury Yields'!$C$180:$N$209,$E36,FALSE)/100,IF($B36=2020,VLOOKUP($BJ36,'Treasury Yields'!$C$215:$N$244,$E36,FALSE)/100,IF($B36=2021,VLOOKUP($BJ36,'Treasury Yields'!$C$250:$N$279,$E36,FALSE)/100,IF($B36=2022,VLOOKUP($BJ36,'Treasury Yields'!$C$285:$N$314,$E36,FALSE)/100)))))))),0) -> 0.02467 | BQ36: =1+BH36*(AN36-BP36)+(AN36-BP36)^2 -> 1.5172073 | BR36: =BQ36*S36 -> 75896776 | BS36: =BR36-AC36 -> 48758167 | BU36: =IF(BJ36="","",ROUND(BJ36+$BT$2,0)) -> 13 | BV36: =1+(BH36+BU36)*(AN36-BK36)+(AN36-BK36)^2*BI36 -> 2.6533894 | BW36: =BV36*J36 -> 2366186.5 | BX36: =(BM36+BW36-O36)*BK36 -> 1231166.5 | BY36: =BK36*(BN36+BW36-O36) -> 823363.67 | BZ36: =SUM(J36:K36) -> 4397521 | CA36: =SUM(BW36+BY36) -> 3189550.2 | CC36: =BR36 -> 75896776 | CD36: =F36 -> Massachusetts | CE36: =BB36 -> 0.54251177 | CF36: =AC36/CC36 -> 0.35757262
A37: 22000000000703 | B37: 2018 | C37: 344 | D37: plan24_y2021 | E37: 6 | F37: Massachusetts | G37: Massachusetts Teachers' Retirement System | H37: TRS | I37: TRUE | J37: 901234 | K37: 3633027 | M37: 92317 | N37: 845000 | O37: 2992578 | Q37: 2479000 | R37: 50024000 | S37: 52503000 | T37: 1314783 | U37: 231734 | V37: 755688 | W37: 2542576 | Y37: 19528 | Z37: -179573 | AA37: 1653102 | AB37: 27138609 | AC37: 28791711 | AD37: 23711289 | AE37: 22885391 | AF37: 825898 | AG37: 6829012 | AH37: 0.19252902 | AI37: TRUE | AK37: 0.075 | AL37: 0.0735 | AM37: 0.0735 | AN37: 0.075 | AO37: 1 | AP37: 0 | AS37: 29482300 | AT37: 18771300 | AU37: p142 of CAFR | AV37: http://www.macomptroller.info/comptroller/docs/reports-audits/cafr/cafr-fy18.pdf | BB37: =AC37/S37 -> 0.54838221 | BD37: =AS37-AD37 -> 5771011 | BE37: =AT37-AD37 -> -4939989 | BF37: =BD37/S37*100 -> 10.991774 | BG37: =BE37/S37*100 -> -9.4089652 | BH37: =(BD37-BE37)/(2*S37)*100 -> 10.20037 | BI37: =(BD37+BE37)/(2*S37*(0.01^2)) -> 79.14043 | BJ37: =ROUND(BH37,0) -> 10 | BK37: =IF($BJ37<=30,IF($B37=2015,VLOOKUP($BJ37,'Treasury Yields'!$C$5:$N$34,$E37,FALSE)/100,IF($B37=2016,VLOOKUP($BJ37,'Treasury Yields'!$C$40:$N$69,$E37,FALSE)/100,IF($B37=2017,VLOOKUP($BJ37,'Treasury Yields'!$C$75:$N$104,$E37,FALSE)/100,IF($B37=2018,VLOOKUP($BJ37,'Treasury Yields'!$C$110:$N$139,$E37,FALSE)/100,IF($B37=2019,VLOOKUP($BJ37,'Treasury Yields'!$C$145:$N$174,$E37,FALSE)/100,IF($B37=2020,VLOOKUP($BJ37,'Treasury Yields'!$C$180:$N$209,$E37,FALSE)/100,IF($B37=2021,VLOOKUP($BJ37,'Treasury Yields'!$C$215:$N$244,$E37,FALSE)/100,IF($B37=2022,VLOOKUP($BJ37,'Treasury Yields'!$C$250:$N$279,$E37,FALSE)/100)))))))),0) -> 0.02467 | BL37: =1+BH37*(AL37-BK37)+(AL37-BK37)^2 -> 1.5004684 | BM37: =BL37*R37 -> 75059432 | BN37: =BM37-AB37 -> 47920823 | BP37: =IF($BJ37<=30,IF($B37=2015,VLOOKUP($BJ37,'Treasury Yields'!$C$40:$N$69,$E37,FALSE)/100,IF($B37=2016,VLOOKUP($BJ37,'Treasury Yields'!$C$75:$N$104,$E37,FALSE)/100,IF($B37=2017,VLOOKUP($BJ37,'Treasury Yields'!$C$110:$N$139,$E37,FALSE)/100,IF($B37=2018,VLOOKUP($BJ37,'Treasury Yields'!$C$145:$N$174,$E37,FALSE)/100,IF($B37=2019,VLOOKUP($BJ37,'Treasury Yields'!$C$180:$N$209,$E37,FALSE)/100,IF($B37=2020,VLOOKUP($BJ37,'Treasury Yields'!$C$215:$N$244,$E37,FALSE)/100,IF($B37=2021,VLOOKUP($BJ37,'Treasury Yields'!$C$250:$N$279,$E37,FALSE)/100,IF($B37=2022,VLOOKUP($BJ37,'Treasury Yields'!$C$285:$N$314,$E37,FALSE)/100)))))))),0) -> 0.02964 | BQ37: =1+BH37*(AN37-BP37)+(AN37-BP37)^2 -> 1.4647463 | BR37: =BQ37*S37 -> 76903574 | BS37: =BR37-AC37 -> 48111863 | BU37: =IF(BJ37="","",ROUND(BJ37+$BT$2,0)) -> 13 | BV37: =1+(BH37+BU37)*(AN37-BK37)+(AN37-BK37)^2*BI37 -> 2.3681459 | BW37: =BV37*J37 -> 2134253.6 | BX37: =(BM37+BW37-O37)*BK37 -> 1830541.3 | BY37: =BK37*(BN37+BW37-O37) -> 1161031.8 | BZ37: =SUM(J37:K37) -> 4534261 | CA37: =SUM(BW37+BY37) -> 3295285.5 | CC37: =BR37 -> 76903574 | CD37: =F37 -> Massachusetts | CE37: =BB37 -> 0.54838221 | CF37: =AC37/CC37 -> 0.37438716
A38: 22000000000703 | B38: 2019 | C38: 344 | D38: plan24_y2021 | E38: 6 | F38: Massachusetts | G38: Massachusetts Teachers' Retirement System | H38: TRS | I38: TRUE | J38: 949262 | K38: 3763191 | M38: 50910 | N38: 577000 | O38: 3092363 | Q38: 2248000 | R38: 52503000 | S38: 54751000 | T38: 1443710 | U38: 234532 | V38: 782431 | W38: 1584770 | Y38: 18324 | Z38: -189487 | AA38: 745269 | AB38: 28791711 | AC38: 29536980 | AD38: 25214020 | AE38: 23711289 | AF38: 1502731 | AG38: 7074960 | AH38: 0.2040591 | AI38: TRUE | AK38: 0.0735 | AL38: 0.0725 | AM38: 0.0725 | AN38: 0.0735 | AO38: 1 | AP38: 0 | AS38: 31232100 | AT38: 20062500 | AU38: p144 of CAFR | AV38: http://www.macomptroller.info/comptroller/docs/reports-audits/ComprehensiveAnnualFinancialReport/comprehensiveannualfinancialreport_fy2019.pdf | BB38: =AC38/S38 -> 0.53947837 | BD38: =AS38-AD38 -> 6018080 | BE38: =AT38-AD38 -> -5151520 | BF38: =BD38/S38*100 -> 10.991726 | BG38: =BE38/S38*100 -> -9.4089971 | BH38: =(BD38-BE38)/(2*S38)*100 -> 10.200362 | BI38: =(BD38+BE38)/(2*S38*(0.01^2)) -> 79.136454 | BJ38: =ROUND(BH38,0) -> 10 | BK38: =IF($BJ38<=30,IF($B38=2015,VLOOKUP($BJ38,'Treasury Yields'!$C$5:$N$34,$E38,FALSE)/100,IF($B38=2016,VLOOKUP($BJ38,'Treasury Yields'!$C$40:$N$69,$E38,FALSE)/100,IF($B38=2017,VLOOKUP($BJ38,'Treasury Yields'!$C$75:$N$104,$E38,FALSE)/100,IF($B38=2018,VLOOKUP($BJ38,'Treasury Yields'!$C$110:$N$139,$E38,FALSE)/100,IF($B38=2019,VLOOKUP($BJ38,'Treasury Yields'!$C$145:$N$174,$E38,FALSE)/100,IF($B38=2020,VLOOKUP($BJ38,'Treasury Yields'!$C$180:$N$209,$E38,FALSE)/100,IF($B38=2021,VLOOKUP($BJ38,'Treasury Yields'!$C$215:$N$244,$E38,FALSE)/100,IF($B38=2022,VLOOKUP($BJ38,'Treasury Yields'!$C$250:$N$279,$E38,FALSE)/100)))))))),0) -> 0.02964 | BL38: =1+BH38*(AL38-BK38)+(AL38-BK38)^2 -> 1.4390245 | BM38: =BL38*R38 -> 75553102 | BN38: =BM38-AB38 -> 46761391 | BP38: =IF($BJ38<=30,IF($B38=2015,VLOOKUP($BJ38,'Treasury Yields'!$C$40:$N$69,$E38,FALSE)/100,IF($B38=2016,VLOOKUP($BJ38,'Treasury Yields'!$C$75:$N$104,$E38,FALSE)/100,IF($B38=2017,VLOOKUP($BJ38,'Treasury Yields'!$C$110:$N$139,$E38,FALSE)/100,IF($B38=2018,VLOOKUP($BJ38,'Treasury Yields'!$C$145:$N$174,$E38,FALSE)/100,IF($B38=2019,VLOOKUP($BJ38,'Treasury Yields'!$C$180:$N$209,$E38,FALSE)/100,IF($B38=2020,VLOOKUP($BJ38,'Treasury Yields'!$C$215:$N$244,$E38,FALSE)/100,IF($B38=2021,VLOOKUP($BJ38,'Treasury Yields'!$C$250:$N$279,$E38,FALSE)/100,IF($B38=2022,VLOOKUP($BJ38,'Treasury Yields'!$C$285:$N$314,$E38,FALSE)/100)))))))),0) -> 0.02126 | BQ38: =1+BH38*(AN38-BP38)+(AN38-BP38)^2 -> 1.5355959 | BR38: =BQ38*S38 -> 84075412 | BS38: =BR38-AC38 -> 54538432 | BU38: =IF(BJ38="","",ROUND(BJ38+$BT$2,0)) -> 13 | BV38: =1+(BH38+BU38)*(AN38-BK38)+(AN38-BK38)^2*BI38 -> 2.1698026 | BW38: =BV38*J38 -> 2059711.2 | BX38: =(BM38+BW38-O38)*BK38 -> 2208786.2 | BY38: =BK38*(BN38+BW38-O38) -> 1355399.8 | BZ38: =SUM(J38:K38) -> 4712453 | CA38: =SUM(BW38+BY38) -> 3415111 | CC38: =BR38 -> 84075412 | CD38: =F38 -> Massachusetts | CE38: =BB38 -> 0.53947837 | CF38: =AC38/CC38 -> 0.35131532
A39: 22000000000703 | B39: 2020 | C39: 344 | D39: plan24_y2021 | E39: 6 | F39: Massachusetts | G39: Massachusetts Teachers' Retirement System | H39: TRS | I39: TRUE | J39: 1019331 | K39: 3927724 | M39: 495599 | N39: 859000 | O39: 3189813 | Q39: 3111841 | R39: 54751000 | S39: 57862841 | T39: 1553433 | U39: 233222 | V39: 821105 | W39: 581648 | Y39: 22391 | Z39: -196187 | AA39: -218983 | AB39: 29536980 | AC39: 29317997 | AD39: 28544844 | AE39: 25214020 | AF39: 3330824 | AG39: 7074960 | AH39: 0.21956774 | AI39: TRUE | AK39: 0.0725 | AL39: 0.0715 | AM39: 0.0715 | AN39: 0.0725 | AO39: 1 | AP39: 0 | AS39: 35411955 | AT39: 22908510 | AU39: p152 of CAFR | AV39: http://www.macomptroller.info/comptroller/docs/reports-audits/ComprehensiveAnnualFinancialReport/comprehensiveannualfinancialreport_fy2020.pdf | BB39: =AC39/S39 -> 0.50668091 | BD39: =AS39-AD39 -> 6867111 | BE39: =AT39-AD39 -> -5636334 | BF39: =BD39/S39*100 -> 11.867912 | BG39: =BE39/S39*100 -> -9.7408525 | BH39: =(BD39-BE39)/(2*S39)*100 -> 10.804382 | BI39: =(BD39+BE39)/(2*S39*(0.01^2)) -> 106.35297 | BJ39: =ROUND(BH39,0) -> 11 | BK39: =IF($BJ39<=30,IF($B39=2015,VLOOKUP($BJ39,'Treasury Yields'!$C$5:$N$34,$E39,FALSE)/100,IF($B39=2016,VLOOKUP($BJ39,'Treasury Yields'!$C$40:$N$69,$E39,FALSE)/100,IF($B39=2017,VLOOKUP($BJ39,'Treasury Yields'!$C$75:$N$104,$E39,FALSE)/100,IF($B39=2018,VLOOKUP($BJ39,'Treasury Yields'!$C$110:$N$139,$E39,FALSE)/100,IF($B39=2019,VLOOKUP($BJ39,'Treasury Yields'!$C$145:$N$174,$E39,FALSE)/100,IF($B39=2020,VLOOKUP($BJ39,'Treasury Yields'!$C$180:$N$209,$E39,FALSE)/100,IF($B39=2021,VLOOKUP($BJ39,'Treasury Yields'!$C$215:$N$244,$E39,FALSE)/100,IF($B39=2022,VLOOKUP($BJ39,'Treasury Yields'!$C$250:$N$279,$E39,FALSE)/100)))))))),0) -> 0.021722 | BL39: =1+BH39*(AL39-BK39)+(AL39-BK39)^2 -> 1.5402984 | BM39: =BL39*R39 -> 84332877 | BN39: =BM39-AB39 -> 54795897 | BP39: =IF($BJ39<=30,IF($B39=2015,VLOOKUP($BJ39,'Treasury Yields'!$C$40:$N$69,$E39,FALSE)/100,IF($B39=2016,VLOOKUP($BJ39,'Treasury Yields'!$C$75:$N$104,$E39,FALSE)/100,IF($B39=2017,VLOOKUP($BJ39,'Treasury Yields'!$C$110:$N$139,$E39,FALSE)/100,IF($B39=2018,VLOOKUP($BJ39,'Treasury Yields'!$C$145:$N$174,$E39,FALSE)/100,IF($B39=2019,VLOOKUP($BJ39,'Treasury Yields'!$C$180:$N$209,$E39,FALSE)/100,IF($B39=2020,VLOOKUP($BJ39,'Treasury Yields'!$C$215:$N$244,$E39,FALSE)/100,IF($B39=2021,VLOOKUP($BJ39,'Treasury Yields'!$C$250:$N$279,$E39,FALSE)/100,IF($B39=2022,VLOOKUP($BJ39,'Treasury Yields'!$C$285:$N$314,$E39,FALSE)/100)))))))),0) -> 0.014551091 | BQ39: =1+BH39*(AN39-BP39)+(AN39-BP39)^2 -> 1.6294602 | BR39: =BQ39*S39 -> 94285199 | BS39: =BR39-AC39 -> 64967202 | BU39: =IF(BJ39="","",ROUND(BJ39+$BT$2,0)) -> 14 | BV39: =1+(BH39+BU39)*(AN39-BK39)+(AN39-BK39)^2*BI39 -> 2.533738 | BW39: =BV39*J39 -> 2582717.7 | BX39: =(BM39+BW39-O39)*BK39 -> 1818691.4 | BY39: =BK39*(BN39+BW39-O39) -> 1177089.1 | BZ39: =SUM(J39:K39) -> 4947055 | CA39: =SUM(BW39+BY39) -> 3759806.8 | CC39: =BR39 -> 94285199 | CD39: =F39 -> Massachusetts | CE39: =BB39 -> 0.50668091 | CF39: =AC39/CC39 -> 0.31095015
A40: 22000000000703 | B40: 2021 | C40: 344 | D40: plan24_y2021 | E40: 6 | F40: Massachusetts | G40: Massachusetts Teachers' Retirement System | H40: TRS | I40: TRUE | J40: 1085414 | K40: 4097558 | M40: -555322 | N40: 584000 | O40: 3279491 | Q40: 1932159 | R40: 57862841 | S40: 59795000 | T40: 1748483 | U40: 254903 | V40: 833236 | W40: 8455507 | Y40: 21783 | Z40: -220728 | AA40: 7770127 | AB40: 29317997 | AC40: 37088124 | AD40: 22706876 | AE40: 28544844 | AF40: -5837968 | AG40: 7670306 | AI40: TRUE | AK40: 0.0715 | AL40: 0.0715 | AM40: 0.0715 | AN40: 0.0715 | AS40: 29687706 | AT40: 16882184 | AU40: p117 of CAFR | AV40: https://www.macomptroller.org/wp-content/uploads/acfr_fy-2021.pdf | BB40: =AC40/S40 -> 0.6202546 | BD40: =AS40-AD40 -> 6980830 | BE40: =AT40-AD40 -> -5824692 | BF40: =BD40/S40*100 -> 11.674605 | BG40: =BE40/S40*100 -> -9.7411021 | BH40: =(BD40-BE40)/(2*S40)*100 -> 10.707853 | BI40: =(BD40+BE40)/(2*S40*(0.01^2)) -> 96.67514 | BJ40: =ROUND(BH40,0) -> 11 | BK40: =IF($BJ40<=30,IF($B40=2015,VLOOKUP($BJ40,'Treasury Yields'!$C$5:$N$34,$E40,FALSE)/100,IF($B40=2016,VLOOKUP($BJ40,'Treasury Yields'!$C$40:$N$69,$E40,FALSE)/100,IF($B40=2017,VLOOKUP($BJ40,'Treasury Yields'!$C$75:$N$104,$E40,FALSE)/100,IF($B40=2018,VLOOKUP($BJ40,'Treasury Yields'!$C$110:$N$139,$E40,FALSE)/100,IF($B40=2019,VLOOKUP($BJ40,'Treasury Yields'!$C$145:$N$174,$E40,FALSE)/100,IF($B40=2020,VLOOKUP($BJ40,'Treasury Yields'!$C$180:$N$209,$E40,FALSE)/100,IF($B40=2021,VLOOKUP($BJ40,'Treasury Yields'!$C$215:$N$244,$E40,FALSE)/100,IF($B40=2022,VLOOKUP($BJ40,'Treasury Yields'!$C$250:$N$279,$E40,FALSE)/100)))))))),0) -> 0.014551091 | BL40: =1+BH40*(AL40-BK40)+(AL40-BK40)^2 -> 1.6130438 | BM40: =BL40*R40 -> 93335294 | BN40: =BM40-AB40 -> 64017297 | BP40: =IF($BJ40<=30,IF($B40=2015,VLOOKUP($BJ40,'Treasury Yields'!$C$40:$N$69,$E40,FALSE)/100,IF($B40=2016,VLOOKUP($BJ40,'Treasury Yields'!$C$75:$N$104,$E40,FALSE)/100,IF($B40=2017,VLOOKUP($BJ40,'Treasury Yields'!$C$110:$N$139,$E40,FALSE)/100,IF($B40=2018,VLOOKUP($BJ40,'Treasury Yields'!$C$145:$N$174,$E40,FALSE)/100,IF($B40=2019,VLOOKUP($BJ40,'Treasury Yields'!$C$180:$N$209,$E40,FALSE)/100,IF($B40=2020,VLOOKUP($BJ40,'Treasury Yields'!$C$215:$N$244,$E40,FALSE)/100,IF($B40=2021,VLOOKUP($BJ40,'Treasury Yields'!$C$250:$N$279,$E40,FALSE)/100,IF($B40=2022,VLOOKUP($BJ40,'Treasury Yields'!$C$285:$N$314,$E40,FALSE)/100)))))))),0) -> 0.021554273 | BQ40: =1+BH40*(AN40-BP40)+(AN40-BP40)^2 -> 1.5373061 | BR40: =BQ40*S40 -> 91923219 | BS40: =BR40-AC40 -> 54835095 | BU40: =IF(BJ40="","",ROUND(BJ40+$BT$2,0)) -> 14 | BV40: =1+(BH40+BU40)*(AN40-BK40)+(AN40-BK40)^2*BI40 -> 2.72062 | BW40: =BV40*J40 -> 2952999.1 | BX40: =(BM40+BW40-O40)*BK40 -> 1353379.5 | BY40: =BK40*(BN40+BW40-O40) -> 926770.7 | BZ40: =SUM(J40:K40) -> 5182972 | CA40: =SUM(BW40+BY40) -> 3879769.7 | CC40: =BR40 -> 91923219 | CD40: =F40 -> Massachusetts | CE40: =BB40 -> 0.6202546 | CF40: =AC40/CC40 -> 0.40346851
A41: 22000000000703 | B41: 2022 | C41: 344 | D41: plan24_y2021 | E41: 6 | F41: Massachusetts | G41: Massachusetts Teachers' Retirement System | H41: TRS | I41: TRUE | J41: 1084503 | K41: 4143763 | M41: -384483 | N41: 0 | O41: 3365783 | Q41: 1478000 | R41: 59795000 | S41: 61273000 | T41: 2104604 | U41: 276758 | V41: 892123 | W41: -1353547 | Y41: 19196 | Z41: -238221 | AA41: -1703262 | AB41: 37088124 | AC41: 35384862 | AD41: 25888138 | AE41: 22706876 | AF41: 3181262 | AG41: 7704176 | AI41: TRUE | AK41: 0.0715 | AL41: 0.07 | AM41: 0.07 | AN41: 0.0715 | AS41: 32734080 | AT41: 20094302 | AV41: https://www.macomptroller.org/wp-content/uploads/acfr_fy-2022.pdf | BB41: =AC41/S41 -> 0.57749518 | BD41: =AS41-AD41 -> 6845942 | BE41: =AT41-AD41 -> -5793836 | BF41: =BD41/S41*100 -> 11.172853 | BG41: =BE41/S41*100 -> -9.4557733 | BH41: =(BD41-BE41)/(2*S41)*100 -> 10.314313 | BI41: =(BD41+BE41)/(2*S41*(0.01^2)) -> 85.853965 | BJ41: =ROUND(BH41,0) -> 10 | BK41: =IF($BJ41<=30,IF($B41=2015,VLOOKUP($BJ41,'Treasury Yields'!$C$5:$N$34,$E41,FALSE)/100,IF($B41=2016,VLOOKUP($BJ41,'Treasury Yields'!$C$40:$N$69,$E41,FALSE)/100,IF($B41=2017,VLOOKUP($BJ41,'Treasury Yields'!$C$75:$N$104,$E41,FALSE)/100,IF($B41=2018,VLOOKUP($BJ41,'Treasury Yields'!$C$110:$N$139,$E41,FALSE)/100,IF($B41=2019,VLOOKUP($BJ41,'Treasury Yields'!$C$145:$N$174,$E41,FALSE)/100,IF($B41=2020,VLOOKUP($BJ41,'Treasury Yields'!$C$180:$N$209,$E41,FALSE)/100,IF($B41=2021,VLOOKUP($BJ41,'Treasury Yields'!$C$215:$N$244,$E41,FALSE)/100,IF($B41=2022,VLOOKUP($BJ41,'Treasury Yields'!$C$250:$N$279,$E41,FALSE)/100)))))))),0) -> 0.022022727 | BL41: =1+BH41*(AL41-BK41)+(AL41-BK41)^2 -> 1.4971544 | BM41: =BL41*R41 -> 89522349 | BN41: =BM41-AB41 -> 52434225 | BP41: =IF($BJ41<=30,IF($B41=2015,VLOOKUP($BJ41,'Treasury Yields'!$C$40:$N$69,$E41,FALSE)/100,IF($B41=2016,VLOOKUP($BJ41,'Treasury Yields'!$C$75:$N$104,$E41,FALSE)/100,IF($B41=2017,VLOOKUP($BJ41,'Treasury Yields'!$C$110:$N$139,$E41,FALSE)/100,IF($B41=2018,VLOOKUP($BJ41,'Treasury Yields'!$C$145:$N$174,$E41,FALSE)/100,IF($B41=2019,VLOOKUP($BJ41,'Treasury Yields'!$C$180:$N$209,$E41,FALSE)/100,IF($B41=2020,VLOOKUP($BJ41,'Treasury Yields'!$C$215:$N$244,$E41,FALSE)/100,IF($B41=2021,VLOOKUP($BJ41,'Treasury Yields'!$C$250:$N$279,$E41,FALSE)/100,IF($B41=2022,VLOOKUP($BJ41,'Treasury Yields'!$C$285:$N$314,$E41,FALSE)/100)))))))),0) -> 0.031469545 | BQ41: =1+BH41*(AN41-BP41)+(AN41-BP41)^2 -> 1.4144891 | BR41: =BQ41*S41 -> 86669989 | BS41: =BR41-AC41 -> 51285127 | BU41: =IF(BJ41="","",ROUND(BJ41+$BT$2,0)) -> 13 | BV41: =1+(BH41+BU41)*(AN41-BK41)+(AN41-BK41)^2*BI41 -> 2.3636992 | BW41: =BV41*J41 -> 2563438.8 | BX41: =(BM41+BW41-O41)*BK41 -> 1953856.5 | BY41: =BK41*(BN41+BW41-O41) -> 1137074.8 | BZ41: =SUM(J41:K41) -> 5228266 | CA41: =SUM(BW41+BY41) -> 3700513.7 | CC41: =BR41 -> 86669989 | CD41: =F41 -> Massachusetts | CE41: =BB41 -> 0.57749518 | CF41: =AC41/CC41 -> 0.40827122
A42: 24000000010301 | B42: 2015 | C42: 568 | D42: plan80_y2021 | E42: 6 | F42: Minnesota | G42: Teachers Retirement Association | H42: TRA | I42: TRUE | J42: 399228 | K42: 2019707 | L42: 0 | M42: 7113 | N42: 576075 | O42: 1669607 | Q42: 1332516 | R42: 25299564 | S42: 26632080 | T42: 340208 | U42: 41587 | V42: 334826 | W42: 887280 | Y42: 11509 | Z42: 3550 | AA42: -73665 | AB42: 20519756 | AC42: 20446091 | AD42: 6185989 | AE42: 4779808 | AF42: 1406181 | AG42: 4306426 | AH42: 0.07900008 | AI42: TRUE | AK42: 0.0825 | AL42: 0.08 | AM42: 0.08 | AN42: 0.0825 | AO42: 1 | AP42: 0 | AS42: 9415876 | AT42: 3490555 | BB42: =AC42/S42 -> 0.76772415 | BD42: =AS42-AD42 -> 3229887 | BE42: =AT42-AD42 -> -2695434 | BF42: =BD42/S42*100 -> 12.127806 | BG42: =BE42/S42*100 -> -10.121004 | BH42: =(BD42-BE42)/(2*S42)*100 -> 11.124405 | BI42: =(BD42+BE42)/(2*S42*(0.01^2)) -> 100.34008 | BJ42: =ROUND(BH42,0) -> 11 | BK42: =IF($BJ42<=30,IF($B42=2015,VLOOKUP($BJ42,'Treasury Yields'!$C$5:$N$34,$E42,FALSE)/100,IF($B42=2016,VLOOKUP($BJ42,'Treasury Yields'!$C$40:$N$69,$E42,FALSE)/100,IF($B42=2017,VLOOKUP($BJ42,'Treasury Yields'!$C$75:$N$104,$E42,FALSE)/100,IF($B42=2018,VLOOKUP($BJ42,'Treasury Yields'!$C$110:$N$139,$E42,FALSE)/100,IF($B42=2019,VLOOKUP($BJ42,'Treasury Yields'!$C$145:$N$174,$E42,FALSE)/100,IF($B42=2020,VLOOKUP($BJ42,'Treasury Yields'!$C$180:$N$209,$E42,FALSE)/100,IF($B42=2021,VLOOKUP($BJ42,'Treasury Yields'!$C$215:$N$244,$E42,FALSE)/100,IF($B42=2022,VLOOKUP($BJ42,'Treasury Yields'!$C$250:$N$279,$E42,FALSE)/100)))))))),0) -> 0.028148 | BL42: =1+BH42*(AL42-BK42)+(AL42-BK42)^2 -> 1.5795113 | BM42: =BL42*R42 -> 39960947 | BN42: =BM42-AB42 -> 19441191 | BP42: =IF($BJ42<=30,IF($B42=2015,VLOOKUP($BJ42,'Treasury Yields'!$C$40:$N$69,$E42,FALSE)/100,IF($B42=2016,VLOOKUP($BJ42,'Treasury Yields'!$C$75:$N$104,$E42,FALSE)/100,IF($B42=2017,VLOOKUP($BJ42,'Treasury Yields'!$C$110:$N$139,$E42,FALSE)/100,IF($B42=2018,VLOOKUP($BJ42,'Treasury Yields'!$C$145:$N$174,$E42,FALSE)/100,IF($B42=2019,VLOOKUP($BJ42,'Treasury Yields'!$C$180:$N$209,$E42,FALSE)/100,IF($B42=2020,VLOOKUP($BJ42,'Treasury Yields'!$C$215:$N$244,$E42,FALSE)/100,IF($B42=2021,VLOOKUP($BJ42,'Treasury Yields'!$C$250:$N$279,$E42,FALSE)/100,IF($B42=2022,VLOOKUP($BJ42,'Treasury Yields'!$C$285:$N$314,$E42,FALSE)/100)))))))),0) -> 0.026258 | BQ42: =1+BH42*(AN42-BP42)+(AN42-BP42)^2 -> 1.628822 | BR42: =BQ42*S42 -> 43378917 | BS42: =BR42-AC42 -> 22932826 | BU42: =IF(BJ42="","",ROUND(BJ42+$BT$2,0)) -> 14 | BV42: =1+(BH42+BU42)*(AN42-BK42)+(AN42-BK42)^2*BI42 -> 2.6619803 | BW42: =BV42*J42 -> 1062737.1 | BX42: =(BM42+BW42-O42)*BK42 -> 1107738.6 | BY42: =BK42*(BN42+BW42-O42) -> 530148.47 | BZ42: =SUM(J42:K42) -> 2418935 | CA42: =SUM(BW42+BY42) -> 1592885.5 | CC42: =BR42 -> 43378917 | CD42: =F42 -> Minnesota | CE42: =BB42 -> 0.76772415 | CF42: =AC42/CC42 -> 0.47133706
A43: 24000000010301 | B43: 2016 | C43: 568 | D43: plan80_y2021 | E43: 6 | F43: Minnesota | G43: Teachers Retirement Association | H43: TRA | I43: TRUE | J43: 438938 | K43: 2062775 | M43: -798 | N43: 15871845 | O43: 1728023 | Q43: 16644737 | R43: 26632080 | S43: 43276817 | T43: 354961 | U43: 35587 | V43: 347256 | W43: -23672 | Y43: 11338 | Z43: 3569 | AA43: -1021660 | AB43: 20446091 | AC43: 19424431 | AD43: 23852386 | AE43: 6185989 | AF43: 17666397 | AG43: 4515699 | AH43: 0.078605992 | AI43: TRUE | AK43: 0.08 | AL43: 0.0466 | AM43: 0.0466 | AN43: 0.08 | AO43: 1 | AP43: 0 | AQ43: 0.0382 | AR43: 2052 | AS43: 30727835 | AT43: 18252557 | AU43: p42 of CAFR | AV43: https://www.minnesotatra.org/images/pdf/2016%20CAFR.pdf | BB43: =AC43/S43 -> 0.44884149 | BD43: =AS43-AD43 -> 6875449 | BE43: =AT43-AD43 -> -5599829 | BF43: =BD43/S43*100 -> 15.887141 | BG43: =BE43/S43*100 -> -12.939558 | BH43: =(BD43-BE43)/(2*S43)*100 -> 14.41335 | BI43: =(BD43+BE43)/(2*S43*(0.01^2)) -> 147.37914 | BJ43: =ROUND(BH43,0) -> 14 | BK43: =IF($BJ43<=30,IF($B43=2015,VLOOKUP($BJ43,'Treasury Yields'!$C$5:$N$34,$E43,FALSE)/100,IF($B43=2016,VLOOKUP($BJ43,'Treasury Yields'!$C$40:$N$69,$E43,FALSE)/100,IF($B43=2017,VLOOKUP($BJ43,'Treasury Yields'!$C$75:$N$104,$E43,FALSE)/100,IF($B43=2018,VLOOKUP($BJ43,'Treasury Yields'!$C$110:$N$139,$E43,FALSE)/100,IF($B43=2019,VLOOKUP($BJ43,'Treasury Yields'!$C$145:$N$174,$E43,FALSE)/100,IF($B43=2020,VLOOKUP($BJ43,'Treasury Yields'!$C$180:$N$209,$E43,FALSE)/100,IF($B43=2021,VLOOKUP($BJ43,'Treasury Yields'!$C$215:$N$244,$E43,FALSE)/100,IF($B43=2022,VLOOKUP($BJ43,'Treasury Yields'!$C$250:$N$279,$E43,FALSE)/100)))))))),0) -> 0.028622 | BL43: =1+BH43*(AL43-BK43)+(AL43-BK43)^2 -> 1.2594464 | BM43: =BL43*R43 -> 33541678 | BN43: =BM43-AB43 -> 13095587 | BP43: =IF($BJ43<=30,IF($B43=2015,VLOOKUP($BJ43,'Treasury Yields'!$C$40:$N$69,$E43,FALSE)/100,IF($B43=2016,VLOOKUP($BJ43,'Treasury Yields'!$C$75:$N$104,$E43,FALSE)/100,IF($B43=2017,VLOOKUP($BJ43,'Treasury Yields'!$C$110:$N$139,$E43,FALSE)/100,IF($B43=2018,VLOOKUP($BJ43,'Treasury Yields'!$C$145:$N$174,$E43,FALSE)/100,IF($B43=2019,VLOOKUP($BJ43,'Treasury Yields'!$C$180:$N$209,$E43,FALSE)/100,IF($B43=2020,VLOOKUP($BJ43,'Treasury Yields'!$C$215:$N$244,$E43,FALSE)/100,IF($B43=2021,VLOOKUP($BJ43,'Treasury Yields'!$C$250:$N$279,$E43,FALSE)/100,IF($B43=2022,VLOOKUP($BJ43,'Treasury Yields'!$C$285:$N$314,$E43,FALSE)/100)))))))),0) -> 0.018742 | BQ43: =1+BH43*(AN43-BP43)+(AN43-BP43)^2 -> 1.8866855 | BR43: =BQ43*S43 -> 81649744 | BS43: =BR43-AC43 -> 62225313 | BU43: =IF(BJ43="","",ROUND(BJ43+$BT$2,0)) -> 17 | BV43: =1+(BH43+BU43)*(AN43-BK43)+(AN43-BK43)^2*BI43 -> 3.0029916 | BW43: =BV43*J43 -> 1318127.1 | BX43: =(BM43+BW43-O43)*BK43 -> 948297.86 | BY43: =BK43*(BN43+BW43-O43) -> 363089.84 | BZ43: =SUM(J43:K43) -> 2501713 | CA43: =SUM(BW43+BY43) -> 1681217 | CC43: =BR43 -> 81649744 | CD43: =F43 -> Minnesota | CE43: =BB43 -> 0.44884149 | CF43: =AC43/CC43 -> 0.23789947
A44: 24000000010301 | B44: 2017 | C44: 568 | D44: plan80_y2021 | E44: 6 | F44: Minnesota | G44: Teachers Retirement Association | H44: TRA | I44: TRUE | J44: 1267304 | K44: 1975771 | M44: -167572 | N44: -3355602 | O44: 1776814 | Q44: -2056913 | R44: 43276817 | S44: 41219904 | T44: 367791 | U44: 35587 | V44: 361175 | W44: 2855218 | Y44: 11702 | Z44: 2404 | AA44: 1833659 | AB44: 19424431 | AC44: 21258090 | AD44: 19961814 | AE44: 23852386 | AF44: -3890572 | AG44: 4688875 | AH44: 0.078439071 | AI44: TRUE | AK44: 0.0466 | AL44: 0.0512 | AM44: 0.075 | AN44: 0.0466 | AO44: 1 | AP44: 0.0238 | AQ44: 0.0356 | AR44: 2053 | AS44: 26345748 | AT44: 14759381 | AU44: p46 of CAFR | AV44: https://minnesotatra.org/wp-content/uploads/2018/07/2017-CAFR.pdf | BB44: =AC44/S44 -> 0.51572391 | BD44: =AS44-AD44 -> 6383934 | BE44: =AT44-AD44 -> -5202433 | BF44: =BD44/S44*100 -> 15.487503 | BG44: =BE44/S44*100 -> -12.621167 | BH44: =(BD44-BE44)/(2*S44)*100 -> 14.054335 | BI44: =(BD44+BE44)/(2*S44*(0.01^2)) -> 143.31681 | BJ44: =ROUND(BH44,0) -> 14 | BK44: =IF($BJ44<=30,IF($B44=2015,VLOOKUP($BJ44,'Treasury Yields'!$C$5:$N$34,$E44,FALSE)/100,IF($B44=2016,VLOOKUP($BJ44,'Treasury Yields'!$C$40:$N$69,$E44,FALSE)/100,IF($B44=2017,VLOOKUP($BJ44,'Treasury Yields'!$C$75:$N$104,$E44,FALSE)/100,IF($B44=2018,VLOOKUP($BJ44,'Treasury Yields'!$C$110:$N$139,$E44,FALSE)/100,IF($B44=2019,VLOOKUP($BJ44,'Treasury Yields'!$C$145:$N$174,$E44,FALSE)/100,IF($B44=2020,VLOOKUP($BJ44,'Treasury Yields'!$C$180:$N$209,$E44,FALSE)/100,IF($B44=2021,VLOOKUP($BJ44,'Treasury Yields'!$C$215:$N$244,$E44,FALSE)/100,IF($B44=2022,VLOOKUP($BJ44,'Treasury Yields'!$C$250:$N$279,$E44,FALSE)/100)))))))),0) -> 0.018742 | BL44: =1+BH44*(AL44-BK44)+(AL44-BK44)^2 -> 1.4572291 | BM44: =BL44*R44 -> 63064239 | BN44: =BM44-AB44 -> 43639808 | BP44: =IF($BJ44<=30,IF($B44=2015,VLOOKUP($BJ44,'Treasury Yields'!$C$40:$N$69,$E44,FALSE)/100,IF($B44=2016,VLOOKUP($BJ44,'Treasury Yields'!$C$75:$N$104,$E44,FALSE)/100,IF($B44=2017,VLOOKUP($BJ44,'Treasury Yields'!$C$110:$N$139,$E44,FALSE)/100,IF($B44=2018,VLOOKUP($BJ44,'Treasury Yields'!$C$145:$N$174,$E44,FALSE)/100,IF($B44=2019,VLOOKUP($BJ44,'Treasury Yields'!$C$180:$N$209,$E44,FALSE)/100,IF($B44=2020,VLOOKUP($BJ44,'Treasury Yields'!$C$215:$N$244,$E44,FALSE)/100,IF($B44=2021,VLOOKUP($BJ44,'Treasury Yields'!$C$250:$N$279,$E44,FALSE)/100,IF($B44=2022,VLOOKUP($BJ44,'Treasury Yields'!$C$285:$N$314,$E44,FALSE)/100)))))))),0) -> 0.0262652 | BQ44: =1+BH44*(AN44-BP44)+(AN44-BP44)^2 -> 1.2862056 | BR44: =BQ44*S44 -> 53017271 | BS44: =BR44-AC44 -> 31759181 | BU44: =IF(BJ44="","",ROUND(BJ44+$BT$2,0)) -> 17 | BV44: =1+(BH44+BU44)*(AN44-BK44)+(AN44-BK44)^2*BI44 -> 1.9763353 | BW44: =BV44*J44 -> 2504617.6 | BX44: =(BM44+BW44-O44)*BK44 -> 1195590.5 | BY44: =BK44*(BN44+BW44-O44) -> 831537.77 | BZ44: =SUM(J44:K44) -> 3243075 | CA44: =SUM(BW44+BY44) -> 3336155.4 | CC44: =BR44 -> 53017271 | CD44: =F44 -> Minnesota | CE44: =BB44 -> 0.51572391 | CF44: =AC44/CC44 -> 0.40096537
A45: 24000000010301 | B45: 2018 | C45: 568 | D45: plan80_y2021 | E45: 6 | F45: Minnesota | G45: Teachers Retirement Association | H45: TRA | I45: TRUE | J45: 1056681 | K45: 2064148 | L45: -3681114 | M45: -17461 | N45: -10167248 | O45: 1831887 | Q45: -12576881 | R45: 41219904 | S45: 28643023 | T45: 378728 | U45: 35587 | V45: 374550 | W45: 2160111 | Y45: 15673 | Z45: 2581 | AA45: 1103997 | AB45: 21258090 | AC45: 22362087 | AD45: 6280936 | AE45: 19961814 | AF45: -13680878 | AG45: 4832917 | AH45: 0.078364267 | AI45: TRUE | AK45: 0.0512 | AL45: 0.075 | AM45: 0.075 | AN45: 0.075 | AO45: 1 | AP45: 0 | AQ45: 0.0389 | AR45: 2053 | AS45: 9967820 | AT45: 3239281 | AU45: p47 of CAFR | AV45: https://minnesotatra.org/wp-content/uploads/2018/12/2018-CAFR.pdf | BB45: =AC45/S45 -> 0.78071672 | BD45: =AS45-AD45 -> 3686884 | BE45: =AT45-AD45 -> -3041655 | BF45: =BD45/S45*100 -> 12.87184 | BG45: =BE45/S45*100 -> -10.619183 | BH45: =(BD45-BE45)/(2*S45)*100 -> 11.745511 | BI45: =(BD45+BE45)/(2*S45*(0.01^2)) -> 112.63284 | BJ45: =ROUND(BH45,0) -> 12 | BK45: =IF($BJ45<=30,IF($B45=2015,VLOOKUP($BJ45,'Treasury Yields'!$C$5:$N$34,$E45,FALSE)/100,IF($B45=2016,VLOOKUP($BJ45,'Treasury Yields'!$C$40:$N$69,$E45,FALSE)/100,IF($B45=2017,VLOOKUP($BJ45,'Treasury Yields'!$C$75:$N$104,$E45,FALSE)/100,IF($B45=2018,VLOOKUP($BJ45,'Treasury Yields'!$C$110:$N$139,$E45,FALSE)/100,IF($B45=2019,VLOOKUP($BJ45,'Treasury Yields'!$C$145:$N$174,$E45,FALSE)/100,IF($B45=2020,VLOOKUP($BJ45,'Treasury Yields'!$C$180:$N$209,$E45,FALSE)/100,IF($B45=2021,VLOOKUP($BJ45,'Treasury Yields'!$C$215:$N$244,$E45,FALSE)/100,IF($B45=2022,VLOOKUP($BJ45,'Treasury Yields'!$C$250:$N$279,$E45,FALSE)/100)))))))),0) -> 0.0254676 | BL45: =1+BH45*(AL45-BK45)+(AL45-BK45)^2 -> 1.5842368 | BM45: =BL45*R45 -> 65302090 | BN45: =BM45-AB45 -> 44044000 | BP45: =IF($BJ45<=30,IF($B45=2015,VLOOKUP($BJ45,'Treasury Yields'!$C$40:$N$69,$E45,FALSE)/100,IF($B45=2016,VLOOKUP($BJ45,'Treasury Yields'!$C$75:$N$104,$E45,FALSE)/100,IF($B45=2017,VLOOKUP($BJ45,'Treasury Yields'!$C$110:$N$139,$E45,FALSE)/100,IF($B45=2018,VLOOKUP($BJ45,'Treasury Yields'!$C$145:$N$174,$E45,FALSE)/100,IF($B45=2019,VLOOKUP($BJ45,'Treasury Yields'!$C$180:$N$209,$E45,FALSE)/100,IF($B45=2020,VLOOKUP($BJ45,'Treasury Yields'!$C$215:$N$244,$E45,FALSE)/100,IF($B45=2021,VLOOKUP($BJ45,'Treasury Yields'!$C$250:$N$279,$E45,FALSE)/100,IF($B45=2022,VLOOKUP($BJ45,'Treasury Yields'!$C$285:$N$314,$E45,FALSE)/100)))))))),0) -> 0.028906473 | BQ45: =1+BH45*(AN45-BP45)+(AN45-BP45)^2 -> 1.5435167 | BR45: =BQ45*S45 -> 44210983 | BS45: =BR45-AC45 -> 21848896 | BU45: =IF(BJ45="","",ROUND(BJ45+$BT$2,0)) -> 15 | BV45: =1+(BH45+BU45)*(AN45-BK45)+(AN45-BK45)^2*BI45 -> 2.6011094 | BW45: =BV45*J45 -> 2748542.9 | BX45: =(BM45+BW45-O45)*BK45 -> 1686432.5 | BY45: =BK45*(BN45+BW45-O45) -> 1145040 | BZ45: =SUM(J45:K45) -> 3120829 | CA45: =SUM(BW45+BY45) -> 3893582.8 | CC45: =BR45 -> 44210983 | CD45: =F45 -> Minnesota | CE45: =BB45 -> 0.78071672 | CF45: =AC45/CC45 -> 0.50580388
A46: 24000000010301 | B46: 2019 | C46: 568 | D46: plan80_y2021 | E46: 6 | F46: Minnesota | G46: Teachers Retirement Association | H46: TRA | I46: TRUE | J46: 476708 | K46: 2079081 | L46: 0 | M46: -70899 | N46: 0 | O46: 1877836 | Q46: 607054 | R46: 28643023 | S46: 29250077 | T46: 403300 | U46: 35587 | V46: 386669 | W46: 1579099 | Y46: 15156 | Z46: 2306 | AA46: 513969 | AB46: 22362087 | AC46: 22876056 | AD46: 6374021 | AE46: 6280936 | AF46: 93085 | AG46: 5000930 | AH46: 0.080645 | AI46: TRUE | AK46: 0.075 | AL46: 0.075 | AM46: 0.075 | AN46: 0.075 | AO46: 1 | AP46: 0 | AQ46: 0.035 | AR46: 2118 | AS46: 10161748 | AT46: 3251096 | AU46: p46 of CAFR | AV46: https://minnesotatra.org/wp-content/uploads/2019/12/TRA-FY19-CAFR-final-4.pdf | BB46: =AC46/S46 -> 0.78208533 | BD46: =AS46-AD46 -> 3787727 | BE46: =AT46-AD46 -> -3122925 | BF46: =BD46/S46*100 -> 12.94946 | BG46: =BE46/S46*100 -> -10.676639 | BH46: =(BD46-BE46)/(2*S46)*100 -> 11.813049 | BI46: =(BD46+BE46)/(2*S46*(0.01^2)) -> 113.64107 | BJ46: =ROUND(BH46,0) -> 12 | BK46: =IF($BJ46<=30,IF($B46=2015,VLOOKUP($BJ46,'Treasury Yields'!$C$5:$N$34,$E46,FALSE)/100,IF($B46=2016,VLOOKUP($BJ46,'Treasury Yields'!$C$40:$N$69,$E46,FALSE)/100,IF($B46=2017,VLOOKUP($BJ46,'Treasury Yields'!$C$75:$N$104,$E46,FALSE)/100,IF($B46=2018,VLOOKUP($BJ46,'Treasury Yields'!$C$110:$N$139,$E46,FALSE)/100,IF($B46=2019,VLOOKUP($BJ46,'Treasury Yields'!$C$145:$N$174,$E46,FALSE)/100,IF($B46=2020,VLOOKUP($BJ46,'Treasury Yields'!$C$180:$N$209,$E46,FALSE)/100,IF($B46=2021,VLOOKUP($BJ46,'Treasury Yields'!$C$215:$N$244,$E46,FALSE)/100,IF($B46=2022,VLOOKUP($BJ46,'Treasury Yields'!$C$250:$N$279,$E46,FALSE)/100)))))))),0) -> 0.028906473 | BL46: =1+BH46*(AL46-BK46)+(AL46-BK46)^2 -> 1.5466297 | BM46: =BL46*R46 -> 44300151 | BN46: =BM46-AB46 -> 21938064 | BP46: =IF($BJ46<=30,IF($B46=2015,VLOOKUP($BJ46,'Treasury Yields'!$C$40:$N$69,$E46,FALSE)/100,IF($B46=2016,VLOOKUP($BJ46,'Treasury Yields'!$C$75:$N$104,$E46,FALSE)/100,IF($B46=2017,VLOOKUP($BJ46,'Treasury Yields'!$C$110:$N$139,$E46,FALSE)/100,IF($B46=2018,VLOOKUP($BJ46,'Treasury Yields'!$C$145:$N$174,$E46,FALSE)/100,IF($B46=2019,VLOOKUP($BJ46,'Treasury Yields'!$C$180:$N$209,$E46,FALSE)/100,IF($B46=2020,VLOOKUP($BJ46,'Treasury Yields'!$C$215:$N$244,$E46,FALSE)/100,IF($B46=2021,VLOOKUP($BJ46,'Treasury Yields'!$C$250:$N$279,$E46,FALSE)/100,IF($B46=2022,VLOOKUP($BJ46,'Treasury Yields'!$C$285:$N$314,$E46,FALSE)/100)))))))),0) -> 0.022184 | BQ46: =1+BH46*(AN46-BP46)+(AN46-BP46)^2 -> 1.6267075 | BR46: =BQ46*S46 -> 47581321 | BS46: =BR46-AC46 -> 24705265 | BU46: =IF(BJ46="","",ROUND(BJ46+$BT$2,0)) -> 15 | BV46: =1+(BH46+BU46)*(AN46-BK46)+(AN46-BK46)^2*BI46 -> 2.4773513 | BW46: =BV46*J46 -> 1180973.2 | BX46: =(BM46+BW46-O46)*BK46 -> 1260417.3 | BY46: =BK46*(BN46+BW46-O46) -> 614008.19 | BZ46: =SUM(J46:K46) -> 2555789 | CA46: =SUM(BW46+BY46) -> 1794981.4 | CC46: =BR46 -> 47581321 | CD46: =F46 -> Minnesota | CE46: =BB46 -> 0.78208533 | CF46: =AC46/CC46 -> 0.48077808
A47: 24000000010301 | B47: 2020 | C47: 568 | D47: plan80_y2021 | E47: 6 | F47: Minnesota | G47: Teachers Retirement Association | H47: TRA | I47: TRUE | J47: 489790 | K47: 2123261 | L47: 0 | M47: 177794 | N47: 6673 | O47: 1914465 | Q47: 883053 | R47: 29250077 | S47: 30133130 | T47: 425223 | U47: 35587 | V47: 396679 | W47: 939748 | Y47: 15392 | Z47: 1560 | AA47: -131060 | AB47: 22876056 | AC47: 22744996 | AD47: 7388134 | AE47: 6374021 | AF47: 1014113 | AG47: 5166241 | AH47: 0.082308007 | AI47: TRUE | AK47: 0.075 | AL47: 0.075 | AM47: 0.075 | AN47: 0.075 | AO47: 1 | AP47: 0 | AQ47: 0.0219 | AR47: 2119 | AS47: 11311155 | AT47: 4155763 | AU47: p46 of CAFR | AV47: https://minnesotatra.org/wp-content/uploads/2020/12/MNTRACAFR2020.pdf | BB47: =AC47/S47 -> 0.75481691 | BD47: =AS47-AD47 -> 3923021 | BE47: =AT47-AD47 -> -3232371 | BF47: =BD47/S47*100 -> 13.018963 | BG47: =BE47/S47*100 -> -10.726967 | BH47: =(BD47-BE47)/(2*S47)*100 -> 11.872965 | BI47: =(BD47+BE47)/(2*S47*(0.01^2)) -> 114.59978 | BJ47: =ROUND(BH47,0) -> 12 | BK47: =IF($BJ47<=30,IF($B47=2015,VLOOKUP($BJ47,'Treasury Yields'!$C$5:$N$34,$E47,FALSE)/100,IF($B47=2016,VLOOKUP($BJ47,'Treasury Yields'!$C$40:$N$69,$E47,FALSE)/100,IF($B47=2017,VLOOKUP($BJ47,'Treasury Yields'!$C$75:$N$104,$E47,FALSE)/100,IF($B47=2018,VLOOKUP($BJ47,'Treasury Yields'!$C$110:$N$139,$E47,FALSE)/100,IF($B47=2019,VLOOKUP($BJ47,'Treasury Yields'!$C$145:$N$174,$E47,FALSE)/100,IF($B47=2020,VLOOKUP($BJ47,'Treasury Yields'!$C$180:$N$209,$E47,FALSE)/100,IF($B47=2021,VLOOKUP($BJ47,'Treasury Yields'!$C$215:$N$244,$E47,FALSE)/100,IF($B47=2022,VLOOKUP($BJ47,'Treasury Yields'!$C$250:$N$279,$E47,FALSE)/100)))))))),0) -> 0.022184 | BL47: =1+BH47*(AL47-BK47)+(AL47-BK47)^2 -> 1.6298721 | BM47: =BL47*R47 -> 47673883 | BN47: =BM47-AB47 -> 24797827 | BP47: =IF($BJ47<=30,IF($B47=2015,VLOOKUP($BJ47,'Treasury Yields'!$C$40:$N$69,$E47,FALSE)/100,IF($B47=2016,VLOOKUP($BJ47,'Treasury Yields'!$C$75:$N$104,$E47,FALSE)/100,IF($B47=2017,VLOOKUP($BJ47,'Treasury Yields'!$C$110:$N$139,$E47,FALSE)/100,IF($B47=2018,VLOOKUP($BJ47,'Treasury Yields'!$C$145:$N$174,$E47,FALSE)/100,IF($B47=2019,VLOOKUP($BJ47,'Treasury Yields'!$C$180:$N$209,$E47,FALSE)/100,IF($B47=2020,VLOOKUP($BJ47,'Treasury Yields'!$C$215:$N$244,$E47,FALSE)/100,IF($B47=2021,VLOOKUP($BJ47,'Treasury Yields'!$C$250:$N$279,$E47,FALSE)/100,IF($B47=2022,VLOOKUP($BJ47,'Treasury Yields'!$C$285:$N$314,$E47,FALSE)/100)))))))),0) -> 0.013689455 | BQ47: =1+BH47*(AN47-BP47)+(AN47-BP47)^2 -> 1.7316969 | BR47: =BQ47*S47 -> 52181449 | BS47: =BR47-AC47 -> 29436453 | BU47: =IF(BJ47="","",ROUND(BJ47+$BT$2,0)) -> 15 | BV47: =1+(BH47+BU47)*(AN47-BK47)+(AN47-BK47)^2*BI47 -> 2.739002 | BW47: =BV47*J47 -> 1341535.8 | BX47: =(BM47+BW47-O47)*BK47 -> 1044887.6 | BY47: =BK47*(BN47+BW47-O47) -> 537405.13 | BZ47: =SUM(J47:K47) -> 2613051 | CA47: =SUM(BW47+BY47) -> 1878940.9 | CC47: =BR47 -> 52181449 | CD47: =F47 -> Minnesota | CE47: =BB47 -> 0.75481691 | CF47: =AC47/CC47 -> 0.4358828
A48: 24000000010301 | B48: 2021 | C48: 568 | D48: plan80_y2021 | E48: 6 | F48: Minnesota | G48: Teachers Retirement Association | H48: TRA | I48: TRUE | J48: 513165 | K48: 2188186 | L48: 0 | M48: -65710 | N48: 1919160 | O48: 1949875 | Q48: 2604926 | R48: 30133130 | S48: 32738056 | T48: 448829 | U48: 37840 | V48: 410162 | W48: 6684106 | Y48: 16022 | Z48: 1721 | AA48: 5616761 | AB48: 22744996 | AC48: 28361757 | AD48: 4376299 | AE48: 7388134 | AF48: -3011835 | AG48: 5326108 | AI48: TRUE | AK48: 0.075 | AL48: 0.07 | AM48: 0.07 | AN48: 0.075 | AS48: 8840337 | AT48: 715432 | BB48: =AC48/S48 -> 0.8663238 | BD48: =AS48-AD48 -> 4464038 | BE48: =AT48-AD48 -> -3660867 | BF48: =BD48/S48*100 -> 13.635623 | BG48: =BE48/S48*100 -> -11.182298 | BH48: =(BD48-BE48)/(2*S48)*100 -> 12.408961 | BI48: =(BD48+BE48)/(2*S48*(0.01^2)) -> 122.66626 | BJ48: =ROUND(BH48,0) -> 12 | BK48: =IF($BJ48<=30,IF($B48=2015,VLOOKUP($BJ48,'Treasury Yields'!$C$5:$N$34,$E48,FALSE)/100,IF($B48=2016,VLOOKUP($BJ48,'Treasury Yields'!$C$40:$N$69,$E48,FALSE)/100,IF($B48=2017,VLOOKUP($BJ48,'Treasury Yields'!$C$75:$N$104,$E48,FALSE)/100,IF($B48=2018,VLOOKUP($BJ48,'Treasury Yields'!$C$110:$N$139,$E48,FALSE)/100,IF($B48=2019,VLOOKUP($BJ48,'Treasury Yields'!$C$145:$N$174,$E48,FALSE)/100,IF($B48=2020,VLOOKUP($BJ48,'Treasury Yields'!$C$180:$N$209,$E48,FALSE)/100,IF($B48=2021,VLOOKUP($BJ48,'Treasury Yields'!$C$215:$N$244,$E48,FALSE)/100,IF($B48=2022,VLOOKUP($BJ48,'Treasury Yields'!$C$250:$N$279,$E48,FALSE)/100)))))))),0) -> 0.013689455 | BL48: =1+BH48*(AL48-BK48)+(AL48-BK48)^2 -> 1.7019262 | BM48: =BL48*R48 -> 51284364 | BN48: =BM48-AB48 -> 28539368 | BP48: =IF($BJ48<=30,IF($B48=2015,VLOOKUP($BJ48,'Treasury Yields'!$C$40:$N$69,$E48,FALSE)/100,IF($B48=2016,VLOOKUP($BJ48,'Treasury Yields'!$C$75:$N$104,$E48,FALSE)/100,IF($B48=2017,VLOOKUP($BJ48,'Treasury Yields'!$C$110:$N$139,$E48,FALSE)/100,IF($B48=2018,VLOOKUP($BJ48,'Treasury Yields'!$C$145:$N$174,$E48,FALSE)/100,IF($B48=2019,VLOOKUP($BJ48,'Treasury Yields'!$C$180:$N$209,$E48,FALSE)/100,IF($B48=2020,VLOOKUP($BJ48,'Treasury Yields'!$C$215:$N$244,$E48,FALSE)/100,IF($B48=2021,VLOOKUP($BJ48,'Treasury Yields'!$C$250:$N$279,$E48,FALSE)/100,IF($B48=2022,VLOOKUP($BJ48,'Treasury Yields'!$C$285:$N$314,$E48,FALSE)/100)))))))),0) -> 0.021085818 | BQ48: =1+BH48*(AN48-BP48)+(AN48-BP48)^2 -> 1.6719257 | BR48: =BQ48*S48 -> 54735597 | BS48: =BR48-AC48 -> 26373840 | BU48: =IF(BJ48="","",ROUND(BJ48+$BT$2,0)) -> 15 | BV48: =1+(BH48+BU48)*(AN48-BK48)+(AN48-BK48)^2*BI48 -> 3.1415587 | BW48: =BV48*J48 -> 1612138 | BX48: =(BM48+BW48-O48)*BK48 -> 697431.54 | BY48: =BK48*(BN48+BW48-O48) -> 386064.95 | BZ48: =SUM(J48:K48) -> 2701351 | CA48: =SUM(BW48+BY48) -> 1998202.9 | CC48: =BR48 -> 54735597 | CD48: =F48 -> Minnesota | CE48: =BB48 -> 0.8663238 | CF48: =AC48/CC48 -> 0.51815927
A49: 24000000010301 | B49: 2022 | C49: 568 | D49: plan80_y2021 | E49: 6 | F49: Minnesota | G49: Teachers Retirement Association | H49: TRA | I49: TRUE | J49: 596232 | K49: 2223274 | L49: 0 | M49: 33875 | N49: 0 | O49: 1987622 | Q49: 865759 | R49: 32738056 | S49: 33603815 | T49: 482679 | U49: 35590 | V49: 428993 | W49: -1710746 | Y49: 15666 | Z49: 1359 | AA49: -2765413 | AB49: 28361757 | AC49: 25596344 | AD49: 8007471 | AE49: 4376299 | AF49: 3631172 | AG49: 5573701 | AI49: TRUE | AK49: 0.07 | AL49: 0.07 | AM49: 0.07 | AN49: 0.07 | AS49: 12623342 | AT49: 4223896 | AV49: https://minnesotatra.org/wp-content/uploads/2023/01/TRA-ACFR-2022.pdf | BB49: =AC49/S49 -> 0.76170947 | BD49: =AS49-AD49 -> 4615871 | BE49: =AT49-AD49 -> -3783575 | BF49: =BD49/S49*100 -> 13.736152 | BG49: =BE49/S49*100 -> -11.259361 | BH49: =(BD49-BE49)/(2*S49)*100 -> 12.497757 | BI49: =(BD49+BE49)/(2*S49*(0.01^2)) -> 123.83951 | BJ49: =ROUND(BH49,0) -> 12 | BK49: =IF($BJ49<=30,IF($B49=2015,VLOOKUP($BJ49,'Treasury Yields'!$C$5:$N$34,$E49,FALSE)/100,IF($B49=2016,VLOOKUP($BJ49,'Treasury Yields'!$C$40:$N$69,$E49,FALSE)/100,IF($B49=2017,VLOOKUP($BJ49,'Treasury Yields'!$C$75:$N$104,$E49,FALSE)/100,IF($B49=2018,VLOOKUP($BJ49,'Treasury Yields'!$C$110:$N$139,$E49,FALSE)/100,IF($B49=2019,VLOOKUP($BJ49,'Treasury Yields'!$C$145:$N$174,$E49,FALSE)/100,IF($B49=2020,VLOOKUP($BJ49,'Treasury Yields'!$C$180:$N$209,$E49,FALSE)/100,IF($B49=2021,VLOOKUP($BJ49,'Treasury Yields'!$C$215:$N$244,$E49,FALSE)/100,IF($B49=2022,VLOOKUP($BJ49,'Treasury Yields'!$C$250:$N$279,$E49,FALSE)/100)))))))),0) -> 0.021085818 | BL49: =1+BH49*(AL49-BK49)+(AL49-BK49)^2 -> 1.6137101 | BM49: =BL49*R49 -> 52829733 | BN49: =BM49-AB49 -> 24467976 | BP49: =IF($BJ49<=30,IF($B49=2015,VLOOKUP($BJ49,'Treasury Yields'!$C$40:$N$69,$E49,FALSE)/100,IF($B49=2016,VLOOKUP($BJ49,'Treasury Yields'!$C$75:$N$104,$E49,FALSE)/100,IF($B49=2017,VLOOKUP($BJ49,'Treasury Yields'!$C$110:$N$139,$E49,FALSE)/100,IF($B49=2018,VLOOKUP($BJ49,'Treasury Yields'!$C$145:$N$174,$E49,FALSE)/100,IF($B49=2019,VLOOKUP($BJ49,'Treasury Yields'!$C$180:$N$209,$E49,FALSE)/100,IF($B49=2020,VLOOKUP($BJ49,'Treasury Yields'!$C$215:$N$244,$E49,FALSE)/100,IF($B49=2021,VLOOKUP($BJ49,'Treasury Yields'!$C$250:$N$279,$E49,FALSE)/100,IF($B49=2022,VLOOKUP($BJ49,'Treasury Yields'!$C$285:$N$314,$E49,FALSE)/100)))))))),0) -> 0.032402273 | BQ49: =1+BH49*(AN49-BP49)+(AN49-BP49)^2 -> 1.4713008 | BR49: =BQ49*S49 -> 49441321 | BS49: =BR49-AC49 -> 23844977 | BU49: =IF(BJ49="","",ROUND(BJ49+$BT$2,0)) -> 15 | BV49: =1+(BH49+BU49)*(AN49-BK49)+(AN49-BK49)^2*BI49 -> 2.6413283 | BW49: =BV49*J49 -> 1574844.5 | BX49: =(BM49+BW49-O49)*BK49 -> 1105254.4 | BY49: =BK49*(BN49+BW49-O49) -> 507223.54 | BZ49: =SUM(J49:K49) -> 2819506 | CA49: =SUM(BW49+BY49) -> 2082068 | CC49: =BR49 -> 49441321 | CD49: =F49 -> Minnesota | CE49: =BB49 -> 0.76170947 | CF49: =AC49/CC49 -> 0.51771157
A50: 22000000011801 | B50: 2015 | C50: 548 | D50: plan24_y2021 | E50: 6 | F50: Massachusetts | G50: State Employees' Retirement System | H50: SERS | I50: TRUE | J50: 700012 | K50: 2411551 | L50: 230302 | M50: 275000 | N50: 1397000 | O50: 1876451 | Q50: 3137414 | R50: 31355000 | S50: 34492414 | T50: 606376 | U50: 29403 | V50: 549493 | W50: 800886 | Y50: 15966 | Z50: 17949 | AA50: 111690 | AB50: 23930895 | AC50: 24042585 | AD50: 10449829 | AE50: 7424105 | AF50: 3025724 | AG50: 5591911 | AH50: 0.10843806 | AI50: TRUE | AK50: 0.08 | AL50: 0.0775 | AM50: 0.0775 | AN50: 0.08 | AO50: 1 | AP50: 0 | AS50: 14205331 | AT50: 7211692 | AU50: p135 of CAFR | AV50: http://www.mass.gov/comptroller/docs/reports-audits/cafr/fy2015-cafr.pdf | BB50: =AC50/S50 -> 0.69703979 | BD50: =AS50-AD50 -> 3755502 | BE50: =AT50-AD50 -> -3238137 | BF50: =BD50/S50*100 -> 10.887907 | BG50: =BE50/S50*100 -> -9.3879686 | BH50: =(BD50-BE50)/(2*S50)*100 -> 10.137938 | BI50: =(BD50+BE50)/(2*S50*(0.01^2)) -> 74.996925 | BJ50: =ROUND(BH50,0) -> 10 | BK50: =IF($BJ50<=30,IF($B50=2015,VLOOKUP($BJ50,'Treasury Yields'!$C$5:$N$34,$E50,FALSE)/100,IF($B50=2016,VLOOKUP($BJ50,'Treasury Yields'!$C$40:$N$69,$E50,FALSE)/100,IF($B50=2017,VLOOKUP($BJ50,'Treasury Yields'!$C$75:$N$104,$E50,FALSE)/100,IF($B50=2018,VLOOKUP($BJ50,'Treasury Yields'!$C$110:$N$139,$E50,FALSE)/100,IF($B50=2019,VLOOKUP($BJ50,'Treasury Yields'!$C$145:$N$174,$E50,FALSE)/100,IF($B50=2020,VLOOKUP($BJ50,'Treasury Yields'!$C$180:$N$209,$E50,FALSE)/100,IF($B50=2021,VLOOKUP($BJ50,'Treasury Yields'!$C$215:$N$244,$E50,FALSE)/100,IF($B50=2022,VLOOKUP($BJ50,'Treasury Yields'!$C$250:$N$279,$E50,FALSE)/100)))))))),0) -> 0.02711 | BL50: =1+BH50*(AL50-BK50)+(AL50-BK50)^2 -> 1.5133898 | BM50: =BL50*R50 -> 47452338 | BN50: =BM50-AB50 -> 23521443 | BP50: =IF($BJ50<=30,IF($B50=2015,VLOOKUP($BJ50,'Treasury Yields'!$C$40:$N$69,$E50,FALSE)/100,IF($B50=2016,VLOOKUP($BJ50,'Treasury Yields'!$C$75:$N$104,$E50,FALSE)/100,IF($B50=2017,VLOOKUP($BJ50,'Treasury Yields'!$C$110:$N$139,$E50,FALSE)/100,IF($B50=2018,VLOOKUP($BJ50,'Treasury Yields'!$C$145:$N$174,$E50,FALSE)/100,IF($B50=2019,VLOOKUP($BJ50,'Treasury Yields'!$C$180:$N$209,$E50,FALSE)/100,IF($B50=2020,VLOOKUP($BJ50,'Treasury Yields'!$C$215:$N$244,$E50,FALSE)/100,IF($B50=2021,VLOOKUP($BJ50,'Treasury Yields'!$C$250:$N$279,$E50,FALSE)/100,IF($B50=2022,VLOOKUP($BJ50,'Treasury Yields'!$C$285:$N$314,$E50,FALSE)/100)))))))),0) -> 0.02547 | BQ50: =1+BH50*(AN50-BP50)+(AN50-BP50)^2 -> 1.5557953 | BR50: =BQ50*S50 -> 53663135 | BS50: =BR50-AC50 -> 29620550 | BU50: =IF(BJ50="","",ROUND(BJ50+$BT$2,0)) -> 13 | BV50: =1+(BH50+BU50)*(AN50-BK50)+(AN50-BK50)^2*BI50 -> 2.4335583 | BW50: =BV50*J50 -> 1703520 | BX50: =(BM50+BW50-O50)*BK50 -> 1281744.7 | BY50: =BK50*(BN50+BW50-O50) -> 632978.17 | BZ50: =SUM(J50:K50) -> 3111563 | CA50: =SUM(BW50+BY50) -> 2336498.2 | CC50: =BR50 -> 53663135 | CD50: =F50 -> Massachusetts | CE50: =BB50 -> 0.69703979 | CF50: =AC50/CC50 -> 0.44802796
A51: 22000000011801 | B51: 2016 | C51: 548 | D51: plan24_y2021 | E51: 6 | F51: Massachusetts | G51: State Employees' Retirement System | H51: SERS | I51: TRUE | J51: 813975 | K51: 2638929 | L51: 400000 | M51: 589009 | O51: 2107327 | Q51: 2334586 | R51: 35425414 | S51: 37760000 | T51: 660818 | U51: 21830 | V51: 16642 | W51: 422938 | Y51: 20624 | Z51: -83824 | AA51: -71429 | AB51: 24042585 | AC51: 23971156 | AD51: 13788844 | AE51: 11382829 | AF51: 2406015 | AG51: 5792288 | AH51: 0.11408583 | AI51: TRUE | AK51: 0.0775 | AL51: 0.075 | AM51: 0.075 | AN51: 0.0775 | AO51: 1 | AP51: 0 | AS51: 17969000 | AT51: 10246000 | AU51: p137 of CAFR | AV51: http://www.mass.gov/comptroller/docs/reports-audits/cafr/2016-cafr.pdf | BB51: =AC51/S51 -> 0.63482934 | BD51: =AS51-AD51 -> 4180156 | BE51: =AT51-AD51 -> -3542844 | BF51: =BD51/S51*100 -> 11.070328 | BG51: =BE51/S51*100 -> -9.3825318 | BH51: =(BD51-BE51)/(2*S51)*100 -> 10.22643 | BI51: =(BD51+BE51)/(2*S51*(0.01^2)) -> 84.389831 | BJ51: =ROUND(BH51,0) -> 10 | BK51: =IF($BJ51<=30,IF($B51=2015,VLOOKUP($BJ51,'Treasury Yields'!$C$5:$N$34,$E51,FALSE)/100,IF($B51=2016,VLOOKUP($BJ51,'Treasury Yields'!$C$40:$N$69,$E51,FALSE)/100,IF($B51=2017,VLOOKUP($BJ51,'Treasury Yields'!$C$75:$N$104,$E51,FALSE)/100,IF($B51=2018,VLOOKUP($BJ51,'Treasury Yields'!$C$110:$N$139,$E51,FALSE)/100,IF($B51=2019,VLOOKUP($BJ51,'Treasury Yields'!$C$145:$N$174,$E51,FALSE)/100,IF($B51=2020,VLOOKUP($BJ51,'Treasury Yields'!$C$180:$N$209,$E51,FALSE)/100,IF($B51=2021,VLOOKUP($BJ51,'Treasury Yields'!$C$215:$N$244,$E51,FALSE)/100,IF($B51=2022,VLOOKUP($BJ51,'Treasury Yields'!$C$250:$N$279,$E51,FALSE)/100)))))))),0) -> 0.02547 | BL51: =1+BH51*(AL51-BK51)+(AL51-BK51)^2 -> 1.5089683 | BM51: =BL51*R51 -> 53455827 | BN51: =BM51-AB51 -> 29413242 | BP51: =IF($BJ51<=30,IF($B51=2015,VLOOKUP($BJ51,'Treasury Yields'!$C$40:$N$69,$E51,FALSE)/100,IF($B51=2016,VLOOKUP($BJ51,'Treasury Yields'!$C$75:$N$104,$E51,FALSE)/100,IF($B51=2017,VLOOKUP($BJ51,'Treasury Yields'!$C$110:$N$139,$E51,FALSE)/100,IF($B51=2018,VLOOKUP($BJ51,'Treasury Yields'!$C$145:$N$174,$E51,FALSE)/100,IF($B51=2019,VLOOKUP($BJ51,'Treasury Yields'!$C$180:$N$209,$E51,FALSE)/100,IF($B51=2020,VLOOKUP($BJ51,'Treasury Yields'!$C$215:$N$244,$E51,FALSE)/100,IF($B51=2021,VLOOKUP($BJ51,'Treasury Yields'!$C$250:$N$279,$E51,FALSE)/100,IF($B51=2022,VLOOKUP($BJ51,'Treasury Yields'!$C$285:$N$314,$E51,FALSE)/100)))))))),0) -> 0.01635 | BQ51: =1+BH51*(AN51-BP51)+(AN51-BP51)^2 -> 1.6290855 | BR51: =BQ51*S51 -> 61514269 | BS51: =BR51-AC51 -> 37543113 | BU51: =IF(BJ51="","",ROUND(BJ51+$BT$2,0)) -> 13 | BV51: =1+(BH51+BU51)*(AN51-BK51)+(AN51-BK51)^2*BI51 -> 2.4369246 | BW51: =BV51*J51 -> 1983595.7 | BX51: =(BM51+BW51-O51)*BK51 -> 1358368.5 | BY51: =BK51*(BN51+BW51-O51) -> 746003.83 | BZ51: =SUM(J51:K51) -> 3452904 | CA51: =SUM(BW51+BY51) -> 2729599.6 | CC51: =BR51 -> 61514269 | CD51: =F51 -> Massachusetts | CE51: =BB51 -> 0.63482934 | CF51: =AC51/CC51 -> 0.38968448
A52: 22000000011801 | B52: 2017 | C52: 548 | D52: plan24_y2021 | E52: 6 | F52: Massachusetts | G52: State Employees' Retirement System | H52: SERS | I52: TRUE | J52: 855440 | K52: 2813374 | L52: 10000 | M52: -428232 | N52: 304000 | O52: 2207582 | Q52: 1347000 | R52: 37760000 | S52: 39107000 | T52: 716266 | U52: 28455 | V52: 7999 | W52: 2987632 | Y52: 30030 | Z52: -58077 | AA52: 2311076 | AB52: 23971156 | AC52: 26282232 | AD52: 12824768 | AE52: 13788844 | AF52: -964076 | AG52: 5927012 | AH52: 0.12084774 | AI52: TRUE | AK52: 0.075 | AL52: 0.075 | AM52: 0.075 | AN52: 0.075 | AO52: 1 | AP52: 0 | AS52: 17466800 | AT52: 9085500 | AU52: p143 of CAFR | AV52: http://www.macomptroller.info/comptroller/docs/reports-audits/cafr/cafr-fy17.pdf | BB52: =AC52/S52 -> 0.67205953 | BD52: =AS52-AD52 -> 4642032 | BE52: =AT52-AD52 -> -3739268 | BF52: =BD52/S52*100 -> 11.87008 | BG52: =BE52/S52*100 -> -9.5616335 | BH52: =(BD52-BE52)/(2*S52)*100 -> 10.715856 | BI52: =(BD52+BE52)/(2*S52*(0.01^2)) -> 115.4223 | BJ52: =ROUND(BH52,0) -> 11 | BK52: =IF($BJ52<=30,IF($B52=2015,VLOOKUP($BJ52,'Treasury Yields'!$C$5:$N$34,$E52,FALSE)/100,IF($B52=2016,VLOOKUP($BJ52,'Treasury Yields'!$C$40:$N$69,$E52,FALSE)/100,IF($B52=2017,VLOOKUP($BJ52,'Treasury Yields'!$C$75:$N$104,$E52,FALSE)/100,IF($B52=2018,VLOOKUP($BJ52,'Treasury Yields'!$C$110:$N$139,$E52,FALSE)/100,IF($B52=2019,VLOOKUP($BJ52,'Treasury Yields'!$C$145:$N$174,$E52,FALSE)/100,IF($B52=2020,VLOOKUP($BJ52,'Treasury Yields'!$C$180:$N$209,$E52,FALSE)/100,IF($B52=2021,VLOOKUP($BJ52,'Treasury Yields'!$C$215:$N$244,$E52,FALSE)/100,IF($B52=2022,VLOOKUP($BJ52,'Treasury Yields'!$C$250:$N$279,$E52,FALSE)/100)))))))),0) -> 0.016948 | BL52: =1+BH52*(AL52-BK52)+(AL52-BK52)^2 -> 1.6254469 | BM52: =BL52*R52 -> 61376876 | BN52: =BM52-AB52 -> 37405720 | BP52: =IF($BJ52<=30,IF($B52=2015,VLOOKUP($BJ52,'Treasury Yields'!$C$40:$N$69,$E52,FALSE)/100,IF($B52=2016,VLOOKUP($BJ52,'Treasury Yields'!$C$75:$N$104,$E52,FALSE)/100,IF($B52=2017,VLOOKUP($BJ52,'Treasury Yields'!$C$110:$N$139,$E52,FALSE)/100,IF($B52=2018,VLOOKUP($BJ52,'Treasury Yields'!$C$145:$N$174,$E52,FALSE)/100,IF($B52=2019,VLOOKUP($BJ52,'Treasury Yields'!$C$180:$N$209,$E52,FALSE)/100,IF($B52=2020,VLOOKUP($BJ52,'Treasury Yields'!$C$215:$N$244,$E52,FALSE)/100,IF($B52=2021,VLOOKUP($BJ52,'Treasury Yields'!$C$250:$N$279,$E52,FALSE)/100,IF($B52=2022,VLOOKUP($BJ52,'Treasury Yields'!$C$285:$N$314,$E52,FALSE)/100)))))))),0) -> 0.0250688 | BQ52: =1+BH52*(AN52-BP52)+(AN52-BP52)^2 -> 1.5375487 | BR52: =BQ52*S52 -> 60128917 | BS52: =BR52-AC52 -> 33846685 | BU52: =IF(BJ52="","",ROUND(BJ52+$BT$2,0)) -> 14 | BV52: =1+(BH52+BU52)*(AN52-BK52)+(AN52-BK52)^2*BI52 -> 2.8237821 | BW52: =BV52*J52 -> 2415576.1 | BX52: =(BM52+BW52-O52)*BK52 -> 1043740.4 | BY52: =BK52*(BN52+BW52-O52) -> 637477.23 | BZ52: =SUM(J52:K52) -> 3668814 | CA52: =SUM(BW52+BY52) -> 3053053.4 | CC52: =BR52 -> 60128917 | CD52: =F52 -> Massachusetts | CE52: =BB52 -> 0.67205953 | CF52: =AC52/CC52 -> 0.43709804
A53: 22000000011801 | B53: 2018 | C53: 548 | D53: plan24_y2021 | E53: 6 | F53: Massachusetts | G53: State Employees' Retirement System | H53: SERS | I53: TRUE | J53: 856200 | K53: 2852239 | L53: 0 | M53: 102008 | N53: 622000 | O53: 2314447 | Q53: 2118000 | R53: 39107000 | S53: 41225000 | T53: 824864 | U53: 33310 | V53: 9564 | W53: 2460748 | Y53: 16369 | Z53: -50434 | AA53: 1712789 | AB53: 26282232 | AC53: 27995021 | AD53: 13229979 | AE53: 12824768 | AF53: 405211 | AG53: 6155194 | AH53: 0.13401105 | AI53: TRUE | AK53: 0.075 | AL53: 0.0735 | AM53: 0.0735 | AN53: 0.075 | AO53: 1 | AP53: 0 | AS53: 17831800 | AT53: 9297000 | AU53: p142 of CAFR | AV53: http://www.macomptroller.info/comptroller/docs/reports-audits/cafr/cafr-fy18.pdf | BB53: =AC53/S53 -> 0.67907874 | BD53: =AS53-AD53 -> 4601821 | BE53: =AT53-AD53 -> -3932979 | BF53: =BD53/S53*100 -> 11.162695 | BG53: =BE53/S53*100 -> -9.5402765 | BH53: =(BD53-BE53)/(2*S53)*100 -> 10.351486 | BI53: =(BD53+BE53)/(2*S53*(0.01^2)) -> 81.120922 | BJ53: =ROUND(BH53,0) -> 10 | BK53: =IF($BJ53<=30,IF($B53=2015,VLOOKUP($BJ53,'Treasury Yields'!$C$5:$N$34,$E53,FALSE)/100,IF($B53=2016,VLOOKUP($BJ53,'Treasury Yields'!$C$40:$N$69,$E53,FALSE)/100,IF($B53=2017,VLOOKUP($BJ53,'Treasury Yields'!$C$75:$N$104,$E53,FALSE)/100,IF($B53=2018,VLOOKUP($BJ53,'Treasury Yields'!$C$110:$N$139,$E53,FALSE)/100,IF($B53=2019,VLOOKUP($BJ53,'Treasury Yields'!$C$145:$N$174,$E53,FALSE)/100,IF($B53=2020,VLOOKUP($BJ53,'Treasury Yields'!$C$180:$N$209,$E53,FALSE)/100,IF($B53=2021,VLOOKUP($BJ53,'Treasury Yields'!$C$215:$N$244,$E53,FALSE)/100,IF($B53=2022,VLOOKUP($BJ53,'Treasury Yields'!$C$250:$N$279,$E53,FALSE)/100)))))))),0) -> 0.02467 | BL53: =1+BH53*(AL53-BK53)+(AL53-BK53)^2 -> 1.5078474 | BM53: =BL53*R53 -> 58967389 | BN53: =BM53-AB53 -> 32685157 | BP53: =IF($BJ53<=30,IF($B53=2015,VLOOKUP($BJ53,'Treasury Yields'!$C$40:$N$69,$E53,FALSE)/100,IF($B53=2016,VLOOKUP($BJ53,'Treasury Yields'!$C$75:$N$104,$E53,FALSE)/100,IF($B53=2017,VLOOKUP($BJ53,'Treasury Yields'!$C$110:$N$139,$E53,FALSE)/100,IF($B53=2018,VLOOKUP($BJ53,'Treasury Yields'!$C$145:$N$174,$E53,FALSE)/100,IF($B53=2019,VLOOKUP($BJ53,'Treasury Yields'!$C$180:$N$209,$E53,FALSE)/100,IF($B53=2020,VLOOKUP($BJ53,'Treasury Yields'!$C$215:$N$244,$E53,FALSE)/100,IF($B53=2021,VLOOKUP($BJ53,'Treasury Yields'!$C$250:$N$279,$E53,FALSE)/100,IF($B53=2022,VLOOKUP($BJ53,'Treasury Yields'!$C$285:$N$314,$E53,FALSE)/100)))))))),0) -> 0.02964 | BQ53: =1+BH53*(AN53-BP53)+(AN53-BP53)^2 -> 1.4716009 | BR53: =BQ53*S53 -> 60666748 | BS53: =BR53-AC53 -> 32671727 | BU53: =IF(BJ53="","",ROUND(BJ53+$BT$2,0)) -> 13 | BV53: =1+(BH53+BU53)*(AN53-BK53)+(AN53-BK53)^2*BI53 -> 2.3807684 | BW53: =BV53*J53 -> 2038413.9 | BX53: =(BM53+BW53-O53)*BK53 -> 1447915.7 | BY53: =BK53*(BN53+BW53-O53) -> 799533.09 | BZ53: =SUM(J53:K53) -> 3708439 | CA53: =SUM(BW53+BY53) -> 2837947 | CC53: =BR53 -> 60666748 | CD53: =F53 -> Massachusetts | CE53: =BB53 -> 0.67907874 | CF53: =AC53/CC53 -> 0.46145577
A54: 22000000011801 | B54: 2019 | C54: 548 | D54: plan24_y2021 | E54: 6 | F54: Massachusetts | G54: State Employees' Retirement System | H54: SERS | I54: TRUE | J54: 897600 | K54: 2965890 | L54: 0 | M54: 303066 | N54: 434000 | O54: 2427556 | Q54: 2173000 | R54: 41225000 | S54: 43398000 | T54: 919545 | U54: 37359 | V54: 10191 | W54: 1543398 | Y54: 15853 | Z54: -64528 | AA54: 768775 | AB54: 27995021 | AC54: 28763796 | AD54: 14634204 | AE54: 13229979 | AF54: 1404225 | AG54: 6354473 | AH54: 0.1447083 | AI54: TRUE | AK54: 0.0735 | AL54: 0.0725 | AM54: 0.0725 | AN54: 0.0735 | AO54: 1 | AP54: 0 | AS54: 19478600 | AT54: 10494900 | AU54: p140 of CAFR | AV54: http://www.macomptroller.info/comptroller/docs/reports-audits/ComprehensiveAnnualFinancialReport/comprehensiveannualfinancialreport_fy2019.pdf | BB54: =AC54/S54 -> 0.66279082 | BD54: =AS54-AD54 -> 4844396 | BE54: =AT54-AD54 -> -4139304 | BF54: =BD54/S54*100 -> 11.162717 | BG54: =BE54/S54*100 -> -9.5380064 | BH54: =(BD54-BE54)/(2*S54)*100 -> 10.350362 | BI54: =(BD54+BE54)/(2*S54*(0.01^2)) -> 81.235541 | BJ54: =ROUND(BH54,0) -> 10 | BK54: =IF($BJ54<=30,IF($B54=2015,VLOOKUP($BJ54,'Treasury Yields'!$C$5:$N$34,$E54,FALSE)/100,IF($B54=2016,VLOOKUP($BJ54,'Treasury Yields'!$C$40:$N$69,$E54,FALSE)/100,IF($B54=2017,VLOOKUP($BJ54,'Treasury Yields'!$C$75:$N$104,$E54,FALSE)/100,IF($B54=2018,VLOOKUP($BJ54,'Treasury Yields'!$C$110:$N$139,$E54,FALSE)/100,IF($B54=2019,VLOOKUP($BJ54,'Treasury Yields'!$C$145:$N$174,$E54,FALSE)/100,IF($B54=2020,VLOOKUP($BJ54,'Treasury Yields'!$C$180:$N$209,$E54,FALSE)/100,IF($B54=2021,VLOOKUP($BJ54,'Treasury Yields'!$C$215:$N$244,$E54,FALSE)/100,IF($B54=2022,VLOOKUP($BJ54,'Treasury Yields'!$C$250:$N$279,$E54,FALSE)/100)))))))),0) -> 0.02964 | BL54: =1+BH54*(AL54-BK54)+(AL54-BK54)^2 -> 1.4454535 | BM54: =BL54*R54 -> 59588820 | BN54: =BM54-AB54 -> 31593799 | BP54: =IF($BJ54<=30,IF($B54=2015,VLOOKUP($BJ54,'Treasury Yields'!$C$40:$N$69,$E54,FALSE)/100,IF($B54=2016,VLOOKUP($BJ54,'Treasury Yields'!$C$75:$N$104,$E54,FALSE)/100,IF($B54=2017,VLOOKUP($BJ54,'Treasury Yields'!$C$110:$N$139,$E54,FALSE)/100,IF($B54=2018,VLOOKUP($BJ54,'Treasury Yields'!$C$145:$N$174,$E54,FALSE)/100,IF($B54=2019,VLOOKUP($BJ54,'Treasury Yields'!$C$180:$N$209,$E54,FALSE)/100,IF($B54=2020,VLOOKUP($BJ54,'Treasury Yields'!$C$215:$N$244,$E54,FALSE)/100,IF($B54=2021,VLOOKUP($BJ54,'Treasury Yields'!$C$250:$N$279,$E54,FALSE)/100,IF($B54=2022,VLOOKUP($BJ54,'Treasury Yields'!$C$285:$N$314,$E54,FALSE)/100)))))))),0) -> 0.02126 | BQ54: =1+BH54*(AN54-BP54)+(AN54-BP54)^2 -> 1.5434319 | BR54: =BQ54*S54 -> 66981858 | BS54: =BR54-AC54 -> 38218062 | BU54: =IF(BJ54="","",ROUND(BJ54+$BT$2,0)) -> 13 | BV54: =1+(BH54+BU54)*(AN54-BK54)+(AN54-BK54)^2*BI54 -> 2.1804196 | BW54: =BV54*J54 -> 1957144.7 | BX54: =(BM54+BW54-O54)*BK54 -> 1752269.6 | BY54: =BK54*(BN54+BW54-O54) -> 922497.21 | BZ54: =SUM(J54:K54) -> 3863490 | CA54: =SUM(BW54+BY54) -> 2879641.9 | CC54: =BR54 -> 66981858 | CD54: =F54 -> Massachusetts | CE54: =BB54 -> 0.66279082 | CF54: =AC54/CC54 -> 0.42942666
A55: 22000000011801 | B55: 2020 | C55: 548 | D55: plan24_y2021 | E55: 6 | F55: Massachusetts | G55: State Employees' Retirement System | H55: SERS | I55: TRUE | J55: 963828 | K55: 3124187 | L55: 0 | M55: 336183 | N55: 442000 | O55: 2539198 | Q55: 2327000 | R55: 43398000 | S55: 45725000 | T55: 1003828 | U55: 38381 | V55: 9718 | W55: 567319 | Y55: 18089 | Z55: -37138 | AA55: -196496 | AB55: 28763796 | AC55: 28567300 | AD55: 17157700 | AE55: 14634204 | AF55: 2523496 | AG55: 6354473 | AH55: 0.15797187 | AI55: TRUE | AK55: 0.0725 | AL55: 0.0715 | AM55: 0.0715 | AN55: 0.0725 | AO55: 1 | AP55: 0 | AS55: 22606331 | AT55: 12679351 | AU55: p148 of CAFR | AV55: http://www.macomptroller.info/comptroller/docs/reports-audits/ComprehensiveAnnualFinancialReport/comprehensiveannualfinancialreport_fy2020.pdf | BB55: =AC55/S55 -> 0.62476326 | BD55: =AS55-AD55 -> 5448631 | BE55: =AT55-AD55 -> -4478349 | BF55: =BD55/S55*100 -> 11.916087 | BG55: =BE55/S55*100 -> -9.7940929 | BH55: =(BD55-BE55)/(2*S55)*100 -> 10.85509 | BI55: =(BD55+BE55)/(2*S55*(0.01^2)) -> 106.09973 | BJ55: =ROUND(BH55,0) -> 11 | BK55: =IF($BJ55<=30,IF($B55=2015,VLOOKUP($BJ55,'Treasury Yields'!$C$5:$N$34,$E55,FALSE)/100,IF($B55=2016,VLOOKUP($BJ55,'Treasury Yields'!$C$40:$N$69,$E55,FALSE)/100,IF($B55=2017,VLOOKUP($BJ55,'Treasury Yields'!$C$75:$N$104,$E55,FALSE)/100,IF($B55=2018,VLOOKUP($BJ55,'Treasury Yields'!$C$110:$N$139,$E55,FALSE)/100,IF($B55=2019,VLOOKUP($BJ55,'Treasury Yields'!$C$145:$N$174,$E55,FALSE)/100,IF($B55=2020,VLOOKUP($BJ55,'Treasury Yields'!$C$180:$N$209,$E55,FALSE)/100,IF($B55=2021,VLOOKUP($BJ55,'Treasury Yields'!$C$215:$N$244,$E55,FALSE)/100,IF($B55=2022,VLOOKUP($BJ55,'Treasury Yields'!$C$250:$N$279,$E55,FALSE)/100)))))))),0) -> 0.021722 | BL55: =1+BH55*(AL55-BK55)+(AL55-BK55)^2 -> 1.5428225 | BM55: =BL55*R55 -> 66955412 | BN55: =BM55-AB55 -> 38191616 | BP55: =IF($BJ55<=30,IF($B55=2015,VLOOKUP($BJ55,'Treasury Yields'!$C$40:$N$69,$E55,FALSE)/100,IF($B55=2016,VLOOKUP($BJ55,'Treasury Yields'!$C$75:$N$104,$E55,FALSE)/100,IF($B55=2017,VLOOKUP($BJ55,'Treasury Yields'!$C$110:$N$139,$E55,FALSE)/100,IF($B55=2018,VLOOKUP($BJ55,'Treasury Yields'!$C$145:$N$174,$E55,FALSE)/100,IF($B55=2019,VLOOKUP($BJ55,'Treasury Yields'!$C$180:$N$209,$E55,FALSE)/100,IF($B55=2020,VLOOKUP($BJ55,'Treasury Yields'!$C$215:$N$244,$E55,FALSE)/100,IF($B55=2021,VLOOKUP($BJ55,'Treasury Yields'!$C$250:$N$279,$E55,FALSE)/100,IF($B55=2022,VLOOKUP($BJ55,'Treasury Yields'!$C$285:$N$314,$E55,FALSE)/100)))))))),0) -> 0.014551091 | BQ55: =1+BH55*(AN55-BP55)+(AN55-BP55)^2 -> 1.6323987 | BR55: =BQ55*S55 -> 74641431 | BS55: =BR55-AC55 -> 46074131 | BU55: =IF(BJ55="","",ROUND(BJ55+$BT$2,0)) -> 14 | BV55: =1+(BH55+BU55)*(AN55-BK55)+(AN55-BK55)^2*BI55 -> 2.5356599 | BW55: =BV55*J55 -> 2443940 | BX55: =(BM55+BW55-O55)*BK55 -> 1452336.3 | BY55: =BK55*(BN55+BW55-O55) -> 827529.09 | BZ55: =SUM(J55:K55) -> 4088015 | CA55: =SUM(BW55+BY55) -> 3271469.1 | CC55: =BR55 -> 74641431 | CD55: =F55 -> Massachusetts | CE55: =BB55 -> 0.62476326 | CF55: =AC55/CC55 -> 0.38272712
A56: 22000000011801 | B56: 2021 | C56: 548 | D56: plan24_y2021 | E56: 6 | F56: Massachusetts | G56: State Employees' Retirement System | H56: SERS | I56: TRUE | J56: 968648 | K56: 3243594 | L56: 0 | M56: -904845 | N56: 101000 | O56: 2657397 | Q56: 751000 | R56: 45725000 | S56: 46476000 | T56: 1105838 | U56: 41963 | V56: 13352 | W56: 8232417 | Y56: 21685 | Z56: -14556 | AA56: 7472171 | AB56: 28567300 | AC56: 36039471 | AD56: 10436529 | AE56: 17157700 | AF56: -6721171 | AG56: 6544575 | AH56: 0.16897018 | AI56: TRUE | AK56: 0.0715 | AL56: 0.07 | AM56: 0.07 | AN56: 0.0715 | AS56: 15974650 | AT56: 5884626 | AV56: https://www.macomptroller.org/wp-content/uploads/acfr_fy-2021.pdf | BB56: =AC56/S56 -> 0.77544262 | BD56: =AS56-AD56 -> 5538121 | BE56: =AT56-AD56 -> -4551903 | BF56: =BD56/S56*100 -> 11.916088 | BG56: =BE56/S56*100 -> -9.7940937 | BH56: =(BD56-BE56)/(2*S56)*100 -> 10.855091 | BI56: =(BD56+BE56)/(2*S56*(0.01^2)) -> 106.09971 | BJ56: =ROUND(BH56,0) -> 11 | BK56: =IF($BJ56<=30,IF($B56=2015,VLOOKUP($BJ56,'Treasury Yields'!$C$5:$N$34,$E56,FALSE)/100,IF($B56=2016,VLOOKUP($BJ56,'Treasury Yields'!$C$40:$N$69,$E56,FALSE)/100,IF($B56=2017,VLOOKUP($BJ56,'Treasury Yields'!$C$75:$N$104,$E56,FALSE)/100,IF($B56=2018,VLOOKUP($BJ56,'Treasury Yields'!$C$110:$N$139,$E56,FALSE)/100,IF($B56=2019,VLOOKUP($BJ56,'Treasury Yields'!$C$145:$N$174,$E56,FALSE)/100,IF($B56=2020,VLOOKUP($BJ56,'Treasury Yields'!$C$180:$N$209,$E56,FALSE)/100,IF($B56=2021,VLOOKUP($BJ56,'Treasury Yields'!$C$215:$N$244,$E56,FALSE)/100,IF($B56=2022,VLOOKUP($BJ56,'Treasury Yields'!$C$250:$N$279,$E56,FALSE)/100)))))))),0) -> 0.014551091 | BL56: =1+BH56*(AL56-BK56)+(AL56-BK56)^2 -> 1.6049775 | BM56: =BL56*R56 -> 73387597 | BN56: =BM56-AB56 -> 44820297 | BP56: =IF($BJ56<=30,IF($B56=2015,VLOOKUP($BJ56,'Treasury Yields'!$C$40:$N$69,$E56,FALSE)/100,IF($B56=2016,VLOOKUP($BJ56,'Treasury Yields'!$C$75:$N$104,$E56,FALSE)/100,IF($B56=2017,VLOOKUP($BJ56,'Treasury Yields'!$C$110:$N$139,$E56,FALSE)/100,IF($B56=2018,VLOOKUP($BJ56,'Treasury Yields'!$C$145:$N$174,$E56,FALSE)/100,IF($B56=2019,VLOOKUP($BJ56,'Treasury Yields'!$C$180:$N$209,$E56,FALSE)/100,IF($B56=2020,VLOOKUP($BJ56,'Treasury Yields'!$C$215:$N$244,$E56,FALSE)/100,IF($B56=2021,VLOOKUP($BJ56,'Treasury Yields'!$C$250:$N$279,$E56,FALSE)/100,IF($B56=2022,VLOOKUP($BJ56,'Treasury Yields'!$C$285:$N$314,$E56,FALSE)/100)))))))),0) -> 0.021554273 | BQ56: =1+BH56*(AN56-BP56)+(AN56-BP56)^2 -> 1.54466 | BR56: =BQ56*S56 -> 71789617 | BS56: =BR56-AC56 -> 35750146 | BU56: =IF(BJ56="","",ROUND(BJ56+$BT$2,0)) -> 14 | BV56: =1+(BH56+BU56)*(AN56-BK56)+(AN56-BK56)^2*BI56 -> 2.7595706 | BW56: =BV56*J56 -> 2673052.5 | BX56: =(BM56+BW56-O56)*BK56 -> 1068097.4 | BY56: =BK56*(BN56+BW56-O56) -> 652412.03 | BZ56: =SUM(J56:K56) -> 4212242 | CA56: =SUM(BW56+BY56) -> 3325464.5 | CC56: =BR56 -> 71789617 | CD56: =F56 -> Massachusetts | CE56: =BB56 -> 0.77544262 | CF56: =AC56/CC56 -> 0.50201509
A57: 22000000011801 | B57: 2022 | C57: 548 | D57: plan24_y2021 | E57: 6 | F57: Massachusetts | G57: State Employees' Retirement System | H57: SERS | I57: TRUE | J57: 981998 | K57: 3223993 | L57: 0 | M57: 160909 | N57: 0 | O57: 2801900 | Q57: 1565000 | R57: 46476000 | S57: 48041000 | T57: 1310596 | U57: 56988 | V57: 11454 | W57: -1297464 | Y57: 14461 | Z57: -34817 | AA57: -1908345 | AB57: 36039471 | AC57: 34131126 | AD57: 13909874 | AE57: 10436529 | AF57: 3473345 | AG57: 6651010 | AH57: 0.19705218 | AI57: TRUE | AK57: 0.07 | AL57: 0.07 | AM57: 0.07 | AN57: 0.07 | AS57: 19184883 | AT57: 9446450 | AV57: https://www.macomptroller.org/wp-content/uploads/acfr_fy-2022.pdf | BB57: =AC57/S57 -> 0.71045828 | BD57: =AS57-AD57 -> 5275009 | BE57: =AT57-AD57 -> -4463424 | BF57: =BD57/S57*100 -> 10.980223 | BG57: =BE57/S57*100 -> -9.2908641 | BH57: =(BD57-BE57)/(2*S57)*100 -> 10.135544 | BI57: =(BD57+BE57)/(2*S57*(0.01^2)) -> 84.467954 | BJ57: =ROUND(BH57,0) -> 10 | BK57: =IF($BJ57<=30,IF($B57=2015,VLOOKUP($BJ57,'Treasury Yields'!$C$5:$N$34,$E57,FALSE)/100,IF($B57=2016,VLOOKUP($BJ57,'Treasury Yields'!$C$40:$N$69,$E57,FALSE)/100,IF($B57=2017,VLOOKUP($BJ57,'Treasury Yields'!$C$75:$N$104,$E57,FALSE)/100,IF($B57=2018,VLOOKUP($BJ57,'Treasury Yields'!$C$110:$N$139,$E57,FALSE)/100,IF($B57=2019,VLOOKUP($BJ57,'Treasury Yields'!$C$145:$N$174,$E57,FALSE)/100,IF($B57=2020,VLOOKUP($BJ57,'Treasury Yields'!$C$180:$N$209,$E57,FALSE)/100,IF($B57=2021,VLOOKUP($BJ57,'Treasury Yields'!$C$215:$N$244,$E57,FALSE)/100,IF($B57=2022,VLOOKUP($BJ57,'Treasury Yields'!$C$250:$N$279,$E57,FALSE)/100)))))))),0) -> 0.022022727 | BL57: =1+BH57*(AL57-BK57)+(AL57-BK57)^2 -> 1.4885776 | BM57: =BL57*R57 -> 69183131 | BN57: =BM57-AB57 -> 33143660 | BP57: =IF($BJ57<=30,IF($B57=2015,VLOOKUP($BJ57,'Treasury Yields'!$C$40:$N$69,$E57,FALSE)/100,IF($B57=2016,VLOOKUP($BJ57,'Treasury Yields'!$C$75:$N$104,$E57,FALSE)/100,IF($B57=2017,VLOOKUP($BJ57,'Treasury Yields'!$C$110:$N$139,$E57,FALSE)/100,IF($B57=2018,VLOOKUP($BJ57,'Treasury Yields'!$C$145:$N$174,$E57,FALSE)/100,IF($B57=2019,VLOOKUP($BJ57,'Treasury Yields'!$C$180:$N$209,$E57,FALSE)/100,IF($B57=2020,VLOOKUP($BJ57,'Treasury Yields'!$C$215:$N$244,$E57,FALSE)/100,IF($B57=2021,VLOOKUP($BJ57,'Treasury Yields'!$C$250:$N$279,$E57,FALSE)/100,IF($B57=2022,VLOOKUP($BJ57,'Treasury Yields'!$C$285:$N$314,$E57,FALSE)/100)))))))),0) -> 0.031469545 | BQ57: =1+BH57*(AN57-BP57)+(AN57-BP57)^2 -> 1.3920117 | BR57: =BQ57*S57 -> 66873634 | BS57: =BR57-AC57 -> 32742508 | BU57: =IF(BJ57="","",ROUND(BJ57+$BT$2,0)) -> 13 | BV57: =1+(BH57+BU57)*(AN57-BK57)+(AN57-BK57)^2*BI57 -> 2.3044102 | BW57: =BV57*J57 -> 2262926.2 | BX57: =(BM57+BW57-O57)*BK57 -> 1511731.5 | BY57: =BK57*(BN57+BW57-O57) -> 718044.1 | BZ57: =SUM(J57:K57) -> 4205991 | CA57: =SUM(BW57+BY57) -> 2980970.3 | CC57: =BR57 -> 66873634 | CD57: =F57 -> Massachusetts | CE57: =BB57 -> 0.71045828 | CF57: =AC57/CC57 -> 0.5103824
A58: 31000000001612 | B58: 2015 | C58: 582 | D58: plan239_y2021 | E58: 6 | F58: New Jersey | G58: Teachers's Pension and Annuity Fund | H58: TPAF -Teachers | I58: TRUE | J58: 2022411.2 | K58: 3797033 | M58: 365228.28 | N58: 5913556 | O58: 4015003.6 | Q58: 8087342 | R58: 81095320 | S58: 89182662 | T58: 807.246 | U58: 539796.29 | V58: 740296.27 | W58: 1066062.9 | X58: 4117.141 | Y58: 13890.08 | Z58: 358.899 | AA58: -1677454.9 | AB58: 27282252 | AC58: 25604798 | AD58: 63577864 | AE58: 53813068 | AF58: 9764796.9 | AG58: 10162263 | AH58: 7.9435653e-05 | AI58: TRUE | AK58: 0.0468 | AL58: 0.0413 | AM58: 0.079 | AN58: 0.079 | AO58: 1 | AP58: 0.0377 | AS58: 75559915 | AT58: 53254610 | BB58: =AC58/S58 -> 0.28710511 | BD58: =AS58-AD58 -> 11982051 | BE58: =AT58-AD58 -> -10323254 | BF58: =BD58/S58*100 -> 13.435404 | BG58: =BE58/S58*100 -> -11.575405 | BH58: =(BD58-BE58)/(2*S58)*100 -> 12.505404 | BI58: =(BD58+BE58)/(2*S58*(0.01^2)) -> 92.999971 | BJ58: =ROUND(BH58,0) -> 13 | BK58: =IF($BJ58<=30,IF($B58=2015,VLOOKUP($BJ58,'Treasury Yields'!$C$5:$N$34,$E58,FALSE)/100,IF($B58=2016,VLOOKUP($BJ58,'Treasury Yields'!$C$40:$N$69,$E58,FALSE)/100,IF($B58=2017,VLOOKUP($BJ58,'Treasury Yields'!$C$75:$N$104,$E58,FALSE)/100,IF($B58=2018,VLOOKUP($BJ58,'Treasury Yields'!$C$110:$N$139,$E58,FALSE)/100,IF($B58=2019,VLOOKUP($BJ58,'Treasury Yields'!$C$145:$N$174,$E58,FALSE)/100,IF($B58=2020,VLOOKUP($BJ58,'Treasury Yields'!$C$180:$N$209,$E58,FALSE)/100,IF($B58=2021,VLOOKUP($BJ58,'Treasury Yields'!$C$215:$N$244,$E58,FALSE)/100,IF($B58=2022,VLOOKUP($BJ58,'Treasury Yields'!$C$250:$N$279,$E58,FALSE)/100)))))))),0) -> 0.030224 | BL58: =1+BH58*(AL58-BK58)+(AL58-BK58)^2 -> 1.1386325 | BM58: =BL58*R58 -> 92337770 | BN58: =BM58-AB58 -> 65055517 | BP58: =IF($BJ58<=30,IF($B58=2015,VLOOKUP($BJ58,'Treasury Yields'!$C$40:$N$69,$E58,FALSE)/100,IF($B58=2016,VLOOKUP($BJ58,'Treasury Yields'!$C$75:$N$104,$E58,FALSE)/100,IF($B58=2017,VLOOKUP($BJ58,'Treasury Yields'!$C$110:$N$139,$E58,FALSE)/100,IF($B58=2018,VLOOKUP($BJ58,'Treasury Yields'!$C$145:$N$174,$E58,FALSE)/100,IF($B58=2019,VLOOKUP($BJ58,'Treasury Yields'!$C$180:$N$209,$E58,FALSE)/100,IF($B58=2020,VLOOKUP($BJ58,'Treasury Yields'!$C$215:$N$244,$E58,FALSE)/100,IF($B58=2021,VLOOKUP($BJ58,'Treasury Yields'!$C$250:$N$279,$E58,FALSE)/100,IF($B58=2022,VLOOKUP($BJ58,'Treasury Yields'!$C$285:$N$314,$E58,FALSE)/100)))))))),0) -> 0.027834 | BQ58: =1+BH58*(AN58-BP58)+(AN58-BP58)^2 -> 1.6424695 | BR58: =BQ58*S58 -> 1.464798e+08 | BS58: =BR58-AC58 -> 1.20875e+08 | BU58: =IF(BJ58="","",ROUND(BJ58+$BT$2,0)) -> 16 | BV58: =1+(BH58+BU58)*(AN58-BK58)+(AN58-BK58)^2*BI58 -> 2.6116357 | BW58: =BV58*J58 -> 5281801.2 | BX58: =(BM58+BW58-O58)*BK58 -> 2829104.4 | BY58: =BK58*(BN58+BW58-O58) -> 2004525.7 | BZ58: =SUM(J58:K58) -> 5819444.2 | CA58: =SUM(BW58+BY58) -> 7286326.9 | CC58: =BR58 -> 1.464798e+08 | CD58: =F58 -> New Jersey | CE58: =BB58 -> 0.28710511 | CF58: =AC58/CC58 -> 0.17480088
A59: 31000000001612 | B59: 2016 | C59: 582 | D59: plan239_y2021 | E59: 6 | F59: New Jersey | G59: Teachers's Pension and Annuity Fund | H59: TPAF -Teachers | I59: TRUE | J59: 2344322 | K59: 3694844 | M59: -134644 | N59: 10827093 | O59: 4169071 | Q59: 12564108 | R59: 89182662 | S59: 101746770 | T59: 1106 | U59: 798963 | V59: 761712 | W59: -267684 | X59: 1564 | Y59: 13768 | Z59: 244 | AA59: -2886935 | AB59: 25604798 | AC59: 22717863 | AD59: 79028907 | AE59: 63577864 | AF59: 15451043 | AG59: 10305472 | AH59: 0.00010732162 | AI59: TRUE | AK59: 0.0413 | AL59: 0.0322 | AM59: 0.0765 | AN59: 0.079 | AO59: 1 | AP59: 0.0443 | AQ59: 0.0285 | AR59: 2029 | AS59: 94378176 | AT59: 66494248 | AU59: p88 of CAFR | AV59: http://www.state.nj.us/treasury/pensions/annrpts/cafr-fy2016.pdf | BB59: =AC59/S59 -> 0.22327847 | BD59: =AS59-AD59 -> 15349269 | BE59: =AT59-AD59 -> -12534659 | BF59: =BD59/S59*100 -> 15.085756 | BG59: =BE59/S59*100 -> -12.319466 | BH59: =(BD59-BE59)/(2*S59)*100 -> 13.702611 | BI59: =(BD59+BE59)/(2*S59*(0.01^2)) -> 138.31446 | BJ59: =ROUND(BH59,0) -> 14 | BK59: =IF($BJ59<=30,IF($B59=2015,VLOOKUP($BJ59,'Treasury Yields'!$C$5:$N$34,$E59,FALSE)/100,IF($B59=2016,VLOOKUP($BJ59,'Treasury Yields'!$C$40:$N$69,$E59,FALSE)/100,IF($B59=2017,VLOOKUP($BJ59,'Treasury Yields'!$C$75:$N$104,$E59,FALSE)/100,IF($B59=2018,VLOOKUP($BJ59,'Treasury Yields'!$C$110:$N$139,$E59,FALSE)/100,IF($B59=2019,VLOOKUP($BJ59,'Treasury Yields'!$C$145:$N$174,$E59,FALSE)/100,IF($B59=2020,VLOOKUP($BJ59,'Treasury Yields'!$C$180:$N$209,$E59,FALSE)/100,IF($B59=2021,VLOOKUP($BJ59,'Treasury Yields'!$C$215:$N$244,$E59,FALSE)/100,IF($B59=2022,VLOOKUP($BJ59,'Treasury Yields'!$C$250:$N$279,$E59,FALSE)/100)))))))),0) -> 0.028622 | BL59: =1+BH59*(AL59-BK59)+(AL59-BK59)^2 -> 1.0490407 | BM59: =BL59*R59 -> 93556246 | BN59: =BM59-AB59 -> 67951448 | BP59: =IF($BJ59<=30,IF($B59=2015,VLOOKUP($BJ59,'Treasury Yields'!$C$40:$N$69,$E59,FALSE)/100,IF($B59=2016,VLOOKUP($BJ59,'Treasury Yields'!$C$75:$N$104,$E59,FALSE)/100,IF($B59=2017,VLOOKUP($BJ59,'Treasury Yields'!$C$110:$N$139,$E59,FALSE)/100,IF($B59=2018,VLOOKUP($BJ59,'Treasury Yields'!$C$145:$N$174,$E59,FALSE)/100,IF($B59=2019,VLOOKUP($BJ59,'Treasury Yields'!$C$180:$N$209,$E59,FALSE)/100,IF($B59=2020,VLOOKUP($BJ59,'Treasury Yields'!$C$215:$N$244,$E59,FALSE)/100,IF($B59=2021,VLOOKUP($BJ59,'Treasury Yields'!$C$250:$N$279,$E59,FALSE)/100,IF($B59=2022,VLOOKUP($BJ59,'Treasury Yields'!$C$285:$N$314,$E59,FALSE)/100)))))))),0) -> 0.018742 | BQ59: =1+BH59*(AN59-BP59)+(AN59-BP59)^2 -> 1.829323 | BR59: =BQ59*S59 -> 1.861277e+08 | BS59: =BR59-AC59 -> 1.6340984e+08 | BU59: =IF(BJ59="","",ROUND(BJ59+$BT$2,0)) -> 17 | BV59: =1+(BH59+BU59)*(AN59-BK59)+(AN59-BK59)^2*BI59 -> 2.8977703 | BW59: =BV59*J59 -> 6793306.8 | BX59: =(BM59+BW59-O59)*BK59 -> 2752877.8 | BY59: =BK59*(BN59+BW59-O59) -> 2020017.2 | BZ59: =SUM(J59:K59) -> 6039166 | CA59: =SUM(BW59+BY59) -> 8813324 | CC59: =BR59 -> 1.861277e+08 | CD59: =F59 -> New Jersey | CE59: =BB59 -> 0.22327847 | CF59: =AC59/CC59 -> 0.12205525
A60: 31000000001612 | B60: 2017 | C60: 582 | D60: plan239_y2021 | E60: 6 | F60: New Jersey | G60: Teachers's Pension and Annuity Fund | H60: TPAF -Teachers | I60: TRUE | J60: 3028690 | K60: 3304988 | M60: 236378 | N60: -13285524 | O60: 4306269 | Q60: -11020399 | R60: 101746770 | S60: 90726371 | T60: 1404 | U60: 1125614 | V60: 790788 | W60: 2736989 | X60: 1338 | Y60: 11924 | Z60: 358 | AA60: 338299 | AB60: 22717863 | AC60: 23056162 | AD60: 67670209 | AE60: 79028907 | AF60: -11358698 | AG60: 10436205 | AH60: 0.00013453166 | AI60: TRUE | AK60: 0.0322 | AL60: 0.0425 | AM60: 0.07 | AN60: 0.0765 | AO60: 1 | AP60: 0.0275 | AQ60: 0.0385 | AR60: 2036 | AS60: 80394331 | AT60: 57188022 | AU60: p60 of CAFR | AV60: https://www.state.nj.us/treasury/pensions/documents/financial/annrpt2017/2017divisioncombined.pdf | BB60: =AC60/S60 -> 0.25412856 | BD60: =AS60-AD60 -> 12724122 | BE60: =AT60-AD60 -> -10482187 | BF60: =BD60/S60*100 -> 14.024723 | BG60: =BE60/S60*100 -> -11.553628 | BH60: =(BD60-BE60)/(2*S60)*100 -> 12.789175 | BI60: =(BD60+BE60)/(2*S60*(0.01^2)) -> 123.55476 | BJ60: =ROUND(BH60,0) -> 13 | BK60: =IF($BJ60<=30,IF($B60=2015,VLOOKUP($BJ60,'Treasury Yields'!$C$5:$N$34,$E60,FALSE)/100,IF($B60=2016,VLOOKUP($BJ60,'Treasury Yields'!$C$40:$N$69,$E60,FALSE)/100,IF($B60=2017,VLOOKUP($BJ60,'Treasury Yields'!$C$75:$N$104,$E60,FALSE)/100,IF($B60=2018,VLOOKUP($BJ60,'Treasury Yields'!$C$110:$N$139,$E60,FALSE)/100,IF($B60=2019,VLOOKUP($BJ60,'Treasury Yields'!$C$145:$N$174,$E60,FALSE)/100,IF($B60=2020,VLOOKUP($BJ60,'Treasury Yields'!$C$180:$N$209,$E60,FALSE)/100,IF($B60=2021,VLOOKUP($BJ60,'Treasury Yields'!$C$215:$N$244,$E60,FALSE)/100,IF($B60=2022,VLOOKUP($BJ60,'Treasury Yields'!$C$250:$N$279,$E60,FALSE)/100)))))))),0) -> 0.018144 | BL60: =1+BH60*(AL60-BK60)+(AL60-BK60)^2 -> 1.3120864 | BM60: =BL60*R60 -> 1.3350055e+08 | BN60: =BM60-AB60 -> 1.1078269e+08 | BP60: =IF($BJ60<=30,IF($B60=2015,VLOOKUP($BJ60,'Treasury Yields'!$C$40:$N$69,$E60,FALSE)/100,IF($B60=2016,VLOOKUP($BJ60,'Treasury Yields'!$C$75:$N$104,$E60,FALSE)/100,IF($B60=2017,VLOOKUP($BJ60,'Treasury Yields'!$C$110:$N$139,$E60,FALSE)/100,IF($B60=2018,VLOOKUP($BJ60,'Treasury Yields'!$C$145:$N$174,$E60,FALSE)/100,IF($B60=2019,VLOOKUP($BJ60,'Treasury Yields'!$C$180:$N$209,$E60,FALSE)/100,IF($B60=2020,VLOOKUP($BJ60,'Treasury Yields'!$C$215:$N$244,$E60,FALSE)/100,IF($B60=2021,VLOOKUP($BJ60,'Treasury Yields'!$C$250:$N$279,$E60,FALSE)/100,IF($B60=2022,VLOOKUP($BJ60,'Treasury Yields'!$C$285:$N$314,$E60,FALSE)/100)))))))),0) -> 0.0258664 | BQ60: =1+BH60*(AN60-BP60)+(AN60-BP60)^2 -> 1.6501257 | BR60: =BQ60*S60 -> 1.4970992e+08 | BS60: =BR60-AC60 -> 1.2665376e+08 | BU60: =IF(BJ60="","",ROUND(BJ60+$BT$2,0)) -> 16 | BV60: =1+(BH60+BU60)*(AN60-BK60)+(AN60-BK60)^2*BI60 -> 3.1007773 | BW60: =BV60*J60 -> 9391293.2 | BX60: =(BM60+BW60-O60)*BK60 -> 2514496.7 | BY60: =BK60*(BN60+BW60-O60) -> 2102303.7 | BZ60: =SUM(J60:K60) -> 6333678 | CA60: =SUM(BW60+BY60) -> 11493597 | CC60: =BR60 -> 1.4970992e+08 | CD60: =F60 -> New Jersey | CE60: =BB60 -> 0.25412856 | CF60: =AC60/CC60 -> 0.15400557
A61: 31000000001612 | B61: 2018 | C61: 582 | D61: plan239_y2021 | E61: 6 | F61: New Jersey | G61: Teachers's Pension and Annuity Fund | H61: TPAF -Teachers | I61: TRUE | J61: 2229422 | K61: 3858188 | M61: 1195858 | N61: -6816856 | O61: 4401203 | Q61: -3928904 | R61: 90726371 | S61: 86797467 | T61: 1724 | U61: 1514408 | V61: 810900 | W61: 2016317 | X61: 5686 | Y61: 13222 | Z61: 346 | AA61: -65045 | AB61: 23056162 | AC61: 22991117 | AD61: 63806350 | AE61: 67670209 | AF61: -3863859 | AG61: 10636814 | AH61: 0.00016207861 | AI61: TRUE | AK61: 0.0425 | AL61: 0.0486 | AM61: 0.07 | AN61: 0.07 | AO61: 1 | AP61: 0.0214 | AQ61: 0.0387 | AR61: 2040 | AS61: 75417895 | AT61: 54180663 | AV61: https://www.nj.gov/treasury/pensions/documents/financial/annrpt2018/cafr-fy2018.pdf | BB61: =AC61/S61 -> 0.26488235 | BD61: =AS61-AD61 -> 11611545 | BE61: =AT61-AD61 -> -9625687 | BF61: =BD61/S61*100 -> 13.377746 | BG61: =BE61/S61*100 -> -11.089825 | BH61: =(BD61-BE61)/(2*S61)*100 -> 12.233786 | BI61: =(BD61+BE61)/(2*S61*(0.01^2)) -> 114.39608 | BJ61: =ROUND(BH61,0) -> 12 | BK61: =IF($BJ61<=30,IF($B61=2015,VLOOKUP($BJ61,'Treasury Yields'!$C$5:$N$34,$E61,FALSE)/100,IF($B61=2016,VLOOKUP($BJ61,'Treasury Yields'!$C$40:$N$69,$E61,FALSE)/100,IF($B61=2017,VLOOKUP($BJ61,'Treasury Yields'!$C$75:$N$104,$E61,FALSE)/100,IF($B61=2018,VLOOKUP($BJ61,'Treasury Yields'!$C$110:$N$139,$E61,FALSE)/100,IF($B61=2019,VLOOKUP($BJ61,'Treasury Yields'!$C$145:$N$174,$E61,FALSE)/100,IF($B61=2020,VLOOKUP($BJ61,'Treasury Yields'!$C$180:$N$209,$E61,FALSE)/100,IF($B61=2021,VLOOKUP($BJ61,'Treasury Yields'!$C$215:$N$244,$E61,FALSE)/100,IF($B61=2022,VLOOKUP($BJ61,'Treasury Yields'!$C$250:$N$279,$E61,FALSE)/100)))))))),0) -> 0.0254676 | BL61: =1+BH61*(AL61-BK61)+(AL61-BK61)^2 -> 1.2835319 | BM61: =BL61*R61 -> 1.1645019e+08 | BN61: =BM61-AB61 -> 93394032 | BP61: =IF($BJ61<=30,IF($B61=2015,VLOOKUP($BJ61,'Treasury Yields'!$C$40:$N$69,$E61,FALSE)/100,IF($B61=2016,VLOOKUP($BJ61,'Treasury Yields'!$C$75:$N$104,$E61,FALSE)/100,IF($B61=2017,VLOOKUP($BJ61,'Treasury Yields'!$C$110:$N$139,$E61,FALSE)/100,IF($B61=2018,VLOOKUP($BJ61,'Treasury Yields'!$C$145:$N$174,$E61,FALSE)/100,IF($B61=2019,VLOOKUP($BJ61,'Treasury Yields'!$C$180:$N$209,$E61,FALSE)/100,IF($B61=2020,VLOOKUP($BJ61,'Treasury Yields'!$C$215:$N$244,$E61,FALSE)/100,IF($B61=2021,VLOOKUP($BJ61,'Treasury Yields'!$C$250:$N$279,$E61,FALSE)/100,IF($B61=2022,VLOOKUP($BJ61,'Treasury Yields'!$C$285:$N$314,$E61,FALSE)/100)))))))),0) -> 0.028906473 | BQ61: =1+BH61*(AN61-BP61)+(AN61-BP61)^2 -> 1.5044181 | BR61: =BQ61*S61 -> 1.3057968e+08 | BS61: =BR61-AC61 -> 1.0758856e+08 | BU61: =IF(BJ61="","",ROUND(BJ61+$BT$2,0)) -> 15 | BV61: =1+(BH61+BU61)*(AN61-BK61)+(AN61-BK61)^2*BI61 -> 2.4396487 | BW61: =BV61*J61 -> 5439006.4 | BX61: =(BM61+BW61-O61)*BK61 -> 2992137.3 | BY61: =BK61*(BN61+BW61-O61) -> 2404952.2 | BZ61: =SUM(J61:K61) -> 6087610 | CA61: =SUM(BW61+BY61) -> 7843958.6 | CC61: =BR61 -> 1.3057968e+08 | CD61: =F61 -> New Jersey | CE61: =BB61 -> 0.26488235 | CF61: =AC61/CC61 -> 0.17606964
A62: 31000000001612 | B62: 2019 | C62: 582 | D62: plan239_y2021 | E62: 6 | F62: New Jersey | G62: Teachers's Pension and Annuity Fund | H62: TPAF -Teachers | I62: TRUE | J62: 1882082 | K62: 4201672 | M62: -155622 | N62: -4005548 | O62: 4510860 | Q62: -2581621 | R62: 86797467 | S62: 84215847 | T62: 2050 | U62: 2013446 | V62: 846166 | W62: 1361781 | X62: 6656 | Y62: 13922 | Z62: 300 | AA62: -294383 | AB62: 22991117 | AC62: 22696734 | AD62: 61519112 | AE62: 63806350 | AF62: -2287238 | AG62: 10823505 | AH62: 0.0001894026 | AI62: TRUE | AK62: 0.0486 | AL62: 0.056 | AM62: 0.07 | AN62: 0.07 | AO62: 1 | AP62: 0.014 | AQ62: 0.035 | AR62: 2054 | AS62: 72544650 | AT62: 52371398 | AU62: p60 of CAFR | AV62: https://www.nj.gov/treasury/pensions/documents/financial/annrpt2019/2019divisioncombined.pdf | BB62: =AC62/S62 -> 0.26950669 | BD62: =AS62-AD62 -> 11025538 | BE62: =AT62-AD62 -> -9147714 | BF62: =BD62/S62*100 -> 13.091999 | BG62: =BE62/S62*100 -> -10.862224 | BH62: =(BD62-BE62)/(2*S62)*100 -> 11.977112 | BI62: =(BD62+BE62)/(2*S62*(0.01^2)) -> 111.48876 | BJ62: =ROUND(BH62,0) -> 12 | BK62: =IF($BJ62<=30,IF($B62=2015,VLOOKUP($BJ62,'Treasury Yields'!$C$5:$N$34,$E62,FALSE)/100,IF($B62=2016,VLOOKUP($BJ62,'Treasury Yields'!$C$40:$N$69,$E62,FALSE)/100,IF($B62=2017,VLOOKUP($BJ62,'Treasury Yields'!$C$75:$N$104,$E62,FALSE)/100,IF($B62=2018,VLOOKUP($BJ62,'Treasury Yields'!$C$110:$N$139,$E62,FALSE)/100,IF($B62=2019,VLOOKUP($BJ62,'Treasury Yields'!$C$145:$N$174,$E62,FALSE)/100,IF($B62=2020,VLOOKUP($BJ62,'Treasury Yields'!$C$180:$N$209,$E62,FALSE)/100,IF($B62=2021,VLOOKUP($BJ62,'Treasury Yields'!$C$215:$N$244,$E62,FALSE)/100,IF($B62=2022,VLOOKUP($BJ62,'Treasury Yields'!$C$250:$N$279,$E62,FALSE)/100)))))))),0) -> 0.028906473 | BL62: =1+BH62*(AL62-BK62)+(AL62-BK62)^2 -> 1.3252363 | BM62: =BL62*R62 -> 1.1502715e+08 | BN62: =BM62-AB62 -> 92036034 | BP62: =IF($BJ62<=30,IF($B62=2015,VLOOKUP($BJ62,'Treasury Yields'!$C$40:$N$69,$E62,FALSE)/100,IF($B62=2016,VLOOKUP($BJ62,'Treasury Yields'!$C$75:$N$104,$E62,FALSE)/100,IF($B62=2017,VLOOKUP($BJ62,'Treasury Yields'!$C$110:$N$139,$E62,FALSE)/100,IF($B62=2018,VLOOKUP($BJ62,'Treasury Yields'!$C$145:$N$174,$E62,FALSE)/100,IF($B62=2019,VLOOKUP($BJ62,'Treasury Yields'!$C$180:$N$209,$E62,FALSE)/100,IF($B62=2020,VLOOKUP($BJ62,'Treasury Yields'!$C$215:$N$244,$E62,FALSE)/100,IF($B62=2021,VLOOKUP($BJ62,'Treasury Yields'!$C$250:$N$279,$E62,FALSE)/100,IF($B62=2022,VLOOKUP($BJ62,'Treasury Yields'!$C$285:$N$314,$E62,FALSE)/100)))))))),0) -> 0.022184 | BQ62: =1+BH62*(AN62-BP62)+(AN62-BP62)^2 -> 1.5749839 | BR62: =BQ62*S62 -> 1.3263861e+08 | BS62: =BR62-AC62 -> 1.0994187e+08 | BU62: =IF(BJ62="","",ROUND(BJ62+$BT$2,0)) -> 15 | BV62: =1+(BH62+BU62)*(AN62-BK62)+(AN62-BK62)^2*BI62 -> 2.2968533 | BW62: =BV62*J62 -> 4322866.2 | BX62: =(BM62+BW62-O62)*BK62 -> 3319595 | BY62: =BK62*(BN62+BW62-O62) -> 2655002.9 | BZ62: =SUM(J62:K62) -> 6083754 | CA62: =SUM(BW62+BY62) -> 6977869.1 | CC62: =BR62 -> 1.3263861e+08 | CD62: =F62 -> New Jersey | CE62: =BB62 -> 0.26950669 | CF62: =AC62/CC62 -> 0.1711171
A63: 31000000001612 | B63: 2020 | C63: 582 | D63: plan239_y2021 | E63: 6 | F63: New Jersey | G63: Teachers's Pension and Annuity Fund | H63: TPAF -Teachers | I63: TRUE | J63: 1643902 | K63: 4680942 | L63: -16738 | M63: -8597 | N63: 1613055 | O63: 4615149 | Q63: 3306832 | R63: 84215847 | S63: 87522679 | T63: 2109 | U63: 2268898 | V63: 867038 | W63: 318393 | X63: 9417 | Y63: 18591 | Z63: 330 | AA63: -1167554 | AB63: 22696734 | AC63: 21529180 | AD63: 65993499 | AE63: 61519112 | AF63: 4474387 | AG63: 11061603 | AH63: 0.00019065953 | AI63: TRUE | AK63: 0.056 | AL63: 0.054 | AM63: 0.07 | AN63: 0.07 | AO63: 1 | AP63: 0.016 | AQ63: 0.0221 | AR63: 2062 | AS63: 77517093 | AT63: 56425088 | AU63: p62 of CAFR | AV63: https://www.nj.gov/treasury/pensions/documents/financial/annrpt2020/2020divisioncombined.pdf | BB63: =AC63/S63 -> 0.24598402 | BD63: =AS63-AD63 -> 11523594 | BE63: =AT63-AD63 -> -9568411 | BF63: =BD63/S63*100 -> 13.166409 | BG63: =BE63/S63*100 -> -10.932493 | BH63: =(BD63-BE63)/(2*S63)*100 -> 12.049451 | BI63: =(BD63+BE63)/(2*S63*(0.01^2)) -> 111.69579 | BJ63: =ROUND(BH63,0) -> 12 | BK63: =IF($BJ63<=30,IF($B63=2015,VLOOKUP($BJ63,'Treasury Yields'!$C$5:$N$34,$E63,FALSE)/100,IF($B63=2016,VLOOKUP($BJ63,'Treasury Yields'!$C$40:$N$69,$E63,FALSE)/100,IF($B63=2017,VLOOKUP($BJ63,'Treasury Yields'!$C$75:$N$104,$E63,FALSE)/100,IF($B63=2018,VLOOKUP($BJ63,'Treasury Yields'!$C$110:$N$139,$E63,FALSE)/100,IF($B63=2019,VLOOKUP($BJ63,'Treasury Yields'!$C$145:$N$174,$E63,FALSE)/100,IF($B63=2020,VLOOKUP($BJ63,'Treasury Yields'!$C$180:$N$209,$E63,FALSE)/100,IF($B63=2021,VLOOKUP($BJ63,'Treasury Yields'!$C$215:$N$244,$E63,FALSE)/100,IF($B63=2022,VLOOKUP($BJ63,'Treasury Yields'!$C$250:$N$279,$E63,FALSE)/100)))))))),0) -> 0.022184 | BL63: =1+BH63*(AL63-BK63)+(AL63-BK63)^2 -> 1.3843776 | BM63: =BL63*R63 -> 1.1658653e+08 | BN63: =BM63-AB63 -> 93889798 | BP63: =IF($BJ63<=30,IF($B63=2015,VLOOKUP($BJ63,'Treasury Yields'!$C$40:$N$69,$E63,FALSE)/100,IF($B63=2016,VLOOKUP($BJ63,'Treasury Yields'!$C$75:$N$104,$E63,FALSE)/100,IF($B63=2017,VLOOKUP($BJ63,'Treasury Yields'!$C$110:$N$139,$E63,FALSE)/100,IF($B63=2018,VLOOKUP($BJ63,'Treasury Yields'!$C$145:$N$174,$E63,FALSE)/100,IF($B63=2019,VLOOKUP($BJ63,'Treasury Yields'!$C$180:$N$209,$E63,FALSE)/100,IF($B63=2020,VLOOKUP($BJ63,'Treasury Yields'!$C$215:$N$244,$E63,FALSE)/100,IF($B63=2021,VLOOKUP($BJ63,'Treasury Yields'!$C$250:$N$279,$E63,FALSE)/100,IF($B63=2022,VLOOKUP($BJ63,'Treasury Yields'!$C$285:$N$314,$E63,FALSE)/100)))))))),0) -> 0.013689455 | BQ63: =1+BH63*(AN63-BP63)+(AN63-BP63)^2 -> 1.681682 | BR63: =BQ63*S63 -> 1.4718532e+08 | BS63: =BR63-AC63 -> 1.2565614e+08 | BU63: =IF(BJ63="","",ROUND(BJ63+$BT$2,0)) -> 15 | BV63: =1+(BH63+BU63)*(AN63-BK63)+(AN63-BK63)^2*BI63 -> 2.5487745 | BW63: =BV63*J63 -> 4189935.4 | BX63: =(BM63+BW63-O63)*BK63 -> 2576922.7 | BY63: =BK63*(BN63+BW63-O63) -> 2073418.3 | BZ63: =SUM(J63:K63) -> 6324844 | CA63: =SUM(BW63+BY63) -> 6263353.8 | CC63: =BR63 -> 1.4718532e+08 | CD63: =F63 -> New Jersey | CE63: =BB63 -> 0.24598402 | CF63: =AC63/CC63 -> 0.14627261
A64: 31000000001612 | B64: 2021 | C64: 582 | D64: plan239_y2021 | E64: 6 | F64: New Jersey | G64: Teachers's Pension and Annuity Fund | H64: TPAF -Teachers | I64: TRUE | J64: 1759508 | K64: 4695759 | M64: 195943 | N64: -14765458 | O64: 4710584 | Q64: -12823545 | R64: 87522679 | S64: 74699134 | T64: 2685 | U64: 2933363 | V64: 883659 | W64: 5902191 | X64: 1288 | Y64: 9043 | Z64: 403 | AA64: 5003963 | AB64: 21529180 | AC64: 26533143 | AD64: 48165991 | AE64: 65993499 | AF64: -17827508 | AG64: 11339929 | AI64: TRUE | AK64: 0.054 | AL64: 0.07 | AM64: 0.07 | AN64: 0.07 | AO64: 1 | AS64: 56988413 | AT64: 40755711 | BB64: =AC64/S64 -> 0.35520014 | BD64: =AS64-AD64 -> 8822422 | BE64: =AT64-AD64 -> -7410280 | BF64: =BD64/S64*100 -> 11.810608 | BG64: =BE64/S64*100 -> -9.9201686 | BH64: =(BD64-BE64)/(2*S64)*100 -> 10.865388 | BI64: =(BD64+BE64)/(2*S64*(0.01^2)) -> 94.521979 | BJ64: =ROUND(BH64,0) -> 11 | BK64: =IF($BJ64<=30,IF($B64=2015,VLOOKUP($BJ64,'Treasury Yields'!$C$5:$N$34,$E64,FALSE)/100,IF($B64=2016,VLOOKUP($BJ64,'Treasury Yields'!$C$40:$N$69,$E64,FALSE)/100,IF($B64=2017,VLOOKUP($BJ64,'Treasury Yields'!$C$75:$N$104,$E64,FALSE)/100,IF($B64=2018,VLOOKUP($BJ64,'Treasury Yields'!$C$110:$N$139,$E64,FALSE)/100,IF($B64=2019,VLOOKUP($BJ64,'Treasury Yields'!$C$145:$N$174,$E64,FALSE)/100,IF($B64=2020,VLOOKUP($BJ64,'Treasury Yields'!$C$180:$N$209,$E64,FALSE)/100,IF($B64=2021,VLOOKUP($BJ64,'Treasury Yields'!$C$215:$N$244,$E64,FALSE)/100,IF($B64=2022,VLOOKUP($BJ64,'Treasury Yields'!$C$250:$N$279,$E64,FALSE)/100)))))))),0) -> 0.014551091 | BL64: =1+BH64*(AL64-BK64)+(AL64-BK64)^2 -> 1.6055485 | BM64: =BL64*R64 -> 1.4052191e+08 | BN64: =BM64-AB64 -> 1.1899273e+08 | BP64: =IF($BJ64<=30,IF($B64=2015,VLOOKUP($BJ64,'Treasury Yields'!$C$40:$N$69,$E64,FALSE)/100,IF($B64=2016,VLOOKUP($BJ64,'Treasury Yields'!$C$75:$N$104,$E64,FALSE)/100,IF($B64=2017,VLOOKUP($BJ64,'Treasury Yields'!$C$110:$N$139,$E64,FALSE)/100,IF($B64=2018,VLOOKUP($BJ64,'Treasury Yields'!$C$145:$N$174,$E64,FALSE)/100,IF($B64=2019,VLOOKUP($BJ64,'Treasury Yields'!$C$180:$N$209,$E64,FALSE)/100,IF($B64=2020,VLOOKUP($BJ64,'Treasury Yields'!$C$215:$N$244,$E64,FALSE)/100,IF($B64=2021,VLOOKUP($BJ64,'Treasury Yields'!$C$250:$N$279,$E64,FALSE)/100,IF($B64=2022,VLOOKUP($BJ64,'Treasury Yields'!$C$285:$N$314,$E64,FALSE)/100)))))))),0) -> 0.021554273 | BQ64: =1+BH64*(AN64-BP64)+(AN64-BP64)^2 -> 1.5287286 | BR64: =BQ64*S64 -> 1.141947e+08 | BS64: =BR64-AC64 -> 87661562 | BU64: =IF(BJ64="","",ROUND(BJ64+$BT$2,0)) -> 14 | BV64: =1+(BH64+BU64)*(AN64-BK64)+(AN64-BK64)^2*BI64 -> 2.6693742 | BW64: =BV64*J64 -> 4696785.2 | BX64: =(BM64+BW64-O64)*BK64 -> 2044546.3 | BY64: =BK64*(BN64+BW64-O64) -> 1731273.2 | BZ64: =SUM(J64:K64) -> 6455267 | CA64: =SUM(BW64+BY64) -> 6428058.4 | CC64: =BR64 -> 1.141947e+08 | CD64: =F64 -> New Jersey | CE64: =BB64 -> 0.35520014 | CF64: =AC64/CC64 -> 0.23235003
A65: 31000000001612 | B65: 2022 | C65: 582 | D65: plan239_y2021 | E65: 6 | F65: New Jersey | G65: Teachers's Pension and Annuity Fund | H65: TPAF -Teachers | I65: TRUE | J65: 1195044 | K65: 5146966 | M65: -20646 | N65: 110220 | O65: 4822987 | Q65: 1617984 | R65: 74699134 | S65: 76317118 | T65: 3758 | U65: 4188158 | V65: 907326 | W65: -2166015 | X65: 9387 | Y65: 12635 | Z65: 396 | AA65: -1892612 | AB65: 26533143 | AC65: 24640531 | AD65: 51676587 | AE65: 48165991 | AF65: 3510596 | AG65: 11509653 | AI65: TRUE | AK65: 0.07 | AL65: 0.07 | AM65: 0.07 | AN65: 0.07 | AO65: 1 | AS65: 60591897 | AT65: 44166559 | AV65: https://www.nj.gov/treasury/pensions/documents/financial/annrpt2022/2022-ACFR-NJDPB.pdf | BB65: =AC65/S65 -> 0.3228703 | BD65: =AS65-AD65 -> 8915310 | BE65: =AT65-AD65 -> -7510028 | BF65: =BD65/S65*100 -> 11.681927 | BG65: =BE65/S65*100 -> -9.840555 | BH65: =(BD65-BE65)/(2*S65)*100 -> 10.761241 | BI65: =(BD65+BE65)/(2*S65*(0.01^2)) -> 92.068597 | BJ65: =ROUND(BH65,0) -> 11 | BK65: =IF($BJ65<=30,IF($B65=2015,VLOOKUP($BJ65,'Treasury Yields'!$C$5:$N$34,$E65,FALSE)/100,IF($B65=2016,VLOOKUP($BJ65,'Treasury Yields'!$C$40:$N$69,$E65,FALSE)/100,IF($B65=2017,VLOOKUP($BJ65,'Treasury Yields'!$C$75:$N$104,$E65,FALSE)/100,IF($B65=2018,VLOOKUP($BJ65,'Treasury Yields'!$C$110:$N$139,$E65,FALSE)/100,IF($B65=2019,VLOOKUP($BJ65,'Treasury Yields'!$C$145:$N$174,$E65,FALSE)/100,IF($B65=2020,VLOOKUP($BJ65,'Treasury Yields'!$C$180:$N$209,$E65,FALSE)/100,IF($B65=2021,VLOOKUP($BJ65,'Treasury Yields'!$C$215:$N$244,$E65,FALSE)/100,IF($B65=2022,VLOOKUP($BJ65,'Treasury Yields'!$C$250:$N$279,$E65,FALSE)/100)))))))),0) -> 0.021554273 | BL65: =1+BH65*(AL65-BK65)+(AL65-BK65)^2 -> 1.5236831 | BM65: =BL65*R65 -> 1.1381781e+08 | BN65: =BM65-AB65 -> 87284668 | BP65: =IF($BJ65<=30,IF($B65=2015,VLOOKUP($BJ65,'Treasury Yields'!$C$40:$N$69,$E65,FALSE)/100,IF($B65=2016,VLOOKUP($BJ65,'Treasury Yields'!$C$75:$N$104,$E65,FALSE)/100,IF($B65=2017,VLOOKUP($BJ65,'Treasury Yields'!$C$110:$N$139,$E65,FALSE)/100,IF($B65=2018,VLOOKUP($BJ65,'Treasury Yields'!$C$145:$N$174,$E65,FALSE)/100,IF($B65=2019,VLOOKUP($BJ65,'Treasury Yields'!$C$180:$N$209,$E65,FALSE)/100,IF($B65=2020,VLOOKUP($BJ65,'Treasury Yields'!$C$215:$N$244,$E65,FALSE)/100,IF($B65=2021,VLOOKUP($BJ65,'Treasury Yields'!$C$250:$N$279,$E65,FALSE)/100,IF($B65=2022,VLOOKUP($BJ65,'Treasury Yields'!$C$285:$N$314,$E65,FALSE)/100)))))))),0) -> 0.031935909 | BQ65: =1+BH65*(AN65-BP65)+(AN65-BP65)^2 -> 1.4110657 | BR65: =BQ65*S65 -> 1.0768847e+08 | BS65: =BR65-AC65 -> 83047939 | BU65: =IF(BJ65="","",ROUND(BJ65+$BT$2,0)) -> 14 | BV65: =1+(BH65+BU65)*(AN65-BK65)+(AN65-BK65)^2*BI65 -> 2.4156603 | BW65: =BV65*J65 -> 2886820.3 | BX65: =(BM65+BW65-O65)*BK65 -> 2411527.5 | BY65: =BK65*(BN65+BW65-O65) -> 1839624.9 | BZ65: =SUM(J65:K65) -> 6342010 | CA65: =SUM(BW65+BY65) -> 4726445.2 | CC65: =BR65 -> 1.0768847e+08 | CD65: =F65 -> New Jersey | CE65: =BB65 -> 0.3228703 | CF65: =AC65/CC65 -> 0.22881308
A66: 1000000003402 | B66: 2015 | C66: 575 | D66: plan277_y2021 | E66: 9 | F66: Alabama | G66: Teachers' Retirement System of Alabama | H66: TRS | I66: TRUE | J66: 660390 | K66: 2421604 | L66: 0 | M66: -70200 | O66: 2080896 | P66: 55898 | Q66: 875000 | R66: 31338446 | S66: 32213446 | T66: 737677 | V66: 477918 | W66: 261461 | Y66: 19331 | Z66: 172982 | AA66: -506087 | AB66: 22253818 | AC66: 21747731 | AD66: 10465715 | AE66: 9084628 | AF66: 1381087 | AG66: 6541054 | AH66: 0.11277647 | AI66: TRUE | AK66: 0.08 | AL66: 0.08 | AM66: 0.08 | AN66: 0.08 | AO66: 1 | AP66: 0 | AS66: 13845362 | AT66: 7599251 | BB66: =AC66/S66 -> 0.67511346 | BD66: =AS66-AD66 -> 3379647 | BE66: =AT66-AD66 -> -2866464 | BF66: =BD66/S66*100 -> 10.491417 | BG66: =BE66/S66*100 -> -8.8983464 | BH66: =(BD66-BE66)/(2*S66)*100 -> 9.6948818 | BI66: =(BD66+BE66)/(2*S66*(0.01^2)) -> 79.65354 | BJ66: =ROUND(BH66,0) -> 10 | BK66: =IF($BJ66<=30,IF($B66=2015,VLOOKUP($BJ66,'Treasury Yields'!$C$5:$N$34,$E66,FALSE)/100,IF($B66=2016,VLOOKUP($BJ66,'Treasury Yields'!$C$40:$N$69,$E66,FALSE)/100,IF($B66=2017,VLOOKUP($BJ66,'Treasury Yields'!$C$75:$N$104,$E66,FALSE)/100,IF($B66=2018,VLOOKUP($BJ66,'Treasury Yields'!$C$110:$N$139,$E66,FALSE)/100,IF($B66=2019,VLOOKUP($BJ66,'Treasury Yields'!$C$145:$N$174,$E66,FALSE)/100,IF($B66=2020,VLOOKUP($BJ66,'Treasury Yields'!$C$180:$N$209,$E66,FALSE)/100,IF($B66=2021,VLOOKUP($BJ66,'Treasury Yields'!$C$215:$N$244,$E66,FALSE)/100,IF($B66=2022,VLOOKUP($BJ66,'Treasury Yields'!$C$250:$N$279,$E66,FALSE)/100)))))))),0) -> 0.02672 | BL66: =1+BH66*(AL66-BK66)+(AL66-BK66)^2 -> 1.5193821 | BM66: =BL66*R66 -> 47615073 | BN66: =BM66-AB66 -> 25361255 | BP66: =IF($BJ66<=30,IF($B66=2015,VLOOKUP($BJ66,'Treasury Yields'!$C$40:$N$69,$E66,FALSE)/100,IF($B66=2016,VLOOKUP($BJ66,'Treasury Yields'!$C$75:$N$104,$E66,FALSE)/100,IF($B66=2017,VLOOKUP($BJ66,'Treasury Yields'!$C$110:$N$139,$E66,FALSE)/100,IF($B66=2018,VLOOKUP($BJ66,'Treasury Yields'!$C$145:$N$174,$E66,FALSE)/100,IF($B66=2019,VLOOKUP($BJ66,'Treasury Yields'!$C$180:$N$209,$E66,FALSE)/100,IF($B66=2020,VLOOKUP($BJ66,'Treasury Yields'!$C$215:$N$244,$E66,FALSE)/100,IF($B66=2021,VLOOKUP($BJ66,'Treasury Yields'!$C$250:$N$279,$E66,FALSE)/100,IF($B66=2022,VLOOKUP($BJ66,'Treasury Yields'!$C$285:$N$314,$E66,FALSE)/100)))))))),0) -> 0.02211 | BQ66: =1+BH66*(AN66-BP66)+(AN66-BP66)^2 -> 1.564588 | BR66: =BQ66*S66 -> 50400770 | BS66: =BR66-AC66 -> 28653039 | BU66: =IF(BJ66="","",ROUND(BJ66+$BT$2,0)) -> 13 | BV66: =1+(BH66+BU66)*(AN66-BK66)+(AN66-BK66)^2*BI66 -> 2.4353005 | BW66: =BV66*J66 -> 1608248.1 | BX66: =(BM66+BW66-O66)*BK66 -> 1259645.6 | BY66: =BK66*(BN66+BW66-O66) -> 665023.57 | BZ66: =SUM(J66:K66) -> 3081994 | CA66: =SUM(BW66+BY66) -> 2273271.6 | CC66: =BR66 -> 50400770 | CD66: =F66 -> Alabama | CE66: =BB66 -> 0.67511346 | CF66: =AC66/CC66 -> 0.43149601
A67: 1000000003402 | B67: 2016 | C67: 575 | D67: plan277_y2021 | E67: 9 | F67: Alabama | G67: Teachers' Retirement System of Alabama | H67: TRS | I67: TRUE | J67: 627938 | K67: 2488310 | L67: 0 | M67: -290388 | N67: 942133 | O67: 2161570 | P67: 57566 | Q67: 1548857 | R67: 32213446 | S67: 33762303 | T67: 751909 | V67: 475980 | W67: 2199396 | Y67: 19582 | Z67: 0 | AA67: 1188567 | AB67: 21747731 | AC67: 22936298 | AD67: 10826005 | AE67: 10465715 | AF67: 360290 | AG67: 6541310 | AH67: 0.11494777 | AI67: TRUE | AK67: 0.08 | AL67: 0.0775 | AM67: 0.08 | AN67: 0.08 | AO67: 1 | AP67: 0.0025 | AS67: 14422630 | AT67: 7781048 | AU67: P60 of CAFR | AV67: http://www.rsa-al.gov/uploads/files/2016_CAFR.pdf | BB67: =AC67/S67 -> 0.67934637 | BD67: =AS67-AD67 -> 3596625 | BE67: =AT67-AD67 -> -3044957 | BF67: =BD67/S67*100 -> 10.652783 | BG67: =BE67/S67*100 -> -9.0188072 | BH67: =(BD67-BE67)/(2*S67)*100 -> 9.8357953 | BI67: =(BD67+BE67)/(2*S67*(0.01^2)) -> 81.698811 | BJ67: =ROUND(BH67,0) -> 10 | BK67: =IF($BJ67<=30,IF($B67=2015,VLOOKUP($BJ67,'Treasury Yields'!$C$5:$N$34,$E67,FALSE)/100,IF($B67=2016,VLOOKUP($BJ67,'Treasury Yields'!$C$40:$N$69,$E67,FALSE)/100,IF($B67=2017,VLOOKUP($BJ67,'Treasury Yields'!$C$75:$N$104,$E67,FALSE)/100,IF($B67=2018,VLOOKUP($BJ67,'Treasury Yields'!$C$110:$N$139,$E67,FALSE)/100,IF($B67=2019,VLOOKUP($BJ67,'Treasury Yields'!$C$145:$N$174,$E67,FALSE)/100,IF($B67=2020,VLOOKUP($BJ67,'Treasury Yields'!$C$180:$N$209,$E67,FALSE)/100,IF($B67=2021,VLOOKUP($BJ67,'Treasury Yields'!$C$215:$N$244,$E67,FALSE)/100,IF($B67=2022,VLOOKUP($BJ67,'Treasury Yields'!$C$250:$N$279,$E67,FALSE)/100)))))))),0) -> 0.02211 | BL67: =1+BH67*(AL67-BK67)+(AL67-BK67)^2 -> 1.5478728 | BM67: =BL67*R67 -> 49862315 | BN67: =BM67-AB67 -> 28114584 | BP67: =IF($BJ67<=30,IF($B67=2015,VLOOKUP($BJ67,'Treasury Yields'!$C$40:$N$69,$E67,FALSE)/100,IF($B67=2016,VLOOKUP($BJ67,'Treasury Yields'!$C$75:$N$104,$E67,FALSE)/100,IF($B67=2017,VLOOKUP($BJ67,'Treasury Yields'!$C$110:$N$139,$E67,FALSE)/100,IF($B67=2018,VLOOKUP($BJ67,'Treasury Yields'!$C$145:$N$174,$E67,FALSE)/100,IF($B67=2019,VLOOKUP($BJ67,'Treasury Yields'!$C$180:$N$209,$E67,FALSE)/100,IF($B67=2020,VLOOKUP($BJ67,'Treasury Yields'!$C$215:$N$244,$E67,FALSE)/100,IF($B67=2021,VLOOKUP($BJ67,'Treasury Yields'!$C$250:$N$279,$E67,FALSE)/100,IF($B67=2022,VLOOKUP($BJ67,'Treasury Yields'!$C$285:$N$314,$E67,FALSE)/100)))))))),0) -> 0.01773 | BQ67: =1+BH67*(AN67-BP67)+(AN67-BP67)^2 -> 1.6163525 | BR67: =BQ67*S67 -> 54571784 | BS67: =BR67-AC67 -> 31635486 | BU67: =IF(BJ67="","",ROUND(BJ67+$BT$2,0)) -> 13 | BV67: =1+(BH67+BU67)*(AN67-BK67)+(AN67-BK67)^2*BI67 -> 2.5957575 | BW67: =BV67*J67 -> 1629974.8 | BX67: =(BM67+BW67-O67)*BK67 -> 1090702.2 | BY67: =BK67*(BN67+BW67-O67) -> 609859.89 | BZ67: =SUM(J67:K67) -> 3116248 | CA67: =SUM(BW67+BY67) -> 2239834.7 | CC67: =BR67 -> 54571784 | CD67: =F67 -> Alabama | CE67: =BB67 -> 0.67934637 | CF67: =AC67/CC67 -> 0.42029592
A68: 1000000003402 | B68: 2017 | C68: 575 | D68: plan277_y2021 | E68: 9 | F68: Alabama | G68: Teachers' Retirement System of Alabama | H68: TRS | I68: TRUE | J68: 617120 | K68: 2532457 | L68: 0 | M68: -261067 | N68: 0 | O68: 2117351 | P68: 53526 | Q68: 717633 | R68: 33762303 | S68: 34479936 | T68: 782702 | V68: 489638 | W68: 2636098 | Y68: 22402 | Z68: 0 | AA68: 1715159 | AB68: 22936298 | AC68: 24651457 | AD68: 9828479 | AE68: 10826005 | AF68: -997526 | AG68: 6623929 | AH68: 0.1181628 | AI68: TRUE | AK68: 0.0775 | AL68: 0.0775 | AM68: 0.0775 | AN68: 0.08 | AO68: 1 | AP68: 0 | AS68: 13556622 | AT68: 6674759 | AU68: P62 of CAFR | AV68: https://www.rsa-al.gov/uploads/files/RSA_2017_CAFR.pdf | BB68: =AC68/S68 -> 0.71495078 | BD68: =AS68-AD68 -> 3728143 | BE68: =AT68-AD68 -> -3153720 | BF68: =BD68/S68*100 -> 10.8125 | BG68: =BE68/S68*100 -> -9.1465367 | BH68: =(BD68-BE68)/(2*S68)*100 -> 9.9795182 | BI68: =(BD68+BE68)/(2*S68*(0.01^2)) -> 83.298153 | BJ68: =ROUND(BH68,0) -> 10 | BK68: =IF($BJ68<=30,IF($B68=2015,VLOOKUP($BJ68,'Treasury Yields'!$C$5:$N$34,$E68,FALSE)/100,IF($B68=2016,VLOOKUP($BJ68,'Treasury Yields'!$C$40:$N$69,$E68,FALSE)/100,IF($B68=2017,VLOOKUP($BJ68,'Treasury Yields'!$C$75:$N$104,$E68,FALSE)/100,IF($B68=2018,VLOOKUP($BJ68,'Treasury Yields'!$C$110:$N$139,$E68,FALSE)/100,IF($B68=2019,VLOOKUP($BJ68,'Treasury Yields'!$C$145:$N$174,$E68,FALSE)/100,IF($B68=2020,VLOOKUP($BJ68,'Treasury Yields'!$C$180:$N$209,$E68,FALSE)/100,IF($B68=2021,VLOOKUP($BJ68,'Treasury Yields'!$C$215:$N$244,$E68,FALSE)/100,IF($B68=2022,VLOOKUP($BJ68,'Treasury Yields'!$C$250:$N$279,$E68,FALSE)/100)))))))),0) -> 0.01773 | BL68: =1+BH68*(AL68-BK68)+(AL68-BK68)^2 -> 1.6000483 | BM68: =BL68*R68 -> 54021314 | BN68: =BM68-AB68 -> 31085016 | BP68: =IF($BJ68<=30,IF($B68=2015,VLOOKUP($BJ68,'Treasury Yields'!$C$40:$N$69,$E68,FALSE)/100,IF($B68=2016,VLOOKUP($BJ68,'Treasury Yields'!$C$75:$N$104,$E68,FALSE)/100,IF($B68=2017,VLOOKUP($BJ68,'Treasury Yields'!$C$110:$N$139,$E68,FALSE)/100,IF($B68=2018,VLOOKUP($BJ68,'Treasury Yields'!$C$145:$N$174,$E68,FALSE)/100,IF($B68=2019,VLOOKUP($BJ68,'Treasury Yields'!$C$180:$N$209,$E68,FALSE)/100,IF($B68=2020,VLOOKUP($BJ68,'Treasury Yields'!$C$215:$N$244,$E68,FALSE)/100,IF($B68=2021,VLOOKUP($BJ68,'Treasury Yields'!$C$250:$N$279,$E68,FALSE)/100,IF($B68=2022,VLOOKUP($BJ68,'Treasury Yields'!$C$285:$N$314,$E68,FALSE)/100)))))))),0) -> 0.02463 | BQ68: =1+BH68*(AN68-BP68)+(AN68-BP68)^2 -> 1.5556318 | BR68: =BQ68*S68 -> 53638084 | BS68: =BR68-AC68 -> 28986627 | BU68: =IF(BJ68="","",ROUND(BJ68+$BT$2,0)) -> 13 | BV68: =1+(BH68+BU68)*(AN68-BK68)+(AN68-BK68)^2*BI68 -> 2.7539276 | BW68: =BV68*J68 -> 1699503.8 | BX68: =(BM68+BW68-O68)*BK68 -> 950389.47 | BY68: =BK68*(BN68+BW68-O68) -> 543728.9 | BZ68: =SUM(J68:K68) -> 3149577 | CA68: =SUM(BW68+BY68) -> 2243232.7 | CC68: =BR68 -> 53638084 | CD68: =F68 -> Alabama | CE68: =BB68 -> 0.71495078 | CF68: =AC68/CC68 -> 0.4595887
