Workbook

Sheet Summary
A1: LEAID | B1: Year | C1: State | D1: state_abv | E1: plan | F1: district_name | G1: employer_code | H1: district_contributions | I1: LEAID_match
A2: =I2 | B2: 2023 | C2: Wisconsin | D2: WI | E2: Wisconsin Retirement System | F2: EXECUTIVE OFFICE | G2: 1101 | H2: 173623.59 | I2: =IFERROR(VLOOKUP(G2,'LEAID Match'!$B$2:$C$427,2,FALSE),"")
A3: =I3 | B3: 2022 | C3: Wisconsin | D3: WI | E3: Wisconsin Retirement System | F3: EXECUTIVE OFFICE | G3: 1101 | H3: 163770.93 | I3: =IFERROR(VLOOKUP(G3,'LEAID Match'!$B$2:$C$427,2,FALSE),"")
A4: =I4 | B4: 2021 | C4: Wisconsin | D4: WI | E4: Wisconsin Retirement System | F4: EXECUTIVE OFFICE | G4: 1101 | H4: 155415.67 | I4: =IFERROR(VLOOKUP(G4,'LEAID Match'!$B$2:$C$427,2,FALSE),"")
A5: =I5 | B5: 2020 | C5: Wisconsin | D5: WI | E5: Wisconsin Retirement System | F5: EXECUTIVE OFFICE | G5: 1101 | H5: 145910.61 | I5: =IFERROR(VLOOKUP(G5,'LEAID Match'!$B$2:$C$427,2,FALSE),"")
A6: =I6 | B6: 2019 | C6: Wisconsin | D6: WI | E6: Wisconsin Retirement System | F6: EXECUTIVE OFFICE | G6: 1101 | H6: 137693.71 | I6: =IFERROR(VLOOKUP(G6,'LEAID Match'!$B$2:$C$427,2,FALSE),"")
A7: =I7 | B7: 2018 | C7: Wisconsin | D7: WI | E7: Wisconsin Retirement System | F7: EXECUTIVE OFFICE | G7: 1101 | H7: 132872.4 | I7: =IFERROR(VLOOKUP(G7,'LEAID Match'!$B$2:$C$427,2,FALSE),"")
A8: =I8 | B8: 2017 | C8: Wisconsin | D8: WI | E8: Wisconsin Retirement System | F8: EXECUTIVE OFFICE | G8: 1101 | H8: 133593.5 | I8: =IFERROR(VLOOKUP(G8,'LEAID Match'!$B$2:$C$427,2,FALSE),"")
A9: =I9 | B9: 2016 | C9: Wisconsin | D9: WI | E9: Wisconsin Retirement System | F9: EXECUTIVE OFFICE | G9: 1101 | H9: 136827.78 | I9: =IFERROR(VLOOKUP(G9,'LEAID Match'!$B$2:$C$427,2,FALSE),"")
A10: =I10 | B10: 2015 | C10: Wisconsin | D10: WI | E10: Wisconsin Retirement System | F10: EXECUTIVE OFFICE | G10: 1101 | H10: 138434.68 | I10: =IFERROR(VLOOKUP(G10,'LEAID Match'!$B$2:$C$427,2,FALSE),"")
A11: =I11 | B11: 2023 | C11: Wisconsin | D11: WI | E11: Wisconsin Retirement System | F11: LIEUTENANT GOVERNOR'S OFFICE | G11: 1102 | H11: 19784.79 | I11: =IFERROR(VLOOKUP(G11,'LEAID Match'!$B$2:$C$427,2,FALSE),"")
A12: =I12 | B12: 2022 | C12: Wisconsin | D12: WI | E12: Wisconsin Retirement System | F12: LIEUTENANT GOVERNOR'S OFFICE | G12: 1102 | H12: 19395.17 | I12: =IFERROR(VLOOKUP(G12,'LEAID Match'!$B$2:$C$427,2,FALSE),"")
A13: =I13 | B13: 2021 | C13: Wisconsin | D13: WI | E13: Wisconsin Retirement System | F13: LIEUTENANT GOVERNOR'S OFFICE | G13: 1102 | H13: 19154.02 | I13: =IFERROR(VLOOKUP(G13,'LEAID Match'!$B$2:$C$427,2,FALSE),"")
... A13849: =I13849 | B13849: 2023 | C13849: Wisconsin | D13849: WI | E13849: Wisconsin Retirement System | F13849: RIB MOUNTAIN, VILLAGE OF | G13849: 5523000 | H13849: 34852.97 | I13849: =IFERROR(VLOOKUP(G13849,'LEAID Match'!$B$2:$C$427,2,FALSE),"")

Sheet GASB 68 Files -->

Sheet 2023
A1: Year | B1: district_name | C1: employer_code | D1: district_contributions
A2: 2023 | B2: EXECUTIVE OFFICE | C2: 1101 | D2: 173623.59 | E2: =IFERROR(VLOOKUP(B2,'LEAID Match'!$A$2:$B$409,2,FALSE),"")
A3: 2023 | B3: LIEUTENANT GOVERNOR'S OFFICE | C3: 1102 | D3: 19784.79 | E3: =IFERROR(VLOOKUP(B3,'LEAID Match'!$A$2:$B$409,2,FALSE),"")
A4: 2023 | B4: SECRETARY OF STATE'S OFFICE | C4: 1103 | D4: 11203.47 | E4: =IFERROR(VLOOKUP(B4,'LEAID Match'!$A$2:$B$409,2,FALSE),"")
A5: 2023 | B5: TREASURER'S OFFICE - STATE | C5: 1104 | D5: 5161.21 | E5: =IFERROR(VLOOKUP(B5,'LEAID Match'!$A$2:$B$409,2,FALSE),"")
A6: 2023 | B6: JUSTICE, DEPT OF | C6: 1105 | D6: 4386299.4 | E6: =IFERROR(VLOOKUP(B6,'LEAID Match'!$A$2:$B$409,2,FALSE),"")
A7: 2023 | B7: PUBLIC INSTRUCTION, DEPT OF | C7: 1106 | D7: 2730069.2 | E7: =IFERROR(VLOOKUP(B7,'LEAID Match'!$A$2:$B$409,2,FALSE),"")
A8: 2023 | B8: MILITARY AFFAIRS, DEPT OF | C8: 1107 | D8: 2533292.8 | E8: =IFERROR(VLOOKUP(B8,'LEAID Match'!$A$2:$B$409,2,FALSE),"")
A9: 2023 | B9: ADMINISTRATION, DEPT OF | C9: 1108 | D9: 7134295.3 | E9: =IFERROR(VLOOKUP(B9,'LEAID Match'!$A$2:$B$409,2,FALSE),"")
A10: 2023 | B10: AGRIC TRADE CONS PROT, DEPT OF | C10: 1109 | D10: 2702863.8 | E10: =IFERROR(VLOOKUP(B10,'LEAID Match'!$A$2:$B$409,2,FALSE),"")
A11: 2023 | B11: EMPLOYEE TRUST FUNDS, DEPT OF | C11: 1110 | D11: 1406975.4 | E11: =IFERROR(VLOOKUP(B11,'LEAID Match'!$A$2:$B$409,2,FALSE),"")
A12: 2023 | B12: HEALTH SERVICES, DEPT OF | C12: 1111 | D12: 33198155 | E12: =IFERROR(VLOOKUP(B12,'LEAID Match'!$A$2:$B$409,2,FALSE),"")
A13: 2023 | B13: WORKFORCE DEVELOPMENT, DEPT OF | C13: 1112 | D13: 6387100.9 | E13: =IFERROR(VLOOKUP(B13,'LEAID Match'!$A$2:$B$409,2,FALSE),"")
... A1610: 2023 | B1610: RIB MOUNTAIN, VILLAGE OF | C1610: 5523000 | D1610: 34852.97 | E1610: =IFERROR(VLOOKUP(B1610,'LEAID Match'!$A$2:$B$409,2,FALSE),"")
D1612: =SUM(D2:D1610) -> 1.2217084e+09
D1614: 1.2217084e+09
D1616: =D1612-D1614 -> -3.0994415e-06

Sheet 2022
A1: Year | B1: district_name | C1: employer_code | D1: district_contributions
A2: 2022 | B2: EXECUTIVE OFFICE | C2: 1101 | D2: 163770.93
A3: 2022 | B3: LIEUTENANT GOVERNOR'S OFFICE | C3: 1102 | D3: 19395.17
A4: 2022 | B4: SECRETARY OF STATE'S OFFICE | C4: 1103 | D4: 11576.13
A5: 2022 | B5: TREASURER'S OFFICE - STATE | C5: 1104 | D5: 5091.19
A6: 2022 | B6: JUSTICE, DEPT OF | C6: 1105 | D6: 4263875.1
A7: 2022 | B7: PUBLIC INSTRUCTION, DEPT OF | C7: 1106 | D7: 2593429.9
A8: 2022 | B8: MILITARY AFFAIRS, DEPT OF | C8: 1107 | D8: 2320513.5
A9: 2022 | B9: ADMINISTRATION, DEPT OF | C9: 1108 | D9: 6776125.7
A10: 2022 | B10: AGRIC TRADE CONS PROT, DEPT OF | C10: 1109 | D10: 2647667.1
A11: 2022 | B11: EMPLOYEE TRUST FUNDS, DEPT OF | C11: 1110 | D11: 1344915
A12: 2022 | B12: HEALTH SERVICES, DEPT OF | C12: 1111 | D12: 30303875
A13: 2022 | B13: WORKFORCE DEVELOPMENT, DEPT OF | C13: 1112 | D13: 6178041.9
... A1591: 2022 | B1591: BROOKLYN FIRE & EMS DISTRICT | C1591: 5517000 | D1591: 7669.37
D1593: =SUM(D2:D1591) -> 1.1566497e+09
D1595: 1.1566497e+09
D1597: =D1593-D1595 -> 0

Sheet 2021
A1: Year | B1: district_name | C1: employer_code | D1: district_contributions
A2: 2021 | B2: EXECUTIVE OFFICE | C2: 1101 | D2: 155415.67
A3: 2021 | B3: LIEUTENANT GOVERNOR'S OFFICE | C3: 1102 | D3: 19154.02
A4: 2021 | B4: SECRETARY OF STATE'S OFFICE | C4: 1103 | D4: 11748.75
A5: 2021 | B5: TREASURER'S OFFICE - STATE | C5: 1104 | D5: 5126.64
A6: 2021 | B6: JUSTICE, DEPT OF | C6: 1105 | D6: 4134213.3
A7: 2021 | B7: PUBLIC INSTRUCTION, DEPT OF | C7: 1106 | D7: 2555010.8
A8: 2021 | B8: MILITARY AFFAIRS, DEPT OF | C8: 1107 | D8: 2169836.7
A9: 2021 | B9: ADMINISTRATION, DEPT OF | C9: 1108 | D9: 6479919.8
A10: 2021 | B10: AGRIC TRADE CONS PROT, DEPT OF | C10: 1109 | D10: 2588642
A11: 2021 | B11: EMPLOYEE TRUST FUNDS, DEPT OF | C11: 1110 | D11: 1282257.8
A12: 2021 | B12: HEALTH SERVICES, DEPT OF | C12: 1111 | D12: 27970407
A13: 2021 | B13: WORKFORCE DEVELOPMENT, DEPT OF | C13: 1112 | D13: 5878634
... A1561: 2021 | B1561: GREENVILLE, VILLAGE OF | C1561: 5511000 | D1561: 158995.7
D1563: =SUM(D2:D1561) -> 1.1134615e+09
D1565: 1.1134615e+09
D1567: =D1563-D1565 -> 0

Sheet 2020
A1: Year | B1: district_name | C1: employer_code | D1: district_contributions
A2: 2020 | B2: EXECUTIVE OFFICE | C2: 1101 | D2: 145910.61
A3: 2020 | B3: LIEUTENANT GOVERNOR'S OFFICE | C3: 1102 | D3: 16817.14
A4: 2020 | B4: SECRETARY OF STATE'S OFFICE | C4: 1103 | D4: 11330.89
A5: 2020 | B5: TREASURER'S OFFICE - STATE | C5: 1104 | D5: 5000.12
A6: 2020 | B6: JUSTICE, DEPT OF | C6: 1105 | D6: 3972490.1
A7: 2020 | B7: PUBLIC INSTRUCTION, DEPT OF | C7: 1106 | D7: 2530413.9
A8: 2020 | B8: MILITARY AFFAIRS, DEPT OF | C8: 1107 | D8: 2007454.4
A9: 2020 | B9: ADMINISTRATION, DEPT OF | C9: 1108 | D9: 5951403.1
A10: 2020 | B10: AGRIC TRADE CONS PROT, DEPT OF | C10: 1109 | D10: 2490553.6
A11: 2020 | B11: EMPLOYEE TRUST FUNDS, DEPT OF | C11: 1110 | D11: 1216270
A12: 2020 | B12: HEALTH SERVICES, DEPT OF | C12: 1111 | D12: 25942259
A13: 2020 | B13: WORKFORCE DEVELOPMENT, DEPT OF | C13: 1112 | D13: 5435058.2
... A1544: 2020 | B1544: BALSAM LK-CENTURA JT POICE DEP | C1544: 5506000 | D1544: 16982.34
D1546: =SUM(D2:D1544) -> 1.0685841e+09
D1548: 1.0685841e+09
D1550: =D1546-D1548 -> 1.0728836e-06

Sheet 2019
A1: Year | B1: district_name | C1: employer_code | D1: district_contributions
A2: 2019 | B2: EXECUTIVE OFFICE | C2: 1101 | D2: 137693.71
A3: 2019 | B3: LIEUTENANT GOVERNOR'S OFFICE | C3: 1102 | D3: 14273.87
A4: 2019 | B4: SECRETARY OF STATE'S OFFICE | C4: 1103 | D4: 10905.43
A5: 2019 | B5: TREASURER'S OFFICE - STATE | C5: 1104 | D5: 4852.7
A6: 2019 | B6: JUSTICE, DEPT OF | C6: 1105 | D6: 3724234.2
A7: 2019 | B7: PUBLIC INSTRUCTION, DEPT OF | C7: 1106 | D7: 2471836.5
A8: 2019 | B8: MILITARY AFFAIRS, DEPT OF | C8: 1107 | D8: 1833133.7
A9: 2019 | B9: ADMINISTRATION, DEPT OF | C9: 1108 | D9: 5200736.9
A10: 2019 | B10: AGRIC TRADE CONS PROT, DEPT OF | C10: 1109 | D10: 2371619.3
A11: 2019 | B11: EMPLOYEE TRUST FUNDS, DEPT OF | C11: 1110 | D11: 1158633.5
A12: 2019 | B12: HEALTH SERVICES, DEPT OF | C12: 1111 | D12: 23918729
A13: 2019 | B13: WORKFORCE DEVELOPMENT, DEPT OF | C13: 1112 | D13: 5176550.6
... A1524: 2019 | B1524: CAMBRIDGE FIRE & EMS COMM | C1524: 5500000 | D1524: 32532.33
D1526: =SUM(D2:D1524) -> 1.029519e+09
D1528: 1.029519e+09
D1530: =D1526-D1528 -> 0

Sheet 2018
A1: Year | B1: district_name | C1: employer_code | D1: district_contributions
A2: 2018 | B2: EXECUTIVE OFFICE | C2: 1101 | D2: 132872.4
A3: 2018 | B3: LIEUTENANT GOVERNOR'S OFFICE | C3: 1102 | D3: 12593.67
A4: 2018 | B4: SECRETARY OF STATE'S OFFICE | C4: 1103 | D4: 10502.89
A5: 2018 | B5: TREASURER'S OFFICE - STATE | C5: 1104 | D5: 4682.4
A6: 2018 | B6: JUSTICE, DEPT OF | C6: 1105 | D6: 3500074.3
A7: 2018 | B7: PUBLIC INSTRUCTION, DEPT OF | C7: 1106 | D7: 2463378.7
A8: 2018 | B8: MILITARY AFFAIRS, DEPT OF | C8: 1107 | D8: 1731244.2
A9: 2018 | B9: ADMINISTRATION, DEPT OF | C9: 1108 | D9: 4656008.2
A10: 2018 | B10: AGRIC TRADE CONS PROT, DEPT OF | C10: 1109 | D10: 2281461.9
A11: 2018 | B11: EMPLOYEE TRUST FUNDS, DEPT OF | C11: 1110 | D11: 1125786.5
A12: 2018 | B12: HEALTH SERVICES, DEPT OF | C12: 1111 | D12: 22947876
A13: 2018 | B13: WORKFORCE DEVELOPMENT, DEPT OF | C13: 1112 | D13: 5127154.7
... A1514: 2018 | B1514: HOLY HILL AREA SCHOOL DIST | C1514: 5494000 | D1514: 168264.85
D1516: =SUM(D2:D1514) -> 9.9798608e+08
D1518: 9.9798608e+08
D1520: =D1516-D1518 -> 1.6689301e-06

Sheet 2017
A1: Year | B1: district_name | C1: employer_code | D1: district_contributions
A2: 2017 | B2: EXECUTIVE OFFICE | C2: 1101 | D2: 133593.5
A3: 2017 | B3: LIEUTENANT GOVERNOR'S OFFICE | C3: 1102 | D3: 14164.93
A4: 2017 | B4: SECRETARY OF STATE'S OFFICE | C4: 1103 | D4: 11386.84
A5: 2017 | B5: TREASURER'S OFFICE - STATE | C5: 1104 | D5: 5260.82
A6: 2017 | B6: JUSTICE, DEPT OF | C6: 1105 | D6: 3261648.9
A7: 2017 | B7: PUBLIC INSTRUCTION, DEPT OF | C7: 1106 | D7: 2468868.3
A8: 2017 | B8: MILITARY AFFAIRS, DEPT OF | C8: 1107 | D8: 1647015.6
A9: 2017 | B9: ADMINISTRATION, DEPT OF | C9: 1108 | D9: 4339814.8
A10: 2017 | B10: AGRIC TRADE CONS PROT, DEPT OF | C10: 1109 | D10: 2204884.5
A11: 2017 | B11: EMPLOYEE TRUST FUNDS, DEPT OF | C11: 1110 | D11: 1096586.8
A12: 2017 | B12: HEALTH SERVICES, DEPT OF | C12: 1111 | D12: 22355724
A13: 2017 | B13: WORKFORCE DEVELOPMENT, DEPT OF | C13: 1112 | D13: 5286928.5
... A1509: 2017 | B1509: SALEM LAKES, VILLAGE OF | C1509: 5491000 | D1509: 118197.89
D1511: =SUM(D2:D1509) -> 9.7666349e+08
D1513: 9.7666349e+08
D1515: =D1511-D1513 -> 0

Sheet 2016
A1: Year | B1: district_name | C1: employer_code | D1: district_contributions
A2: 2016 | B2: EXECUTIVE OFFICE | C2: 1101 | D2: 136827.78
A3: 2016 | B3: LIEUTENANT GOVERNOR'S OFFICE | C3: 1102 | D3: 14577.46
A4: 2016 | B4: SECRETARY OF STATE'S OFFICE | C4: 1103 | D4: 12598.78
A5: 2016 | B5: TREASURER'S OFFICE ‐ STATE | C5: 1104 | D5: 9593.68
A6: 2016 | B6: JUSTICE, DEPT OF | C6: 1105 | D6: 3035398.4
A7: 2016 | B7: PUBLIC INSTRUCTION, DEPT OF | C7: 1106 | D7: 2461531.4
A8: 2016 | B8: MILITARY AFFAIRS, DEPT OF | C8: 1107 | D8: 1595835.5
A9: 2016 | B9: ADMINISTRATION, DEPT OF | C9: 1108 | D9: 4233944.2
A10: 2016 | B10: AGRIC TRADE CONS PROT, DEPT OF | C10: 1109 | D10: 2141890.7
A11: 2016 | B11: EMPLOYEE TRUST FUNDS, DEPT OF | C11: 1110 | D11: 1063409.8
A12: 2016 | B12: HEALTH SERVICES, DEPT OF | C12: 1111 | D12: 22024185
A13: 2016 | B13: WORKFORCE DEVELOPMENT, DEPT OF | C13: 1112 | D13: 5495331.8
... A1507: 2016 | B1507: HERMAN‐NEOSHO‐RUBICAN SD | C1507: 5484000 | D1507: 59183.08
D1509: =SUM(D2:D1507) -> 9.6663388e+08
D1511: 9.6663388e+08
D1513: =D1509-D1511 -> 0.059999108

Sheet 2015
A1: Year | B1: district_name | C1: employer_code | D1: district_contributions
A2: 2015 | B2: EXECUTIVE OFFICE | C2: 1101 | D2: 138434.68
A3: 2015 | B3: LIEUTENANT GOVERNOR'S OFFICE | C3: 1102 | D3: 14461.16
A4: 2015 | B4: SECRETARY OF STATE'S OFFICE | C4: 1103 | D4: 14011.85
A5: 2015 | B5: TREASURER'S OFFICE - STATE | C5: 1104 | D5: 16894.99
A6: 2015 | B6: JUSTICE, DEPT OF | C6: 1105 | D6: 2869497.1
A7: 2015 | B7: PUBLIC INSTRUCTION, DEPT OF | C7: 1106 | D7: 2415257.3
A8: 2015 | B8: MILITARY AFFAIRS, DEPT OF | C8: 1107 | D8: 1556279.7
A9: 2015 | B9: ADMINISTRATION, DEPT OF | C9: 1108 | D9: 4071484.4
A10: 2015 | B10: AGRIC TRADE CONS PROT, DEPT OF | C10: 1109 | D10: 2049034.4
A11: 2015 | B11: EMPLOYEE TRUST FUNDS, DEPT OF | C11: 1110 | D11: 1018122.8
A12: 2015 | B12: HEALTH SERVICES, DEPT OF | C12: 1111 | D12: 21413032
A13: 2015 | B13: WORKFORCE DEVELOPMENT, DEPT OF | C13: 1112 | D13: 5599333.3
... A1497: 2015 | B1497: SULLIVAN SANITARY DISTRICT #1 | C1497: 5470000 | D1497: 2978.91
D1499: =SUM(D2:D1497) -> 9.500632e+08
D1501: 9.500632e+08
D1503: =D1499-D1501 -> -0.11999869

Sheet NCES Data ->

Sheet LEAID Match
A1: district_name | B1: employer_code | C1: LEAID
A2: ABBOTSFORD SCHOOL DISTRICT | B2: 4375000 | C2: 5500030
A3: ADAMS-FRIENDSHIP AREA SCH DIST | B3: 3986000 | C3: 5500060
A4: ALBANY SCHOOL DISTRICT | B4: 1113000 | C4: 5500120
A5: ALGOMA SCHOOL DISTRICT | B5: 4596000 | C5: 5500150
A6: ALMA CENTER-HUMBRD-MERIL SCH D | B6: 717000 | C6: 5500210
A7: ALMA SCHOOL DISTRICT | B7: 186000 | C7: 5500180
A8: ALMOND-BANCROFT SCHOOL DIST | B8: 779000 | C8: 5500240
A9: ALTOONA SCHOOL DISTRICT | B9: 344000 | C9: 5500270
A10: AMERY SCHOOL DISTRICT | B10: 407000 | C10: 5500300
A11: ANTIGO UNIFIED SCHOOL DISTRICT | B11: 4376000 | C11: 5500360
A12: APPLETON AREA SCHOOL DISTRICT | B12: 5063000 | C12: 5500390
A13: ARBOR VITAE-WOODRUFF JSD #1 | B13: 445000 | C13: 5500084
... A427: YORKVILLE JT SCH DIST #2 ETAL | B427: 4599000 | C427: 5517220
