Workbook

Sheet Summary
A1: LEAID | B1: Year | C1: State | D1: state_abv | E1: plan | F1: district_name | G1: district_contributions | H1: LEAID_match
A2: =H2 | B2: 2015 | C2: Mississippi | D2: MS | E2: Public Employees' Retirement System of Mississippi | F2: Aberdeen City Of | G2: 404810 | H2: =IFERROR(VLOOKUP(F2,'LEAID Match'!$A$2:$B$142,2,FALSE),"")
A3: =H3 | B3: 2016 | C3: Mississippi | D3: MS | E3: Public Employees' Retirement System of Mississippi | F3: Aberdeen City Of | G3: 435766 | H3: =IFERROR(VLOOKUP(F3,'LEAID Match'!$A$2:$B$142,2,FALSE),"")
A4: =H4 | B4: 2017 | C4: Mississippi | D4: MS | E4: Public Employees' Retirement System of Mississippi | F4: Aberdeen City Of | G4: 469758 | H4: =IFERROR(VLOOKUP(F4,'LEAID Match'!$A$2:$B$142,2,FALSE),"")
A5: =H5 | B5: 2018 | C5: Mississippi | D5: MS | E5: Public Employees' Retirement System of Mississippi | F5: Aberdeen City Of | G5: 482544 | H5: =IFERROR(VLOOKUP(F5,'LEAID Match'!$A$2:$B$142,2,FALSE),"")
A6: =H6 | B6: 2019 | C6: Mississippi | D6: MS | E6: Public Employees' Retirement System of Mississippi | F6: Aberdeen City Of | G6: 492583 | H6: =IFERROR(VLOOKUP(F6,'LEAID Match'!$A$2:$B$142,2,FALSE),"")
A7: =H7 | B7: 2020 | C7: Mississippi | D7: MS | E7: Public Employees' Retirement System of Mississippi | F7: Aberdeen City Of | G7: 561880 | H7: =IFERROR(VLOOKUP(F7,'LEAID Match'!$A$2:$B$142,2,FALSE),"")
A8: =H8 | B8: 2021 | C8: Mississippi | D8: MS | E8: Public Employees' Retirement System of Mississippi | F8: Aberdeen City Of | G8: 597612 | H8: =IFERROR(VLOOKUP(F8,'LEAID Match'!$A$2:$B$142,2,FALSE),"")
A9: =H9 | B9: 2022 | C9: Mississippi | D9: MS | E9: Public Employees' Retirement System of Mississippi | F9: Aberdeen City Of | G9: 625086 | H9: =IFERROR(VLOOKUP(F9,'LEAID Match'!$A$2:$B$142,2,FALSE),"")
A10: =H10 | B10: 2023 | C10: Mississippi | D10: MS | E10: Public Employees' Retirement System of Mississippi | F10: Aberdeen City Of | G10: 684599 | H10: =IFERROR(VLOOKUP(F10,'LEAID Match'!$A$2:$B$142,2,FALSE),"")
A11: =H11 | B11: 2024 | C11: Mississippi | D11: MS | E11: Public Employees' Retirement System of Mississippi | F11: Aberdeen City Of | G11: 660418 | H11: =IFERROR(VLOOKUP(F11,'LEAID Match'!$A$2:$B$142,2,FALSE),"")
A12: =H12 -> 2800360 | B12: 2015 | C12: Mississippi | D12: MS | E12: Public Employees' Retirement System of Mississippi | F12: Aberdeen Mun Sep Schools | G12: 1050045 | H12: =IFERROR(VLOOKUP(F12,'LEAID Match'!$A$2:$B$142,2,FALSE),"") -> 2800360
A13: =H13 -> 2800360 | B13: 2016 | C13: Mississippi | D13: MS | E13: Public Employees' Retirement System of Mississippi | F13: Aberdeen Mun Sep Schools | G13: 1143889 | H13: =IFERROR(VLOOKUP(F13,'LEAID Match'!$A$2:$B$142,2,FALSE),"") -> 2800360
... A8627: =H8627 | B8627: 2024 | C8627: Mississippi | D8627: MS | E8627: Public Employees' Retirement System of Mississippi | F8627: Yellow Creek Port Authority | G8627: 145091 | H8627: =IFERROR(VLOOKUP(F8627,'LEAID Match'!$A$2:$B$142,2,FALSE),"")

Sheet GASB Data -->

Sheet 2024
A1: Year | B1: Employer | C1: employer_contributions | D1: employer_allocation
A2: 2024 | B2: Aberdeen City Of | C2: 660418 | D2: 0.00049529
A3: 2024 | B3: Aberdeen Mun Sep Schools | C3: 1490844 | D3: 0.00111808
A4: 2024 | B4: Ackerman City Of | C4: 112983 | D4: 8.473e-05
A5: 2024 | B5: Adams Co Airport Commission | C5: 49052 | D5: 3.679e-05
A6: 2024 | B6: Adams Co Bd Of Supr Chancery | C6: 1505070 | D6: 0.00112875
A7: 2024 | B7: Adams Co Soil & Water Consv District | C7: 15377 | D7: 1.153e-05
A8: 2024 | B8: Administrative Office Of Court | C8: 3315652 | D8: 0.00248661
A9: 2024 | B9: Agric And Commerce Dept | C9: 1831440 | D9: 0.00137351
A10: 2024 | B10: Alcorn Co Bd Of Ed | C10: 3974339 | D10: 0.0029806
A11: 2024 | B11: Alcorn Co Bd Of Supr | C11: 1389690 | D11: 0.00104221
A12: 2024 | B12: Alcorn State Univ | C12: 4713818 | D12: 0.00353518
A13: 2024 | B13: Amite Co Bd Of Ed | C13: 1415599 | D13: 0.00106165
... A861: 2024 | B861: Yellow Creek Port Authority | C861: 145091 | D861: 0.00010881
B863: Summed Amount | C863: =SUM(C2:C861) -> 1333400773
B865: GASB 68 Figure | C865: 1333400791
B867: Check | C867: =C863-C865 -> -18

Sheet 2023
A1: Year | B1: Employer | C1: employer_contributions | D1: employer_allocation
A2: 2023 | B2: Aberdeen City Of | C2: 684599 | D2: 0.00053077
A3: 2023 | B3: Aberdeen Mun Sep Schools | C3: 1428807 | D3: 0.00110776
A4: 2023 | B4: Ackerman City Of | C4: 113564 | D4: 8.805e-05
A5: 2023 | B5: Adams Co Airport Commission | C5: 44180 | D5: 3.425e-05
A6: 2023 | B6: Adams Co Bd Of Supr Chancery | C6: 1569793 | D6: 0.00121706
A7: 2023 | B7: Adams Co Soil & Water Consv District | C7: 15817 | D7: 1.226e-05
A8: 2023 | B8: Administrative Office Of Court | C8: 3070271 | D8: 0.00238039
A9: 2023 | B9: Agric And Commerce Dept | C9: 1754905 | D9: 0.00136058
A10: 2023 | B10: Alcorn Co Bd Of Ed | C10: 3635718 | D10: 0.00281878
A11: 2023 | B11: Alcorn Co Bd Of Supr | C11: 1342888 | D11: 0.00104114
A12: 2023 | B12: Alcorn State Univ | C12: 4269771 | D12: 0.00331036
A13: 2023 | B13: Amite Co Bd Of Ed | C13: 1330125 | D13: 0.00103125
... A863: 2023 | B863: Yellow Creek Port Authority | C863: 113585 | D863: 8.806e-05
B865: Summed Amount | C865: =SUM(C2:C863) -> 1289820046
B867: GASB 68 Figure | C867: 1289820038
B869: Check | C869: =C865-C867 -> 8

Sheet 2022
A1: Year | B1: Employer | C1: employer_contributions | D1: employer_allocation
A2: 2022 | B2: Aberdeen City Of | C2: 625086 | D2: 0.00052183
A3: 2022 | B3: Aberdeen Mun Sep Schools | C3: 1335037 | D3: 0.00111451
A4: 2022 | B4: Ackerman City Of | C4: 116120 | D4: 9.694e-05
A5: 2022 | B5: Adams Co Airport Commission | C5: 35157 | D5: 2.935e-05
A6: 2022 | B6: Adams Co Bd Of Supr Chancery | C6: 1531599 | D6: 0.0012786
A7: 2022 | B7: Adams Co Soil & Water Consv District | C7: 14764 | D7: 1.233e-05
A8: 2022 | B8: Administrative Office Of Court | C8: 3023001 | D8: 0.00252365
A9: 2022 | B9: Agric And Commerce Dept | C9: 1548280 | D9: 0.00129253
A10: 2022 | B10: Alcorn Co Bd Of Ed | C10: 3190701 | D10: 0.00266364
A11: 2022 | B11: Alcorn Co Bd Of Supr | C11: 1256825 | D11: 0.00104922
A12: 2022 | B12: Alcorn State Univ | C12: 4172359 | D12: 0.00348315
A13: 2022 | B13: Amite Co Bd Of Ed | C13: 1231860 | D13: 0.00102837
... A863: 2022 | B863: Yellow Creek Port Authority | C863: 103072 | D863: 8.605e-05
B865: Summed Amount | C865: =SUM(C2:C863) -> 1197870890
B867: GASB 68 Figure | C867: 1197870900
B869: Check | C869: =C865-C867 -> -10

Sheet 2021
A1: Year | B1: Employer | C1: employer_contributions | D1: employer_allocation
A2: 2021 | B2: Aberdeen City Of | C2: 597612 | D2: 0.00051655
A3: 2021 | B3: Aberdeen Mun Sep Schools | C3: 1223385 | D3: 0.00105745
A4: 2021 | B4: Ackerman City Of | C4: 110759 | D4: 9.574e-05
A5: 2021 | B5: Adams Co Airport Commission | C5: 30908 | D5: 2.672e-05
A6: 2021 | B6: Adams Co Bd Of Supr Chancery | C6: 1416239 | D6: 0.00122414
A7: 2021 | B7: Adams Co Soil & Water Consv District | C7: 13616 | D7: 1.177e-05
A8: 2021 | B8: Administrative Office Of Court | C8: 3076796 | D8: 0.00265946
A9: 2021 | B9: Agric And Commerce Dept | C9: 1505318 | D9: 0.00130114
A10: 2021 | B10: Alcorn Co Bd Of Ed | C10: 3082201 | D10: 0.00266414
A11: 2021 | B11: Alcorn Co Bd Of Supr | C11: 1099253 | D11: 0.00095015
A12: 2021 | B12: Alcorn State Univ | C12: 4341099 | D12: 0.00375228
A13: 2021 | B13: Amite Co Bd Of Ed | C13: 1133842 | D13: 0.00098005
... A861: 2021 | B861: Yellow Creek Port Authority | C861: 106820 | D861: 9.233e-05
B863: Summed Amount | C863: =SUM(C2:C861) -> 1156923367
B865: GASB 68 Figure | C865: 1156923368
B867: Check | C867: =C863-C865 -> -1

Sheet 2020
A1: Year | B1: Employer | C1: employer_contributions | D1: employer_allocation
A2: 2020 | B2: Aberdeen City Of | C2: 561880 | D2: 0.00048495
A3: 2020 | B3: Aberdeen Mun Sep Schools | C3: 1243082 | D3: 0.00107289
A4: 2020 | B4: Ackerman City Of | C4: 105061 | D4: 9.068e-05
A5: 2020 | B5: Adams Co Airport Commission | C5: 30833 | D5: 2.661e-05
A6: 2020 | B6: Adams Co Bd Of Supr Chancery | C6: 1411904 | D6: 0.0012186
A7: 2020 | B7: Adams Co Soil & Water Consv District | C7: 13616 | D7: 1.175e-05
A8: 2020 | B8: Administrative Office Of Court | C8: 2996676 | D8: 0.00258641
A9: 2020 | B9: Agric And Commerce Dept | C9: 1377564 | D9: 0.00118897
A10: 2020 | B10: Alcorn Co Bd Of Ed | C10: 3078090 | D10: 0.00265668
A11: 2020 | B11: Alcorn Co Bd Of Supr | C11: 1063282 | D11: 0.00091771
A12: 2020 | B12: Alcorn State Univ | C12: 4842398 | D12: 0.00417944
A13: 2020 | B13: Amite Co Bd Of Ed | C13: 1209007 | D13: 0.00104349
... A857: 2020 | B857: Yellow Creek Port Authority | C857: 103232 | D857: 8.91e-05
B859: Summed Amount | C859: =SUM(C2:C857) -> 1158624121
B861: GASB 68 Figure | C861: 1158624120
B863: Check | C863: =C859-C861 -> 1

Sheet 2019
A1: Year | B1: Employer | C1: employer_contributions | D1: employer_allocation
A2: 2019 | B2: Aberdeen City Of | C2: 492583 | D2: 0.00048021
A3: 2019 | B3: Aberdeen Mun Sep Schools | C3: 1061590 | D3: 0.00103493
A4: 2019 | B4: Ackerman City Of | C4: 92219 | D4: 8.99e-05
A5: 2019 | B5: Adams Co Airport Commission | C5: 28154 | D5: 2.745e-05
A6: 2019 | B6: Adams Co Board Of Supervisors Chancery | C6: 1296181 | D6: 0.00126363
A7: 2019 | B7: Adams Co Soil & Water Consv District | C7: 12275 | D7: 1.197e-05
A8: 2019 | B8: Administrative Office Of Court | C8: 2673191 | D8: 0.00260607
A9: 2019 | B9: Agric And Commerce Dept | C9: 1066422 | D9: 0.00103964
A10: 2019 | B10: Alcorn Co Bd Of Education | C10: 2770724 | D10: 0.00270115
A11: 2019 | B11: Alcorn Co Bd Of Supervisors | C11: 915263 | D11: 0.00089228
A12: 2019 | B12: Alcorn State University | C12: 4419020 | D12: 0.00430806
A13: 2019 | B13: Amite Co Bd Of Education | C13: 1073280 | D13: 0.00104633
... A860: 2019 | B860: Yellow Creek Port Authority | C860: 85580 | D860: 8.343e-05
B862: Summed Amount | C862: =SUM(C2:C860) -> 1025757103
B864: GASB 68 Figure | C864: 1025757093
B866: Check | C866: =C862-C864 -> 10

Sheet 2018
A1: Year | B1: Employer | C1: employer_contributions | D1: employer_allocation
A2: 2018 | B2: ABERDEEN CITY OF | C2: 482544 | D2: 0.00047977
A3: 2018 | B3: ABERDEEN MUN SEP SCHOOLS | C3: 1045955 | D3: 0.00103994
A4: 2018 | B4: ACKERMAN CITY OF | C4: 89941 | D4: 8.942e-05
A5: 2018 | B5: ADAMS CO AIRPORT COMMISSION | C5: 26640 | D5: 2.649e-05
A6: 2018 | B6: ADAMS CO BD OF SUPR CHANCERY CLK | C6: 1301215 | D6: 0.00129373
A7: 2018 | B7: ADAMS CO SOIL & WATER CONSV DIST | C7: 11632 | D7: 1.157e-05
A8: 2018 | B8: ADMINISTRATIVE OFFICE OF COURTS | C8: 2679148 | D8: 0.00266373
A9: 2018 | B9: AGRIC AND COMMERCE DEPT | C9: 1033708 | D9: 0.00102776
A10: 2018 | B10: ALCORN CO BD OF ED | C10: 2661788 | D10: 0.00264647
A11: 2018 | B11: ALCORN CO BD OF SUPR | C11: 839012 | D11: 0.00083418
A12: 2018 | B12: ALCORN STATE UNIV | C12: 4544686 | D12: 0.00451853
A13: 2018 | B13: AMITE CO BD OF ED | C13: 1055164 | D13: 0.00104909
... A866: 2018 | B866: YELLOW CREEK PORT AUTHORITY | C866: 81943 | D866: 8.147e-05
B868: Summed Amount | C868: =SUM(C2:C866) -> 1005788104
B870: GASB 68 Figure | C870: 1005788098
B872: Check | C872: =C868-C870 -> 6

Sheet 2017
A1: Year | B1: Employer | C1: employer_contributions | D1: employer_allocation
A2: 2017 | B2: ABERDEEN CITY OF | C2: 469758 | D2: 0.00046494
A3: 2017 | B3: ABERDEEN MUN SEP SCHOOLS | C3: 1085421 | D3: 0.00107428
A4: 2017 | B4: ACKERMAN CITY OF | C4: 89391 | D4: 8.847e-05
A5: 2017 | B5: ADAMS CO AIRPORT COMMISSION | C5: 26329 | D5: 2.606e-05
A6: 2017 | B6: ADAMS CO BD OF SUPR CHANCERY CLK | C6: 1199053 | D6: 0.00118675
A7: 2017 | B7: ADAMS CO SOIL & WATER CONSV DIST | C7: 10883 | D7: 1.077e-05
A8: 2017 | B8: ADMINISTRATIVE OFFICE OF COURTS | C8: 2588779 | D8: 0.00256221
A9: 2017 | B9: AGRIC AND COMMERCE DEPT | C9: 1069438 | D9: 0.00105846
A10: 2017 | B10: ALCORN CO BD OF ED | C10: 2483551 | D10: 0.00245806
A11: 2017 | B11: ALCORN CO BD OF SUPR | C11: 820649 | D11: 0.00081223
A12: 2017 | B12: ALCORN STATE UNIV | C12: 4615287 | D12: 0.00456791
A13: 2017 | B13: AMITE CO BD OF ED | C13: 1010235 | D13: 0.00099986
... A864: 2017 | B864: YELLOW CREEK PORT AUTHORITY | C864: 77357 | D864: 7.656e-05
B866: Summed Amount | C866: =SUM(C2:C864) -> 1010371362
B868: GASB 68 Figure | C868: 1010371350
B870: Check | C870: =C866-C868 -> 12

Sheet 2016
A1: Year | B1: Employer | C1: employer_contributions | D1: employer_allocation
A2: 2016 | B2: ABERDEEN CITY OF | C2: 435766 | D2: 0.00043249
A3: 2016 | B3: ABERDEEN MUN SEP SCHOOLS | C3: 1143889 | D3: 0.0011353
A4: 2016 | B4: ACKERMAN CITY OF | C4: 89945 | D4: 8.927e-05
A5: 2016 | B5: ADAMS CO AIRPORT COMMISSION | C5: 25765 | D5: 2.557e-05
A6: 2016 | B6: ADAMS CO BD OF SUPR CHANCERY CLK | C6: 1145625 | D6: 0.00113702
A7: 2016 | B7: ADAMS CO SOIL & WATER CONSV DIST | C7: 10785 | D7: 1.07e-05
A8: 2016 | B8: ADMINISTRATIVE OFFICE OF COURTS | C8: 2372527 | D8: 0.00235471
A9: 2016 | B9: AGRIC AND COMMERCE DEPT | C9: 1092803 | D9: 0.0010846
A10: 2016 | B10: ALCORN CO BD OF ED | C10: 2708379 | D10: 0.00268804
A11: 2016 | B11: ALCORN CO BD OF SUPR | C11: 770723 | D11: 0.00076494
A12: 2016 | B12: ALCORN STATE UNIV | C12: 4636447 | D12: 0.00460163
A13: 2016 | B13: AMITE CO BD OF ED | C13: 1069753 | D13: 0.00106172
... A866: 2016 | B866: YELLOW CREEK PORT AUTHORITY | C866: 73945 | D866: 7.339e-05
B868: Summed Amount | C868: =SUM(C2:C866) -> 1007565534
B870: GASB 68 Figure | C870: 1007565534
B872: Check | C872: =C868-C870 -> 0

Sheet 2015
A1: Year | B1: Employer | C1: employer_contributions | D1: employer_allocation
A2: 2015 | B2: ABERDEEN CITY OF | C2: 404810 | D2: 0.0004114
A3: 2015 | B3: ABERDEEN MUNICIPAL SEPARATE SCHOOLS | C3: 1050045 | D3: 0.106715
A4: 2015 | B4: ACKERMAN CITY OF | C4: 87227 | D4: 0.008865
A5: 2015 | B5: ADAMS COUNTY AIRPORT COMMISSION | C5: 30396 | D5: 0.003089
A6: 2015 | B6: ADAMS COUNTY BOARD OF SUPERVISORS CHANCERY CLERK | C6: 1158635 | D6: 0.117751
A7: 2015 | B7: ADAMS COUNTY SOIL & WATER CONSERVATION DISTRICT | C7: 11977 | D7: 0.001217
A8: 2015 | B8: ADMINISTRATIVE OFFICE OF COURTS | C8: 2209129 | D8: 0.224512
A9: 2015 | B9: AGRICULTURE AND COMMERCE DEPARTMENT | C9: 1108197 | D9: 0.112625
A10: 2015 | B10: ALCORN COUNTY BOARD OF EDUCATION | C10: 2599751 | D10: 0.26421
A11: 2015 | B11: ALCORN COUNTY BOARD OF SUPERVISORS | C11: 754153 | D11: 0.076644
A12: 2015 | B12: ALCORN STATE UNIVERSITY | C12: 4521679 | D12: 0.459534
A13: 2015 | B13: AMITE COUNTY BOARD OF EDUCATION | C13: 1031190 | D13: 0.104799
... A878: 2015 | B878: YELLOW CREEK PORT AUTHORITY | C878: 59948 | D878: 0.006092
B880: Summed Amount | C880: =SUM(C2:C878) -> 983969966
B882: GASB 68 Figure | C882: 983969966
B884: Check | C884: =C880-C882 -> 0

Sheet NCES Data -->

Sheet LEAID Match
A1: district_name | B1: LEAID | D1: count
A2: Aberdeen Mun Sep Schools | B2: 2800360 | D2: =COUNTIF(Summary!$H$2:$H$8627,'LEAID Match'!B2) -> 10
A3: Alcorn Co Bd Of Ed | B3: 2800390 | D3: =COUNTIF(Summary!$H$2:$H$8627,'LEAID Match'!B3) -> 10
A4: Amite Co Bd Of Ed | B4: 2800420 | D4: =COUNTIF(Summary!$H$2:$H$8627,'LEAID Match'!B4) -> 10
A5: Amory Mun Sep Schools | B5: 2800450 | D5: =COUNTIF(Summary!$H$2:$H$8627,'LEAID Match'!B5) -> 10
A6: Attala Co Bd Of Ed | B6: 2800510 | D6: =COUNTIF(Summary!$H$2:$H$8627,'LEAID Match'!B6) -> 10
A7: Baldwyn Mun Sep Schools | B7: 2800540 | D7: =COUNTIF(Summary!$H$2:$H$8627,'LEAID Match'!B7) -> 10
A8: Bay St Louis‐Waveland Schl Dis | B8: 2800570 | D8: =COUNTIF(Summary!$H$2:$H$8627,'LEAID Match'!B8) -> 10
A9: Benton Co Bd Of Ed | B9: 2800600 | D9: =COUNTIF(Summary!$H$2:$H$8627,'LEAID Match'!B9) -> 10
A10: Biloxi Mun Sep Schools | B10: 2800630 | D10: =COUNTIF(Summary!$H$2:$H$8627,'LEAID Match'!B10) -> 10
A11: Booneville Mun Sep Schools | B11: 2800820 | D11: =COUNTIF(Summary!$H$2:$H$8627,'LEAID Match'!B11) -> 10
A12: Brookhaven Mun Sep Schools | B12: 2800840 | D12: =COUNTIF(Summary!$H$2:$H$8627,'LEAID Match'!B12) -> 10
A13: Calhoun Co Bd Of Ed | B13: 2800870 | D13: =COUNTIF(Summary!$H$2:$H$8627,'LEAID Match'!B13) -> 10
... A50: Holly Springs Mun Sep Schools | B50: 2801950 | D50: =COUNTIF(Summary!$H$2:$H$8627,'LEAID Match'!B50) -> 10
A51: Holmes County Consolidated School | B51: 2800195 | C51: 2801980 | D51: =COUNTIF(Summary!$H$2:$H$8627,'LEAID Match'!B51) -> 10
A52: Humphreys Co Bd Of Ed | B52: 2802040 | D52: =COUNTIF(Summary!$H$2:$H$8627,'LEAID Match'!B52) -> 10
A53: Itawamba Co Bd Of Ed | B53: 2802100 | D53: =COUNTIF(Summary!$H$2:$H$8627,'LEAID Match'!B53) -> 10
A54: Jackson Co Bd Of Ed | B54: 2802160 | D54: =COUNTIF(Summary!$H$2:$H$8627,'LEAID Match'!B54) -> 10
A55: Jackson Mun Sep Schools | B55: 2802190 | D55: =COUNTIF(Summary!$H$2:$H$8627,'LEAID Match'!B55) -> 10
A56: Jefferson Co Bd Of Ed | B56: 2802220 | D56: =COUNTIF(Summary!$H$2:$H$8627,'LEAID Match'!B56) -> 10
A57: Jefferson Davis Co Bd Of Ed | B57: 2802250 | D57: =COUNTIF(Summary!$H$2:$H$8627,'LEAID Match'!B57) -> 10
A58: Jones Co Bd Of Ed | B58: 2802280 | D58: =COUNTIF(Summary!$H$2:$H$8627,'LEAID Match'!B58) -> 10
A59: Kemper Co Bd Of Ed | B59: 2802310 | D59: =COUNTIF(Summary!$H$2:$H$8627,'LEAID Match'!B59) -> 10
A60: Kosciusko Mun Sep Schools | B60: 2802340 | D60: =COUNTIF(Summary!$H$2:$H$8627,'LEAID Match'!B60) -> 10
A61: Lafayette Co Bd Of Ed | B61: 2802370 | D61: =COUNTIF(Summary!$H$2:$H$8627,'LEAID Match'!B61) -> 10
A62: Lamar Co Bd Of Ed | B62: 2802400 | D62: =COUNTIF(Summary!$H$2:$H$8627,'LEAID Match'!B62) -> 10
A63: Lauderdale Co Bd Of Ed | B63: 2802430 | D63: =COUNTIF(Summary!$H$2:$H$8627,'LEAID Match'!B63) -> 10
... A139: Wilkinson Co Bd Of Ed | B139: 2804710 | D139: =COUNTIF(Summary!$H$2:$H$8627,'LEAID Match'!B139) -> 10
A140: Winona‐Montgomery Consolidated | B140: 2800196 | C140: 2804740 | D140: =COUNTIF(Summary!$H$2:$H$8627,'LEAID Match'!B140) -> 10
A141: Yazoo City Mun Sep Schools | B141: 2804770 | D141: =COUNTIF(Summary!$H$2:$H$8627,'LEAID Match'!B141) -> 10
A142: Yazoo Co Bd Of Ed | B142: 2804800 | D142: =COUNTIF(Summary!$H$2:$H$8627,'LEAID Match'!B142) -> 10
