Workbook
Name AZ: #REF!
Name DISTRICT_TEMP: #REF!

Sheet Final
A1: LEAID | B1: Year | C1: employer_code | D1: State | E1: state_abv | F1: standardized_employer_name | G1: employer_name | H1: district_contributions | I1: LEAID Match | J1: state_contributions | K1: total_contributions
B2: 2015 | C2: 100000 | D2: Arizona | E2: AZ | F2: Arizona Department of Administration | G2: Arizona Department Of Administration | H2: 3731576 | I2: =IFERROR(VLOOKUP(Final!F2,'LEAID Match'!$A$2:$B$374,2,FALSE),"") | K2: =SUM(H2,J2) -> 3731576
B3: 2016 | C3: 100000 | D3: Arizona | E3: AZ | F3: Arizona Department of Administration | G3: Arizona Department Of Administration | H3: 3519985 | I3: =IFERROR(VLOOKUP(Final!F3,'LEAID Match'!$A$2:$B$374,2,FALSE),"") | K3: =SUM(H3,J3) -> 3519985
B4: 2017 | C4: 100000 | D4: Arizona | E4: AZ | F4: Arizona Department of Administration | G4: Arizona Department of Administration | H4: 3638820 | I4: =IFERROR(VLOOKUP(Final!F4,'LEAID Match'!$A$2:$B$374,2,FALSE),"") | K4: =SUM(H4,J4) -> 3638820
B5: 2018 | C5: 100000 | D5: Arizona | E5: AZ | F5: Arizona Department of Administration | G5: Arizona Department of Administratio | H5: 3590201 | I5: =IFERROR(VLOOKUP(Final!F5,'LEAID Match'!$A$2:$B$374,2,FALSE),"") | K5: =SUM(H5,J5) -> 3590201
B6: 2019 | C6: 100000 | D6: Arizona | E6: AZ | F6: Arizona Department of Administration | G6: Arizona Department of Administration | H6: 3635238 | I6: =IFERROR(VLOOKUP(Final!F6,'LEAID Match'!$A$2:$B$374,2,FALSE),"") | K6: =SUM(H6,J6) -> 3635238
B7: 2020 | C7: 100000 | D7: Arizona | E7: AZ | F7: Arizona Department of Administration | G7: Arizona Department of Administration | H7: 3841165 | I7: =IFERROR(VLOOKUP(Final!F7,'LEAID Match'!$A$2:$B$374,2,FALSE),"") | K7: =SUM(H7,J7) -> 3841165
B8: 2021 | C8: 100000 | D8: Arizona | E8: AZ | F8: Arizona Department of Administration | G8: Arizona Department of Administration | H8: 4064362 | I8: =IFERROR(VLOOKUP(Final!F8,'LEAID Match'!$A$2:$B$374,2,FALSE),"") | K8: =SUM(H8,J8) -> 4064362
B9: 2022 | C9: 100000 | D9: Arizona | E9: AZ | F9: Arizona Department of Administration | G9: Arizona Department of Administration | H9: 4081015 | I9: =IFERROR(VLOOKUP(Final!F9,'LEAID Match'!$A$2:$B$374,2,FALSE),"") | K9: =SUM(H9,J9) -> 4081015
B10: 2023 | C10: 100000 | D10: Arizona | E10: AZ | F10: Arizona Department of Administration | G10: Arizona Department of Administration | H10: 5043498 | I10: =IFERROR(VLOOKUP(Final!F10,'LEAID Match'!$A$2:$B$374,2,FALSE),"") | K10: =SUM(H10,J10) -> 5043498
B11: 2015 | C11: 101030 | D11: Arizona | E11: AZ | F11: Arizona State Personnel Board | G11: Arizona Personnel Board | H11: 11736 | I11: =IFERROR(VLOOKUP(Final!F11,'LEAID Match'!$A$2:$B$374,2,FALSE),"") | K11: =SUM(H11,J11) -> 11736
B12: 2016 | C12: 101030 | D12: Arizona | E12: AZ | F12: Arizona State Personnel Board | G12: Arizona Personnel Board | H12: 11889 | I12: =IFERROR(VLOOKUP(Final!F12,'LEAID Match'!$A$2:$B$374,2,FALSE),"") | K12: =SUM(H12,J12) -> 11889
B13: 2017 | C13: 101030 | D13: Arizona | E13: AZ | F13: Arizona State Personnel Board | G13: Arizona State Personnel Board | H13: 12065 | I13: =IFERROR(VLOOKUP(Final!F13,'LEAID Match'!$A$2:$B$374,2,FALSE),"") | K13: =SUM(H13,J13) -> 12065
... B55: 2023 | C55: 101150 | D55: Arizona | E55: AZ | F55: Arizona Court of Appeals Division Two | G55: Arizona Court of Appeals Division Two | H55: 279134 | I55: =IFERROR(VLOOKUP(Final!F55,'LEAID Match'!$A$2:$B$374,2,FALSE),"") | K55: =SUM(H55,J55) -> 279134
A56: 400836 | B56: 2015 | C56: 101170 | D56: Arizona | E56: AZ | F56: Arizona Supreme Court | G56: Arizona Supreme Court | H56: 2617136 | I56: =IFERROR(VLOOKUP(Final!F56,'LEAID Match'!$A$2:$B$374,2,FALSE),"") -> 400836 | K56: =SUM(H56,J56) -> 2617136
A57: 400836 | B57: 2016 | C57: 101170 | D57: Arizona | E57: AZ | F57: Arizona Supreme Court | G57: Arizona Supreme Court | H57: 2676023 | I57: =IFERROR(VLOOKUP(Final!F57,'LEAID Match'!$A$2:$B$374,2,FALSE),"") -> 400836 | K57: =SUM(H57,J57) -> 2676023
A58: 400836 | B58: 2017 | C58: 101170 | D58: Arizona | E58: AZ | F58: Arizona Supreme Court | G58: Arizona Supreme Court | H58: 2829783 | I58: =IFERROR(VLOOKUP(Final!F58,'LEAID Match'!$A$2:$B$374,2,FALSE),"") -> 400836 | K58: =SUM(H58,J58) -> 2829783
A59: 400836 | B59: 2018 | C59: 101170 | D59: Arizona | E59: AZ | F59: Arizona Supreme Court | G59: Arizona Supreme Court | H59: 2975713 | I59: =IFERROR(VLOOKUP(Final!F59,'LEAID Match'!$A$2:$B$374,2,FALSE),"") -> 400836 | K59: =SUM(H59,J59) -> 2975713
A60: 400836 | B60: 2019 | C60: 101170 | D60: Arizona | E60: AZ | F60: Arizona Supreme Court | G60: Arizona Supreme Court | H60: 3092437 | I60: =IFERROR(VLOOKUP(Final!F60,'LEAID Match'!$A$2:$B$374,2,FALSE),"") -> 400836 | K60: =SUM(H60,J60) -> 3092437
A61: 400836 | B61: 2020 | C61: 101170 | D61: Arizona | E61: AZ | F61: Arizona Supreme Court | G61: Arizona Supreme Court | H61: 3364390 | I61: =IFERROR(VLOOKUP(Final!F61,'LEAID Match'!$A$2:$B$374,2,FALSE),"") -> 400836 | K61: =SUM(H61,J61) -> 3364390
A62: 400836 | B62: 2021 | C62: 101170 | D62: Arizona | E62: AZ | F62: Arizona Supreme Court | G62: Arizona Supreme Court | H62: 3550057 | I62: =IFERROR(VLOOKUP(Final!F62,'LEAID Match'!$A$2:$B$374,2,FALSE),"") -> 400836 | K62: =SUM(H62,J62) -> 3550057
A63: 400836 | B63: 2022 | C63: 101170 | D63: Arizona | E63: AZ | F63: Arizona Supreme Court | G63: Arizona Supreme Court | H63: 3669397 | I63: =IFERROR(VLOOKUP(Final!F63,'LEAID Match'!$A$2:$B$374,2,FALSE),"") -> 400836 | K63: =SUM(H63,J63) -> 3669397
A64: 400836 | B64: 2023 | C64: 101170 | D64: Arizona | E64: AZ | F64: Arizona Supreme Court | G64: Arizona Supreme Court | H64: 4187131 | I64: =IFERROR(VLOOKUP(Final!F64,'LEAID Match'!$A$2:$B$374,2,FALSE),"") -> 400836 | K64: =SUM(H64,J64) -> 4187131
B65: 2015 | C65: 101190 | D65: Arizona | E65: AZ | F65: Arizona Criminal Justice Commission | G65: Arizona Criminal Justice Commission | H65: 151115 | I65: =IFERROR(VLOOKUP(Final!F65,'LEAID Match'!$A$2:$B$374,2,FALSE),"") | K65: =SUM(H65,J65) -> 151115
B66: 2016 | C66: 101190 | D66: Arizona | E66: AZ | F66: Arizona Criminal Justice Commission | G66: Arizona Criminal Justice Commission | H66: 144532 | I66: =IFERROR(VLOOKUP(Final!F66,'LEAID Match'!$A$2:$B$374,2,FALSE),"") | K66: =SUM(H66,J66) -> 144532
B67: 2017 | C67: 101190 | D67: Arizona | E67: AZ | F67: Arizona Criminal Justice Commission | G67: Arizona Criminal Justice Commission | H67: 141505 | I67: =IFERROR(VLOOKUP(Final!F67,'LEAID Match'!$A$2:$B$374,2,FALSE),"") | K67: =SUM(H67,J67) -> 141505
B68: 2018 | C68: 101190 | D68: Arizona | E68: AZ | F68: Arizona Criminal Justice Commission | G68: Arizona Criminal Justice Commission | H68: 143946 | I68: =IFERROR(VLOOKUP(Final!F68,'LEAID Match'!$A$2:$B$374,2,FALSE),"") | K68: =SUM(H68,J68) -> 143946
B69: 2019 | C69: 101190 | D69: Arizona | E69: AZ | F69: Arizona Criminal Justice Commission | G69: Arizona Criminal Justice Commission | H69: 135242 | I69: =IFERROR(VLOOKUP(Final!F69,'LEAID Match'!$A$2:$B$374,2,FALSE),"") | K69: =SUM(H69,J69) -> 135242
B70: 2020 | C70: 101190 | D70: Arizona | E70: AZ | F70: Arizona Criminal Justice Commission | G70: Arizona Criminal Justice Commission | H70: 148711 | I70: =IFERROR(VLOOKUP(Final!F70,'LEAID Match'!$A$2:$B$374,2,FALSE),"") | K70: =SUM(H70,J70) -> 148711
B71: 2021 | C71: 101190 | D71: Arizona | E71: AZ | F71: Arizona Criminal Justice Commission | G71: Arizona Criminal Justice Commission | H71: 167453 | I71: =IFERROR(VLOOKUP(Final!F71,'LEAID Match'!$A$2:$B$374,2,FALSE),"") | K71: =SUM(H71,J71) -> 167453
B72: 2022 | C72: 101190 | D72: Arizona | E72: AZ | F72: Arizona Criminal Justice Commission | G72: Arizona Criminal Justice Commission | H72: 170486 | I72: =IFERROR(VLOOKUP(Final!F72,'LEAID Match'!$A$2:$B$374,2,FALSE),"") | K72: =SUM(H72,J72) -> 170486
B73: 2023 | C73: 101190 | D73: Arizona | E73: AZ | F73: Arizona Criminal Justice Commission | G73: Arizona Criminal Justice Commission | H73: 185626 | I73: =IFERROR(VLOOKUP(Final!F73,'LEAID Match'!$A$2:$B$374,2,FALSE),"") | K73: =SUM(H73,J73) -> 185626
B74: 2015 | C74: 101400 | D74: Arizona | E74: AZ | F74: Arizona Governor's Office | G74: Arizona Governor's Office | H74: 746406 | I74: =IFERROR(VLOOKUP(Final!F74,'LEAID Match'!$A$2:$B$374,2,FALSE),"") | K74: =SUM(H74,J74) -> 746406
B75: 2016 | C75: 101400 | D75: Arizona | E75: AZ | F75: Arizona Governor's Office | G75: Arizona Governor's Office | H75: 685628 | I75: =IFERROR(VLOOKUP(Final!F75,'LEAID Match'!$A$2:$B$374,2,FALSE),"") | K75: =SUM(H75,J75) -> 685628
B76: 2017 | C76: 101400 | D76: Arizona | E76: AZ | F76: Arizona Governor's Office | G76: Arizona Governor's Office | H76: 751445 | I76: =IFERROR(VLOOKUP(Final!F76,'LEAID Match'!$A$2:$B$374,2,FALSE),"") | K76: =SUM(H76,J76) -> 751445
... B82: 2023 | C82: 101400 | D82: Arizona | E82: AZ | F82: Arizona Governor's Office | G82: Arizona Governor's Office | H82: 1034084 | I82: =IFERROR(VLOOKUP(Final!F82,'LEAID Match'!$A$2:$B$374,2,FALSE),"") | K82: =SUM(H82,J82) -> 1034084
B83: 2015 | C83: 101410 | D83: Arizona | E83: AZ | F83: Arizona Office of Equal Opportunity | G83: Arizona Office Of Equal Opportunity | I83: =IFERROR(VLOOKUP(Final!F83,'LEAID Match'!$A$2:$B$374,2,FALSE),"") | K83: =SUM(H83,J83) -> 0
B84: 2016 | C84: 101410 | D84: Arizona | E84: AZ | F84: Arizona Office of Equal Opportunity | G84: Arizona Office Of Equal Opportunity | I84: =IFERROR(VLOOKUP(Final!F84,'LEAID Match'!$A$2:$B$374,2,FALSE),"") | K84: =SUM(H84,J84) -> 0
B85: 2017 | C85: 101410 | D85: Arizona | E85: AZ | F85: Arizona Office of Equal Opportunity | G85: Arizona Office of Equal Opportunity | I85: =IFERROR(VLOOKUP(Final!F85,'LEAID Match'!$A$2:$B$374,2,FALSE),"") | K85: =SUM(H85,J85) -> 0
B86: 2018 | C86: 101410 | D86: Arizona | E86: AZ | F86: Arizona Office of Equal Opportunity | G86: Arizona Office of Equal Opportunity | I86: =IFERROR(VLOOKUP(Final!F86,'LEAID Match'!$A$2:$B$374,2,FALSE),"") | K86: =SUM(H86,J86) -> 0
B87: 2015 | C87: 101430 | D87: Arizona | E87: AZ | F87: Arizona Office of Tourism | G87: Arizona Office Of Tourism | H87: 183598 | I87: =IFERROR(VLOOKUP(Final!F87,'LEAID Match'!$A$2:$B$374,2,FALSE),"") | K87: =SUM(H87,J87) -> 183598
B88: 2016 | C88: 101430 | D88: Arizona | E88: AZ | F88: Arizona Office of Tourism | G88: Arizona Office Of Tourism | H88: 138403 | I88: =IFERROR(VLOOKUP(Final!F88,'LEAID Match'!$A$2:$B$374,2,FALSE),"") | K88: =SUM(H88,J88) -> 138403
B89: 2017 | C89: 101430 | D89: Arizona | E89: AZ | F89: Arizona Office of Tourism | G89: Arizona Office of Tourism | H89: 162896 | I89: =IFERROR(VLOOKUP(Final!F89,'LEAID Match'!$A$2:$B$374,2,FALSE),"") | K89: =SUM(H89,J89) -> 162896
B90: 2018 | C90: 101430 | D90: Arizona | E90: AZ | F90: Arizona Office of Tourism | G90: Arizona Office of Tourism | H90: 174182 | I90: =IFERROR(VLOOKUP(Final!F90,'LEAID Match'!$A$2:$B$374,2,FALSE),"") | K90: =SUM(H90,J90) -> 174182
B91: 2019 | C91: 101430 | D91: Arizona | E91: AZ | F91: Arizona Office of Tourism | G91: Arizona Office of Tourism | H91: 198319 | I91: =IFERROR(VLOOKUP(Final!F91,'LEAID Match'!$A$2:$B$374,2,FALSE),"") | K91: =SUM(H91,J91) -> 198319
B92: 2020 | C92: 101430 | D92: Arizona | E92: AZ | F92: Arizona Office of Tourism | G92: Arizona Office of Tourism | H92: 192092 | I92: =IFERROR(VLOOKUP(Final!F92,'LEAID Match'!$A$2:$B$374,2,FALSE),"") | K92: =SUM(H92,J92) -> 192092
B93: 2021 | C93: 101430 | D93: Arizona | E93: AZ | F93: Arizona Office of Tourism | G93: Arizona Office of Tourism | H93: 207227 | I93: =IFERROR(VLOOKUP(Final!F93,'LEAID Match'!$A$2:$B$374,2,FALSE),"") | K93: =SUM(H93,J93) -> 207227
B94: 2022 | C94: 101430 | D94: Arizona | E94: AZ | F94: Arizona Office of Tourism | G94: Arizona Office of Tourism | H94: 201190 | I94: =IFERROR(VLOOKUP(Final!F94,'LEAID Match'!$A$2:$B$374,2,FALSE),"") | K94: =SUM(H94,J94) -> 201190
B95: 2023 | C95: 101430 | D95: Arizona | E95: AZ | F95: Arizona Office of Tourism | G95: Arizona Office of Tourism | H95: 217715 | I95: =IFERROR(VLOOKUP(Final!F95,'LEAID Match'!$A$2:$B$374,2,FALSE),"") | K95: =SUM(H95,J95) -> 217715
B96: 2015 | C96: 101470 | D96: Arizona | E96: AZ | F96: Arizona Law Enforcement Merit System Council | G96: Arizona Law Enforc ement Merit SysCouncil | I96: =IFERROR(VLOOKUP(Final!F96,'LEAID Match'!$A$2:$B$374,2,FALSE),"") | K96: =SUM(H96,J96) -> 0
B97: 2016 | C97: 101470 | D97: Arizona | E97: AZ | F97: Arizona Law Enforcement Merit System Council | G97: Arizona Law Enforcement Merit SysCouncil | I97: =IFERROR(VLOOKUP(Final!F97,'LEAID Match'!$A$2:$B$374,2,FALSE),"") | K97: =SUM(H97,J97) -> 0
B98: 2017 | C98: 101470 | D98: Arizona | E98: AZ | F98: Arizona Law Enforcement Merit System Council | G98: Arizona Law Enforcement Merit System Council | I98: =IFERROR(VLOOKUP(Final!F98,'LEAID Match'!$A$2:$B$374,2,FALSE),"") | K98: =SUM(H98,J98) -> 0
B99: 2018 | C99: 101470 | D99: Arizona | E99: AZ | F99: Arizona Law Enforcement Merit System Council | G99: Arizona Law Enforcement Merit Syste | I99: =IFERROR(VLOOKUP(Final!F99,'LEAID Match'!$A$2:$B$374,2,FALSE),"") | K99: =SUM(H99,J99) -> 0
B100: 2015 | C100: 101510 | D100: Arizona | E100: AZ | F100: Arizona State Senate | G100: Arizona State Senate | H100: 454238 | I100: =IFERROR(VLOOKUP(Final!F100,'LEAID Match'!$A$2:$B$374,2,FALSE),"") | K100: =SUM(H100,J100) -> 454238
B101: 2016 | C101: 101510 | D101: Arizona | E101: AZ | F101: Arizona State Senate | G101: Arizona State Senate | H101: 451532 | I101: =IFERROR(VLOOKUP(Final!F101,'LEAID Match'!$A$2:$B$374,2,FALSE),"") | K101: =SUM(H101,J101) -> 451532
B102: 2017 | C102: 101510 | D102: Arizona | E102: AZ | F102: Arizona State Senate | G102: Arizona State Senate | H102: 499596 | I102: =IFERROR(VLOOKUP(Final!F102,'LEAID Match'!$A$2:$B$374,2,FALSE),"") | K102: =SUM(H102,J102) -> 499596
B103: 2018 | C103: 101510 | D103: Arizona | E103: AZ | F103: Arizona State Senate | G103: Arizona State Senate | H103: 519832 | I103: =IFERROR(VLOOKUP(Final!F103,'LEAID Match'!$A$2:$B$374,2,FALSE),"") | K103: =SUM(H103,J103) -> 519832
B104: 2019 | C104: 101510 | D104: Arizona | E104: AZ | F104: Arizona State Senate | G104: Arizona State Senate | H104: 560700 | I104: =IFERROR(VLOOKUP(Final!F104,'LEAID Match'!$A$2:$B$374,2,FALSE),"") | K104: =SUM(H104,J104) -> 560700
B105: 2020 | C105: 101510 | D105: Arizona | E105: AZ | F105: Arizona State Senate | G105: Arizona State Senate | H105: 631885 | I105: =IFERROR(VLOOKUP(Final!F105,'LEAID Match'!$A$2:$B$374,2,FALSE),"") | K105: =SUM(H105,J105) -> 631885
B106: 2021 | C106: 101510 | D106: Arizona | E106: AZ | F106: Arizona State Senate | G106: Arizona State Senate | H106: 657528 | I106: =IFERROR(VLOOKUP(Final!F106,'LEAID Match'!$A$2:$B$374,2,FALSE),"") | K106: =SUM(H106,J106) -> 657528
B107: 2022 | C107: 101510 | D107: Arizona | E107: AZ | F107: Arizona State Senate | G107: Arizona State Senate | H107: 731340 | I107: =IFERROR(VLOOKUP(Final!F107,'LEAID Match'!$A$2:$B$374,2,FALSE),"") | K107: =SUM(H107,J107) -> 731340
B108: 2023 | C108: 101510 | D108: Arizona | E108: AZ | F108: Arizona State Senate | G108: Arizona State Senate | H108: 866623 | I108: =IFERROR(VLOOKUP(Final!F108,'LEAID Match'!$A$2:$B$374,2,FALSE),"") | K108: =SUM(H108,J108) -> 866623
B109: 2015 | C109: 101520 | D109: Arizona | E109: AZ | F109: Arizona House of Representatives | G109: Arizona House Of Representatives | H109: 650833 | I109: =IFERROR(VLOOKUP(Final!F109,'LEAID Match'!$A$2:$B$374,2,FALSE),"") | K109: =SUM(H109,J109) -> 650833
B110: 2016 | C110: 101520 | D110: Arizona | E110: AZ | F110: Arizona House of Representatives | G110: Arizona House Of Representatives | H110: 672156 | I110: =IFERROR(VLOOKUP(Final!F110,'LEAID Match'!$A$2:$B$374,2,FALSE),"") | K110: =SUM(H110,J110) -> 672156
B111: 2017 | C111: 101520 | D111: Arizona | E111: AZ | F111: Arizona House of Representatives | G111: Arizona House of Representatives | H111: 687308 | I111: =IFERROR(VLOOKUP(Final!F111,'LEAID Match'!$A$2:$B$374,2,FALSE),"") | K111: =SUM(H111,J111) -> 687308
... B254: 2016 | C254: 103010 | D254: Arizona | E254: AZ | F254: Arizona Department of Weights and Measures | G254: Arizona Dept Of Weights & Measures | H254: 128154 | I254: =IFERROR(VLOOKUP(Final!F254,'LEAID Match'!$A$2:$B$374,2,FALSE),"") | K254: =SUM(H254,J254) -> 128154
B255: 2017 | C255: 103010 | D255: Arizona | E255: AZ | F255: Arizona Department of Weights and Measures | G255: Arizona Department of Weights and Measures | I255: =IFERROR(VLOOKUP(Final!F255,'LEAID Match'!$A$2:$B$374,2,FALSE),"") | K255: =SUM(H255,J255) -> 0
B256: 2018 | C256: 103010 | D256: Arizona | E256: AZ | F256: Arizona Department of Weights and Measures | G256: Arizona Department of Weights and M | I256: =IFERROR(VLOOKUP(Final!F256,'LEAID Match'!$A$2:$B$374,2,FALSE),"") | K256: =SUM(H256,J256) -> 0
B257: 2019 | C257: 103010 | D257: Arizona | E257: AZ | F257: Arizona Department of Weights and Measures | G257: Arizona Department of Weights and Measures | I257: =IFERROR(VLOOKUP(Final!F257,'LEAID Match'!$A$2:$B$374,2,FALSE),"") | K257: =SUM(H257,J257) -> 0
B258: 2020 | C258: 103010 | D258: Arizona | E258: AZ | F258: Arizona Department of Weights and Measures | G258: Arizona Department of Weights and Measures | I258: =IFERROR(VLOOKUP(Final!F258,'LEAID Match'!$A$2:$B$374,2,FALSE),"") | K258: =SUM(H258,J258) -> 0
B259: 2015 | C259: 103020 | D259: Arizona | E259: AZ | F259: Arizona State Board of Accountancy | G259: Arizona Board Of Accountancy | H259: 62765 | I259: =IFERROR(VLOOKUP(Final!F259,'LEAID Match'!$A$2:$B$374,2,FALSE),"") | K259: =SUM(H259,J259) -> 62765
B260: 2016 | C260: 103020 | D260: Arizona | E260: AZ | F260: Arizona State Board of Accountancy | G260: Arizona Board Of Accountancy | H260: 68469 | I260: =IFERROR(VLOOKUP(Final!F260,'LEAID Match'!$A$2:$B$374,2,FALSE),"") | K260: =SUM(H260,J260) -> 68469
B261: 2017 | C261: 103020 | D261: Arizona | E261: AZ | F261: Arizona State Board of Accountancy | G261: Arizona State Board of Accountancy | H261: 83895 | I261: =IFERROR(VLOOKUP(Final!F261,'LEAID Match'!$A$2:$B$374,2,FALSE),"") | K261: =SUM(H261,J261) -> 83895
B262: 2018 | C262: 103020 | D262: Arizona | E262: AZ | F262: Arizona State Board of Accountancy | G262: Arizona State Board of Accountancy | H262: 78051 | I262: =IFERROR(VLOOKUP(Final!F262,'LEAID Match'!$A$2:$B$374,2,FALSE),"") | K262: =SUM(H262,J262) -> 78051
B263: 2019 | C263: 103020 | D263: Arizona | E263: AZ | F263: Arizona State Board of Accountancy | G263: Arizona State Board of Accountancy | H263: 74273 | I263: =IFERROR(VLOOKUP(Final!F263,'LEAID Match'!$A$2:$B$374,2,FALSE),"") | K263: =SUM(H263,J263) -> 74273
B264: 2020 | C264: 103020 | D264: Arizona | E264: AZ | F264: Arizona State Board of Accountancy | G264: Arizona State Board of Accountancy | H264: 77163 | I264: =IFERROR(VLOOKUP(Final!F264,'LEAID Match'!$A$2:$B$374,2,FALSE),"") | K264: =SUM(H264,J264) -> 77163
B265: 2021 | C265: 103020 | D265: Arizona | E265: AZ | F265: Arizona State Board of Accountancy | G265: Arizona State Board of Accountancy | H265: 80643 | I265: =IFERROR(VLOOKUP(Final!F265,'LEAID Match'!$A$2:$B$374,2,FALSE),"") | K265: =SUM(H265,J265) -> 80643
B266: 2022 | C266: 103020 | D266: Arizona | E266: AZ | F266: Arizona State Board of Accountancy | G266: Arizona State Board of Accountancy | H266: 88278 | I266: =IFERROR(VLOOKUP(Final!F266,'LEAID Match'!$A$2:$B$374,2,FALSE),"") | K266: =SUM(H266,J266) -> 88278
B267: 2023 | C267: 103020 | D267: Arizona | E267: AZ | F267: Arizona State Board of Accountancy | G267: Arizona State Board of Accountancy | H267: 95503 | I267: =IFERROR(VLOOKUP(Final!F267,'LEAID Match'!$A$2:$B$374,2,FALSE),"") | K267: =SUM(H267,J267) -> 95503
B268: 2015 | C268: 103060 | D268: Arizona | E268: AZ | F268: Arizona Department of Agriculture | G268: Arizona Dept Of Agriculture | H268: 869767 | I268: =IFERROR(VLOOKUP(Final!F268,'LEAID Match'!$A$2:$B$374,2,FALSE),"") | K268: =SUM(H268,J268) -> 869767
B269: 2016 | C269: 103060 | D269: Arizona | E269: AZ | F269: Arizona Department of Agriculture | G269: Arizona Dept Of Agriculture | H269: 948053 | I269: =IFERROR(VLOOKUP(Final!F269,'LEAID Match'!$A$2:$B$374,2,FALSE),"") | K269: =SUM(H269,J269) -> 948053
B270: 2017 | C270: 103060 | D270: Arizona | E270: AZ | F270: Arizona Department of Agriculture | G270: Arizona Department of Agriculture | H270: 1182486 | I270: =IFERROR(VLOOKUP(Final!F270,'LEAID Match'!$A$2:$B$374,2,FALSE),"") | K270: =SUM(H270,J270) -> 1182486
... B277: 2015 | C277: 103070 | D277: Arizona | E277: AZ | F277: Arizona Board Of Appraisal | G277: Arizona Board Of Appraisal | H277: 33410 | I277: =IFERROR(VLOOKUP(Final!F277,'LEAID Match'!$A$2:$B$374,2,FALSE),"") | K277: =SUM(H277,J277) -> 33410
B278: 2016 | C278: 103070 | D278: Arizona | E278: AZ | F278: Arizona Board Of Appraisal | G278: Arizona Board Of Appraisal | I278: =IFERROR(VLOOKUP(Final!F278,'LEAID Match'!$A$2:$B$374,2,FALSE),"") | K278: =SUM(H278,J278) -> 0
B279: 2017 | C279: 103070 | D279: Arizona | E279: AZ | F279: Arizona Board Of Appraisal | G279: Arizona Department of Financial Institutions | I279: =IFERROR(VLOOKUP(Final!F279,'LEAID Match'!$A$2:$B$374,2,FALSE),"") | K279: =SUM(H279,J279) -> 0
B280: 2018 | C280: 103070 | D280: Arizona | E280: AZ | F280: Arizona Board Of Appraisal | G280: Arizona Department of Financial Ins | I280: =IFERROR(VLOOKUP(Final!F280,'LEAID Match'!$A$2:$B$374,2,FALSE),"") | K280: =SUM(H280,J280) -> 0
B281: 2019 | C281: 103070 | D281: Arizona | E281: AZ | F281: Arizona Board Of Appraisal | G281: Arizona Department of Financial Institutions | I281: =IFERROR(VLOOKUP(Final!F281,'LEAID Match'!$A$2:$B$374,2,FALSE),"") | K281: =SUM(H281,J281) -> 0
B282: 2015 | C282: 103100 | D282: Arizona | E282: AZ | F282: Arizona Radiation Regulatory Agency | G282: Arizona Radiation Regulatory Agency | H282: 134783 | I282: =IFERROR(VLOOKUP(Final!F282,'LEAID Match'!$A$2:$B$374,2,FALSE),"") | K282: =SUM(H282,J282) -> 134783
B283: 2016 | C283: 103100 | D283: Arizona | E283: AZ | F283: Arizona Radiation Regulatory Agency | G283: Arizona Radiation Regulatory Agency | H283: 139402 | I283: =IFERROR(VLOOKUP(Final!F283,'LEAID Match'!$A$2:$B$374,2,FALSE),"") | K283: =SUM(H283,J283) -> 139402
B284: 2017 | C284: 103100 | D284: Arizona | E284: AZ | F284: Arizona Radiation Regulatory Agency | G284: Arizona Radiation Regulatory Agency | H284: 139823 | I284: =IFERROR(VLOOKUP(Final!F284,'LEAID Match'!$A$2:$B$374,2,FALSE),"") | K284: =SUM(H284,J284) -> 139823
B285: 2018 | C285: 103100 | D285: Arizona | E285: AZ | F285: Arizona Radiation Regulatory Agency | G285: Arizona Radiation Regulatory Agency | H285: 71541 | I285: =IFERROR(VLOOKUP(Final!F285,'LEAID Match'!$A$2:$B$374,2,FALSE),"") | K285: =SUM(H285,J285) -> 71541
B286: 2019 | C286: 103100 | D286: Arizona | E286: AZ | F286: Arizona Radiation Regulatory Agency | G286: Arizona Radiation Regulatory Agency | I286: =IFERROR(VLOOKUP(Final!F286,'LEAID Match'!$A$2:$B$374,2,FALSE),"") | K286: =SUM(H286,J286) -> 0
B287: 2020 | C287: 103100 | D287: Arizona | E287: AZ | F287: Arizona Radiation Regulatory Agency | G287: Arizona Radiation Regulatory Agency | I287: =IFERROR(VLOOKUP(Final!F287,'LEAID Match'!$A$2:$B$374,2,FALSE),"") | K287: =SUM(H287,J287) -> 0
B288: 2021 | C288: 103100 | D288: Arizona | E288: AZ | F288: Arizona Radiation Regulatory Agency | G288: Arizona Radiation Regulatory Agency | I288: =IFERROR(VLOOKUP(Final!F288,'LEAID Match'!$A$2:$B$374,2,FALSE),"") | K288: =SUM(H288,J288) -> 0
B289: 2022 | C289: 103100 | D289: Arizona | E289: AZ | F289: Arizona Radiation Regulatory Agency | G289: Arizona Radiation Regulatory Agency | I289: =IFERROR(VLOOKUP(Final!F289,'LEAID Match'!$A$2:$B$374,2,FALSE),"") | K289: =SUM(H289,J289) -> 0
B290: 2023 | C290: 103100 | D290: Arizona | E290: AZ | F290: Arizona Radiation Regulatory Agency | G290: Arizona Radiation Regulatory Agency | I290: =IFERROR(VLOOKUP(Final!F290,'LEAID Match'!$A$2:$B$374,2,FALSE),"") | K290: =SUM(H290,J290) -> 0
B291: 2015 | C291: 103120 | D291: Arizona | E291: AZ | F291: Arizona Department of Financial Institutions | G291: Arizona Dept Of Financial Institutions | H291: 249707 | I291: =IFERROR(VLOOKUP(Final!F291,'LEAID Match'!$A$2:$B$374,2,FALSE),"") | K291: =SUM(H291,J291) -> 249707
B292: 2016 | C292: 103120 | D292: Arizona | E292: AZ | F292: Arizona Department of Financial Institutions | G292: Arizona Dept Of Financial Institutions | H292: 291664 | I292: =IFERROR(VLOOKUP(Final!F292,'LEAID Match'!$A$2:$B$374,2,FALSE),"") | K292: =SUM(H292,J292) -> 291664
B293: 2017 | C293: 103120 | D293: Arizona | E293: AZ | F293: Arizona Department of Financial Institutions | G293: Arizona Department of Financial Institutions | H293: 291341 | I293: =IFERROR(VLOOKUP(Final!F293,'LEAID Match'!$A$2:$B$374,2,FALSE),"") | K293: =SUM(H293,J293) -> 291341
B294: 2018 | C294: 103120 | D294: Arizona | E294: AZ | F294: Arizona Department of Financial Institutions | G294: Arizona Department of Financial Ins | H294: 319270 | I294: =IFERROR(VLOOKUP(Final!F294,'LEAID Match'!$A$2:$B$374,2,FALSE),"") | K294: =SUM(H294,J294) -> 319270
...

Sheet Dataset Checks & NCES Match -->

Sheet Contributions Check
A1: Employer Contribution Check
A2: Year | B2: Reported Total | C2: Total From Formula | D2: Difference
A3: 2015 | B3: 1003030750 | C3: =SUMIF(Final!B$2:B$6407,'Contributions Check'!A3,Final!H$2:H$6407) -> 1003030750 | D3: =B3-C3 -> 0
A4: 2016 | B4: 1015920247 | C4: =SUMIF(Final!B$2:B$6407,'Contributions Check'!A4,Final!H$2:H$6407) -> 1015920247 | D4: =B4-C4 -> 0
A5: 2017 | B5: 1051469476 | C5: =SUMIF(Final!B$2:B$6407,'Contributions Check'!A5,Final!H$2:H$6407) -> 1051469476 | D5: =B5-C5 -> 0
A6: 2018 | B6: 1083432138 | C6: =SUMIF(Final!B$2:B$6407,'Contributions Check'!A6,Final!H$2:H$6407) -> 1083432138 | D6: =B6-C6 -> 0
A7: 2019 | B7: 1179092833 | C7: =SUMIF(Final!B$2:B$6407,'Contributions Check'!A7,Final!H$2:H$6407) -> 1179092833 | D7: =B7-C7 -> 0
A8: 2020 | B8: 1251493308 | C8: =SUMIF(Final!B$2:B$6407,'Contributions Check'!A8,Final!H$2:H$6407) -> 1251493308 | D8: =B8-C8 -> 0
A9: 2021 | B9: 1309666248 | C9: =SUMIF(Final!B$2:B$6407,'Contributions Check'!A9,Final!H$2:H$6407) -> 1309666244 | D9: =B9-C9 -> 4
A10: 2022 | B10: 1429670650 | C10: =SUMIF(Final!B$2:B$6407,'Contributions Check'!A10,Final!H$2:H$6407) -> 1429670650 | D10: =B10-C10 -> 0
A11: 2023 | B11: 1556007811 | C11: =SUMIF(Final!B$2:B$6407,'Contributions Check'!A11,Final!H$2:H$6407) -> 1556007811 | D11: =B11-C11 -> 0

Sheet LEAID Match
A1: standardized_employer_name | B1: LEAID
A2: Cave Creek Unified School District No. 93 | B2: 400001
A3: Clarkdale-Jerome Elementary School District #3 | B3: 400004
A4: Salome Consolidated Elementary School District #30 | B4: 400005
A5: Pine Forest Charter School | B5: 400018
A6: Flagstaff Arts And Leadership Academy | B6: 400019
A7: Colorado City Unified School District #14 | B7: 400021
A8: Vernon Elementary School District #9 | B8: 400022
A9: Pinon Unified School District #4 | B9: 400023
A10: Heber-Overgaard Unified School District #6 | B10: 400026
A11: Triumphant Learning Center | B11: 400028
A12: Ridgeline Academy | B12: 400031
A13: STEP UP School | B13: 400040
... A374: Sedona-Oak Creek Unified School District #9 | B374: 409733
A375: Arizona Charter Academy
A376: Arizona Community Development Corporation (La Paloma Academy)
A377: Arts Academy at Estrella Mountain
A378: Chino Valley Unified School District #51
A379: Desert Mosaic School
A380: Edkey (Arizona Conservatory for Arts and Academics)
A381: Ehrenberg Improvement District
A382: Grand Canyon College Preparatory Charter School
A383: Intelli-School (Paradise Valley)
A384: Navajo County Arizona - Hope School
A385: Navajo County Arizona - Special Services Consortium
A386: Northern Arizona Academy for Career Development
... A397: Willow Creek Charter

Sheet Old Data -->

Sheet Data As Collected
A1: year | B1: employer_code | C1: employer_name | D1: employer_contribution | E1: allocation_percentage
A2: 2015 | B2: 102300 | C2: A H C C C S | D2: 4565257 | E2: 0.0045515
A3: 2015 | B3: 307810 | C3: AAEC Paradise Valley | D3: 478197 | E3: 0.0004768
A4: 2015 | B4: 307850 | C4: Academy Of Excellence | D4: 28397 | E4: 2.83e-05
A5: 2015 | B5: 450540 | C5: Academy Of Tucson | D5: 263201 | E5: 0.0002624
A6: 2015 | B6: 307940 | C6: Accelerated Elem And Secondary Schls | D6: 66764 | E6: 6.66e-05
A7: 2015 | B7: 303320 | C7: Accelerated Learning Center | D7: 77520 | E7: 7.73e-05
A8: 2015 | B8: 307490 | C8: ACCLAIM Charter School (ACCLAIM Academy) | D8: 134215 | E8: 0.0001338
A9: 2015 | B9: 302160 | C9: Agua Fria Union High Sch Dist 216 | D9: 3407931 | E9: 0.0033976
A10: 2015 | B10: 300630 | C10: Aguila School District 63 | D10: 98855 | E10: 9.86e-05
A11: 2015 | B11: 302310 | C11: AIBT Chtr HS (RCB Medical Arts Academy) | D11: 70606 | E11: 7.04e-05
A12: 2015 | B12: 450150 | C12: Ajo USD | D12: 212251 | E12: 0.0002116
A13: 2015 | B13: 302800 | C13: Akimel O'Otham Pee Posh Chtr Schl (3-5) | D13: 24816 | E13: 2.47e-05
... A56: 2015 | B56: 103830 | C56: Arizona Board Of Physical Therapy | D56: 20761 | E56: 2.07e-05
A57: 2015 | B57: 109220 | C57: Arizona CapPostConvictionPublic Defender | E57: 0
A58: 2015 | B58: 495900 | C58: Arizona City Sanitary District | D58: 58187 | E58: 5.8e-05
A59: 2015 | B59: 102100 | C59: Arizona Comm For Deaf & Hard Of Hearing | D59: 87962 | E59: 8.77e-05
A60: 2015 | B60: 109030 | C60: Arizona Comm For Postsecondary Educ ation | D60: 36425 | E60: 3.63e-05
A61: 2015 | B61: 104820 | C61: Arizona Commission On The Arts | D61: 56835 | E61: 5.67e-05
A62: 2015 | B62: 103250 | C62: Arizona Corporation Commission | D62: 1632964 | E62: 0.001628
A63: 2015 | B63: 109270 | C63: Arizona Cotton Research & Protection | D63: 105805 | E63: 0.0001055
A64: 2015 | B64: 497380 | C64: Arizona Counties Insurance Pool | D64: 89528 | E64: 8.93e-05
A65: 2015 | B65: 101140 | C65: Arizona Court Of Appeals Division One | D65: 348019 | E65: 0.000347
A66: 2015 | B66: 101150 | C66: Arizona Court Of Appeals Division Two | D66: 161378 | E66: 0.0001609
A67: 2015 | B67: 101190 | C67: Arizona Criminal Justice Commission | D67: 151115 | E67: 0.0001507
A68: 2015 | B68: 100000 | C68: Arizona Department Of Administration | D68: 3731576 | E68: 0.0037203
A69: 2015 | B69: 103880 | C69: Arizona Department Of Racing | D69: 143598 | E69: 0.0001432
... A99: 2015 | B99: 104920 | C99: Arizona Historical Society | D99: 173717 | E99: 0.0001732
A100: 2015 | B100: 103200 | C100: Arizona Homeopathic Medical Examiners | E100: 0
A101: 2015 | B101: 101520 | C101: Arizona House Of Representatives | D101: 650833 | E101: 0.0006489
A102: 2015 | B102: 109150 | C102: Arizona Independent Redistricting Com | D102: 27218 | E102: 2.71e-05
A103: 2015 | B103: 103500 | C103: Arizona Industrial Commission | D103: 1134350 | E103: 0.0011309
A104: 2015 | B104: 495300 | C104: Arizona Interscholastic Association | D104: 148014 | E104: 0.0001476
A105: 2015 | B105: 101540 | C105: Arizona Joint Legislative Budget Commit | D105: 161433 | E105: 0.0001609
A106: 2015 | B106: 101470 | C106: Arizona Law Enforc ement Merit SysCouncil | E106: 0
A107: 2015 | B107: 101530 | C107: Arizona Legislative Council | D107: 335529 | E107: 0.0003345
A108: 2015 | B108: 103610 | C108: Arizona Lottery | D108: 421061 | E108: 0.0004198
A109: 2015 | B109: 103620 | C109: Arizona Medical Board | D109: 263790 | E109: 0.000263
A110: 2015 | B110: 495090 | C110: Arizona Municipal Water Users Assn | D110: 59547 | E110: 5.94e-05
A111: 2015 | B111: 103680 | C111: Arizona Naturopathic Phys Bd Of Med Exam | D111: 8905 | E111: 8.9e-06
A112: 2015 | B112: 109040 | C112: Arizona Navigable Stream Adjudicatn Comm | D112: 7708 | E112: 7.7e-06
A113: 2015 | B113: 101590 | C113: Arizona Office Of Auditor General | D113: 1376489 | E113: 0.0013723
A114: 2015 | B114: 101410 | C114: Arizona Office Of Equal Opportunity | E114: 0
A115: 2015 | B115: 103940 | C115: Arizona Office Of Pest Management | D115: 77743 | E115: 7.75e-05
A116: 2015 | B116: 101430 | C116: Arizona Office Of Tourism | D116: 183598 | E116: 0.000183
A117: 2015 | B117: 109070 | C117: Arizona Office Of Administrative Hearings | D117: 106558 | E117: 0.0001062
A118: 2015 | B118: 101030 | C118: Arizona Personnel Board | D118: 11736 | E118: 1.17e-05
A119: 2015 | B119: 102700 | C119: Arizona Pioneers' Home | D119: 322297 | E119: 0.0003213
A120: 2015 | B120: 109990 | C120: Arizona Power Authority | D120: 59443 | E120: 5.93e-05
A121: 2015 | B121: 103870 | C121: Arizona Private Postsecondary Educ Bd | D121: 28092 | E121: 2.8e-05
A122: 2015 | B122: 496750 | C122: Arizona Prosecuting Attorneys' Adv Co | D122: 42349 | E122: 4.22e-05
A123: 2015 | B123: 103100 | C123: Arizona Radiation Regulatory Agency | D123: 134783 | E123: 0.0001344
A124: 2015 | B124: 103220 | C124: Arizona Registrar Of Contrac tors | D124: 467809 | E124: 0.0004664
A125: 2015 | B125: 103260 | C125: Arizona ResidentialUtilityConsumerOffic e | D125: 56288 | E125: 5.61e-05
A126: 2015 | B126: 109080 | C126: Arizona School Facilities Board | D126: 100148 | E126: 9.98e-05
... A149: 2015 | B149: 304040 | C149: AZ Community Dev. Corp. (La Paloma Acad) | D149: 621590 | E149: 0.0006197
A150: 2015 | B150: 302870 | C150: AZ Sch For Integrated Academic s & Tech | E150: 0
A151: 2015 | B151: 450400 | C151: Baboquivari Unified School District | D151: 996612 | E151: 0.0009936
A152: 2015 | B152: 492200 | C152: Bagdad USD | D152: 306384 | E152: 0.0003055
A153: 2015 | B153: 302240 | C153: Ball Charter Schools (Dobson Academy) | D153: 272049 | E153: 0.0002712
A154: 2015 | B154: 307430 | C154: Ball Charter Schools (Hearn Academy) | D154: 257980 | E154: 0.0002572
A155: 2015 | B155: 200280 | C155: Ball Charter Schools (Val Vista Academy) | D155: 155883 | E155: 0.0001554
A156: 2015 | B156: 300310 | C156: Balsz Elementary School District 31 | D156: 1288350 | E156: 0.0012845
A157: 2015 | B157: 492260 | C157: Beaver Creek Elementary School Dist 26 | D157: 168086 | E157: 0.0001676
A158: 2015 | B158: 302080 | C158: Benchmark School | D158: 146810 | E158: 0.0001464
A159: 2015 | B159: 306910 | C159: Benjamin Franklin Charter School | D159: 807684 | E159: 0.0008052
A160: 2015 | B160: 462090 | C160: Benson USD #9 | D160: 585808 | E160: 0.000584
A161: 2015 | B161: 494760 | C161: Bicentennial USD # 76 | D161: 110538 | E161: 0.0001102
A162: 2015 | B162: 462020 | C162: Bisbee USD #2 | D162: 436870 | E162: 0.0004355
... A165: 2015 | B165: 482320 | C165: Blue Ridge USD #32 | D165: 858732 | E165: 0.0008561
A166: 2015 | B166: 302860 | C166: Blueprint Educ . (Hope HS, Blueprint HS) | D166: 38489 | E166: 3.84e-05
A167: 2015 | B167: 472100 | C167: Bonita Elementary SD #16 | D167: 98866 | E167: 9.86e-05
A168: 2015 | B168: 494260 | C168: Bouse Elementary SD #26 | D168: 46414 | E168: 4.63e-05
A169: 2015 | B169: 462140 | C169: Bowie USD # 14 | D169: 55923 | E169: 5.58e-05
A170: 2015 | B170: 300330 | C170: Buckeye Elementary SD # 33 | D170: 1940952 | E170: 0.0019351
A171: 2015 | B171: 302010 | C171: Buckeye Union HSD #201 | D171: 1744191 | E171: 0.0017389
A172: 2015 | B172: 495020 | C172: Buckeye Valley Fire District | D172: 77103 | E172: 7.69e-05
A173: 2015 | B173: 497430 | C173: Buckeye Water Conserv & Drainage Dist | D173: 56474 | E173: 5.63e-05
A174: 2015 | B174: 481150 | C174: Bullhead City Elem SD # 15 | D174: 1188659 | E174: 0.0011851
A175: 2015 | B175: 495000 | C175: Bullhead City Fire District | D175: 126860 | E175: 0.0001265
A176: 2015 | B176: 480120 | C176: Camp Verde Fire District | D176: 31176 | E176: 3.11e-05
A177: 2015 | B177: 492280 | C177: Camp Verde USD | D177: 732070 | E177: 0.0007299
... A252: 2015 | B252: 410110 | C252: Cochise County | D252: 2738855 | E252: 0.0027306
A253: 2015 | B253: 462000 | C253: Cochise County School Office | E253: 0
A254: 2015 | B254: 462260 | C254: Cochise Elementary SD #26 | D254: 75473 | E254: 7.52e-05
A255: 2015 | B255: 463230 | C255: Cochise Technology District #01 | D255: 16393 | E255: 1.63e-05
A256: 2015 | B256: 410130 | C256: Coconino County | D256: 3839986 | E256: 0.0038284
A257: 2015 | B257: 464990 | C257: Coconino County Community College | D257: 750800 | E257: 0.0007485
A258: 2015 | B258: 303060 | C258: Coconino County Regional Accomm Sch | D258: 91356 | E258: 9.11e-05
A259: 2015 | B259: 481140 | C259: Colorado City USD #14 | D259: 156536 | E259: 0.0001561
A260: 2015 | B260: 480020 | C260: Colorado River Sewage Sys Jt Venture | D260: 41482 | E260: 4.14e-05
A261: 2015 | B261: 481920 | C261: Colorado River Union HSD #2 | D261: 826868 | E261: 0.0008244
A262: 2015 | B262: 461060 | C262: Concho Elementary SD #6 | D262: 145915 | E262: 0.0001455
A263: 2015 | B263: 492170 | C263: Congress Elementary SD #17 | D263: 100727 | E263: 0.0001004
A264: 2015 | B264: 450390 | C264: Continental School Dist | D264: 267216 | E264: 0.0002664
A265: 2015 | B265: 200210 | C265: Coolidge USD # 21 | D265: 1559852 | E265: 0.0015551
... A303: 2015 | B303: 307080 | C303: EDUPRIZE SCHOOLS | D303: 1217194 | E303: 0.0012135
A304: 2015 | B304: 302520 | C304: El Centro for the Study of Primary and Secondary Educ ation | E304: 0
A305: 2015 | B305: 462120 | C305: Elfrida Elementary SD #12 | D305: 75359 | E305: 7.51e-05
A306: 2015 | B306: 495100 | C306: Elfrida Fire District | D306: 14904 | E306: 1.49e-05
...

Sheet Backup
A1: year | B1: employer_code | C1: standardized_employer_name | D1: employer_name | E1: employer_contribution | F1: allocation_percentage
A2: 2015 | B2: 102300 | C2: Arizona Health Care Cost Containment System | D2: A H C C C S | E2: 4565257 | F2: 0.0045515
A3: 2015 | B3: 307810 | C3: Arizona Agribusiness & Equine Center | D3: AAEC Paradise Valley | E3: 478197 | F3: 0.0004768
A4: 2015 | B4: 307850 | C4: Academy Of Excellence | D4: Academy Of Excellence | E4: 28397 | F4: 2.83e-05
A5: 2015 | B5: 450540 | C5: Academy Of Tucson | D5: Academy Of Tucson | E5: 263201 | F5: 0.0002624
A6: 2015 | B6: 307940 | C6: Accelerated Elementary and Secondary Schools | D6: Accelerated Elem And Secondary Schls | E6: 66764 | F6: 6.66e-05
A7: 2015 | B7: 303320 | C7: Accelerated Learning Center | D7: Accelerated Learning Center | E7: 77520 | F7: 7.73e-05
A8: 2015 | B8: 307490 | C8: Acclaim Charter School | D8: ACCLAIM Charter School (ACCLAIM Academy) | E8: 134215 | F8: 0.0001338
A9: 2015 | B9: 302160 | C9: Agua Fria Union High School District #216 | D9: Agua Fria Union High Sch Dist 216 | E9: 3407931 | F9: 0.0033976
A10: 2015 | B10: 300630 | C10: Aguila Elementary School District #63 | D10: Aguila School District 63 | E10: 98855 | F10: 9.86e-05
A11: 2015 | B11: 302310 | C11: AIBT Non-Profit Charter High School | D11: AIBT Chtr HS (RCB Medical Arts Academy) | E11: 70606 | F11: 7.04e-05
A12: 2015 | B12: 450150 | C12: Ajo Unified School District | D12: Ajo USD | E12: 212251 | F12: 0.0002116
A13: 2015 | B13: 302800 | C13: Akimel O'Otham Pee Posh (3-5) | D13: Akimel O'Otham Pee Posh Chtr Schl (3-5) | E13: 24816 | F13: 2.47e-05
... A56: 2015 | B56: 103830 | C56: Arizona State Board of Physical Therapy | D56: Arizona Board Of Physical Therapy | E56: 20761 | F56: 2.07e-05
A57: 2015 | B57: 109220 | C57: Arizona Capital Post Conviction Pub | D57: Arizona CapPostConvictionPublic Defender | F57: 0
A58: 2015 | B58: 495900 | C58: Arizona City Sanitary District | D58: Arizona City Sanitary District | E58: 58187 | F58: 5.8e-05
A59: 2015 | B59: 102100 | C59: Arizona Commission for the Deaf and Hard of Hearing | D59: Arizona Comm For Deaf & Hard Of Hearing | E59: 87962 | F59: 8.77e-05
A60: 2015 | B60: 109030 | C60: Arizona Commission for Postsecondary Education | D60: Arizona Comm For Postsecondary Educ ation | E60: 36425 | F60: 3.63e-05
A61: 2015 | B61: 104820 | C61: Arizona Commission on the Arts | D61: Arizona Commission On The Arts | E61: 56835 | F61: 5.67e-05
A62: 2015 | B62: 103250 | C62: Arizona Corporation Commission | D62: Arizona Corporation Commission | E62: 1632964 | F62: 0.001628
A63: 2015 | B63: 109270 | C63: Arizona Cotton Research and Protection Council | D63: Arizona Cotton Research & Protection | E63: 105805 | F63: 0.0001055
A64: 2015 | B64: 497380 | C64: Arizona Counties Insurance Pool | D64: Arizona Counties Insurance Pool | E64: 89528 | F64: 8.93e-05
A65: 2015 | B65: 101140 | C65: Arizona Court of Appeals Division One | D65: Arizona Court Of Appeals Division One | E65: 348019 | F65: 0.000347
A66: 2015 | B66: 101150 | C66: Arizona Court of Appeals Division Two | D66: Arizona Court Of Appeals Division Two | E66: 161378 | F66: 0.0001609
A67: 2015 | B67: 101190 | C67: Arizona Criminal Justice Commission | D67: Arizona Criminal Justice Commission | E67: 151115 | F67: 0.0001507
A68: 2015 | B68: 100000 | C68: Arizona Department of Administration | D68: Arizona Department Of Administration | E68: 3731576 | F68: 0.0037203
A69: 2015 | B69: 103880 | C69: Arizona Department of Gaming / Racing Division | D69: Arizona Department Of Racing | E69: 143598 | F69: 0.0001432
... A99: 2015 | B99: 104920 | C99: Arizona Historical Society | D99: Arizona Historical Society | E99: 173717 | F99: 0.0001732
A100: 2015 | B100: 103200 | C100: Arizona Board of Homeopathic and Integrated Medicine Examiners | D100: Arizona Homeopathic Medical Examiners | F100: 0
A101: 2015 | B101: 101520 | C101: Arizona House of Representatives | D101: Arizona House Of Representatives | E101: 650833 | F101: 0.0006489
A102: 2015 | B102: 109150 | C102: Arizona Independent Redistricting Commission | D102: Arizona Independent Redistricting Com | E102: 27218 | F102: 2.71e-05
A103: 2015 | B103: 103500 | C103: Arizona Industrial Commission | D103: Arizona Industrial Commission | E103: 1134350 | F103: 0.0011309
A104: 2015 | B104: 495300 | C104: Arizona Interscholastic Association | D104: Arizona Interscholastic Association | E104: 148014 | F104: 0.0001476
A105: 2015 | B105: 101540 | C105: Arizona Joint Legislative Budget Committee | D105: Arizona Joint Legislative Budget Commit | E105: 161433 | F105: 0.0001609
A106: 2015 | B106: 101470 | C106: Arizona Law Enforcement Merit Syste | D106: Arizona Law Enforc ement Merit SysCouncil | F106: 0
A107: 2015 | B107: 101530 | C107: Arizona Legislative Council | D107: Arizona Legislative Council | E107: 335529 | F107: 0.0003345
A108: 2015 | B108: 103610 | C108: Arizona State Lottery | D108: Arizona Lottery | E108: 421061 | F108: 0.0004198
A109: 2015 | B109: 103620 | C109: Arizona Medical Board | D109: Arizona Medical Board | E109: 263790 | F109: 0.000263
A110: 2015 | B110: 495090 | C110: Arizona Municipal Water Users Association | D110: Arizona Municipal Water Users Assn | E110: 59547 | F110: 5.94e-05
A111: 2015 | B111: 103680 | C111: Arizona Naturopathic Physicians Board of Medical Examiners | D111: Arizona Naturopathic Phys Bd Of Med Exam | E111: 8905 | F111: 8.9e-06
A112: 2015 | B112: 109040 | C112: Arizona Navigable Streams Adjudication Commission | D112: Arizona Navigable Stream Adjudicatn Comm | E112: 7708 | F112: 7.7e-06
A113: 2015 | B113: 101590 | C113: Arizona Office of the Auditor General | D113: Arizona Office Of Auditor General | E113: 1376489 | F113: 0.0013723
A114: 2015 | B114: 101410 | C114: Arizona Office of Equal Opportunity | D114: Arizona Office Of Equal Opportunity | F114: 0
A115: 2015 | B115: 103940 | C115: Arizona Office of Pest Management | D115: Arizona Office Of Pest Management | E115: 77743 | F115: 7.75e-05
A116: 2015 | B116: 101430 | C116: Arizona Office of Tourism | D116: Arizona Office Of Tourism | E116: 183598 | F116: 0.000183
A117: 2015 | B117: 109070 | C117: Arizona Office of Administrative Hearings | D117: Arizona Office Of Administrative Hearings | E117: 106558 | F117: 0.0001062
A118: 2015 | B118: 101030 | C118: Arizona State Personnel Board | D118: Arizona Personnel Board | E118: 11736 | F118: 1.17e-05
A119: 2015 | B119: 102700 | C119: Arizona Pioneers' Home | D119: Arizona Pioneers' Home | E119: 322297 | F119: 0.0003213
A120: 2015 | B120: 109990 | C120: Arizona Power Authority | D120: Arizona Power Authority | E120: 59443 | F120: 5.93e-05
A121: 2015 | B121: 103870 | C121: Arizona State Board for Private Postsecondary | D121: Arizona Private Postsecondary Educ Bd | E121: 28092 | F121: 2.8e-05
A122: 2015 | B122: 496750 | C122: Arizona Prosecuting Attorneys' Advisory Council | D122: Arizona Prosecuting Attorneys' Adv Co | E122: 42349 | F122: 4.22e-05
A123: 2015 | B123: 103100 | C123: Arizona Radiation Regulatory Agency | D123: Arizona Radiation Regulatory Agency | E123: 134783 | F123: 0.0001344
A124: 2015 | B124: 103220 | C124: Arizona Registrar of Contractors | D124: Arizona Registrar Of Contrac tors | E124: 467809 | F124: 0.0004664
A125: 2015 | B125: 103260 | C125: Arizona Residential Utility Consumer Office | D125: Arizona ResidentialUtilityConsumerOffic e | E125: 56288 | F125: 5.61e-05
A126: 2015 | B126: 109080 | C126: Arizona School Facilities Board | D126: Arizona School Facilities Board | E126: 100148 | F126: 9.98e-05
... A149: 2015 | B149: 304040 | C149: Arizona Community Development Corporation (La Paloma Academy) | D149: AZ Community Dev. Corp. (La Paloma Acad) | E149: 621590 | F149: 0.0006197
A150: 2015 | B150: 302870 | C150: Arizona School for Integrated Acade | D150: AZ Sch For Integrated Academic s & Tech | F150: 0
A151: 2015 | B151: 450400 | C151: Baboquivari Unified School District #40 | D151: Baboquivari Unified School District | E151: 996612 | F151: 0.0009936
A152: 2015 | B152: 492200 | C152: Bagdad Unified School District | D152: Bagdad USD | E152: 306384 | F152: 0.0003055
A153: 2015 | B153: 302240 | C153: Ball Charter Schools (Dobson Academy) | D153: Ball Charter Schools (Dobson Academy) | E153: 272049 | F153: 0.0002712
A154: 2015 | B154: 307430 | C154: Ball Charter Schools (Hearn Academy) | D154: Ball Charter Schools (Hearn Academy) | E154: 257980 | F154: 0.0002572
A155: 2015 | B155: 200280 | C155: Ball Charter Schools (Val Vista Academy) | D155: Ball Charter Schools (Val Vista Academy) | E155: 155883 | F155: 0.0001554
A156: 2015 | B156: 300310 | C156: Balsz Elementary School District #31 | D156: Balsz Elementary School District 31 | E156: 1288350 | F156: 0.0012845
A157: 2015 | B157: 492260 | C157: Beaver Creek Elementary School District #26 | D157: Beaver Creek Elementary School Dist 26 | E157: 168086 | F157: 0.0001676
A158: 2015 | B158: 302080 | C158: Benchmark School | D158: Benchmark School | E158: 146810 | F158: 0.0001464
A159: 2015 | B159: 306910 | C159: Benjamin Franklin Charter School | D159: Benjamin Franklin Charter School | E159: 807684 | F159: 0.0008052
A160: 2015 | B160: 462090 | C160: Benson Unified School District #9 | D160: Benson USD #9 | E160: 585808 | F160: 0.000584
A161: 2015 | B161: 494760 | C161: Bicentennial Union High School District #76 | D161: Bicentennial USD # 76 | E161: 110538 | F161: 0.0001102
A162: 2015 | B162: 462020 | C162: Bisbee Unified School District #2 | D162: Bisbee USD #2 | E162: 436870 | F162: 0.0004355
... A252: 2015 | B252: 410110 | C252: Cochise County | D252: Cochise County | E252: 2738855 | F252: 0.0027306
A253: 2015 | B253: 462000 | C253: Cochise County School Office | D253: Cochise County School Office | F253: 0
A254: 2015 | B254: 462260 | C254: Cochise Elementary School District #26 | D254: Cochise Elementary SD #26 | E254: 75473 | F254: 7.52e-05
A255: 2015 | B255: 463230 | C255: Cochise Technology District #1 | D255: Cochise Technology District #01 | E255: 16393 | F255: 1.63e-05
A256: 2015 | B256: 410130 | C256: Coconino County | D256: Coconino County | E256: 3839986 | F256: 0.0038284
A257: 2015 | B257: 464990 | C257: Coconino County Community College | D257: Coconino County Community College | E257: 750800 | F257: 0.0007485
A258: 2015 | B258: 303060 | C258: Coconino County Regional Accommodation School District | D258: Coconino County Regional Accomm Sch | E258: 91356 | F258: 9.11e-05
A259: 2015 | B259: 481140 | C259: Colorado City Unified School District #14 | D259: Colorado City USD #14 | E259: 156536 | F259: 0.0001561
A260: 2015 | B260: 480020 | C260: Colorado River Sewage System Joint Venture | D260: Colorado River Sewage Sys Jt Venture | E260: 41482 | F260: 4.14e-05
A261: 2015 | B261: 481920 | C261: Colorado River Union High School District #2 | D261: Colorado River Union HSD #2 | E261: 826868 | F261: 0.0008244
A262: 2015 | B262: 461060 | C262: Concho Elementary School District #6 | D262: Concho Elementary SD #6 | E262: 145915 | F262: 0.0001455
A263: 2015 | B263: 492170 | C263: Congress Elementary School District #17 | D263: Congress Elementary SD #17 | E263: 100727 | F263: 0.0001004
A264: 2015 | B264: 450390 | C264: Continental School District | D264: Continental School Dist | E264: 267216 | F264: 0.0002664
A265: 2015 | B265: 200210 | C265: Coolidge Unified School District 21 | D265: Coolidge USD # 21 | E265: 1559852 | F265: 0.0015551
... A303: 2015 | B303: 307080 | C303: EduPrize Schools | D303: EDUPRIZE SCHOOLS | E303: 1217194 | F303: 0.0012135
A304: 2015 | B304: 302520 | C304: El Centro for the Study of Primary and Secondary Education | D304: El Centro for the Study of Primary and Secondary Educ ation | F304: 0
A305: 2015 | B305: 462120 | C305: Elfrida Elementary School District #12 | D305: Elfrida Elementary SD #12 | E305: 75359 | F305: 7.51e-05
A306: 2015 | B306: 495100 | C306: Elfrida Fire District | D306: Elfrida Fire District | E306: 14904 | F306: 1.49e-05
A307: 2015 | B307: 200110 | C307: Eloy Elementary School District #11 | D307: Eloy Elementary SD #11 | E307: 510477 | F307: 0.0005089
A308: 2015 | B308: 495080 | C308: Eloy Fire District | D308: Eloy Fire Dist | E308: 10565 | F308: 1.05e-05
A309: 2015 | B309: 303080 | C309: Esperanza Community Collegial Academy | D309: Esperanza Community Collegial Academy | F309: 0
A310: 2015 | B310: 306730 | C310: Espiritu Community Development Corporation (NFL YET) | D310: Espiritu Community Dev Corp (NFL YET) | E310: 194014 | F310: 0.0001934
A311: 2015 | B311: 302290 | C311: Excalibur Charter School (Avalon Elementary) | D311: Exc alibur Charter School (Avalon Elem) | E311: 111876 | F311: 0.0001115
A312: 2015 | B312: 302540 | C312: Flagstaff Arts And Leadership Academy | D312: Flagstaff Arts And Leadership Academy | E312: 142211 | F312: 0.0001418
A313: 2015 | B313: 493910 | C313: Flagstaff Junior Academy | D313: Flagstaff Junior Academy | E313: 126262 | F313: 0.0001259
A314: 2015 | B314: 464010 | C314: Flagstaff Unified School District #1 | D314: Flagstaff USD # 1 | E314: 4949469 | F314: 0.0049345
A315: 2015 | B315: 200010 | C315: Florence Unified School District No. 1 | D315: Florence USD # 1 | E315: 3594078 | F315: 0.0035832
A316: 2015 | B316: 496770 | C316: Flowing Wells Irrigation District | D316: Flowing Wells Irrigation District | E316: 52185 | F316: 5.2e-05
A317: 2015 | B317: 450080 | C317: Flowing Wells Unified School District #8 | D317: Flowing Wells USD # 8 | E317: 2648808 | F317: 0.0026408
A318: 2015 | B318: 463000 | C318: Fort Huachuca Accommodation Schools | D318: Fort Huachuca Accommodation Sch | E318: 637256 | F318: 0.0006353
A319: 2015 | B319: 497480 | C319: Fort Mojave Mesa Fire District | D319: Fort Mojave Mesa Fire Department | E319: 13829 | F319: 1.38e-05
...
